Workbook

Sheet Synergies
F2: P&L | G2: P&L @ 70% retention
B3: Annualized adjusted P&L | F3: ='26 EBITDA ADJ (2)'!Y23 -> 767548.18 | G3: =F3+F4 -> 1430073.9 | J3: =-'26 EBITDA ADJ (2)'!E6*2 -> 9390375.3 | K3: =-'26 EBITDA ADJ (2)'!E6*0.7*2 -> 6573262.7 | L3: =J3-K3 -> 2817112.6
B4: Synergies | F4: =-H15 -> 662525.69 | G4: =-L4 -> -845133.77 | H4: 30% of sls drop | L4: =L3*0.3 -> 845133.77
B5: Depreciation new co 12yrs (300,000 equip)(20x15k) | F5: =-300000/12 -> -25000 | G5: =F5 -> -25000
B6: 4% Sales (Full Sales) | F6: =-J3*0.04 -> -375615.01 | G6: =-K3*0.04 -> -262930.51
B7: $500k Upfront (paid over 5 years) 6.6% | F7: =-9806*12 -> -117672 | G7: =F7 -> -117672
B8: $1M Inv Carry Cost @7% | F8: =-1000000*0.07 -> -70000 | G8: =-1000000*0.07 -> -70000
B9: Extra Profit to Wise (Yrly) | F9: =SUM(F3:F8) -> 841786.86 | G9: =SUM(G3:G8) -> 109337.59
B12: HCF Acquistion | E12: 2026 HY1 | G12: After
B13: SYNERGIES | E13: Before | F13: 2026 Est | G13: Acqusition | H13: Adjusmt
B15: TOTAL SYNERGIES | H15: =H16+H24+H44+H45+H46 -> -662525.69 | J15: Supporting Calculations
B16: RENT | F16: =SUM(F17:F22) -> 294253.68 | G16: =SUM(G17:G22) -> 192414 | H16: =G16-F16 -> -101839.68 | J16: Sqft | K16: Price NNN | L16: New Calc | M16: NNN?
B17: Rent | C17: Hillsboro | E17: 0 | G17: =L17 -> 151914 | H17: =G17-F17 -> 151914 | J17: 75957 | K17: 2 | L17: =J17*K17 -> 151914
B18: Rent | C18: Angola | E18: ='SORTED B VS P'!N102 -> 48000 | F18: =E18*2 -> 96000 | G18: 0 | H18: =G18-F18 -> -96000
B19: Rent | C19: Fordyce | E19: ='SORTED B VS P'!N103 -> 15000 | F19: =E19*2 -> 30000 | G19: =L19 -> 40500 | H19: =G19-F19 -> 10500 | J19: 15000 | K19: 2.7 | L19: =J19*K19 -> 40500
B20: Utilities | C20: Angola | E20: ='SORTED B VS P'!M206 -> 61340.06 | F20: =E20*2 -> 122680.12 | G20: 0 | H20: =G20-F20 -> -122680.12 | J20: Verified-"Nothing from corporate in Angola Utilities - they should all go away with the building" | R20: Only things coded are NIPSCO - electric provide and City of Angola which is water and sewer.
B21: Caretaking | C21: Angola | E21: ='SORTED B VS P'!M100+'SORTED B VS P'!M214+'SORTED B VS P'!N226 -> 10647.46 | F21: =E21*2 -> 21294.92 | G21: 0 | H21: =G21-F21 -> -21294.92
B22: General Insurance | C22: Angola | E22: ='SORTED B VS P'!N224 -> 12139.32 | F22: =E22*2 -> 24278.64 | G22: 0 | H22: =G22-F22 -> -24278.64 | J22: We allocate the premiums based on previous years sales percentages to each location. The annual premium will go down once we remove the building from the policy. Not sure how much $.
B24: PEOPLE | F24: =SUM(F25:F43) -> 952694 | G24: =SUM(G25:G43) -> 635486 | H24: =SUM(H25:H43) -> -317208
B25: Owner 1 | F25: 100000 | G25: =F25 -> 100000 | H25: =G25-F25 -> 0
B26: Owner 2 | C26: Corp | F26: 100000 | G26: 0 | H26: =G26-F26 -> -100000 | J26: 1 less owner, keeping one
B27: Rhonda - CFO to GM | C27: Corp | F27: 71000 | G27: =F27*1.2 -> 85200 | H27: =G27-F27 -> 14200 | J27: 20% Incr for more repons
B28: Brooke - Accting/Inv | C28: Corp | F28: 68000 | G28: =F28*1.1 -> 74800 | H28: =G28-F28 -> 6800 | J28: 10% Incr for more repons
B29: COMP (remote) | C29: Corp | D29: Jeff Hensley | F29: 45240 | G29: 0 | H29: =G29-F29 -> -45240 | J29: 1961 closer to retire but doesn't think wants to
B30: COMP (remote) | C30: Corp | D30: Darin Murtle | F30: 49608 | G30: 0 | H30: =G30-F30 -> -49608 | J30: May need one but rehire in FTW
B31: Cust Sls | C31: Corp | D31: Keth Dick | F31: 51854 | G31: =F31 -> 51854 | H31: =G31-F31 -> 0 | J31: Cust Serv, truck driver, jack all trades,ship,, mat hand, scheuling
B32: Cust Sls (remote) | C32: Corp | D32: Carmen Martin | F32: 45032 | G32: =F32 -> 45032 | H32: =G32-F32 -> 0 | J32: orders intergrated paper, does all integ estimates
B33: Cust Sls | C33: Corp | D33: Mary Wills | F33: 44720 | G33: =F33 -> 44720 | H33: =G33-F33 -> 0 | J33: Work with Terri on govt stuff (maybe could train on paperwork or sales side??)
B34: Outside Sls | C34: Corp | D34: Terri | F34: 79000 | G34: =F34 -> 79000 | H34: =G34-F34 -> 0 | J34: Need for State work
B35: Outside Sls | C35: Corp | D35: Noah | F35: 56080 | G35: =F35 -> 56080 | H35: =G35-F35 -> 0 | J35: Have him develop sales
H36: =G36-F36 -> 0
B37: Plant Super | C37: Angola | D37: Tim Mcconah | F37: 61200 | H37: =G37-F37 -> -61200
B38: Scheduling/OfficeMgr | C38: Angola | D38: Melody Maguire | F38: 44720 | G38: =F38 -> 44720 | H38: =G38-F38 -> 0 | J38: Lives with Hamilton Martinez (Press)
B39: Scheduling | C39: Angola | D39: Dena Melchi | F39: 40560 | H39: =G39-F39 -> -40560 | J39: No need job jackets, runs reports for Rob, bindery when needed, used to burn plates before operators trained to burn own plates ANGOLA only; use 3rd party for flexo
B40: Shipping | C40: Angola | D40: Benji Hawkins | F40: 41600 | G40: 0 | H40: =G40-F40 -> -41600 | J40: No need for position
B42: Cust Sls | C42: Hillsboro | D42: Jason Miller | F42: 54080 | G42: =F42 -> 54080 | J42: Keep - cust service - all stock orders, sales HCF.com; lots logistics, complaints, frt schuling big jobs (VERY VALUABLE, knows computer system)
B44: PAPER | F44: =SUM(F45:F58) -> 0 | G44: =SUM(G45:G58) -> 0 | H44: =-'[1]Summary Savings'!$E$3 -> -243478.01
B45: Heatlhcare
B46: IT Synergies

Sheet Pixlle
D4: TYPE | E4: IS
D5: HCF FINANCIALS HY1 2026
D6: Sum of NET_CHANGE | E6: Column Labels
D7: Row Labels | E7: Pixelle | F7: Grand Total
D8: 1. Sales | E8: -962160.67 | F8: -962160.67
D9: 2. Variable cost Labor | E9: 315753.08 | F9: 315753.08
D10: 3. Mfg IDL | E10: 12414.36 | F10: 12414.36
D11: 4. Mfg OVHD | E11: 82744.57 | F11: 82744.57
D12: Grand Total | E12: -551248.66 | F12: -551248.66
R13: WITHOUT 6days
I14: Forecast | K14: =I14 -> Forecast | T14: Should be
E15: Jan-Dec2025 | G15: Jan-Jun2026 | I15: Jul-Dec2026 | K15: FY 2026 Est | M15: Est 2027 | N15: Assumption | Q15: Valuation | R15: =G15 -> Jan-Jun2026 | S15: =I15 -> Jul-Dec2026 | T15: Valatuion
D16: SALES | E16: =-[2]Pivot!$D$5 -> 870156.16 | F16: % Sales | G16: =-'26 EBITDA ADJ'!D6 -> 962160.67 | H16: % Sales | I16: =450000*2 -> 900000 | J16: % Sales | K16: =G16+I16 -> 1862160.7 | L16: % Sales | M16: =450000*4 -> 1800000 | N16: $450k x 4 | P16: =Q16 -> 1924321.3 | Q16: =G16*2 -> 1924321.3 | R16: =551308/6*5+410852+41000 -> 911275.33 | S16: =I16 -> 900000 | T16: =R16+S16 -> 1811275.3
A17: VARLAB | B17: 60700 | C17: 50 | D17: PRODUCTION WAGES | E17: 169152.01 | F17: =E17/E$16 -> 0.19439271 | G17: 192924.91 | H17: =G17/G$16 -> 0.20051216 | I17: =H17*I$16 -> 180460.94 | J17: =I17/I$16 -> 0.20051216 | K17: =G17+I17 -> 373385.85 | L17: =K17/K$16 -> 0.20051216 | M17: =N17*M$16 -> 360921.88 | N17: =L17 -> 0.20051216 | Q17: =G17*2 -> 385849.82 | R17: =I17 -> 180460.94 | S17: =I17 -> 180460.94 | T17: =R17+S17 -> 360921.88
A18: VARLAB | B18: 60710 | C18: 50 | D18: PRODUCTION OVERTIME | E18: 11359.5 | F18: =E18/E$16 -> 0.013054553 | G18: 16086.61 | H18: =G18/G$16 -> 0.016719255 | I18: =F18*I16 -> 11749.098 | J18: =I18/I$16 -> 0.013054553 | K18: =G18+I18 -> 27835.708 | L18: =K18/K$16 -> 0.01494807 | M18: =N18*M$16 -> 23498.196 | N18: =J18 -> 0.013054553 | O18: Assum reduces to 1.3% | Q18: =G18*2 -> 32173.22 | R18: =I18 -> 11749.098 | S18: =I18 -> 11749.098 | T18: =R18+S18 -> 23498.196
A19: VARLAB | B19: 60720 | C19: 50 | D19: PRODUCTION VACATION | E19: 10905.8 | F19: =E19/E$16 -> 0.012533153 | G19: 3777.6 | H19: =G19/G$16 -> 0.0039261634 | I19: =H19*I$16 -> 3533.5471 | J19: =I19/I$16 -> 0.0039261634 | K19: =G19+I19 -> 7311.1471 | L19: =K19/K$16 -> 0.0039261634 | M19: =N19*M$16 -> 7067.0941 | N19: =J19 -> 0.0039261634 | Q19: =G19*2 -> 7555.2 | R19: =I19 -> 3533.5471 | S19: =I19 -> 3533.5471 | T19: =R19+S19 -> 7067.0941
A20: VARLAB | B20: 60730 | C20: 50 | D20: PRODUCTION HOLIDAY | E20: 6821.6 | F20: =E20/E$16 -> 0.0078395124 | G20: 3916.4 | H20: =G20/G$16 -> 0.004070422 | I20: =H20*I$16 -> 3663.3798 | J20: =I20/I$16 -> 0.004070422 | K20: =G20+I20 -> 7579.7798 | L20: =K20/K$16 -> 0.004070422 | M20: =N20*M$16 -> 7326.7597 | N20: =J20 -> 0.004070422 | Q20: =G20*2 -> 7832.8 | R20: =I20 -> 3663.3798 | S20: =I20 -> 3663.3798 | T20: =R20+S20 -> 7326.7597
A21: VARLAB | B21: 60750 | C21: 50 | D21: MAINT. WAGES | E21: -11914.34 | F21: =E21/E$16 -> -0.013692186 | G21: -8500.32 | H21: =G21/G$16 -> -0.0088346159 | I21: =H21*I$16 -> -7951.1544 | J21: =I21/I$16 -> -0.0088346159 | K21: =G21+I21 -> -16451.474 | L21: =K21/K$16 -> -0.0088346159 | M21: =N21*M$16 -> -15902.309 | N21: =J21 -> -0.0088346159 | Q21: =G21*2 -> -17000.64 | R21: =I21 -> -7951.1544 | S21: =I21 -> -7951.1544 | T21: =R21+S21 -> -15902.309
A22: VARLAB | B22: 60751 | C22: 50 | D22: MAINT. O.T. WAGES | E22: 619.41 | F22: =E22/E$16 -> 0.00071183775 | G22: 30 | H22: =G22/G$16 -> 3.1179824e-05 | I22: =H22*I$16 -> 28.061841 | J22: =I22/I$16 -> 3.1179824e-05 | K22: =G22+I22 -> 58.061841 | L22: =K22/K$16 -> 3.1179824e-05 | M22: =N22*M$16 -> 56.123683 | N22: =J22 -> 3.1179824e-05 | Q22: =G22*2 -> 60 | R22: =I22 -> 28.061841 | S22: =I22 -> 28.061841 | T22: =R22+S22 -> 56.123683
A23: VARLAB | B23: 60752 | C23: 50 | D23: MAINT. VAC. WAGES | E23: 3400.2 | F23: =E23/E$16 -> 0.0039075745 | G23: 800 | H23: =G23/G$16 -> 0.00083146196 | I23: =H23*I$16 -> 748.31577 | J23: =I23/I$16 -> 0.00083146196 | K23: =G23+I23 -> 1548.3158 | L23: =K23/K$16 -> 0.00083146196 | M23: =N23*M$16 -> 1496.6315 | N23: =J23 -> 0.00083146196 | Q23: =G23*2 -> 1600 | R23: =I23 -> 748.31577 | S23: =I23 -> 748.31577 | T23: =R23+S23 -> 1496.6315
A24: VARLAB | B24: 60753 | C24: 50 | D24: MAINT. HOLIDAY WAGES | E24: 1257.6 | F24: =E24/E$16 -> 0.0014452578 | G24: 480 | H24: =G24/G$16 -> 0.00049887718 | I24: =H24*I$16 -> 448.98946 | J24: =I24/I$16 -> 0.00049887718 | K24: =G24+I24 -> 928.98946 | L24: =K24/K$16 -> 0.00049887718 | M24: =N24*M$16 -> 897.97892 | N24: =J24 -> 0.00049887718 | Q24: =G24*2 -> 960 | R24: =I24 -> 448.98946 | S24: =I24 -> 448.98946 | T24: =R24+S24 -> 897.97892
A25: IDL | B25: 60770 | C25: 50 | D25: PLANT SUPERVISION | E25: 56669.65 | F25: =E25/E$16 -> 0.065125839 | G25: 28614.88 | H25: =G25/G$16 -> 0.02974023 | I25: =H25*I$16 -> 26766.207 | J25: =I25/I$16 -> 0.02974023 | K25: =G25+I25 -> 55381.087 | L25: =K25/K$16 -> 0.02974023 | M25: =N25*M$16 -> 53532.415 | N25: =J25 -> 0.02974023 | Q25: =G25*2 -> 57229.76 | R25: =I25 -> 26766.207 | S25: =I25 -> 26766.207 | T25: =R25+S25 -> 53532.415
A26: IDL | B26: 60840 | C26: 50 | D26: SHIPPING WAGES | E26: 40683.75 | F26: =E26/E$16 -> 0.046754539 | G26: 22463.2 | H26: =G26/G$16 -> 0.02334662 | I26: =H26*I$16 -> 21011.958 | J26: =I26/I$16 -> 0.02334662 | K26: =G26+I26 -> 43475.158 | L26: =K26/K$16 -> 0.02334662 | M26: =N26*M$16 -> 42023.917 | N26: =J26 -> 0.02334662 | Q26: =G26*2 -> 44926.4 | R26: =I26 -> 21011.958 | S26: =I26 -> 21011.958 | T26: =R26+S26 -> 42023.917
A27: IDL | B27: 60841 | C27: 50 | D27: SHIPPING O.T. WAGES | E27: 87.33 | F27: =E27/E$16 -> 0.0001003613 | G27: 0 | H27: =G27/G$16 -> 0 | I27: =H27*I$16 -> 0 | J27: =I27/I$16 -> 0 | K27: =G27+I27 -> 0 | L27: =K27/K$16 -> 0 | M27: =N27*M$16 -> 0 | N27: =J27 -> 0 | Q27: =G27*2 -> 0 | R27: =I27 -> 0 | S27: =I27 -> 0 | T27: =R27+S27 -> 0
A28: IDL | B28: 60842 | C28: 50 | D28: SHIPPING VAC. WAGES | E28: 1498.5 | F28: =E28/E$16 -> 0.0017221047 | G28: 2422 | H28: =G28/G$16 -> 0.0025172511 | I28: =H28*I$16 -> 2265.526 | J28: =I28/I$16 -> 0.0025172511 | K28: =G28+I28 -> 4687.526 | L28: =K28/K$16 -> 0.0025172511 | M28: =N28*M$16 -> 4531.052 | N28: =J28 -> 0.0025172511 | Q28: =G28*2 -> 4844 | R28: =I28 -> 2265.526 | S28: =I28 -> 2265.526 | T28: =R28+S28 -> 4531.052
A29: IDL | B29: 60843 | C29: 50 | D29: SHIPPING HOLIDAY WAGES | E29: 810 | F29: =E29/E$16 -> 0.0009308674 | G29: 0 | H29: =G29/G$16 -> 0 | I29: =H29*I$16 -> 0 | J29: =I29/I$16 -> 0 | K29: =G29+I29 -> 0 | L29: =K29/K$16 -> 0 | M29: =N29*M$16 -> 0 | N29: =J29 -> 0 | Q29: =G29*2 -> 0 | R29: =I29 -> 0 | S29: =I29 -> 0 | T29: =R29+S29 -> 0
D30: Misc Incom 12k Premium Saturdays | G30: -12000 | I30: =H30*I$16 -> 0 | K30: =G30+I30 -> -12000 | L30: =K30/K$16 -> -0.0064441271 | M30: =N30*M$16 -> 0 | N30: =J30 -> 0 | O30: Assume doesn't repeat | Q30: =G30*2 -> -24000 | S30: =I30 -> 0 | T30: =R30+S30 -> 0
D31: Labor Cost | E31: =SUM(E17:E30) -> 291351.01 | F31: =E31/E$16 -> 0.33482612 | G31: =SUM(G17:G30) -> 251015.28 | H31: =G31/G$16 -> 0.26088707 | J31: =I31/I$16 -> 0 | K31: =SUM(K17:K30) -> 493740.15 | L31: =K31/K$16 -> 0.26514369 | M31: =SUM(M17:M30) -> 485449.74 | N31: =M31/M$16 -> 0.2696943 | Q31: =G34*2 -> -82171.44 | R31: 0 | S31: =I31 -> 0 | T31: =R31+S31 -> 0
E32: =E16-E31 -> 578805.15 | F32: =E32/E$16 -> 0.66517388 | G32: =G16-G31 -> 711145.39 | I32: =I16-I31 -> 900000 | K32: =K16-K31 -> 1368420.5 | M32: =M16-M31 -> 1314550.3 | P32: =Q32 -> 1504462.2 | Q32: =Q16-SUM(Q17:Q31) -> 1504462.2 | R32: =R16-SUM(R17:R31) -> 668550.46 | S32: =S16-SUM(S17:S31) -> 657275.13 | T32: =T16-SUM(T17:T31) -> 1325825.6
G33: $12,000 is for a premium we paid employees to work Saturdays | P33: =G32-G34 -> 752231.11 | Q33: =Q32/2 -> 752231.11 | T33: =Q32-T32 -> 178636.63
B34: 60850 | C34: 50 | D34: SUPERVISORY SALARIES | E34: -118069.05 | G34: -41085.72 | K34: 0 | M34: ??? | P34: =P33-Q33 -> 0 | T34: =T33*3.5 -> 625228.19
B35: Is there normally a cost in supervisor salary in Fordyce facility?
B36: or is it zero and you are just running the credit through this account?
D38: Rest Labor FICA | G38: ='SORTED B VS P'!M172+'SORTED B VS P'!M176+'SORTED B VS P'!M180+'SORTED B VS P'!M184+'SORTED B VS P'!M188+'SORTED B VS P'!M192 -> 106237.88 | I38: =G38 -> 106237.88 | K38: =G38+I38 -> 212475.76 | M38: =SUM(G17:G29)*2 -> 526030.56 | N38: =SUM(M17:M30) -> 485449.74 | P38: =-G38*2 -> -212475.76 | Q38: =-G38*2 -> -212475.76 | R38: =-G38 -> -106237.88 | S38: =-I38 -> -106237.88 | T38: =R38+S38 -> -212475.76
G39: =SUM(G17:G29)+G38+G34+G30 -> 316167.44 | I39: =SUM(I17:I29)+I38+I34 -> 348962.75 | K39: =SUM(K17:K29)+K38+K34 -> 718215.91 | N39: =N38-M38 -> -40580.821 | P39: =P32+P38 -> 1291986.5 | Q39: =Q32+Q38 -> 1291986.5 | R39: =R32+R38 -> 562312.58 | S39: =S32+S38 -> 551037.25 | T39: =R39+S39 -> 1113349.8
T40: =T39-Q39 -> -178636.63
D41: Var & IDL | G41: ='26 EBITDA ADJ'!D7+'26 EBITDA ADJ'!D12-12000 -> 316167.44 | I41: =G41*2 -> 632334.88 | K41: =G41+I41 -> 948502.32 | T41: =T40*3.5 -> -625228.19
D42: Sales - VARL&IDL | G42: =G16-G41 -> 645993.23
G43: =Pivot!D7+Pivot!D12+Pivot!D14+Pivot!D15+Pivot!D18 -> 103410.32 | Q43: =-G43 -> -103410.32 | R43: =Q43 -> -103410.32 | S43: =R43 -> -103410.32
G44: =G42-G43 -> 542582.91 | Q44: =Q39+Q43 -> 1188576.1 | R44: =R39+R43 -> 458902.26 | S44: =S39+S43 -> 447626.93
F45: ck fig | G45: =-'26 EBITDA ADJ'!D22+12000 -> 542582.91 | P45: =Q45-G44 -> 51705.16 | Q45: =Q44/2 -> 594288.07
J50: Should Sales have been about 40k more in HY1 2026?
J51: Based on what you invoiced for issues?
H54: CM
H55: 14930 | I55: Jan
H56: 9466.39 | I56: Feb
H57: 8319.56 | I57: Mar
H58: 4031.56 | I58: Apr
H59: 4338 | I59: May
H60: 4031 | I60: Jun
H61: =SUM(H55:H60) -> 45116.51

Sheet 26 EBITDA ADJ (2)
V1: Pixelle Sales | X1: =(551308+410852)*2 -> 1924320 | Y1: =(410852+444994)*2 -> 1711692 | Z1: =Y1-X1 -> -212628
A2: TYPE | B2: IS
A3: HCF FINANCIALS HY1 2026 | L3: Adjustment Calcs | N3: Pixelle | O3: =N3 -> Pixelle | Q3: 2026 6Months | AC3: 2026 12Months
A4: Sum of NET_CHANGE | B4: Column Labels | N4: Adjustment | O4: Adj 2026 HY1 | S4: Adjusted | T4: 2026 Adj 5Days | V4: Adjusted EBITDA | W4: 2026 6Mo | X4: Orignal | Y4: Adjusted | Z4: Diff | AA4: Diff 3.5x | AB4: Explanation of new EBITDA Adjustments | AE4: Adjusted | AF4: 2026 Adj 5Days
A5: Row Labels | B5: Angola | C5: Hillsboro | D5: Pixelle | E5: Grand Total | F5: Original | G5: =B5 -> Angola | H5: =C5 -> Hillsboro | I5: =D5 -> Pixelle | J5: Total | L5: Adjust 6days vs 5 days | N5: Avg/Day | O5: 5Days Sls | Q5: =B5 -> Angola | R5: =C5 -> Hillsboro | S5: =D5 -> Pixelle | T5: =E5 -> Grand Total | W5: Original | X5: Annualized | Y5: Annualized | AA5: Valuation | AC5: =M5 -> 0 | AD5: =N5 -> Avg/Day | AE5: =O5 -> 5Days Sls | AF5: =P5 -> 0
A6: 1. Sales | B6: -1500193.9 | C6: -2232833 | D6: -962160.67 | E6: -4695187.6 | G6: % of Sales Totals | L6: Sales if 5Days | N6: =D6+O6 -> -91884.67 | O6: =435138*2 -> 870276 | Q6: =B6 -> -1500193.9 | R6: =C6 -> -2232833 | S6: =-O6 -> -870276 | T6: =SUM(Q6:S6) -> -4603303 | U6: =T6*2 -> -9206605.9 | V6: Sales | W6: =-E6 -> 4695187.6 | X6: =W6*2 -> 9390375.3 | Y6: =((410852+444994)/2)*4-B6*2-C6*2 -> 9177745.9 | Z6: =Y6-X6 -> -212629.34 | AB6: Pixelle Q1 overinflated working 6 days, use average of Q2&Q3 | AC6: =Q6*2 -> -3000387.9 | AD6: =R6*2 -> -4465666.1 | AE6: 1800000 | AF6: =SUM(AC6:AE6) -> -5666053.9
A7: 2. Variable cost Labor | B7: 343188.12 | C7: 498256.51 | D7: 315753.08 | E7: 1157197.7 | G7: =-B7/B$6 -> 0.2287625 | H7: =-C7/C$6 -> 0.22314992 | I7: =-D7/D$6 -> 0.32817084 | J7: =-E7/E$6 -> 0.24646464 | N7: =5/6 -> 0.83333333 | O7: =N7*551308 -> 459423.33 | Q7: =B7 -> 343188.12 | R7: =C7 -> 498256.51 | S7: =D7 -> 315753.08 | T7: =SUM(Q7:S7) -> 1157197.7 | U7: =T7*2 -> 2314395.4 | V7: Net Profit | W7: =F22 -> 467828 | X7: =W7*2 -> 935656 | AC7: =Q7*2 -> 686376.24 | AD7: =R7*2 -> 996513.02 | AE7: =O7 -> 459423.33 | AF7: =SUM(AC7:AE7) -> 2142312.6
A8: 2. Variable cost Mat | B8: 855851.1 | C8: 1143410.8 | D8: 22188.07 | E8: 2021450 | G8: =-B8/B$6 -> 0.57049364 | H8: =-C8/C$6 -> 0.5120897 | I8: =-D8/D$6 -> 0.02306067 | J8: =-E8/E$6 -> 0.43053657 | O8: 410852 | Q8: =B8 -> 855851.1 | R8: =C8 -> 1143410.8 | S8: =D8 -> 22188.07 | T8: =SUM(Q8:S8) -> 2021450 | U8: =T8*2 -> 4042899.9 | V8: Deduct Debt Forgiveness | W8: =-'[3]2-T5Y IS (Cont.)'!$D$66 -> -133786 | X8: =W8*2 -> -267572 | AC8: =Q8*2 -> 1711702.2 | AD8: =R8*2 -> 2286821.6 | AE8: =O8 -> 410852 | AF8: =SUM(AC8:AE8) -> 4409375.8
A9: 2a. Variable cost Mat | C9: -19607.13 | E9: -19607.13 | G9: =-B9/B$6 -> 0 | H9: =-C9/C$6 -> -0.0087812791 | I9: =-D9/D$6 -> 0 | J9: =-E9/E$6 -> -0.0041760056 | O9: =AVERAGE(O7:O9) -> 0 | Q9: =B9 -> 0 | R9: =C9 -> -19607.13 | S9: =D9 -> 0 | T9: =SUM(Q9:S9) -> -19607.13 | U9: =T9*2 -> -39214.26 | V9: Net Profit after Debt Adj | W9: =W7+W8 -> 334042 | X9: =W9*2 -> 668084 | Y9: =X9 -> 668084 | Z9: =Y9-X9 -> 0 | AC9: =Q9*2 -> 0 | AD9: =R9*2 -> -39214.26 | AE9: =O9 -> 0 | AF9: =SUM(AC9:AE9) -> -19607.13
A10: 2a. Variable cost Mat Out/Env | C10: 11708.17 | E10: 11708.17 | G10: =-B10/B$6 -> 0 | H10: =-C10/C$6 -> 0.0052436388 | I10: =-D10/D$6 -> 0 | J10: =-E10/E$6 -> 0.0024936533 | Q10: =B10 -> 0 | R10: =C10 -> 11708.17 | S10: =D10 -> 0 | T10: =SUM(Q10:S10) -> 11708.17 | U10: =T10*2 -> 23416.34 | V10: Add back Interest Expense | W10: ='SORTED B VS P'!N288+'SORTED B VS P'!M292 -> 1784.75 | X10: =W10*2 -> 3569.5 | Y10: =X10 -> 3569.5 | Z10: =Y10-X10 -> 0 | AC10: =Q10*2 -> 0 | AD10: =R10*2 -> 23416.34 | AE10: =O10 -> 0 | AF10: =SUM(AC10:AE10) -> 23416.34
A11: 8c. Frt Exp | B11: 5732.8 | C11: 7801.63 | E11: 13534.43 | G11: =-B11/B$6 -> 0.0038213726 | H11: =-C11/C$6 -> 0.0034940499 | I11: =-D11/D$6 -> 0 | J11: =-E11/E$6 -> 0.0028826175 | Q11: =B11 -> 5732.8 | R11: =C11 -> 7801.63 | S11: =D11 -> 0 | T11: =SUM(Q11:S11) -> 13534.43 | U11: =T11*2 -> 27068.86 | V11: Add back Depreciation | W11: =('SORTED B VS P'!N195+'SORTED B VS P'!N196+'SORTED B VS P'!N197+'SORTED B VS P'!N198+'SORTED B VS P'!N199+'SORTED B VS P'!N200+'SORTED B VS P'!N201+'SORTED B VS P'!N202++'SORTED B VS P'!N203+'SORTED B VS P'!N204) -> 106590.78 | X11: =W11*2 -> 213181.56 | Y11: =X11 -> 213181.56 | Z11: =Y11-X11 -> 0 | AC11: =Q11*2 -> 11465.6 | AD11: =R11*2 -> 15603.26 | AE11: =O11 -> 0 | AF11: =SUM(AC11:AE11) -> 27068.86
A12: 3. Mfg IDL | B12: 87123.01 | C12: 115278.5 | D12: 12414.36 | E12: 214815.87 | G12: =-B12/B$6 -> 0.058074498 | H12: =-C12/C$6 -> 0.051628805 | I12: =-D12/D$6 -> 0.012902585 | J12: =-E12/E$6 -> 0.04575235 | L12: CREDIT PIXELLE | N12: -41085 | O12: =D12-N12 -> 53499.36 | Q12: =B12 -> 87123.01 | R12: =C12 -> 115278.5 | S12: =D12 -> 12414.36 | T12: =SUM(Q12:S12) -> 214815.87 | U12: =T12*2 -> 429631.74 | V12: Add back Bank Charges② | W12: ='SORTED B VS P'!N212 -> 17884.74 | X12: =W12*2 -> 35769.48 | Y12: =X12 -> 35769.48 | Z12: =Y12-X12 -> 0 | AC12: =Q12*2 -> 174246.02 | AD12: =R12*2 -> 230557 | AF12: =SUM(AC12:AE12) -> 404803.02
A13: 4. Mfg OVHD | B13: 186209.89 | C13: 202999.64 | D13: 82744.57 | E13: 471954.1 | G13: =-B13/B$6 -> 0.12412388 | H13: =-C13/C$6 -> 0.090915728 | I13: =-D13/D$6 -> 0.085998703 | J13: =-E13/E$6 -> 0.10051869 | Q13: =B13 -> 186209.89 | R13: =C13 -> 202999.64 | S13: =D13 -> 82744.57 | T13: =SUM(Q13:S13) -> 471954.1 | U13: =T13*2 -> 943908.2 | V13: Estimated Fair Market Rent | W13: 0 | X13: =W13*2 -> 0 | Y13: =-AB33 -> -66414 | Z13: =Y13-X13 -> -66414 | AA13: =Z13*3.5 -> -232449 | AC13: =Q13*2 -> 372419.78 | AD13: =R13*2 -> 405999.28 | AE13: =O13 -> 0 | AF13: =SUM(AC13:AE13) -> 778419.06
A14: 7. Selling | B14: 36556.54 | C14: 177818.79 | E14: 214375.33 | G14: =-B14/B$6 -> 0.024367876 | H14: =-C14/C$6 -> 0.079638194 | I14: =-D14/D$6 -> 0 | J14: =-E14/E$6 -> 0.045658522 | Q14: =B14 -> 36556.54 | R14: =C14 -> 177818.79 | S14: =D14 -> 0 | T14: =SUM(Q14:S14) -> 214375.33 | U14: =T14*2 -> 428750.66 | V14: Estimated Fair Market Rent NNN (30%?) | Y14: =Y13*0.35 -> -23244.9 | Z14: =Y14-X14 -> -23244.9 | AA14: =Z14*3.5 -> -81357.15 | AB14: Per AI NNN is usually 25-50% of rent | AC14: =Q14*2 -> 73113.08 | AD14: =R14*2 -> 355637.58 | AE14: =O14 -> 0 | AF14: =SUM(AC14:AE14) -> 428750.66
A15: 8. Admin | B15: 40430.47 | C15: 340312.03 | D15: 19495.37 | E15: 400237.87 | G15: =-B15/B$6 -> 0.026950162 | H15: =-C15/C$6 -> 0.15241266 | I15: =-D15/D$6 -> 0.020262073 | J15: =-E15/E$6 -> 0.085244276 | Q15: =B15 -> 40430.47 | R15: =C15 -> 340312.03 | S15: =D15 -> 19495.37 | T15: =SUM(Q15:S15) -> 400237.87 | U15: =T15*2 -> 800475.74 | V15: Add back 1 owner salary | W15: 0 | X15: =W15*2 -> 0 | Y15: 100000 | Z15: =Y15-X15 -> 100000 | AA15: =Z15*3.5 -> 350000 | AC15: =Q15*2 -> 80860.94 | AD15: =R15*2 -> 680624.06 | AE15: =O15 -> 0 | AF15: =SUM(AC15:AE15) -> 761485
A16: 8. Admin IT | B16: 971.64 | C16: 12346.79 | D16: 825.31 | E16: 14143.74 | G16: =-B16/B$6 -> 0.00064767626 | H16: =-C16/C$6 -> 0.0055296522 | I16: =-D16/D$6 -> 0.00085776734 | J16: =-E16/E$6 -> 0.0030123908 | Q16: =B16 -> 971.64 | R16: =C16 -> 12346.79 | S16: =D16 -> 825.31 | T16: =SUM(Q16:S16) -> 14143.74 | U16: =T16*2 -> 28287.48 | V16: Deduct Gain on Sale of Assets | AC16: =Q16*2 -> 1943.28 | AD16: =R16*2 -> 24693.58 | AE16: =O16 -> 0 | AF16: =SUM(AC16:AE16) -> 26636.86
A17: 8a. Frt Income | B17: -186087.68 | C17: -145148.52 | E17: -331236.2 | F17: how does this tie if Fordyce not in TB? | G17: =-B17/B$6 -> -0.12404242 | H17: =-C17/C$6 -> -0.065006437 | I17: =-D17/D$6 -> 0 | J17: =-E17/E$6 -> -0.070548022 | Q17: =B17 -> -186087.68 | R17: =C17 -> -145148.52 | S17: =D17 -> 0 | T17: =SUM(Q17:S17) -> -331236.2 | U17: =T17*2 -> -662472.4 | V17: Deduct EXCESS Purchase Discounts | AC17: =Q17*2 -> -372175.36 | AD17: =R17*2 -> -290297.04 | AE17: =O17 -> 0 | AF17: =SUM(AC17:AE17) -> -662472.4
A18: 8b. Frt Exp | B18: 145827.64 | C18: 125457.9 | E18: 271285.54 | G18: =-B18/B$6 -> 0.097205859 | H18: =-C18/C$6 -> 0.056187766 | I18: =-D18/D$6 -> 0 | J18: =-E18/E$6 -> 0.057779489 | Q18: =B18 -> 145827.64 | R18: =C18 -> 125457.9 | S18: =D18 -> 0 | T18: =SUM(Q18:S18) -> 271285.54 | U18: =T18*2 -> 542571.08 | V18: Deduct Other Income④ | AC18: =Q18*2 -> 291655.28 | AD18: =R18*2 -> 250915.8 | AE18: =O18 -> 0 | AF18: =SUM(AC18:AE18) -> 542571.08
A19: 9. Scrap & Misc Inc | B19: -2555.07 | C19: -56104.61 | D19: -21843 | E19: -80502.68 | G19: =-B19/B$6 -> -0.0017031598 | H19: =-C19/C$6 -> -0.025127096 | I19: =-D19/D$6 -> -0.02270203 | J19: =-E19/E$6 -> -0.017145786 | Q19: =B19 -> -2555.07 | R19: =C19 -> -56104.61 | S19: =D19 -> -21843 | T19: =SUM(Q19:S19) -> -80502.68 | U19: =T19*2 -> -161005.36 | V19: Pixelle Abnormal Sales Q1 | Y19: =N6 -> -91884.67 | Z19: =Y19-X19 -> -91884.67 | AA19: =Z19*3.5 -> -321596.35 | AB19: HCF ran 6 days (abnormal) to help Pixelle catch up from Mill closer (5/6)= .83%=Adjust out of Sales $91,885 | AC19: =Q19*2 -> -5110.14 | AD19: =R19*2 -> -112209.22 | AE19: =O19 -> 0 | AF19: =SUM(AC19:AE19) -> -117319.36
A20: 91. Other Inc/Exp | B20: 4.33 | C20: -132001.55 | E20: -131997.22 | G20: =-B20/B$6 -> 2.8862935e-06 | H20: =-C20/C$6 -> -0.059118415 | I20: =-D20/D$6 -> 0 | J20: =-E20/E$6 -> -0.0281133 | Q20: =B20 -> 4.33 | R20: 0 | S20: =D20 -> 0 | T20: =SUM(Q20:S20) -> 4.33 | V20: Pixelle Abnormal Sales Duplicated in HY2 2026 Forecast | Y20: =Y19 -> -91884.67 | Z20: =Y20-X20 -> -91884.67 | AA20: =Z20*3.5 -> -321596.35 | AB20: Due the same for Jul-Dec since the P&L was annaulized for the second half year | AC20: =Q20*2 -> 8.66 | AD20: =R20*2 -> 0 | AE20: =O20 -> 0 | AF20: =SUM(AC20:AE20) -> 8.66
A21: 99. Elim | B21: 0 | C21: 0 | D21: 0 | E21: 0 | G21: =-B21/B$6 -> 0 | H21: =-C21/C$6 -> 0 | I21: =-D21/D$6 -> 0 | J21: =-E21/E$6 -> 0 | Q21: =B21 -> 0 | R21: =C21 -> 0 | T21: =SUM(Q21:S21) -> 0 | V21: DLabor Adjustment for Sales Diff | Y21: ='[4]Pixelle P&L'!$D$29 -> 10185.941 | Z21: =Y21-X21 -> 10185.941 | AA21: =Z21*3.5 -> 35650.792 | AC21: =Q21*2 -> 0 | AD21: =R21*2 -> 0 | AF21: =SUM(AC21:AE21) -> 0
A22: Grand Total | B22: 13058.86 | C22: 49695.92 | D22: -530582.91 | E22: -467828.13 | F22: ='[3]2-T5Y IS (Cont.)'!$D$70 -> 467828 | G22: =-B22/B$6 -> 0.0087047813 | H22: =-C22/C$6 -> 0.02225689 | I22: =-D22/D$6 -> -0.55144939 | J22: =-E22/E$6 -> -0.099639922 | Q22: =SUM(Q6:Q21) -> 13058.86 | R22: =SUM(R6:R21) -> 181697.47 | S22: =SUM(S6:S21) -> -438698.24 | T22: =SUM(T6:T21) -> -243941.91 | U22: =SUM(U6:U21) -> -487892.48 | V22: DLabor Adjustment for Sales Diff Dupl in HY2 2026 Forecast | Y22: =Y21 -> 10185.941 | Z22: =Y22-X22 -> 10185.941 | AA22: =Z22*3.5 -> 35650.792 | AC22: =SUM(AC6:AC21) -> 26117.72 | AD22: =SUM(AD6:AD21) -> 363394.94 | AE22: =SUM(AE6:AE21) -> -438698.24 | AF22: =SUM(AF6:AF21) -> -243941.91
A23: 26 Annualized (minus debt forgive) | B23: =-B22*2 -> -26117.72 | C23: =-(C22-C20)*2 -> -363394.94 | D23: =-D22*2 -> 1061165.8 | E23: =-(E22-E20)*2 -> 671661.82 | F23: =(F22+C20)*2 -> 671652.9 | L23: Total Adj | N23: =N6+N12 -> -132969.67 | Q23: =-Q22*2 -> -26117.72 | R23: =-R22*2 -> -363394.94 | S23: =-S22*2 -> 877396.48 | T23: =-T22*2 -> 487883.82 | U23: =-U22*2 -> 975784.96 | V23: Adjusted EBITDA | W23: =SUM(W9:W22) -> 460302.27 | X23: =SUM(X9:X22) -> 920604.54 | Y23: =SUM(Y9:Y22) -> 767548.18 | Z23: =Y23-X23 -> -153056.36 | AA23: =SUM(AA10:AA22) -> -535697.26 | AC23: =-AC22*2 -> -52235.44 | AD23: =-AD22*2 -> -726789.88 | AE23: =-AE22*2 -> 877396.48 | AF23: =-AF22*2 -> 487883.82
A24: 2025 | B24: =[2]Pivot!B$22 -> -188567.02 | C24: =[2]Pivot!C$22 -> 507482.26 | D24: =[2]Pivot!D$22 -> -393948.69 | E24: =[2]Pivot!E$22 -> -75033.45 | F24: =E22-C20 -> -335826.58 | Q24: Difference | T24: =T23-E23 -> -183778 | V24: Valuation 3.5x | X24: =3.5*X23 -> 3222115.9 | Y24: =3.5*Y23 -> 2686418.6 | Z24: =Z23*3.5 -> -535697.26 | AC24: Difference | AF24: =AF23-P23 -> -183778
F25: =F22+C20 -> 335826.45 | L25: =551308+410852 -> 962160
A26: Estimated Jun2026 Full Yr to Full Yr 2025 | F26: =F25*2 -> 671652.9 | G26: 2026 % Change toi 2025 | L26: =L25*2 -> 1924320 | Q26: Pixelle Sales Adjusted by 100k Q1 & 100k HY2 = 200k | W26: 0 | X26: =W26*2 -> 0 | Y26: =X26 -> 0 | Z26: =Y26-X26 -> 0
A27: =A6 -> 1. Sales | B27: =B6*2 -> -3000387.9 | C27: =C6*2 -> -4465666.1 | D27: =D6*2 -> -1924321.3 | E27: =E6*2 -> -9390375.3 | G27: =B27/[2]Pivot!B5-1 -> -0.11822123 | H27: =C27/[2]Pivot!C5-1 -> 0.048125645 | I27: =D27/[2]Pivot!D5-1 -> 1.2114667 | J27: =E27/[2]Pivot!E5-1 -> 0.10042202 | Q27: essentially no cost reductions 2025&2026 cost same | W27: 0 | X27: =W27*2 -> 0 | Y27: =X27 -> 0 | Z27: =Y27-X27 -> 0
A28: =A7 -> 2. Variable cost Labor | B28: =B7*2 -> 686376.24 | C28: =C7*2 -> 996513.02 | D28: =D7*2 -> 631506.16 | E28: =E7*2 -> 2314395.4 | G28: =G7-[2]Pivot!F6 -> 0.027699236 | H28: =H7-[2]Pivot!G6 -> -0.00066119334 | I28: =I7-[2]Pivot!H6 -> -0.017588737 | J28: =J7-[2]Pivot!I6 -> 0.019288972 | L28: $12,000 is for a premium we paid employees to work Saturdays | Q28: 41k Pixelle credit x 2 = 82k full year adjsuted
A29: =A8 -> 2. Variable cost Mat | B29: =B8*2 -> 1711702.2 | C29: =C8*2 -> 2286821.6 | D29: =D8*2 -> 44376.14 | E29: =E8*2 -> 4042899.9 | G29: =G8-[2]Pivot!F7 -> 0.028061849 | H29: =H8-[2]Pivot!G7 -> 0.0057809979 | I29: =I8-[2]Pivot!H7 -> -0.0042176288 | J29: =J8-[2]Pivot!I7 -> -0.041329144 | Q29: Need to understand what issues were and what are extra costs | U29: HCF Acquistion | X29: 2026 HY1 | Z29: After
A30: =A9 -> 2a. Variable cost Mat | B30: =B9*2 -> 0 | C30: =C9*2 -> -39214.26 | D30: =D9*2 -> 0 | E30: =E9*2 -> -39214.26 | G30: =G9-[2]Pivot!F8 -> 0 | H30: =H9-[2]Pivot!G8 -> 0.0035708313 | I30: =I9-[2]Pivot!H8 -> 0 | J30: =J9-[2]Pivot!I8 -> 0.0019912278 | Q30: or are they not producing as much and sales would be higher | U30: SYNERGIES | X30: Before | Y30: 2026 Est | Z30: Acqusition | AB30: Adjusmt
A31: =A10 -> 2a. Variable cost Mat Out/Env | B31: =B10*2 -> 0 | C31: =C10*2 -> 23416.34 | D31: =D10*2 -> 0 | E31: =E10*2 -> 23416.34 | G31: =G10-[2]Pivot!F9 -> -0.00015188439 | H31: =H10-[2]Pivot!G9 -> -0.0016654386 | I31: =I10-[2]Pivot!H9 -> 0 | J31: =J10-[2]Pivot!I9 -> -0.001016514
A32: =A11 -> 8c. Frt Exp | B32: =B11*2 -> 11465.6 | C32: =C11*2 -> 15603.26 | D32: =D11*2 -> 0 | E32: =E11*2 -> 27068.86 | G32: =G11-[2]Pivot!F10 -> -0.0010742856 | H32: =H11-[2]Pivot!G10 -> 4.2578791e-05 | I32: =I11-[2]Pivot!H10 -> -0.00010336076 | J32: =J11-[2]Pivot!I10 -> -0.00080330678 | U32: TOTAL SYNERGIES
A33: =A12 -> 3. Mfg IDL | B33: =B12*2 -> 174246.02 | C33: =C12*2 -> 230557 | D33: =D12*2 -> 24828.72 | E33: =E12*2 -> 429631.74 | G33: =G12-[2]Pivot!F11 -> 0.006868519 | H33: =H12-[2]Pivot!G11 -> -0.013437409 | I33: =I12-[2]Pivot!H11 -> -0.10173113 | J33: =J12-[2]Pivot!I11 -> -0.018841589 | U33: RENT | Y33: =SUM(Y34:Y36) -> 126000 | Z33: =SUM(Z34:Z36) -> 192414 | AB33: =SUM(AB34:AB36) -> 66414
A34: =A13 -> 4. Mfg OVHD | B34: =B13*2 -> 372419.78 | C34: =C13*2 -> 405999.28 | D34: =D13*2 -> 165489.14 | E34: =E13*2 -> 943908.2 | G34: =G13-[2]Pivot!F13 -> 0.010265792 | H34: =H13-[2]Pivot!G13 -> 0.005674589 | I34: =I13-[2]Pivot!H13 -> -0.074265473 | J34: =J13-[2]Pivot!I13 -> -0.0037834038 | U34: Rent | V34: Hillsboro | X34: 0 | Z34: 151914 | AB34: 151914
A35: =A14 -> 7. Selling | B35: =B14*2 -> 73113.08 | C35: =C14*2 -> 355637.58 | D35: =D14*2 -> 0 | E35: =E14*2 -> 428750.66 | G35: =G14-[2]Pivot!F14 -> 0.002703289 | H35: =H14-[2]Pivot!G14 -> -0.009789405 | I35: =I14-[2]Pivot!H14 -> 0 | J35: =J14-[2]Pivot!I14 -> -0.0076300312 | U35: Rent | V35: Angola | X35: 48000 | Y35: 96000 | Z35: 0 | AB35: -96000
A36: =A15 -> 8. Admin | B36: =B15*2 -> 80860.94 | C36: =C15*2 -> 680624.06 | D36: =D15*2 -> 38990.74 | E36: =E15*2 -> 800475.74 | G36: =G15-[2]Pivot!F15 -> -0.00065113526 | H36: =H15-[2]Pivot!G15 -> -0.03125465 | I36: =I15-[2]Pivot!H15 -> -0.017910397 | J36: =J15-[2]Pivot!I15 -> -0.021356514 | U36: Rent | V36: Fordyce | X36: 15000 | Y36: 30000 | Z36: 40500 | AB36: 10500
A37: =A16 -> 8. Admin IT | B37: =B16*2 -> 1943.28 | C37: =C16*2 -> 24693.58 | D37: =D16*2 -> 1650.62 | E37: =E16*2 -> 28287.48 | G37: =G16-[2]Pivot!F16 -> -0.00016828979 | H37: =H16-[2]Pivot!G16 -> 0.00081743291 | I37: =I16-[2]Pivot!H16 -> -0.00083706638 | J37: =J16-[2]Pivot!I16 -> 0.00016146245
A38: =A17 -> 8a. Frt Income | B38: =B17*2 -> -372175.36 | C38: =C17*2 -> -290297.04 | D38: =D17*2 -> 0 | E38: =E17*2 -> -662472.4 | G38: =G17-[2]Pivot!F17 -> -0.033929055 | H38: =H17-[2]Pivot!G17 -> 0.00080304336 | I38: =I17-[2]Pivot!H17 -> 0 | J38: =J17-[2]Pivot!I17 -> -0.0017581263
A39: =A18 -> 8b. Frt Exp | B39: =B18*2 -> 291655.28 | C39: =C18*2 -> 250915.8 | D39: =D18*2 -> 0 | E39: =E18*2 -> 542571.08 | G39: =G18-[2]Pivot!F18 -> 0.024880993 | H39: =H18-[2]Pivot!G18 -> 0.0037073921 | I39: =I18-[2]Pivot!H18 -> 0 | J39: =J18-[2]Pivot!I18 -> 0.002737681
A40: =A19 -> 9. Scrap & Misc Inc | B40: =B19*2 -> -5110.14 | C40: =C19*2 -> -112209.22 | D40: =D19*2 -> -43686 | E40: =E19*2 -> -161005.36 | F40: 12k sale of asset? | G40: =G19-[2]Pivot!F19 -> -0.00038598201 | H40: =H19-[2]Pivot!G19 -> 0.0021395681 | I40: =I19-[2]Pivot!H19 -> -0.01774947 | J40: =J19-[2]Pivot!I19 -> -0.0025016967
A41: =A20 -> 91. Other Inc/Exp | B41: =B20*2 -> 8.66 | C41: 0 | D41: =D20*2 -> 0 | E41: 0 | G41: =G20-[2]Pivot!F20 -> 3.3682703e-06 | H41: 0 | I41: =I20-[2]Pivot!H20 -> 0 | J41: =J20-[2]Pivot!I20 -> -0.029842116
A42: =A21 -> 99. Elim | B42: =B21*2 -> 0 | C42: =C21*2 -> 0 | D42: =D21*2 -> 0 | E42: =E21*2 -> 0 | G42: =G21-[2]Pivot!F21 -> 0 | H42: =H21-[2]Pivot!G21 -> 0 | I42: =I21-[2]Pivot!H21 -> 0 | J42: =J21-[2]Pivot!I21 -> 0
A43: =A22 -> Grand Total | B43: =SUM(B27:B42) -> 26117.72 | C43: =SUM(C27:C42) -> 363394.94 | D43: =SUM(D27:D42) -> -1061165.8 | E43: =SUM(E27:E42) -> -671661.82 | G43: =G22-[2]Pivot!F22 -> 0.064122415 | H43: =H22-[2]Pivot!G22 -> -0.096853039 | I43: =I22-[2]Pivot!H22 -> -0.098716062 | J43: =J22-[2]Pivot!I22 -> -0.09084704
A44: 2026 Estimate | B44: =-B43 -> -26117.72 | C44: =-C43 -> -363394.94 | D44: =-D43 -> 1061165.8 | E44: =-E43 -> 671661.82
A45: 2025 | B45: =-[2]Pivot!B$22 -> 188567.02 | C45: =-[2]Pivot!C$22 -> -507482.26 | D45: =-[2]Pivot!D$22 -> 393948.69 | E45: =-[2]Pivot!E$22 -> 75033.45
A46: Extra profit (loss) | B46: =B44-B45 -> -214684.74 | C46: =C44-C45 -> 144087.32 | D46: =D44-D45 -> 667217.13 | E46: =E44-E45 -> 596628.37
A48: EXPLANATION
A49: Sales | B49: =-400000*0.15 -> -60000 | C49: =200000*0.15 -> 30000 | D49: =-(D27-[2]Pivot!$D$5)*0.6 -> 632499.11 | E49: =SUM(B49:D49) -> 602499.11
A50: 3% higher lab&mat impact | B50: =0.06*B27 -> -180023.27 | E50: =SUM(B50:D50) -> -180023.27
A51: Mfg INDL | C51: =[2]Pivot!$C$11-C33 -> 46665.47 | E51: =SUM(B51:D51) -> 46665.47
A52: =A34 -> 4. Mfg OVHD | C52: =[2]Pivot!$C$13-C34 -> -42819.1 | E52: =SUM(B52:D52) -> -42819.1
A53: Admin | C53: =-(C36-[2]Pivot!$C$15) -> 101912.74 | E53: =SUM(B53:D53) -> 101912.74 | F53: 74k bonus not in 2026, also -14k credit in 2026
A54: Scrap&Misc | C54: =C40-[2]Pivot!$C$19-[2]Pivot!$C$20 -> -10790.67 | D54: =-D40+[2]Pivot!$D$19 -> 39376.5 | E54: =SUM(B54:D54) -> 28585.83
A55: Frt Inc | B55: 20000 | C55: 16000 | E55: =SUM(B55:D55) -> 36000
B56: =SUM(B49:B55) -> -220023.27 | C56: =SUM(C49:C55) -> 140968.44 | D56: =SUM(D49:D55) -> 671875.61 | E56: =SUM(E49:E55) -> 592820.78
A58: miscellaneous income of $12,000 is for a premium we paid employees to work Saturdays for several months this year to get more Pixelle products produced and get backorders filled. Pixelle agreed to reimburse us for those costs.

Sheet 26 EBITDA ADJ
A2: TYPE | B2: IS
A3: HCF FINANCIALS HY1 2026 | L3: Adjustment Calcs | N3: Pixelle | O3: =N3 -> Pixelle | Q3: 2026 6Months | X3: Orignal | Y3: Adjusted | AB3: 2026 12Months
A4: Sum of NET_CHANGE | B4: Column Labels | N4: Adjustment | O4: Adj 2026 HY1 | S4: Adjusted | T4: 2026 Adj 5Days | V4: Adjusted EBITDA | W4: 2026 6Mo | X4: Annualized | Y4: Annualized | Z4: Diff | AD4: Adjusted | AE4: 2026 Adj 5Days
A5: Row Labels | B5: Angola | C5: Hillsboro | D5: Pixelle | E5: Grand Total | F5: Original | G5: =B5 -> Angola | H5: =C5 -> Hillsboro | I5: =D5 -> Pixelle | J5: Total | L5: Adjust 6days vs 5 days | N5: Avg/Day | O5: 5Days Sls | Q5: =B5 -> Angola | R5: =C5 -> Hillsboro | S5: =D5 -> Pixelle | T5: =E5 -> Grand Total | W5: Original | AB5: =M5 -> 0 | AC5: =N5 -> Avg/Day | AD5: =O5 -> 5Days Sls | AE5: =P5 -> 0
A6: 1. Sales | B6: -1500193.9 | C6: -2232833 | D6: -962160.67 | E6: -4695187.6 | G6: % of Sales Totals | L6: Sales if 5Days | N6: =D6+O6 -> -91884.67 | O6: =435138*2 -> 870276 | Q6: =B6 -> -1500193.9 | R6: =C6 -> -2232833 | S6: =-O6 -> -870276 | T6: =SUM(Q6:S6) -> -4603303 | U6: =T6*2 -> -9206605.9 | V6: Net Profit | W6: =F22 -> 467828 | X6: =W6*2 -> 935656 | AB6: =Q6*2 -> -3000387.9 | AC6: =R6*2 -> -4465666.1 | AD6: 1800000 | AE6: =SUM(AB6:AD6) -> -5666053.9
A7: 2. Variable cost Labor | B7: 343188.12 | C7: 498256.51 | D7: 315753.08 | E7: 1157197.7 | G7: =-B7/B$6 -> 0.2287625 | H7: =-C7/C$6 -> 0.22314992 | I7: =-D7/D$6 -> 0.32817084 | J7: =-E7/E$6 -> 0.24646464 | N7: =5/6 -> 0.83333333 | O7: =N7*551308 -> 459423.33 | Q7: =B7 -> 343188.12 | R7: =C7 -> 498256.51 | S7: =D7 -> 315753.08 | T7: =SUM(Q7:S7) -> 1157197.7 | U7: =T7*2 -> 2314395.4 | V7: Deduct Debt Forgiveness | W7: =-'[3]2-T5Y IS (Cont.)'!$D$66 -> -133786 | X7: =W7*2 -> -267572 | AB7: =Q7*2 -> 686376.24 | AC7: =R7*2 -> 996513.02 | AD7: =O7 -> 459423.33 | AE7: =SUM(AB7:AD7) -> 2142312.6
A8: 2. Variable cost Mat | B8: 855851.1 | C8: 1143410.8 | D8: 22188.07 | E8: 2021450 | G8: =-B8/B$6 -> 0.57049364 | H8: =-C8/C$6 -> 0.5120897 | I8: =-D8/D$6 -> 0.02306067 | J8: =-E8/E$6 -> 0.43053657 | O8: 410852 | Q8: =B8 -> 855851.1 | R8: =C8 -> 1143410.8 | S8: =D8 -> 22188.07 | T8: =SUM(Q8:S8) -> 2021450 | U8: =T8*2 -> 4042899.9 | V8: Net Profit after Debt Adj | W8: =W6+W7 -> 334042 | X8: =W8*2 -> 668084 | Y8: =T23 -> 487883.82 | Z8: =Y8-X8 -> -180200.18 | AB8: =Q8*2 -> 1711702.2 | AC8: =R8*2 -> 2286821.6 | AD8: =O8 -> 410852 | AE8: =SUM(AB8:AD8) -> 4409375.8
A9: 2a. Variable cost Mat | C9: -19607.13 | E9: -19607.13 | G9: =-B9/B$6 -> 0 | H9: =-C9/C$6 -> -0.0087812791 | I9: =-D9/D$6 -> 0 | J9: =-E9/E$6 -> -0.0041760056 | O9: =AVERAGE(O7:O9) -> 0 | Q9: =B9 -> 0 | R9: =C9 -> -19607.13 | S9: =D9 -> 0 | T9: =SUM(Q9:S9) -> -19607.13 | U9: =T9*2 -> -39214.26 | V9: Add back Interest Expense/Inc | W9: ='SORTED B VS P'!N288+'SORTED B VS P'!M292 -> 1784.75 | X9: =W9*2 -> 3569.5 | Y9: =X9 -> 3569.5 | Z9: =Y9-X9 -> 0 | AB9: =Q9*2 -> 0 | AC9: =R9*2 -> -39214.26 | AD9: =O9 -> 0 | AE9: =SUM(AB9:AD9) -> -19607.13
A10: 2a. Variable cost Mat Out/Env | C10: 11708.17 | E10: 11708.17 | G10: =-B10/B$6 -> 0 | H10: =-C10/C$6 -> 0.0052436388 | I10: =-D10/D$6 -> 0 | J10: =-E10/E$6 -> 0.0024936533 | Q10: =B10 -> 0 | R10: =C10 -> 11708.17 | S10: =D10 -> 0 | T10: =SUM(Q10:S10) -> 11708.17 | U10: =T10*2 -> 23416.34 | V10: Add back Depreciation | W10: =('SORTED B VS P'!N195+'SORTED B VS P'!N196+'SORTED B VS P'!N197+'SORTED B VS P'!N198+'SORTED B VS P'!N199+'SORTED B VS P'!N200+'SORTED B VS P'!N201+'SORTED B VS P'!N202++'SORTED B VS P'!N203+'SORTED B VS P'!N204) -> 106590.78 | X10: =W10*2 -> 213181.56 | Y10: =X10 -> 213181.56 | Z10: =Y10-X10 -> 0 | AB10: =Q10*2 -> 0 | AC10: =R10*2 -> 23416.34 | AD10: =O10 -> 0 | AE10: =SUM(AB10:AD10) -> 23416.34
A11: 8c. Frt Exp | B11: 5732.8 | C11: 7801.63 | E11: 13534.43 | G11: =-B11/B$6 -> 0.0038213726 | H11: =-C11/C$6 -> 0.0034940499 | I11: =-D11/D$6 -> 0 | J11: =-E11/E$6 -> 0.0028826175 | Q11: =B11 -> 5732.8 | R11: =C11 -> 7801.63 | S11: =D11 -> 0 | T11: =SUM(Q11:S11) -> 13534.43 | U11: =T11*2 -> 27068.86 | V11: Estimated Fair Market Rent | W11: =-90000/2 -> -45000 | X11: =W11*2 -> -90000 | Y11: =-AA33 -> -66414 | Z11: =Y11-X11 -> 23586 | AB11: =Q11*2 -> 11465.6 | AC11: =R11*2 -> 15603.26 | AD11: =O11 -> 0 | AE11: =SUM(AB11:AD11) -> 27068.86
A12: 3. Mfg IDL | B12: 87123.01 | C12: 115278.5 | D12: 12414.36 | E12: 214815.87 | G12: =-B12/B$6 -> 0.058074498 | H12: =-C12/C$6 -> 0.051628805 | I12: =-D12/D$6 -> 0.012902585 | J12: =-E12/E$6 -> 0.04575235 | L12: CREDIT PIXELLE | N12: -41085 | O12: =D12-N12 -> 53499.36 | Q12: =B12 -> 87123.01 | R12: =C12 -> 115278.5 | S12: =D12 -> 12414.36 | T12: =SUM(Q12:S12) -> 214815.87 | U12: =T12*2 -> 429631.74 | V12: Add back Bank Charges② | W12: ='SORTED B VS P'!N212 -> 17884.74 | X12: =W12*2 -> 35769.48 | Y12: =X12 -> 35769.48 | Z12: =Y12-X12 -> 0 | AB12: =Q12*2 -> 174246.02 | AC12: =R12*2 -> 230557 | AE12: =SUM(AB12:AD12) -> 404803.02
A13: 4. Mfg OVHD | B13: 186209.89 | C13: 202999.64 | D13: 82744.57 | E13: 471954.1 | G13: =-B13/B$6 -> 0.12412388 | H13: =-C13/C$6 -> 0.090915728 | I13: =-D13/D$6 -> 0.085998703 | J13: =-E13/E$6 -> 0.10051869 | Q13: =B13 -> 186209.89 | R13: =C13 -> 202999.64 | S13: =D13 -> 82744.57 | T13: =SUM(Q13:S13) -> 471954.1 | U13: =T13*2 -> 943908.2 | V13: Add back Bad Debt③ | W13: ='SORTED B VS P'!N209 -> 0 | X13: =W13*2 -> 0 | Y13: =X13 -> 0 | Z13: =Y13-X13 -> 0 | AB13: =Q13*2 -> 372419.78 | AC13: =R13*2 -> 405999.28 | AD13: =O13 -> 0 | AE13: =SUM(AB13:AD13) -> 778419.06
A14: 7. Selling | B14: 36556.54 | C14: 177818.79 | E14: 214375.33 | G14: =-B14/B$6 -> 0.024367876 | H14: =-C14/C$6 -> 0.079638194 | I14: =-D14/D$6 -> 0 | J14: =-E14/E$6 -> 0.045658522 | Q14: =B14 -> 36556.54 | R14: =C14 -> 177818.79 | S14: =D14 -> 0 | T14: =SUM(Q14:S14) -> 214375.33 | U14: =T14*2 -> 428750.66 | V14: Deduct Gain on Sale of Assets | W14: 0 | X14: =W14*2 -> 0 | Y14: =X14 -> 0 | Z14: =Y14-X14 -> 0 | AB14: =Q14*2 -> 73113.08 | AC14: =R14*2 -> 355637.58 | AD14: =O14 -> 0 | AE14: =SUM(AB14:AD14) -> 428750.66
A15: 8. Admin | B15: 40430.47 | C15: 340312.03 | D15: 19495.37 | E15: 400237.87 | G15: =-B15/B$6 -> 0.026950162 | H15: =-C15/C$6 -> 0.15241266 | I15: =-D15/D$6 -> 0.020262073 | J15: =-E15/E$6 -> 0.085244276 | Q15: =B15 -> 40430.47 | R15: =C15 -> 340312.03 | S15: =D15 -> 19495.37 | T15: =SUM(Q15:S15) -> 400237.87 | U15: =T15*2 -> 800475.74 | V15: Deduct EXCESS Purchase Discounts | W15: 0 | X15: =W15*2 -> 0 | Y15: =X15 -> 0 | Z15: =Y15-X15 -> 0 | AB15: =Q15*2 -> 80860.94 | AC15: =R15*2 -> 680624.06 | AD15: =O15 -> 0 | AE15: =SUM(AB15:AD15) -> 761485
A16: 8. Admin IT | B16: 971.64 | C16: 12346.79 | D16: 825.31 | E16: 14143.74 | G16: =-B16/B$6 -> 0.00064767626 | H16: =-C16/C$6 -> 0.0055296522 | I16: =-D16/D$6 -> 0.00085776734 | J16: =-E16/E$6 -> 0.0030123908 | Q16: =B16 -> 971.64 | R16: =C16 -> 12346.79 | S16: =D16 -> 825.31 | T16: =SUM(Q16:S16) -> 14143.74 | U16: =T16*2 -> 28287.48 | V16: Deduct Other Income④ | W16: 0 | X16: =W16*2 -> 0 | Y16: =X16 -> 0 | Z16: =Y16-X16 -> 0 | AB16: =Q16*2 -> 1943.28 | AC16: =R16*2 -> 24693.58 | AD16: =O16 -> 0 | AE16: =SUM(AB16:AD16) -> 26636.86
A17: 8a. Frt Income | B17: -186087.68 | C17: -145148.52 | E17: -331236.2 | F17: how does this tie if Fordyce not in TB? | G17: =-B17/B$6 -> -0.12404242 | H17: =-C17/C$6 -> -0.065006437 | I17: =-D17/D$6 -> 0 | J17: =-E17/E$6 -> -0.070548022 | Q17: =B17 -> -186087.68 | R17: =C17 -> -145148.52 | S17: =D17 -> 0 | T17: =SUM(Q17:S17) -> -331236.2 | U17: =T17*2 -> -662472.4 | V17: Add back Est. Owners' Perqs | W17: 50000 | X17: =W17*2 -> 100000 | Y17: =X17 -> 100000 | Z17: =Y17-X17 -> 0 | AB17: =Q17*2 -> -372175.36 | AC17: =R17*2 -> -290297.04 | AD17: =O17 -> 0 | AE17: =SUM(AB17:AD17) -> -662472.4
A18: 8b. Frt Exp | B18: 145827.64 | C18: 125457.9 | E18: 271285.54 | G18: =-B18/B$6 -> 0.097205859 | H18: =-C18/C$6 -> 0.056187766 | I18: =-D18/D$6 -> 0 | J18: =-E18/E$6 -> 0.057779489 | Q18: =B18 -> 145827.64 | R18: =C18 -> 125457.9 | S18: =D18 -> 0 | T18: =SUM(Q18:S18) -> 271285.54 | U18: =T18*2 -> 542571.08 | V18: Estimated Fair Market Rent NNN | X18: =W18*2 -> 0 | Y18: =X18 -> 0 | Z18: =Y18-X18 -> 0 | AB18: =Q18*2 -> 291655.28 | AC18: =R18*2 -> 250915.8 | AD18: =O18 -> 0 | AE18: =SUM(AB18:AD18) -> 542571.08
A19: 9. Scrap & Misc Inc | B19: -2555.07 | C19: -56104.61 | D19: -21843 | E19: -80502.68 | G19: =-B19/B$6 -> -0.0017031598 | H19: =-C19/C$6 -> -0.025127096 | I19: =-D19/D$6 -> -0.02270203 | J19: =-E19/E$6 -> -0.017145786 | Q19: =B19 -> -2555.07 | R19: =C19 -> -56104.61 | S19: =D19 -> -21843 | T19: =SUM(Q19:S19) -> -80502.68 | U19: =T19*2 -> -161005.36 | V19: Pixelle Abnormal Sales Q1 | X19: =W19*2 -> 0 | Y19: =X19 -> 0 | Z19: =Y19-X19 -> 0 | AB19: =Q19*2 -> -5110.14 | AC19: =R19*2 -> -112209.22 | AD19: =O19 -> 0 | AE19: =SUM(AB19:AD19) -> -117319.36
A20: 91. Other Inc/Exp | B20: 4.33 | C20: -132001.55 | E20: -131997.22 | G20: =-B20/B$6 -> 2.8862935e-06 | H20: =-C20/C$6 -> -0.059118415 | I20: =-D20/D$6 -> 0 | J20: =-E20/E$6 -> -0.0281133 | Q20: =B20 -> 4.33 | R20: 0 | S20: =D20 -> 0 | T20: =SUM(Q20:S20) -> 4.33 | X20: =W20*2 -> 0 | Y20: =X20 -> 0 | Z20: =Y20-X20 -> 0 | AB20: =Q20*2 -> 8.66 | AC20: =R20*2 -> 0 | AD20: =O20 -> 0 | AE20: =SUM(AB20:AD20) -> 8.66
A21: 99. Elim | B21: 0 | C21: 0 | D21: 0 | E21: 0 | G21: =-B21/B$6 -> 0 | H21: =-C21/C$6 -> 0 | I21: =-D21/D$6 -> 0 | J21: =-E21/E$6 -> 0 | Q21: =B21 -> 0 | R21: =C21 -> 0 | T21: =SUM(Q21:S21) -> 0 | X21: =W21*2 -> 0 | Y21: =X21 -> 0 | Z21: =Y21-X21 -> 0 | AB21: =Q21*2 -> 0 | AC21: =R21*2 -> 0 | AE21: =SUM(AB21:AD21) -> 0
A22: Grand Total | B22: 13058.86 | C22: 49695.92 | D22: -530582.91 | E22: -467828.13 | F22: ='[3]2-T5Y IS (Cont.)'!$D$70 -> 467828 | G22: =-B22/B$6 -> 0.0087047813 | H22: =-C22/C$6 -> 0.02225689 | I22: =-D22/D$6 -> -0.55144939 | J22: =-E22/E$6 -> -0.099639922 | Q22: =SUM(Q6:Q21) -> 13058.86 | R22: =SUM(R6:R21) -> 181697.47 | S22: =SUM(S6:S21) -> -438698.24 | T22: =SUM(T6:T21) -> -243941.91 | U22: =SUM(U6:U21) -> -487892.48 | X22: =W22*2 -> 0 | Y22: =X22 -> 0 | Z22: =Y22-X22 -> 0 | AB22: =SUM(AB6:AB21) -> 26117.72 | AC22: =SUM(AC6:AC21) -> 363394.94 | AD22: =SUM(AD6:AD21) -> -438698.24 | AE22: =SUM(AE6:AE21) -> -243941.91
A23: 26 Annualized (minus debt forgive) | B23: =-B22*2 -> -26117.72 | C23: =-(C22-C20)*2 -> -363394.94 | D23: =-D22*2 -> 1061165.8 | E23: =-(E22-E20)*2 -> 671661.82 | F23: =(F22+C20)*2 -> 671652.9 | L23: Total Adj | N23: =N6+N12 -> -132969.67 | Q23: =-Q22*2 -> -26117.72 | R23: =-R22*2 -> -363394.94 | S23: =-S22*2 -> 877396.48 | T23: =-T22*2 -> 487883.82 | U23: =-U22*2 -> 975784.96 | V23: Adjusted EBITDA | W23: =SUM(W8:W22) -> 465302.27 | X23: =SUM(X8:X22) -> 930604.54 | Y23: =SUM(Y8:Y22) -> 773990.36 | Z23: =Y23-X23 -> -156614.18 | AB23: =-AB22*2 -> -52235.44 | AC23: =-AC22*2 -> -726789.88 | AD23: =-AD22*2 -> 877396.48 | AE23: =-AE22*2 -> 487883.82
A24: 2025 | B24: =[2]Pivot!B$22 -> -188567.02 | C24: =[2]Pivot!C$22 -> 507482.26 | D24: =[2]Pivot!D$22 -> -393948.69 | E24: =[2]Pivot!E$22 -> -75033.45 | F24: =E22-C20 -> -335826.58 | Q24: Difference | T24: =T23-E23 -> -183778 | V24: Valuation 3.5x | X24: =3.5*X23 -> 3257115.9 | Y24: =3.5*Y23 -> 2708966.3 | Z24: =Y24-X24 -> -548149.63 | AB24: Difference | AE24: =AE23-P23 -> -183778
V25: Red-RENT Need to validate still
A26: Estimated Jun2026 Full Yr to Full Yr 2025 | G26: 2026 % Change toi 2025 | Q26: Pixelle Sales Adjusted by 100k Q1 & 100k HY2 = 200k
A27: =A6 -> 1. Sales | B27: =B6*2 -> -3000387.9 | C27: =C6*2 -> -4465666.1 | D27: =D6*2 -> -1924321.3 | E27: =E6*2 -> -9390375.3 | G27: =B27/[2]Pivot!B5-1 -> -0.11822123 | H27: =C27/[2]Pivot!C5-1 -> 0.048125645 | I27: =D27/[2]Pivot!D5-1 -> 1.2114667 | J27: =E27/[2]Pivot!E5-1 -> 0.10042202 | Q27: essentially no cost reductions 2025&2026 cost same
A28: =A7 -> 2. Variable cost Labor | B28: =B7*2 -> 686376.24 | C28: =C7*2 -> 996513.02 | D28: =D7*2 -> 631506.16 | E28: =E7*2 -> 2314395.4 | G28: =G7-[2]Pivot!F6 -> 0.027699236 | H28: =H7-[2]Pivot!G6 -> -0.00066119334 | I28: =I7-[2]Pivot!H6 -> -0.017588737 | J28: =J7-[2]Pivot!I6 -> 0.019288972 | L28: $12,000 is for a premium we paid employees to work Saturdays | Q28: 41k Pixelle credit x 2 = 82k full year adjsuted
A29: =A8 -> 2. Variable cost Mat | B29: =B8*2 -> 1711702.2 | C29: =C8*2 -> 2286821.6 | D29: =D8*2 -> 44376.14 | E29: =E8*2 -> 4042899.9 | G29: =G8-[2]Pivot!F7 -> 0.028061849 | H29: =H8-[2]Pivot!G7 -> 0.0057809979 | I29: =I8-[2]Pivot!H7 -> -0.0042176288 | J29: =J8-[2]Pivot!I7 -> -0.041329144 | Q29: Need to understand what issues were and what are extra costs | U29: HCF Acquistion | X29: 2026 HY1 | Z29: After
A30: =A9 -> 2a. Variable cost Mat | B30: =B9*2 -> 0 | C30: =C9*2 -> -39214.26 | D30: =D9*2 -> 0 | E30: =E9*2 -> -39214.26 | G30: =G9-[2]Pivot!F8 -> 0 | H30: =H9-[2]Pivot!G8 -> 0.0035708313 | I30: =I9-[2]Pivot!H8 -> 0 | J30: =J9-[2]Pivot!I8 -> 0.0019912278 | Q30: or are they not producing as much and sales would be higher | U30: SYNERGIES | X30: Before | Y30: 2026 Est | Z30: Acqusition | AA30: Adjusmt
A31: =A10 -> 2a. Variable cost Mat Out/Env | B31: =B10*2 -> 0 | C31: =C10*2 -> 23416.34 | D31: =D10*2 -> 0 | E31: =E10*2 -> 23416.34 | G31: =G10-[2]Pivot!F9 -> -0.00015188439 | H31: =H10-[2]Pivot!G9 -> -0.0016654386 | I31: =I10-[2]Pivot!H9 -> 0 | J31: =J10-[2]Pivot!I9 -> -0.001016514
A32: =A11 -> 8c. Frt Exp | B32: =B11*2 -> 11465.6 | C32: =C11*2 -> 15603.26 | D32: =D11*2 -> 0 | E32: =E11*2 -> 27068.86 | G32: =G11-[2]Pivot!F10 -> -0.0010742856 | H32: =H11-[2]Pivot!G10 -> 4.2578791e-05 | I32: =I11-[2]Pivot!H10 -> -0.00010336076 | J32: =J11-[2]Pivot!I10 -> -0.00080330678 | U32: TOTAL SYNERGIES
A33: =A12 -> 3. Mfg IDL | B33: =B12*2 -> 174246.02 | C33: =C12*2 -> 230557 | D33: =D12*2 -> 24828.72 | E33: =E12*2 -> 429631.74 | G33: =G12-[2]Pivot!F11 -> 0.006868519 | H33: =H12-[2]Pivot!G11 -> -0.013437409 | I33: =I12-[2]Pivot!H11 -> -0.10173113 | J33: =J12-[2]Pivot!I11 -> -0.018841589 | U33: RENT | Y33: =SUM(Y34:Y36) -> 126000 | Z33: =SUM(Z34:Z36) -> 192414 | AA33: =SUM(AA34:AA36) -> 66414
A34: =A13 -> 4. Mfg OVHD | B34: =B13*2 -> 372419.78 | C34: =C13*2 -> 405999.28 | D34: =D13*2 -> 165489.14 | E34: =E13*2 -> 943908.2 | G34: =G13-[2]Pivot!F13 -> 0.010265792 | H34: =H13-[2]Pivot!G13 -> 0.005674589 | I34: =I13-[2]Pivot!H13 -> -0.074265473 | J34: =J13-[2]Pivot!I13 -> -0.0037834038 | U34: Rent | V34: Hillsboro | X34: 0 | Z34: 151914 | AA34: 151914
A35: =A14 -> 7. Selling | B35: =B14*2 -> 73113.08 | C35: =C14*2 -> 355637.58 | D35: =D14*2 -> 0 | E35: =E14*2 -> 428750.66 | G35: =G14-[2]Pivot!F14 -> 0.002703289 | H35: =H14-[2]Pivot!G14 -> -0.009789405 | I35: =I14-[2]Pivot!H14 -> 0 | J35: =J14-[2]Pivot!I14 -> -0.0076300312 | U35: Rent | V35: Angola | X35: 48000 | Y35: 96000 | Z35: 0 | AA35: -96000
A36: =A15 -> 8. Admin | B36: =B15*2 -> 80860.94 | C36: =C15*2 -> 680624.06 | D36: =D15*2 -> 38990.74 | E36: =E15*2 -> 800475.74 | G36: =G15-[2]Pivot!F15 -> -0.00065113526 | H36: =H15-[2]Pivot!G15 -> -0.03125465 | I36: =I15-[2]Pivot!H15 -> -0.017910397 | J36: =J15-[2]Pivot!I15 -> -0.021356514 | U36: Rent | V36: Fordyce | X36: 15000 | Y36: 30000 | Z36: 40500 | AA36: 10500
A37: =A16 -> 8. Admin IT | B37: =B16*2 -> 1943.28 | C37: =C16*2 -> 24693.58 | D37: =D16*2 -> 1650.62 | E37: =E16*2 -> 28287.48 | G37: =G16-[2]Pivot!F16 -> -0.00016828979 | H37: =H16-[2]Pivot!G16 -> 0.00081743291 | I37: =I16-[2]Pivot!H16 -> -0.00083706638 | J37: =J16-[2]Pivot!I16 -> 0.00016146245
A38: =A17 -> 8a. Frt Income | B38: =B17*2 -> -372175.36 | C38: =C17*2 -> -290297.04 | D38: =D17*2 -> 0 | E38: =E17*2 -> -662472.4 | G38: =G17-[2]Pivot!F17 -> -0.033929055 | H38: =H17-[2]Pivot!G17 -> 0.00080304336 | I38: =I17-[2]Pivot!H17 -> 0 | J38: =J17-[2]Pivot!I17 -> -0.0017581263
A39: =A18 -> 8b. Frt Exp | B39: =B18*2 -> 291655.28 | C39: =C18*2 -> 250915.8 | D39: =D18*2 -> 0 | E39: =E18*2 -> 542571.08 | G39: =G18-[2]Pivot!F18 -> 0.024880993 | H39: =H18-[2]Pivot!G18 -> 0.0037073921 | I39: =I18-[2]Pivot!H18 -> 0 | J39: =J18-[2]Pivot!I18 -> 0.002737681
A40: =A19 -> 9. Scrap & Misc Inc | B40: =B19*2 -> -5110.14 | C40: =C19*2 -> -112209.22 | D40: =D19*2 -> -43686 | E40: =E19*2 -> -161005.36 | F40: 12k sale of asset? | G40: =G19-[2]Pivot!F19 -> -0.00038598201 | H40: =H19-[2]Pivot!G19 -> 0.0021395681 | I40: =I19-[2]Pivot!H19 -> -0.01774947 | J40: =J19-[2]Pivot!I19 -> -0.0025016967
A41: =A20 -> 91. Other Inc/Exp | B41: =B20*2 -> 8.66 | C41: 0 | D41: =D20*2 -> 0 | E41: 0 | G41: =G20-[2]Pivot!F20 -> 3.3682703e-06 | H41: 0 | I41: =I20-[2]Pivot!H20 -> 0 | J41: =J20-[2]Pivot!I20 -> -0.029842116
A42: =A21 -> 99. Elim | B42: =B21*2 -> 0 | C42: =C21*2 -> 0 | D42: =D21*2 -> 0 | E42: =E21*2 -> 0 | G42: =G21-[2]Pivot!F21 -> 0 | H42: =H21-[2]Pivot!G21 -> 0 | I42: =I21-[2]Pivot!H21 -> 0 | J42: =J21-[2]Pivot!I21 -> 0
A43: =A22 -> Grand Total | B43: =SUM(B27:B42) -> 26117.72 | C43: =SUM(C27:C42) -> 363394.94 | D43: =SUM(D27:D42) -> -1061165.8 | E43: =SUM(E27:E42) -> -671661.82 | G43: =G22-[2]Pivot!F22 -> 0.064122415 | H43: =H22-[2]Pivot!G22 -> -0.096853039 | I43: =I22-[2]Pivot!H22 -> -0.098716062 | J43: =J22-[2]Pivot!I22 -> -0.09084704
A44: 2026 Estimate | B44: =-B43 -> -26117.72 | C44: =-C43 -> -363394.94 | D44: =-D43 -> 1061165.8 | E44: =-E43 -> 671661.82
A45: 2025 | B45: =-[2]Pivot!B$22 -> 188567.02 | C45: =-[2]Pivot!C$22 -> -507482.26 | D45: =-[2]Pivot!D$22 -> 393948.69 | E45: =-[2]Pivot!E$22 -> 75033.45
A46: Extra profit (loss) | B46: =B44-B45 -> -214684.74 | C46: =C44-C45 -> 144087.32 | D46: =D44-D45 -> 667217.13 | E46: =E44-E45 -> 596628.37
A48: EXPLANATION
A49: Sales | B49: =-400000*0.15 -> -60000 | C49: =200000*0.15 -> 30000 | D49: =-(D27-[2]Pivot!$D$5)*0.6 -> 632499.11 | E49: =SUM(B49:D49) -> 602499.11
A50: 3% higher lab&mat impact | B50: =0.06*B27 -> -180023.27 | E50: =SUM(B50:D50) -> -180023.27
A51: Mfg INDL | C51: =[2]Pivot!$C$11-C33 -> 46665.47 | E51: =SUM(B51:D51) -> 46665.47
A52: =A34 -> 4. Mfg OVHD | C52: =[2]Pivot!$C$13-C34 -> -42819.1 | E52: =SUM(B52:D52) -> -42819.1
A53: Admin | C53: =-(C36-[2]Pivot!$C$15) -> 101912.74 | E53: =SUM(B53:D53) -> 101912.74 | F53: 74k bonus not in 2026, also -14k credit in 2026
A54: Scrap&Misc | C54: =C40-[2]Pivot!$C$19-[2]Pivot!$C$20 -> -10790.67 | D54: =-D40+[2]Pivot!$D$19 -> 39376.5 | E54: =SUM(B54:D54) -> 28585.83
A55: Frt Inc | B55: 20000 | C55: 16000 | E55: =SUM(B55:D55) -> 36000
B56: =SUM(B49:B55) -> -220023.27 | C56: =SUM(C49:C55) -> 140968.44 | D56: =SUM(D49:D55) -> 671875.61 | E56: =SUM(E49:E55) -> 592820.78
A58: miscellaneous income of $12,000 is for a premium we paid employees to work Saturdays for several months this year to get more Pixelle products produced and get backorders filled. Pixelle agreed to reimburse us for those costs.

Sheet Pivot
A1: TYPE | B1: IS | K1: TYPE | L1: IS
S2: Half YR | Y2: Full YR
A3: Sum of NET_CHANGE | B3: Column Labels | K3: Sum of NET_CHANGE | L3: Column Labels | S3: Current w/ Allocated Corp 100% to Hillsboro | Y3: BEFORE Acquire | AA3: AFTER Acquire | AG3: BEFORE | AI3: AFTER Acquire
A4: Row Labels | B4: Angola | C4: Hillsboro | D4: Pixelle | E4: Grand Total | F4: =B4 -> Angola | G4: =C4 -> Hillsboro | H4: =D4 -> Pixelle | I4: Total | K4: Row Labels | L4: Angola | M4: Hillsboro | N4: Pixelle | O4: Corp | P4: Grand Total | Q4: Comments | S4: Hills/Ang | T4: =N4 -> Pixelle | U4: Total | V4: =S4 -> Hills/Ang | W4: =T4 -> Pixelle | Y4: Hillsboro | Z4: Synergies | AA4: Hillsboro | AB4: =T4 -> Pixelle | AC4: TOTAL | AE4: Pixelle Higher | AG4: Full Yr No Pix | AH4: =Z4 -> Synergies | AI4: Hillsboro
A5: 1. Sales | B5: -1500193.9 | C5: -2232833 | D5: -962160.67 | E5: -4695187.6 | F5: % of Sales Totals | K5: 1. Sales | L5: -1500193.9 | M5: -2232833 | N5: -962160.67 | O5: 0 | P5: -4695187.6 | S5: =M5+L5 -> -3733027 | T5: =N5 -> -962160.67 | U5: =SUM(S5:T5) -> -4695187.6 | X5: =K5 -> 1. Sales | Y5: =S5*2 -> -7466053.9 | AA5: =Y5+Z5 -> -7466053.9 | AB5: =-450000*2*2 -> -1800000 | AC5: =AA5+AB5 -> -9266053.9 | AE5: =U5*2 -> -9390375.3 | AG5: =-(L5+M5)*2 -> 7466053.9 | AI5: =AG5+AH5 -> 7466053.9
A6: 2. Variable cost Labor | B6: 343188.12 | C6: 498256.51 | D6: 315753.08 | E6: 1157197.7 | F6: =-B6/B$5 -> 0.2287625 | G6: =-C6/C$5 -> 0.22314992 | H6: =-D6/D$5 -> 0.32817084 | I6: =-E6/E$5 -> 0.24646464 | K6: 2. Variable cost Labor | L6: 343188.12 | M6: 498256.51 | N6: 315753.08 | O6: 0 | P6: 1157197.7 | S6: =M6+L6 -> 841444.63 | T6: =N6 -> 315753.08 | U6: =SUM(S6:T6) -> 1157197.7 | V6: =-S6/S$5 -> 0.22540545 | W6: =-T6/T$5 -> 0.32817084 | X6: =K6 -> 2. Variable cost Labor | Y6: =S6*2 -> 1682889.3 | AA6: =Y6+Z6 -> 1682889.3 | AB6: =(T6-U36)*2 -> 611134.28 | AC6: =AA6+AB6 -> 2294023.5 | AE6: =AC6+20000 -> 2314023.5 | AG6: =(L6+M6+O6)*2 -> 1682889.3 | AI6: =AG6+AH6 -> 1682889.3
A7: 2. Variable cost Mat | B7: 855851.1 | C7: 1143410.8 | D7: 22188.07 | E7: 2021450 | F7: =-B7/B$5 -> 0.57049364 | G7: =-C7/C$5 -> 0.5120897 | H7: =-D7/D$5 -> 0.02306067 | I7: =-E7/E$5 -> 0.43053657 | K7: 2. Variable cost Mat | L7: 855851.1 | M7: 1143410.8 | N7: 22188.07 | P7: 2021450 | S7: =M7+L7 -> 1999261.9 | T7: =N7 -> 22188.07 | U7: =SUM(S7:T7) -> 2021450 | V7: =-S7/S$5 -> 0.53556053 | W7: =-T7/T$5 -> 0.02306067 | X7: =K7 -> 2. Variable cost Mat | Y7: =S7*2 -> 3998523.8 | Z7: =Synergies!H44 -> -243478.01 | AA7: =Y7+Z7 -> 3755045.8 | AB7: =T7*2 -> 44376.14 | AC7: =AA7+AB7 -> 3799421.9 | AE7: =AC7 -> 3799421.9 | AG7: =(L7+M7+O7)*2 -> 3998523.8 | AH7: =Synergies!H44 -> -243478.01 | AI7: =AG7+AH7 -> 3755045.8 | AJ7: Paper Synergies
A8: 2a. Variable cost Mat | C8: -19607.13 | E8: -19607.13 | F8: =-B8/B$5 -> 0 | G8: =-C8/C$5 -> -0.0087812791 | H8: =-D8/D$5 -> 0 | I8: =-E8/E$5 -> -0.0041760056 | K8: 2a. Variable cost Mat | O8: -19607.13 | P8: -19607.13 | Q8: ALL Purch Discts | S8: =O8 -> -19607.13 | T8: =N8 -> 0 | U8: =SUM(S8:T8) -> -19607.13 | V8: =-S8/S$5 -> -0.0052523409 | W8: =-T8/T$5 -> 0 | X8: =K8 -> 2a. Variable cost Mat | Y8: =S8*2 -> -39214.26 | AA8: =Y8+Z8 -> -39214.26 | AB8: =T8*2 -> 0 | AC8: =AA8+AB8 -> -39214.26 | AE8: =AC8 -> -39214.26 | AG8: =(L8+M8+O8)*2 -> -39214.26 | AI8: =AG8+AH8 -> -39214.26
A9: 2a. Variable cost Mat Out/Env | C9: 11708.17 | E9: 11708.17 | F9: =-B9/B$5 -> 0 | G9: =-C9/C$5 -> 0.0052436388 | H9: =-D9/D$5 -> 0 | I9: =-E9/E$5 -> 0.0024936533 | K9: 8c. Frt Exp | L9: 5732.8 | M9: 7767.41 | O9: 34.22 | P9: 13534.43 | S9: =M9+L9+O9 -> 13534.43 | T9: =N9 -> 0 | U9: =SUM(S9:T9) -> 13534.43 | V9: =-S9/S$5 -> 0.0036255913 | W9: =-T9/T$5 -> 0 | X9: =K9 -> 8c. Frt Exp | Y9: =S9*2 -> 27068.86 | AA9: =Y9+Z9 -> 27068.86 | AB9: =T9*2 -> 0 | AC9: =AA9+AB9 -> 27068.86 | AE9: =AC9 -> 27068.86 | AG9: =(L9+M9+O9)*2 -> 27068.86 | AI9: =AG9+AH9 -> 27068.86
A10: 8c. Frt Exp | B10: 5732.8 | C10: 7801.63 | E10: 13534.43 | F10: =-B10/B$5 -> 0.0038213726 | G10: =-C10/C$5 -> 0.0034940499 | H10: =-D10/D$5 -> 0 | I10: =-E10/E$5 -> 0.0028826175 | K10: 3. Mfg IDL | L10: 87123.01 | M10: 66748.99 | N10: 12414.36 | O10: 48529.51 | P10: 214815.87 | Q10: Super Sal - Who? | S10: =M10+L10+O10 -> 202401.51 | T10: =N10 -> 12414.36 | U10: =SUM(S10:T10) -> 214815.87 | V10: =-S10/S$5 -> 0.05421914 | W10: =-T10/T$5 -> 0.012902585 | X10: =K10 -> 3. Mfg IDL | Y10: =S10*2 -> 404803.02 | Z10: =-S51-S52 -> -82160 | AA10: =Y10+Z10 -> 322643.02 | AB10: =T10*2 -> 24828.72 | AC10: =AA10+AB10 -> 347471.74 | AE10: =AC10 -> 347471.74 | AG10: =(L10+M10+O10)*2 -> 404803.02 | AH10: =-S51-S52 -> -82160 | AI10: =AG10+AH10 -> 322643.02 | AJ10: IDL Synergies
A11: 3. Mfg IDL | B11: 87123.01 | C11: 115278.5 | D11: 12414.36 | E11: 214815.87 | F11: =-B11/B$5 -> 0.058074498 | G11: =-C11/C$5 -> 0.051628805 | H11: =-D11/D$5 -> 0.012902585 | I11: =-E11/E$5 -> 0.04575235 | K11: 4. Mfg OVHD | L11: 186209.89 | M11: 196237.06 | N11: 82744.57 | O11: 6762.58 | P11: 471954.1 | S11: =M11+L11+O11 -> 389209.53 | T11: =N11 -> 82744.57 | U11: =SUM(S11:T11) -> 471954.1 | V11: =-S11/S$5 -> 0.10426111 | W11: =-T11/T$5 -> 0.085998703 | X11: =K11 -> 4. Mfg OVHD | Y11: =S11*2 -> 778419.06 | Z11: =-S50-S47-S45 -> -208158.76 | AA11: =Y11+Z11 -> 570260.3 | AB11: =T11*2 -> 165489.14 | AC11: =AA11+AB11 -> 735749.44 | AE11: =AC11 -> 735749.44 | AG11: =(L11+M11+O11)*2 -> 778419.06 | AH11: =-S50-S47-S45 -> -208158.76 | AI11: =AG11+AH11 -> 570260.3 | AJ11: OHD Synergies
A12: 4. Mfg OVHD | B12: 186209.89 | C12: 202999.64 | D12: 82744.57 | E12: 471954.1 | F12: =-B12/B$5 -> 0.12412388 | G12: =-C12/C$5 -> 0.090915728 | H12: =-D12/D$5 -> 0.085998703 | I12: =-E12/E$5 -> 0.10051869 | K12: 7. Selling | L12: 36556.54 | M12: 91.2 | O12: 177727.59 | P12: 214375.33 | Q12: Repairs | S12: =M12+L12+O12 -> 214375.33 | T12: =N12 -> 0 | U12: =SUM(S12:T12) -> 214375.33 | V12: =-S12/S$5 -> 0.057426676 | W12: =-T12/T$5 -> 0 | X12: =K12 -> 7. Selling | Y12: =S12*2 -> 428750.66 | AA12: =Y12+Z12 -> 428750.66 | AB12: =T12*2 -> 0 | AC12: =AA12+AB12 -> 428750.66 | AE12: =AC12 -> 428750.66 | AG12: =(L12+M12+O12)*2 -> 428750.66 | AI12: =AG12+AH12 -> 428750.66
A13: 7. Selling | B13: 36556.54 | C13: 177818.79 | E13: 214375.33 | F13: =-B13/B$5 -> 0.024367876 | G13: =-C13/C$5 -> 0.079638194 | H13: =-D13/D$5 -> 0 | I13: =-E13/E$5 -> 0.045658522 | K13: 8. Admin | L13: 40430.47 | M13: 88731 | N13: 19495.37 | O13: 251581.03 | P13: 400237.87 | S13: =M13+L13+(O13) -> 380742.5 | T13: =N13 -> 19495.37 | U13: =SUM(S13:T13) -> 400237.87 | V13: =-S13/S$5 -> 0.10199297 | W13: =-T13/T$5 -> 0.020262073 | X13: =K13 -> 8. Admin | Y13: =S13*2 -> 761485 | Z13: =-S48-S49-S46 -> -116142.92 | AA13: =Y13+Z13 -> 645342.08 | AB13: =T13*2 -> 38990.74 | AC13: =AA13+AB13 -> 684332.82 | AE13: =AC13 -> 684332.82 | AG13: =(L13+M13+O13)*2 -> 761485 | AH13: =-S48-S49-S46 -> -116142.92 | AI13: =AG13+AH13 -> 645342.08 | AJ13: ADMIN Synergies
A14: 8. Admin | B14: 40430.47 | C14: 340312.03 | D14: 19495.37 | E14: 400237.87 | F14: =-B14/B$5 -> 0.026950162 | G14: =-C14/C$5 -> 0.15241266 | H14: =-D14/D$5 -> 0.020262073 | I14: =-E14/E$5 -> 0.085244276 | K14: 8. Admin IT | L14: 971.64 | N14: 825.31 | O14: 12346.79 | P14: 14143.74 | S14: =M14+L14+O14 -> 13318.43 | T14: =N14 -> 825.31 | U14: =SUM(S14:T14) -> 14143.74 | V14: =-S14/S$5 -> 0.0035677294 | W14: =-T14/T$5 -> 0.00085776734 | X14: =K14 -> 8. Admin IT | Y14: =S14*2 -> 26636.86 | AA14: =Y14+Z14 -> 26636.86 | AB14: =T14*2 -> 1650.62 | AC14: =AA14+AB14 -> 28287.48 | AE14: =AC14 -> 28287.48 | AG14: =(L14+M14+O14)*2 -> 26636.86 | AI14: =AG14+AH14 -> 26636.86
A15: 8. Admin IT | B15: 971.64 | C15: 12346.79 | D15: 825.31 | E15: 14143.74 | F15: =-B15/B$5 -> 0.00064767626 | G15: =-C15/C$5 -> 0.0055296522 | H15: =-D15/D$5 -> 0.00085776734 | I15: =-E15/E$5 -> 0.0030123908 | K15: 8a. Frt Income | L15: -186087.68 | M15: -145148.52 | P15: -331236.2 | S15: =M15+L15 -> -331236.2 | T15: =N15 -> 0 | U15: =SUM(S15:T15) -> -331236.2 | V15: =-S15/S$5 -> -0.088731264 | W15: =-T15/T$5 -> 0 | X15: =K15 -> 8a. Frt Income | Y15: =S15*2 -> -662472.4 | AA15: =Y15+Z15 -> -662472.4 | AB15: =T15*2 -> 0 | AC15: =AA15+AB15 -> -662472.4 | AE15: =AC15 -> -662472.4 | AG15: =(L15+M15+O15)*2 -> -662472.4 | AI15: =AG15+AH15 -> -662472.4
A16: 8a. Frt Income | B16: -186087.68 | C16: -145148.52 | E16: -331236.2 | F16: =-B16/B$5 -> -0.12404242 | G16: =-C16/C$5 -> -0.065006437 | H16: =-D16/D$5 -> 0 | I16: =-E16/E$5 -> -0.070548022 | K16: 8b. Frt Exp | L16: 145827.64 | M16: 125457.9 | P16: 271285.54 | S16: =M16+L16 -> 271285.54 | T16: =N16 -> 0 | U16: =SUM(S16:T16) -> 271285.54 | V16: =-S16/S$5 -> 0.072671733 | W16: =-T16/T$5 -> 0 | X16: =K16 -> 8b. Frt Exp | Y16: =S16*2 -> 542571.08 | AA16: =Y16+Z16 -> 542571.08 | AB16: =T16*2 -> 0 | AC16: =AA16+AB16 -> 542571.08 | AE16: =AC16 -> 542571.08 | AG16: =(L16+M16+O16)*2 -> 542571.08 | AI16: =AG16+AH16 -> 542571.08
A17: 8b. Frt Exp | B17: 145827.64 | C17: 125457.9 | E17: 271285.54 | F17: =-B17/B$5 -> 0.097205859 | G17: =-C17/C$5 -> 0.056187766 | H17: =-D17/D$5 -> 0 | I17: =-E17/E$5 -> 0.057779489 | K17: 9. Scrap & Misc Inc | L17: -2555.07 | M17: -53579.61 | N17: -21843 | O17: -2525 | P17: -80502.68 | S17: =M17+L17+O17 -> -58659.68 | T17: =N17+O17 -> -24368 | U17: =SUM(S17:T17) -> -83027.68 | V17: =-S17/S$5 -> -0.015713704 | W17: =-T17/T$5 -> -0.025326331 | X17: =K17 -> 9. Scrap & Misc Inc | Y17: =S17*2 -> -117319.36 | AA17: =Y17+Z17 -> -117319.36 | AB17: =T17*2 -> -48736 | AC17: =AA17+AB17 -> -166055.36 | AE17: =AC17 -> -166055.36 | AG17: =(L17+M17+O17)*2 -> -117319.36 | AI17: =AG17+AH17 -> -117319.36
A18: 9. Scrap & Misc Inc | B18: -2555.07 | C18: -56104.61 | D18: -21843 | E18: -80502.68 | F18: =-B18/B$5 -> -0.0017031598 | G18: =-C18/C$5 -> -0.025127096 | H18: =-D18/D$5 -> -0.02270203 | I18: =-E18/E$5 -> -0.017145786 | K18: 91. Other Inc/Exp | L18: 4.33 | O18: -132001.55 | P18: -131997.22 | Q18: Mostly Pix | U18: =SUM(S18:T18) -> 0 | V18: =-S18/S$5 -> 0 | W18: =-T18/T$5 -> 0 | X18: =K18 -> 91. Other Inc/Exp | Y18: =S18*2 -> 0 | AA18: =Y18+Z18 -> 0 | AB18: =T18*2 -> 0 | AC18: =AA18+AB18 -> 0 | AE18: =AC18 -> 0 | AG18: 0 | AI18: =AG18+AH18 -> 0
A19: 91. Other Inc/Exp | B19: 4.33 | C19: -132001.55 | E19: -131997.22 | F19: =-B19/B$5 -> 2.8862935e-06 | G19: =-C19/C$5 -> -0.059118415 | H19: =-D19/D$5 -> 0 | I19: =-E19/E$5 -> -0.0281133 | K19: 99. Elim | L19: 0 | M19: 0 | N19: 0 | P19: 0 | S19: =M19+L19 -> 0 | T19: =N19 -> 0 | U19: =SUM(S19:T19) -> 0 | V19: =-S19/S$5 -> 0 | W19: =-T19/T$5 -> 0 | X19: =K19 -> 99. Elim | Y19: =S19*2 -> 0 | AA19: =Y19+Z19 -> 0 | AB19: =T19*2 -> 0 | AC19: =AA19+AB19 -> 0 | AE19: =AC19 -> 0 | AG19: =(L19+M19+O19)*2 -> 0 | AI19: =AG19+AH19 -> 0
A20: 99. Elim | B20: 0 | C20: 0 | D20: 0 | E20: 0 | F20: =-B20/B$5 -> 0 | G20: =-C20/C$5 -> 0 | H20: =-D20/D$5 -> 0 | I20: =-E20/E$5 -> 0 | K20: 2a. Variable cost Mat Out/Env | M20: 11708.17 | P20: 11708.17 | S20: =M20+L20 -> 11708.17 | T20: =N20 -> 0 | U20: =SUM(S20:T20) -> 11708.17 | V20: =-S20/S$5 -> 0.0031363743 | W20: =-T20/T$5 -> 0 | X20: =K20 -> 2a. Variable cost Mat Out/Env | Y20: =S20*2 -> 23416.34 | AA20: =Y20+Z20 -> 23416.34 | AB20: =T20*2 -> 0 | AC20: =AA20+AB20 -> 23416.34 | AE20: =AC20 -> 23416.34 | AG20: =(L20+M20+O20)*2 -> 23416.34 | AI20: =AG20+AH20 -> 23416.34
A21: Grand Total | B21: 13058.86 | C21: 49695.92 | D21: -530582.91 | E21: -467828.13 | F21: =-B21/B$5 -> 0.0087047813 | G21: =-C21/C$5 -> 0.02225689 | H21: =-D21/D$5 -> -0.55144939 | I21: =-E21/E$5 -> -0.099639922 | K21: Grand Total | L21: 13058.86 | M21: -293152.12 | N21: -530582.91 | O21: 342848.04 | P21: -467828.13 | S21: =SUM(S5:S20) -> 194752 | T21: =SUM(T5:T20) -> -533107.91 | U21: =SUM(U5:U20) -> -338355.91 | V21: =-S21/S$5 -> 0.052169996 | W21: =-T21/T$5 -> -0.55407369 | X21: =K21 -> Grand Total | Y21: =SUM(Y5:Y20) -> 389504 | Z21: =SUM(Z5:Z20) -> -649939.69 | AA21: =SUM(AA5:AA20) -> -260435.69 | AB21: =SUM(AB5:AB20) -> -962266.36 | AC21: =AA21+AB21 -> -1222702 | AD21: =SUM(AD5:AD20) -> 0 | AE21: =SUM(AE5:AE20) -> -1327023.4 | AF21: =SUM(AF5:AF20) -> 0 | AG21: =AG5-SUM(AG6:AG20) -> -389504 | AH21: =AH5-SUM(AH6:AH20) -> 649939.69 | AI21: =AI5-SUM(AI6:AI20) -> 260435.69 | AJ21: Profit Full Yr
A22: Annualized (minus debt forgive) | B22: =-B21*2 -> -26117.72 | C22: =-(C21-C19)*2 -> -363394.94 | D22: =-D21*2 -> 1061165.8 | E22: =-(E21-E19)*2 -> 671661.82 | K22: Profit remove debt forgive | L22: =-L21 -> -13058.86 | M22: =-M21 -> 293152.12 | N22: =-N21 -> 530582.91 | O22: =-(O21-O18) -> -474849.59 | P22: =SUM(L22:O22) -> 335826.58 | Q22: =L22+M22+O22 -> -194756.33 | S22: =-S21 -> -194752 | T22: =-T21 -> 533107.91 | U22: =-U21 -> 338355.91 | V22: Flip Signs | X22: Income HY1 | AL22: =420*5 -> 2100
A23: 2025 | B23: =[2]Pivot!B$22 -> -188567.02 | C23: =[2]Pivot!C$22 -> 507482.26 | D23: =[2]Pivot!D$22 -> -393948.69 | E23: =[2]Pivot!E$22 -> -75033.45 | G23: =SUM(G6:G10) -> 0.73519603 | H23: =SUM(H6:H10) -> 0.35123152 | K23: Alloc Corp | M23: =1-N23 -> 0.79507514 | N23: =N5/P5 -> 0.20492486 | Q23: =Q22*2 -> -389512.66 | S23: =S22*2 -> -389504 | T23: =T22*2 -> 1066215.8 | U23: =U22*2 -> 676711.82 | V23: Profit Full Year | X23: Income Full YR | Y23: =-Y21 -> -389504 | Z23: =-Z21 -> 649939.69 | AA23: =-AA21 -> 260435.69 | AB23: =-AB21 -> 962266.36 | AC23: =-AC21 -> 1222702 | AD23: Income Full YR | AE23: =-AE21 -> 1327023.4 | AI23: =AI21 -> 260435.69 | AJ23: =AJ21 -> Profit Full Yr
E24: =(-E21+C19)*2 -> 671653.16 | M24: =M23*O22 -> -377541.1 | N24: =N23*O22 -> -97308.486 | O24: =SUM(M6:M9)/(-M5) -> 0.73871834 | P24: =SUM(N6:N9)/(-N5) -> 0.35123152 | Q24: Full Yr no Pix | AA24: =AA23/AC23 -> 0.21300012 | AB24: =AB23/AC23 -> 0.78699988 | AC24: =AC23-U23 -> 545990.23 | AD24: Additional Income
A25: Estimated Jun2026 Full Yr to Full Yr 2025 | F25: % Change toi 2025 | K25: Net income | M25: =M22-M24 -> 670693.22 | N25: =N22-N24 -> 627891.4 | S25: ='26 EBITDA ADJ (2)'!Y10 -> 3569.5 | T25: 0 | U25: =S25+T25 -> 3569.5 | X25: ='26 EBITDA ADJ (2)'!V10 -> Add back Interest Expense | AA25: =AA5*0.02 -> -149321.08 | AB25: =AB5*0.05 -> -90000 | AC25: =AA25+AB25 -> -239321.08 | AD25: Earnout Hills 2%, Pix 5% | AE25: =AE5*0.04 -> -375615.01 | AI25: =-AI5*0.02 -> -149321.08 | AJ25: Earnout Hills2%/yr
A26: =A5 -> 1. Sales | B26: =B5*2 -> -3000387.9 | C26: =C5*2 -> -4465666.1 | D26: =D5*2 -> -1924321.3 | E26: =E5*2 -> -9390375.3 | F26: =B26/[2]Pivot!B5-1 -> -0.11822123 | G26: =C26/[2]Pivot!C5-1 -> 0.048125645 | H26: =D26/[2]Pivot!D5-1 -> 1.2114667 | I26: =E26/[2]Pivot!E5-1 -> 0.10042202 | S26: ='26 EBITDA ADJ (2)'!Y11-T26 -> 208628.56 | T26: 4553 | U26: =S26+T26 -> 213181.56 | X26: ='26 EBITDA ADJ (2)'!V11 -> Add back Depreciation | AA26: =AC26*AA24 -> -25064.15 | AB26: =AC26*AB24 -> -92607.85 | AC26: =Synergies!F7 -> -117672 | AD26: =Synergies!B7 -> $500k Upfront (paid over 5 years) 6.6% | AE26: =AC26 -> -117672 | AI26: 0 | AJ26: $0 Upfront
A27: =A6 -> 2. Variable cost Labor | B27: =B6*2 -> 686376.24 | C27: =C6*2 -> 996513.02 | D27: =D6*2 -> 631506.16 | E27: =E6*2 -> 2314395.4 | F27: =F6-[2]Pivot!F6 -> 0.027699236 | G27: =G6-[2]Pivot!G6 -> -0.00066119334 | H27: =H6-[2]Pivot!H6 -> -0.017588737 | I27: =I6-[2]Pivot!I6 -> 0.019288972 | S27: ='26 EBITDA ADJ (2)'!Y12 -> 35769.48 | U27: =S27+T27 -> 35769.48 | X27: ='26 EBITDA ADJ (2)'!V12 -> Add back Bank Charges② | AA27: =AC27*AA24 -> -14910.009 | AB27: =AC27*AB24 -> -55089.991 | AC27: =Synergies!F8 -> -70000 | AD27: =Synergies!B8 -> $1M Inv Carry Cost @7% | AE27: =AC27 -> -70000 | AI27: =AC27 -> -70000 | AJ27: $1M Inv Carry Cost @7%
A28: =A7 -> 2. Variable cost Mat | B28: =B7*2 -> 1711702.2 | C28: =C7*2 -> 2286821.6 | D28: =D7*2 -> 44376.14 | E28: =E7*2 -> 4042899.9 | F28: =F7-[2]Pivot!F7 -> 0.028061849 | G28: =G7-[2]Pivot!G7 -> 0.0057809979 | H28: =H7-[2]Pivot!H7 -> -0.0042176288 | I28: =I7-[2]Pivot!I7 -> -0.041329144 | K28: Net Frt Income | L28: =(L16+L17)/L16 -> 0.98247884 | M28: =(M16+M17)/M16 -> 0.57292757 | S28: ='26 EBITDA ADJ (2)'!Y13-T28 -> -55914 | T28: =-'26 EBITDA ADJ (2)'!AB36 -> -10500 | U28: =S28+T28 -> -66414 | X28: Estimated Fair Mkt Rent | AA28: =Synergies!F5-AB28 -> -20000 | AB28: =-5000 -> -5000 | AC28: =SUM(AA28:AB28) -> -25000 | AD28: Deprec new co 12yrs (300,000 equip)(20x15k) | AE28: =AC28 -> -25000 | AI28: =-240000/12 -> -20000 | AJ28: Deprec new co 12yrs (240,000 equip)(20x15k)
A29: =A8 -> 2a. Variable cost Mat | B29: =B8*2 -> 0 | C29: =C8*2 -> -39214.26 | D29: =D8*2 -> 0 | E29: =E8*2 -> -39214.26 | F29: =F8-[2]Pivot!F8 -> 0 | G29: =G8-[2]Pivot!G8 -> 0.0035708313 | H29: =H8-[2]Pivot!H8 -> 0 | I29: =I8-[2]Pivot!I8 -> 0.0019912278 | S29: ='26 EBITDA ADJ (2)'!Y14 -> -23244.9 | U29: =S29+T29 -> -23244.9 | X29: Estimated Fair Mkt Rent NNN (30%?)
A30: =A9 -> 2a. Variable cost Mat Out/Env | B30: =B9*2 -> 0 | C30: =C9*2 -> 23416.34 | D30: =D9*2 -> 0 | E30: =E9*2 -> 23416.34 | F30: =F9-[2]Pivot!F9 -> -0.00015188439 | G30: =G9-[2]Pivot!G9 -> -0.0016654386 | H30: =H9-[2]Pivot!H9 -> 0 | I30: =I9-[2]Pivot!I9 -> -0.001016514 | S30: ='26 EBITDA ADJ (2)'!Y15*0.8 -> 80000 | T30: ='26 EBITDA ADJ (2)'!Y15*0.2 -> 20000 | U30: =S30+T30 -> 100000 | X30: ='26 EBITDA ADJ (2)'!V15 -> Add back 1 owner salary
A31: =A10 -> 8c. Frt Exp | B31: =B10*2 -> 11465.6 | C31: =C10*2 -> 15603.26 | D31: =D10*2 -> 0 | E31: =E10*2 -> 27068.86 | F31: =F10-[2]Pivot!F10 -> -0.0010742856 | G31: =G10-[2]Pivot!G10 -> 4.2578791e-05 | H31: =H10-[2]Pivot!H10 -> -0.00010336076 | I31: =I10-[2]Pivot!I10 -> -0.00080330678 | S31: =SUM(S23:S30) -> -140695.36 | T31: =SUM(T23:T30) -> 1080268.8 | U31: =SUM(U23:U30) -> 939573.46 | X31: ADJ EBITDA Full YR LOI | AA31: =AA23+SUM(AA25:AA30) -> 51140.449 | AB31: =AB23+SUM(AB25:AB30) -> 719568.52 | AC31: =AC23+SUM(AC25:AC30) -> 770708.97 | AD31: Profit & Loss Ongoing | AE31: =AE23+SUM(AE25:AE30) -> 738736.38 | AI31: =AI23+SUM(AI25:AI30) -> 21114.608 | AJ31: Profit & Loss Ongoing
A32: =A11 -> 3. Mfg IDL | B32: =B11*2 -> 174246.02 | C32: =C11*2 -> 230557 | D32: =D11*2 -> 24828.72 | E32: =E11*2 -> 429631.74 | F32: =F11-[2]Pivot!F11 -> 0.006868519 | G32: =G11-[2]Pivot!G11 -> -0.013437409 | H32: =H11-[2]Pivot!H11 -> -0.10173113 | I32: =I11-[2]Pivot!I11 -> -0.018841589 | K32: Another Pixlle credit? | S32: 3.5 | T32: =S32 -> 3.5 | U32: =T32 -> 3.5 | X32: Multiple | AI32: =-Synergies!G38-Synergies!G33-Synergies!F28 -> -157440 | AJ32: Possibly 1-2 more cust service & 1 Accting
A33: =A12 -> 4. Mfg OVHD | B33: =B12*2 -> 372419.78 | C33: =C12*2 -> 405999.28 | D33: =D12*2 -> 165489.14 | E33: =E12*2 -> 943908.2 | F33: =F12-[2]Pivot!F13 -> 0.010265792 | G33: =G12-[2]Pivot!G13 -> 0.005674589 | H33: =H12-[2]Pivot!H13 -> -0.074265473 | I33: =I12-[2]Pivot!I13 -> -0.0037834038 | K33: As a % lower due to sls, $ are higher, why up 20k? | S33: =S31*S32 -> -492433.76 | T33: =T31*T32 -> 3780940.9 | U33: =U31*U32 -> 3288507.1 | X33: Valuation LOI | AI33: -100000 | AJ33: Rob
A34: =A13 -> 7. Selling | B34: =B13*2 -> 73113.08 | C34: =C13*2 -> 355637.58 | D34: =D13*2 -> 0 | E34: =E13*2 -> 428750.66 | F34: =F13-[2]Pivot!F14 -> 0.002703289 | G34: =G13-[2]Pivot!G14 -> -0.009789405 | H34: =H13-[2]Pivot!H14 -> 0 | I34: =I13-[2]Pivot!I14 -> -0.0076300312 | T34: ='26 EBITDA ADJ (2)'!Y19 -> -91884.67 | U34: =S34+T34 -> -91884.67 | X34: Pixelle Abnormal Sales Q1 | AI34: =AI31-AI32-AI33 -> 278554.61 | AJ34: =AJ31 -> Profit & Loss Ongoing
A35: =A14 -> 8. Admin | B35: =B14*2 -> 80860.94 | C35: =C14*2 -> 680624.06 | D35: =D14*2 -> 38990.74 | E35: =E14*2 -> 800475.74 | F35: =F14-[2]Pivot!F15 -> -0.00065113526 | G35: =G14-[2]Pivot!G15 -> -0.03125465 | H35: =H14-[2]Pivot!H15 -> -0.017910397 | I35: =I14-[2]Pivot!I15 -> -0.021356514 | T35: ='26 EBITDA ADJ (2)'!Y20 -> -91884.67 | U35: =S35+T35 -> -91884.67 | X35: Pixelle Abnormal Sls HY2 Overstated | AJ35: Earnout Options
A36: =A15 -> 8. Admin IT | B36: =B15*2 -> 1943.28 | C36: =C15*2 -> 24693.58 | D36: =D15*2 -> 1650.62 | E36: =E15*2 -> 28287.48 | F36: =F15-[2]Pivot!F16 -> -0.00016828979 | G36: =G15-[2]Pivot!G16 -> 0.00081743291 | H36: =H15-[2]Pivot!H16 -> -0.00083706638 | I36: =I15-[2]Pivot!I16 -> 0.00016146245 | T36: ='26 EBITDA ADJ (2)'!Y21 -> 10185.941 | U36: =S36+T36 -> 10185.941 | X36: DLabor Adjustment for Sales Diff | AI36: =AI5*0.03*3 -> 671944.85 | AJ36: 3% Forms for 3Years
A37: =A16 -> 8a. Frt Income | B37: =B16*2 -> -372175.36 | C37: =C16*2 -> -290297.04 | D37: =D16*2 -> 0 | E37: =E16*2 -> -662472.4 | F37: =F16-[2]Pivot!F17 -> -0.033929055 | G37: =G16-[2]Pivot!G17 -> 0.00080304336 | H37: =H16-[2]Pivot!H17 -> 0 | I37: =I16-[2]Pivot!I17 -> -0.0017581263 | T37: ='26 EBITDA ADJ (2)'!Y22 -> 10185.941 | U37: =S37+T37 -> 10185.941 | X37: Dlabor Adjustment HY2 Overstated | AA37: =AA4 -> Hillsboro | AB37: =AB4 -> Pixelle | AC37: =AC4 -> TOTAL | AH37: Prefer this | AI37: =AI5*0.02*4.5 -> 671944.85 | AJ37: 2% Forms for 4.5Years
A38: =A17 -> 8b. Frt Exp | B38: =B17*2 -> 291655.28 | C38: =C17*2 -> 250915.8 | D38: =D17*2 -> 0 | E38: =E17*2 -> 542571.08 | F38: =F17-[2]Pivot!F18 -> 0.024880993 | G38: =G17-[2]Pivot!G18 -> 0.0037073921 | H38: =H17-[2]Pivot!H18 -> 0 | I38: =I17-[2]Pivot!I18 -> 0.002737681 | S38: =S31+SUM(S34:S37) -> -140695.36 | T38: =T31+SUM(T34:T37) -> 916871.36 | U38: =U31+SUM(U34:U37) -> 776176 | X38: ADJ EBITDA Full YR APA | AA38: =-AA5 -> 7466053.9 | AB38: =-AB5 -> 1800000 | AC38: =-AC5 -> 9266053.9 | AD38: Sales
A39: =A18 -> 9. Scrap & Misc Inc | B39: =B18*2 -> -5110.14 | C39: =C18*2 -> -112209.22 | D39: =D18*2 -> -43686 | E39: =E18*2 -> -161005.36 | F39: =F18-[2]Pivot!F19 -> -0.00038598201 | G39: =G18-[2]Pivot!G19 -> 0.0021395681 | H39: =H18-[2]Pivot!H19 -> -0.01774947 | I39: =I18-[2]Pivot!I19 -> -0.0025016967 | S39: 3.5 | T39: =S39 -> 3.5 | U39: =T39 -> 3.5 | X39: Multiple | AA39: 0.02 | AB39: 0.05 | AD39: Earnout Hills 2%, Pix 4% | AI39: =AI37 -> 671944.85 | AJ39: =AJ37 -> 2% Forms for 4.5Years
A40: =A19 -> 91. Other Inc/Exp | B40: =B19*2 -> 8.66 | C40: 0 | D40: =D19*2 -> 0 | E40: 0 | F40: =F19-[2]Pivot!F20 -> 3.3682703e-06 | G40: 0 | H40: =H19-[2]Pivot!H20 -> 0 | I40: =I19-[2]Pivot!I20 -> -0.029842116 | S40: =S38*S39 -> -492433.76 | T40: =T38*T39 -> 3209049.8 | U40: =U38*U39 -> 2716616 | X40: Valuation APA | AA40: =AA38*AA39 -> 149321.08 | AB40: =AB38*AB39 -> 90000 | AC40: =SUM(AA40:AB40) -> 239321.08 | AD40: Earnout $ | AI40: 1000000 | AJ40: Inventory
A41: =A20 -> 99. Elim | B41: =B20*2 -> 0 | C41: =C20*2 -> 0 | D41: =D20*2 -> 0 | E41: =E20*2 -> 0 | F41: =F20-[2]Pivot!F21 -> 0 | G41: =G20-[2]Pivot!G21 -> 0 | H41: =H20-[2]Pivot!H21 -> 0 | I41: =I20-[2]Pivot!I21 -> 0 | U41: -1500000 | X41: Pay Upfront | AA41: 5 | AB41: 5 | AD41: 5 Years
A42: =A21 -> Grand Total | B42: =SUM(B26:B41) -> 26117.72 | C42: =SUM(C26:C41) -> 363394.94 | D42: =SUM(D26:D41) -> -1061165.8 | E42: =SUM(E26:E41) -> -671661.82 | F42: =F21-[2]Pivot!F22 -> 0.064122415 | G42: =G21-[2]Pivot!G22 -> -0.096853039 | H42: =H21-[2]Pivot!H22 -> -0.098716062 | I42: =I21-[2]Pivot!I22 -> -0.09084704 | U42: =U40+U41 -> 1216616 | X42: Remaining to Earnout 1.2M | AA42: =AA40*AA41 -> 746605.39 | AB42: =AB40*AB41 -> 450000 | AC42: =SUM(AA42:AB42) -> 1196605.4 | AD42: Total Earnout | AI42: =AI39+AI40 -> 1671944.9 | AJ42: Total Payout
A43: 2026 Estimate | B43: =-B42 -> -26117.72 | C43: =-C42 -> -363394.94 | D43: =-D42 -> 1061165.8 | E43: =-E42 -> 671661.82
A44: 2025 | B44: =-[2]Pivot!B$22 -> 188567.02 | C44: =-[2]Pivot!C$22 -> -507482.26 | D44: =-[2]Pivot!D$22 -> 393948.69 | E44: =-[2]Pivot!E$22 -> 75033.45 | U44: =U40-U33 -> -571891.11 | AB44: =962000*2+AB5 -> 124000 | AD44: If Pixelle Sales Hit 1.925M run rate/yr
A45: Extra profit (loss) | B45: =B43-B44 -> -214684.74 | C45: =C43-C44 -> 144087.32 | D45: =D43-D44 -> 667217.13 | E45: =E43-E44 -> 596628.37 | G45: CREDIT PIXELLE | S45: =-Synergies!H20 -> 122680.12 | U45: =S45+T45 -> 122680.12 | X45: =Synergies!B20 -> Utilities | AB45: 0.812 | AD45: % to pay if exceed yrly run rate of 1.8 | AI45: =3.2-1 -> 2.2
S46: =-Synergies!H21 -> 21294.92 | U46: =S46+T46 -> 21294.92 | X46: =Synergies!B21 -> Caretaking | AB46: =AB44*AB45 -> 100688 | AD46: Extra $ per Yr
A47: Sales | B47: =-400000*0.15 -> -60000 | C47: =200000*0.15 -> 30000 | D47: =-(D26-[2]Pivot!$D$5)*0.6 -> 632499.11 | E47: =SUM(B47:D47) -> 602499.11 | S47: =-Synergies!H22 -> 24278.64 | U47: =S47+T47 -> 24278.64 | X47: =Synergies!B22 -> General Insurance | AB47: 5 | AD47: 5 Years
A48: 3% higher lab&mat impact | B48: =0.06*B26 -> -180023.27 | E48: =SUM(B48:D48) -> -180023.27 | S48: =-Synergies!H29 -> 45240 | U48: =S48+T48 -> 45240 | X48: =Synergies!B29 -> COMP (remote) | AB48: =AB46*AB47 -> 503440 | AC48: =AB48+AC42 -> 1700045.4 | AD48: New Total Earnout
A49: Mfg INDL | C49: =[2]Pivot!$C$11-C32 -> 46665.47 | E49: =SUM(B49:D49) -> 46665.47 | S49: =-Synergies!H30 -> 49608 | U49: =S49+T49 -> 49608 | X49: =Synergies!B30 -> COMP (remote)
C50: =[2]Pivot!$C$13-C33 -> -42819.1 | E50: =SUM(B50:D50) -> -42819.1 | S50: =-Synergies!H37 -> 61200 | U50: =S50+T50 -> 61200 | X50: =Synergies!B37 -> Plant Super
A51: Admin | C51: =-(C35-[2]Pivot!$C$15) -> 101912.74 | E51: =SUM(B51:D51) -> 101912.74 | S51: =-Synergies!H39 -> 40560 | U51: =S51+T51 -> 40560 | X51: =Synergies!B39 -> Scheduling
A52: Scrap&Misc | C52: =C39-[2]Pivot!$C$19-[2]Pivot!$C$20 -> -10790.67 | D52: =-D39+[2]Pivot!$D$19 -> 39376.5 | E52: =SUM(B52:D52) -> 28585.83 | S52: =-Synergies!H40 -> 41600 | U52: =S52+T52 -> 41600 | X52: =Synergies!B40 -> Shipping
A53: Frt Inc | B53: 20000 | C53: 16000 | E53: =SUM(B53:D53) -> 36000 | S53: =-Synergies!H44 -> 243478.01 | U53: =S53+T53 -> 243478.01 | X53: =Synergies!B44 -> PAPER
B54: =SUM(B47:B53) -> -220023.27 | C54: =SUM(C47:C53) -> 140968.44 | D54: =SUM(D47:D53) -> 671875.61 | E54: =SUM(E47:E53) -> 592820.78 | S54: =SUM(S45:S53) -> 649939.69 | T54: =SUM(T45:T53) -> 0 | U54: =SUM(U45:U53) -> 649939.69 | X54: SYNERGIES

Sheet SORTED B VS P
B1: TYPE | C1: Cat1 | D1: Cat2 | E1: Plant1 | F1: Plant2 | G1: ACCOUNT# | H1: LEVEL1 | I1: DESCRIPTION | J1: ACCOUNT TYPE | K1: DESCRIPTION | L1: BEG_BAL_JAN2026 | M1: NET_CHANGE | N1: END_BAL_JUN2026 | P1: 2025 | Q1: half | R1: deff
A2: =G2&H2 -> 100101 | B2: BS | C2: 1. Cash | E2: =IF(H2=1,"Hillsboro",IF(H2=2,"Angola",IF(H2=9,"Hillsboro",IF(H2=99,"Hillsboro",IF(H2=50,"Pixelle","???"))))) -> Hillsboro | F2: =IF(H2=1,"Hillsboro",IF(H2=2,"Angola",IF(H2=9,"Corp",IF(H2=99,"Corp",IF(H2=50,"Pixelle","???"))))) -> Hillsboro | G2: 10010 | H2: 1 | I2: CASH - FIRST STATE BANK | J2: B | L2: 534702.04 | M2: 171363.5 | N2: 706065.54
A3: =G3&H3 -> 100201 | B3: BS | C3: 1. Cash | E3: =IF(H3=1,"Hillsboro",IF(H3=2,"Angola",IF(H3=9,"Hillsboro",IF(H3=99,"Hillsboro",IF(H3=50,"Pixelle","???"))))) -> Hillsboro | F3: =IF(H3=1,"Hillsboro",IF(H3=2,"Angola",IF(H3=9,"Corp",IF(H3=99,"Corp",IF(H3=50,"Pixelle","???"))))) -> Hillsboro | G3: 10020 | H3: 1 | I3: PETTY CASH | J3: B | L3: 400 | M3: 0 | N3: 400
A4: =G4&H4 -> 100202 | B4: BS | C4: 1. Cash | E4: =IF(H4=1,"Hillsboro",IF(H4=2,"Angola",IF(H4=9,"Hillsboro",IF(H4=99,"Hillsboro",IF(H4=50,"Pixelle","???"))))) -> Angola | F4: =IF(H4=1,"Hillsboro",IF(H4=2,"Angola",IF(H4=9,"Corp",IF(H4=99,"Corp",IF(H4=50,"Pixelle","???"))))) -> Angola | G4: 10020 | H4: 2 | I4: PETTY CASH | J4: B | L4: 400 | M4: 0 | N4: 400
A5: =G5&H5 -> 101201 | B5: BS | C5: 1. Cash | E5: =IF(H5=1,"Hillsboro",IF(H5=2,"Angola",IF(H5=9,"Hillsboro",IF(H5=99,"Hillsboro",IF(H5=50,"Pixelle","???"))))) -> Hillsboro | F5: =IF(H5=1,"Hillsboro",IF(H5=2,"Angola",IF(H5=9,"Corp",IF(H5=99,"Corp",IF(H5=50,"Pixelle","???"))))) -> Hillsboro | G5: 10120 | H5: 1 | I5: CASH - HEALTH INS. ACCT | J5: B | L5: 14649.31 | M5: 510.18 | N5: 15159.49
A6: =G6&H6 -> 101301 | B6: BS | C6: 1. Cash | E6: =IF(H6=1,"Hillsboro",IF(H6=2,"Angola",IF(H6=9,"Hillsboro",IF(H6=99,"Hillsboro",IF(H6=50,"Pixelle","???"))))) -> Hillsboro | F6: =IF(H6=1,"Hillsboro",IF(H6=2,"Angola",IF(H6=9,"Corp",IF(H6=99,"Corp",IF(H6=50,"Pixelle","???"))))) -> Hillsboro | G6: 10130 | H6: 1 | I6: CASH - FSA HEALTH ACCT | J6: B | K6: CASH - FSA HEALTH ACCT | L6: 17101.9 | M6: 797.5 | N6: 17899.4
A7: =G7&H7 -> 110001 | B7: BS | C7: 2. AR | E7: =IF(H7=1,"Hillsboro",IF(H7=2,"Angola",IF(H7=9,"Hillsboro",IF(H7=99,"Hillsboro",IF(H7=50,"Pixelle","???"))))) -> Hillsboro | F7: =IF(H7=1,"Hillsboro",IF(H7=2,"Angola",IF(H7=9,"Corp",IF(H7=99,"Corp",IF(H7=50,"Pixelle","???"))))) -> Hillsboro | G7: 11000 | H7: 1 | I7: ACCOUNTS RECEIVABLE | J7: B | L7: 674695.59 | M7: 104791.93 | N7: 779487.52
A8: =G8&H8 -> 111001 | B8: BS | C8: 2. AR | E8: =IF(H8=1,"Hillsboro",IF(H8=2,"Angola",IF(H8=9,"Hillsboro",IF(H8=99,"Hillsboro",IF(H8=50,"Pixelle","???"))))) -> Hillsboro | F8: =IF(H8=1,"Hillsboro",IF(H8=2,"Angola",IF(H8=9,"Corp",IF(H8=99,"Corp",IF(H8=50,"Pixelle","???"))))) -> Hillsboro | G8: 11100 | H8: 1 | I8: ACCOUNTS RECEIVABLE-OTHER | J8: B | L8: 40084.73 | M8: -40068.98 | N8: 15.75
A9: =G9&H9 -> 120001 | B9: BS | C9: 3. Prepaid | E9: =IF(H9=1,"Hillsboro",IF(H9=2,"Angola",IF(H9=9,"Hillsboro",IF(H9=99,"Hillsboro",IF(H9=50,"Pixelle","???"))))) -> Hillsboro | F9: =IF(H9=1,"Hillsboro",IF(H9=2,"Angola",IF(H9=9,"Corp",IF(H9=99,"Corp",IF(H9=50,"Pixelle","???"))))) -> Hillsboro | G9: 12000 | H9: 1 | I9: PREPAID EXPENSES | J9: B | L9: 4763.44 | M9: 16989.6 | N9: 21753.04
A10: =G10&H10 -> 121001 | B10: BS | C10: 3. Prepaid | E10: =IF(H10=1,"Hillsboro",IF(H10=2,"Angola",IF(H10=9,"Hillsboro",IF(H10=99,"Hillsboro",IF(H10=50,"Pixelle","???"))))) -> Hillsboro | F10: =IF(H10=1,"Hillsboro",IF(H10=2,"Angola",IF(H10=9,"Corp",IF(H10=99,"Corp",IF(H10=50,"Pixelle","???"))))) -> Hillsboro | G10: 12100 | H10: 1 | I10: DEPOSITS | J10: B | L10: 500 | M10: 0 | N10: 500
A11: =G11&H11 -> 121101 | B11: BS | C11: 3. Prepaid | E11: =IF(H11=1,"Hillsboro",IF(H11=2,"Angola",IF(H11=9,"Hillsboro",IF(H11=99,"Hillsboro",IF(H11=50,"Pixelle","???"))))) -> Hillsboro | F11: =IF(H11=1,"Hillsboro",IF(H11=2,"Angola",IF(H11=9,"Corp",IF(H11=99,"Corp",IF(H11=50,"Pixelle","???"))))) -> Hillsboro | G11: 12110 | H11: 1 | I11: PREPAID INSURANCE | J11: B | L11: 7868 | M11: 3594.5 | N11: 11462.5
A12: =G12&H12 -> 131001 | B12: BS | C12: 4. Inv Paper | E12: =IF(H12=1,"Hillsboro",IF(H12=2,"Angola",IF(H12=9,"Hillsboro",IF(H12=99,"Hillsboro",IF(H12=50,"Pixelle","???"))))) -> Hillsboro | F12: =IF(H12=1,"Hillsboro",IF(H12=2,"Angola",IF(H12=9,"Corp",IF(H12=99,"Corp",IF(H12=50,"Pixelle","???"))))) -> Hillsboro | G12: 13100 | H12: 1 | I12: INVENTORY-BOND PAPER | J12: B | L12: 444806.9 | M12: -67895.92 | N12: 376910.98
A13: =G13&H13 -> 131002 | B13: BS | C13: 4. Inv Paper | E13: =IF(H13=1,"Hillsboro",IF(H13=2,"Angola",IF(H13=9,"Hillsboro",IF(H13=99,"Hillsboro",IF(H13=50,"Pixelle","???"))))) -> Angola | F13: =IF(H13=1,"Hillsboro",IF(H13=2,"Angola",IF(H13=9,"Corp",IF(H13=99,"Corp",IF(H13=50,"Pixelle","???"))))) -> Angola | G13: 13100 | H13: 2 | I13: INVENTORY-BOND PAPER | J13: B | L13: 416192.86 | M13: -33401.99 | N13: 382790.87
A14: =G14&H14 -> 131502 | B14: BS | C14: 4. Inv Label Mat | E14: =IF(H14=1,"Hillsboro",IF(H14=2,"Angola",IF(H14=9,"Hillsboro",IF(H14=99,"Hillsboro",IF(H14=50,"Pixelle","???"))))) -> Angola | F14: =IF(H14=1,"Hillsboro",IF(H14=2,"Angola",IF(H14=9,"Corp",IF(H14=99,"Corp",IF(H14=50,"Pixelle","???"))))) -> Angola | G14: 13150 | H14: 2 | I14: INVENTORY-LABEL MATERIAL | J14: B | K14: INVENTORY-LABEL MATERIAL | L14: 29721.35 | M14: -6933.75 | N14: 22787.6
A15: =G15&H15 -> 132001 | B15: BS | C15: 4. Inv Carbon | E15: =IF(H15=1,"Hillsboro",IF(H15=2,"Angola",IF(H15=9,"Hillsboro",IF(H15=99,"Hillsboro",IF(H15=50,"Pixelle","???"))))) -> Hillsboro | F15: =IF(H15=1,"Hillsboro",IF(H15=2,"Angola",IF(H15=9,"Corp",IF(H15=99,"Corp",IF(H15=50,"Pixelle","???"))))) -> Hillsboro | G15: 13200 | H15: 1 | I15: INVENTORY-CARBON | J15: B | L15: 574.15 | M15: 1293.09 | N15: 1867.24
A16: =G16&H16 -> 133001 | B16: BS | C16: 4. Inv Cartons | E16: =IF(H16=1,"Hillsboro",IF(H16=2,"Angola",IF(H16=9,"Hillsboro",IF(H16=99,"Hillsboro",IF(H16=50,"Pixelle","???"))))) -> Hillsboro | F16: =IF(H16=1,"Hillsboro",IF(H16=2,"Angola",IF(H16=9,"Corp",IF(H16=99,"Corp",IF(H16=50,"Pixelle","???"))))) -> Hillsboro | G16: 13300 | H16: 1 | I16: INVENTORY-CARTONS | J16: B | L16: 33340.31 | M16: 5010.1 | N16: 38350.41
A17: =G17&H17 -> 133002 | B17: BS | C17: 4. Inv Cartons | E17: =IF(H17=1,"Hillsboro",IF(H17=2,"Angola",IF(H17=9,"Hillsboro",IF(H17=99,"Hillsboro",IF(H17=50,"Pixelle","???"))))) -> Angola | F17: =IF(H17=1,"Hillsboro",IF(H17=2,"Angola",IF(H17=9,"Corp",IF(H17=99,"Corp",IF(H17=50,"Pixelle","???"))))) -> Angola | G17: 13300 | H17: 2 | I17: INVENTORY-CARTONS | J17: B | L17: 51299.41 | M17: 6066.08 | N17: 57365.49
A18: =G18&H18 -> 134001 | B18: BS | C18: 4. Inv FGS | E18: =IF(H18=1,"Hillsboro",IF(H18=2,"Angola",IF(H18=9,"Hillsboro",IF(H18=99,"Hillsboro",IF(H18=50,"Pixelle","???"))))) -> Hillsboro | F18: =IF(H18=1,"Hillsboro",IF(H18=2,"Angola",IF(H18=9,"Corp",IF(H18=99,"Corp",IF(H18=50,"Pixelle","???"))))) -> Hillsboro | G18: 13400 | H18: 1 | I18: INVENTORY-F/G | J18: B | L18: 63844 | M18: -20387.89 | N18: 43456.11
A19: =G19&H19 -> 134002 | B19: BS | C19: 4. Inv FGS | E19: =IF(H19=1,"Hillsboro",IF(H19=2,"Angola",IF(H19=9,"Hillsboro",IF(H19=99,"Hillsboro",IF(H19=50,"Pixelle","???"))))) -> Angola | F19: =IF(H19=1,"Hillsboro",IF(H19=2,"Angola",IF(H19=9,"Corp",IF(H19=99,"Corp",IF(H19=50,"Pixelle","???"))))) -> Angola | G19: 13400 | H19: 2 | I19: INVENTORY-F/G | J19: B | L19: 139992.39 | M19: -23582.06 | N19: 116410.33
A20: =G20&H20 -> 136001 | B20: BS | C20: 4. Inv Supplies | E20: =IF(H20=1,"Hillsboro",IF(H20=2,"Angola",IF(H20=9,"Hillsboro",IF(H20=99,"Hillsboro",IF(H20=50,"Pixelle","???"))))) -> Hillsboro | F20: =IF(H20=1,"Hillsboro",IF(H20=2,"Angola",IF(H20=9,"Corp",IF(H20=99,"Corp",IF(H20=50,"Pixelle","???"))))) -> Hillsboro | G20: 13600 | H20: 1 | I20: INVENTORY-SUPPLIES | J20: B | L20: 18618.51 | M20: -10172.45 | N20: 8446.06
A21: =G21&H21 -> 136002 | B21: BS | C21: 4. Inv Supplies | E21: =IF(H21=1,"Hillsboro",IF(H21=2,"Angola",IF(H21=9,"Hillsboro",IF(H21=99,"Hillsboro",IF(H21=50,"Pixelle","???"))))) -> Angola | F21: =IF(H21=1,"Hillsboro",IF(H21=2,"Angola",IF(H21=9,"Corp",IF(H21=99,"Corp",IF(H21=50,"Pixelle","???"))))) -> Angola | G21: 13600 | H21: 2 | I21: INVENTORY-SUPPLIES | J21: B | L21: 3642.35 | M21: -407.48 | N21: 3234.87
A22: =G22&H22 -> 136501 | B22: BS | C22: 4. Inv TAMARACK & HUNKELER | E22: =IF(H22=1,"Hillsboro",IF(H22=2,"Angola",IF(H22=9,"Hillsboro",IF(H22=99,"Hillsboro",IF(H22=50,"Pixelle","???"))))) -> Hillsboro | F22: =IF(H22=1,"Hillsboro",IF(H22=2,"Angola",IF(H22=9,"Corp",IF(H22=99,"Corp",IF(H22=50,"Pixelle","???"))))) -> Hillsboro | G22: 13650 | H22: 1 | I22: INVENTORY-TAMARACK & HUNKELER | J22: B | K22: INVENTORY-TAMARACK & HUNKELER | L22: 28760.58 | M22: 5714.28 | N22: 34474.86
A23: =G23&H23 -> 139501 | B23: BS | C23: 4. Inv Envelopes | E23: =IF(H23=1,"Hillsboro",IF(H23=2,"Angola",IF(H23=9,"Hillsboro",IF(H23=99,"Hillsboro",IF(H23=50,"Pixelle","???"))))) -> Hillsboro | F23: =IF(H23=1,"Hillsboro",IF(H23=2,"Angola",IF(H23=9,"Corp",IF(H23=99,"Corp",IF(H23=50,"Pixelle","???"))))) -> Hillsboro | G23: 13950 | H23: 1 | I23: INVENTORY-ENVELOPES | J23: B | L23: 9108.79 | M23: 3303.83 | N23: 12412.62
A24: =G24&H24 -> 140001 | B24: BS | C24: 5. M&E | E24: =IF(H24=1,"Hillsboro",IF(H24=2,"Angola",IF(H24=9,"Hillsboro",IF(H24=99,"Hillsboro",IF(H24=50,"Pixelle","???"))))) -> Hillsboro | F24: =IF(H24=1,"Hillsboro",IF(H24=2,"Angola",IF(H24=9,"Corp",IF(H24=99,"Corp",IF(H24=50,"Pixelle","???"))))) -> Hillsboro | G24: 14000 | H24: 1 | I24: MACHINERY & EQUIPMENT | J24: B | L24: 3796655.2 | M24: 0 | N24: 3796655.2
A25: =G25&H25 -> 140002 | B25: BS | C25: 5. M&E | E25: =IF(H25=1,"Hillsboro",IF(H25=2,"Angola",IF(H25=9,"Hillsboro",IF(H25=99,"Hillsboro",IF(H25=50,"Pixelle","???"))))) -> Angola | F25: =IF(H25=1,"Hillsboro",IF(H25=2,"Angola",IF(H25=9,"Corp",IF(H25=99,"Corp",IF(H25=50,"Pixelle","???"))))) -> Angola | G25: 14000 | H25: 2 | I25: MACHINERY & EQUIPMENT | J25: B | L25: 2670303.1 | M25: 0 | N25: 2670303.1
A26: =G26&H26 -> 1400050 | B26: BS | C26: 5. M&E | E26: =IF(H26=1,"Hillsboro",IF(H26=2,"Angola",IF(H26=9,"Hillsboro",IF(H26=99,"Hillsboro",IF(H26=50,"Pixelle","???"))))) -> Pixelle | F26: =IF(H26=1,"Hillsboro",IF(H26=2,"Angola",IF(H26=9,"Corp",IF(H26=99,"Corp",IF(H26=50,"Pixelle","???"))))) -> Pixelle | G26: 14000 | H26: 50 | I26: MACHINERY & EQUIPMENT | J26: B | L26: 334582.36 | M26: 10000 | N26: 344582.36
A27: =G27&H27 -> 141001 | B27: BS | C27: 5. M&E | E27: =IF(H27=1,"Hillsboro",IF(H27=2,"Angola",IF(H27=9,"Hillsboro",IF(H27=99,"Hillsboro",IF(H27=50,"Pixelle","???"))))) -> Hillsboro | F27: =IF(H27=1,"Hillsboro",IF(H27=2,"Angola",IF(H27=9,"Corp",IF(H27=99,"Corp",IF(H27=50,"Pixelle","???"))))) -> Hillsboro | G27: 14100 | H27: 1 | I27: ACCUM.DEPR.-MACH.& EQ. | J27: B | L27: -3390862.3 | M27: -39273.3 | N27: -3430135.6
A28: =G28&H28 -> 141002 | B28: BS | C28: 5. M&E | E28: =IF(H28=1,"Hillsboro",IF(H28=2,"Angola",IF(H28=9,"Hillsboro",IF(H28=99,"Hillsboro",IF(H28=50,"Pixelle","???"))))) -> Angola | F28: =IF(H28=1,"Hillsboro",IF(H28=2,"Angola",IF(H28=9,"Corp",IF(H28=99,"Corp",IF(H28=50,"Pixelle","???"))))) -> Angola | G28: 14100 | H28: 2 | I28: ACCUM.DEPR.-MACH.& EQ. | J28: B | L28: -2321058.3 | M28: -30196.14 | N28: -2351254.5
A29: =G29&H29 -> 1410050 | B29: BS | C29: 5. M&E | E29: =IF(H29=1,"Hillsboro",IF(H29=2,"Angola",IF(H29=9,"Hillsboro",IF(H29=99,"Hillsboro",IF(H29=50,"Pixelle","???"))))) -> Pixelle | F29: =IF(H29=1,"Hillsboro",IF(H29=2,"Angola",IF(H29=9,"Corp",IF(H29=99,"Corp",IF(H29=50,"Pixelle","???"))))) -> Pixelle | G29: 14100 | H29: 50 | I29: ACCUM.DEPR.-MACH.& EQ. | J29: B | L29: -303087.13 | M29: -3133.38 | N29: -306220.51
A30: =G30&H30 -> 150001 | B30: BS | C30: 5. M&E | E30: =IF(H30=1,"Hillsboro",IF(H30=2,"Angola",IF(H30=9,"Hillsboro",IF(H30=99,"Hillsboro",IF(H30=50,"Pixelle","???"))))) -> Hillsboro | F30: =IF(H30=1,"Hillsboro",IF(H30=2,"Angola",IF(H30=9,"Corp",IF(H30=99,"Corp",IF(H30=50,"Pixelle","???"))))) -> Hillsboro | G30: 15000 | H30: 1 | I30: VEHICLES | J30: B | L30: 84861.54 | M30: 0 | N30: 84861.54
A31: =G31&H31 -> 150002 | B31: BS | C31: 5. M&E | E31: =IF(H31=1,"Hillsboro",IF(H31=2,"Angola",IF(H31=9,"Hillsboro",IF(H31=99,"Hillsboro",IF(H31=50,"Pixelle","???"))))) -> Angola | F31: =IF(H31=1,"Hillsboro",IF(H31=2,"Angola",IF(H31=9,"Corp",IF(H31=99,"Corp",IF(H31=50,"Pixelle","???"))))) -> Angola | G31: 15000 | H31: 2 | I31: VEHICLES | J31: B | L31: 64451.23 | M31: 0 | N31: 64451.23
A32: =G32&H32 -> 151001 | B32: BS | C32: 5. M&E | E32: =IF(H32=1,"Hillsboro",IF(H32=2,"Angola",IF(H32=9,"Hillsboro",IF(H32=99,"Hillsboro",IF(H32=50,"Pixelle","???"))))) -> Hillsboro | F32: =IF(H32=1,"Hillsboro",IF(H32=2,"Angola",IF(H32=9,"Corp",IF(H32=99,"Corp",IF(H32=50,"Pixelle","???"))))) -> Hillsboro | G32: 15100 | H32: 1 | I32: ACCUM.DEPR.-VEHICLES | J32: B | L32: -77553.05 | M32: -2192.58 | N32: -79745.63
A33: =G33&H33 -> 151002 | B33: BS | C33: 5. M&E | E33: =IF(H33=1,"Hillsboro",IF(H33=2,"Angola",IF(H33=9,"Hillsboro",IF(H33=99,"Hillsboro",IF(H33=50,"Pixelle","???"))))) -> Angola | F33: =IF(H33=1,"Hillsboro",IF(H33=2,"Angola",IF(H33=9,"Corp",IF(H33=99,"Corp",IF(H33=50,"Pixelle","???"))))) -> Angola | G33: 15100 | H33: 2 | I33: ACCUM.DEPR.-VEHICLES | J33: B | L33: -64451.23 | M33: 0 | N33: -64451.23
A34: =G34&H34 -> 160001 | B34: BS | C34: 5. M&E | E34: =IF(H34=1,"Hillsboro",IF(H34=2,"Angola",IF(H34=9,"Hillsboro",IF(H34=99,"Hillsboro",IF(H34=50,"Pixelle","???"))))) -> Hillsboro | F34: =IF(H34=1,"Hillsboro",IF(H34=2,"Angola",IF(H34=9,"Corp",IF(H34=99,"Corp",IF(H34=50,"Pixelle","???"))))) -> Hillsboro | G34: 16000 | H34: 1 | I34: FURNITURE & FIXTURES | J34: B | L34: 38802.65 | M34: 0 | N34: 38802.65
... A43: =G43&H43 -> 1710050 | B43: BS | C43: 5. M&E | E43: =IF(H43=1,"Hillsboro",IF(H43=2,"Angola",IF(H43=9,"Hillsboro",IF(H43=99,"Hillsboro",IF(H43=50,"Pixelle","???"))))) -> Pixelle | F43: =IF(H43=1,"Hillsboro",IF(H43=2,"Angola",IF(H43=9,"Corp",IF(H43=99,"Corp",IF(H43=50,"Pixelle","???"))))) -> Pixelle | G43: 17100 | H43: 50 | I43: ACCUM.DEPR.-LEASEHOLD | J43: B | L43: -39765.33 | M43: -4553.52 | N43: -44318.85
A44: =G44&H44 -> 175001 | B44: BS | C44: 6. Intangible | E44: =IF(H44=1,"Hillsboro",IF(H44=2,"Angola",IF(H44=9,"Hillsboro",IF(H44=99,"Hillsboro",IF(H44=50,"Pixelle","???"))))) -> Hillsboro | F44: =IF(H44=1,"Hillsboro",IF(H44=2,"Angola",IF(H44=9,"Corp",IF(H44=99,"Corp",IF(H44=50,"Pixelle","???"))))) -> Hillsboro | G44: 17500 | H44: 1 | I44: GOODWILL | J44: B | K44: GOODWILL | L44: 10000 | M44: 0 | N44: 10000
A45: =G45&H45 -> 180001 | B45: BS | C45: 5. M&E | E45: =IF(H45=1,"Hillsboro",IF(H45=2,"Angola",IF(H45=9,"Hillsboro",IF(H45=99,"Hillsboro",IF(H45=50,"Pixelle","???"))))) -> Hillsboro | F45: =IF(H45=1,"Hillsboro",IF(H45=2,"Angola",IF(H45=9,"Corp",IF(H45=99,"Corp",IF(H45=50,"Pixelle","???"))))) -> Hillsboro | G45: 18000 | H45: 1 | I45: COMPUTER | J45: B | L45: 180345.65 | M45: 0 | N45: 180345.65
A46: =G46&H46 -> 180002 | B46: BS | C46: 5. M&E | E46: =IF(H46=1,"Hillsboro",IF(H46=2,"Angola",IF(H46=9,"Hillsboro",IF(H46=99,"Hillsboro",IF(H46=50,"Pixelle","???"))))) -> Angola | F46: =IF(H46=1,"Hillsboro",IF(H46=2,"Angola",IF(H46=9,"Corp",IF(H46=99,"Corp",IF(H46=50,"Pixelle","???"))))) -> Angola | G46: 18000 | H46: 2 | I46: COMPUTER | J46: B | L46: 8360.14 | M46: 0 | N46: 8360.14
A47: =G47&H47 -> 181001 | B47: BS | C47: 5. M&E | E47: =IF(H47=1,"Hillsboro",IF(H47=2,"Angola",IF(H47=9,"Hillsboro",IF(H47=99,"Hillsboro",IF(H47=50,"Pixelle","???"))))) -> Hillsboro | F47: =IF(H47=1,"Hillsboro",IF(H47=2,"Angola",IF(H47=9,"Corp",IF(H47=99,"Corp",IF(H47=50,"Pixelle","???"))))) -> Hillsboro | G47: 18100 | H47: 1 | I47: ACCUM.DEPR.-COMPUTER | J47: B | L47: -165011.04 | M47: -2359.14 | N47: -167370.18
A48: =G48&H48 -> 181002 | B48: BS | C48: 5. M&E | E48: =IF(H48=1,"Hillsboro",IF(H48=2,"Angola",IF(H48=9,"Hillsboro",IF(H48=99,"Hillsboro",IF(H48=50,"Pixelle","???"))))) -> Angola | F48: =IF(H48=1,"Hillsboro",IF(H48=2,"Angola",IF(H48=9,"Corp",IF(H48=99,"Corp",IF(H48=50,"Pixelle","???"))))) -> Angola | G48: 18100 | H48: 2 | I48: ACCUM.DEPR.-COMPUTER | J48: B | L48: -5573.42 | M48: -1393.38 | N48: -6966.8
A49: =G49&H49 -> 190001 | B49: BS | C49: 5. M&E | E49: =IF(H49=1,"Hillsboro",IF(H49=2,"Angola",IF(H49=9,"Hillsboro",IF(H49=99,"Hillsboro",IF(H49=50,"Pixelle","???"))))) -> Hillsboro | F49: =IF(H49=1,"Hillsboro",IF(H49=2,"Angola",IF(H49=9,"Corp",IF(H49=99,"Corp",IF(H49=50,"Pixelle","???"))))) -> Hillsboro | G49: 19000 | H49: 1 | I49: BUILDING AND LAND | J49: B | L49: 600000 | M49: 0 | N49: 600000
A50: =G50&H50 -> 191001 | B50: BS | C50: 5. M&E | E50: =IF(H50=1,"Hillsboro",IF(H50=2,"Angola",IF(H50=9,"Hillsboro",IF(H50=99,"Hillsboro",IF(H50=50,"Pixelle","???"))))) -> Hillsboro | F50: =IF(H50=1,"Hillsboro",IF(H50=2,"Angola",IF(H50=9,"Corp",IF(H50=99,"Corp",IF(H50=50,"Pixelle","???"))))) -> Hillsboro | G50: 19100 | H50: 1 | I50: ACCUM.DEPR.-BUILDING | J50: B | L50: -87500 | M50: -6249.96 | N50: -93749.96
A51: =G51&H51 -> 200001 | B51: BS | C51: 7. AP | E51: =IF(H51=1,"Hillsboro",IF(H51=2,"Angola",IF(H51=9,"Hillsboro",IF(H51=99,"Hillsboro",IF(H51=50,"Pixelle","???"))))) -> Hillsboro | F51: =IF(H51=1,"Hillsboro",IF(H51=2,"Angola",IF(H51=9,"Corp",IF(H51=99,"Corp",IF(H51=50,"Pixelle","???"))))) -> Hillsboro | G51: 20000 | H51: 1 | I51: ACCOUNTS PAYABLE | J51: B | L51: -451707.84 | M51: 141621.69 | N51: -310086.15
A52: =G52&H52 -> 215001 | B52: BS | C52: 7. AP | E52: =IF(H52=1,"Hillsboro",IF(H52=2,"Angola",IF(H52=9,"Hillsboro",IF(H52=99,"Hillsboro",IF(H52=50,"Pixelle","???"))))) -> Hillsboro | F52: =IF(H52=1,"Hillsboro",IF(H52=2,"Angola",IF(H52=9,"Corp",IF(H52=99,"Corp",IF(H52=50,"Pixelle","???"))))) -> Hillsboro | G52: 21500 | H52: 1 | I52: CUSTOMER PAYMENTS ACCOUNT | J52: B | L52: 0 | M52: 0 | N52: 0
A53: =G53&H53 -> 215101 | B53: BS | C53: 9. NP | E53: =IF(H53=1,"Hillsboro",IF(H53=2,"Angola",IF(H53=9,"Hillsboro",IF(H53=99,"Hillsboro",IF(H53=50,"Pixelle","???"))))) -> Hillsboro | F53: =IF(H53=1,"Hillsboro",IF(H53=2,"Angola",IF(H53=9,"Corp",IF(H53=99,"Corp",IF(H53=50,"Pixelle","???"))))) -> Hillsboro | G53: 21510 | H53: 1 | I53: NOTE PAYABLE W & J | J53: B | K53: NOTE PAYABLE W & J | L53: -193786.3 | M53: 193786.3 | N53: 0
A54: =G54&H54 -> 218601 | B54: BS | C54: 9. NP | E54: =IF(H54=1,"Hillsboro",IF(H54=2,"Angola",IF(H54=9,"Hillsboro",IF(H54=99,"Hillsboro",IF(H54=50,"Pixelle","???"))))) -> Hillsboro | F54: =IF(H54=1,"Hillsboro",IF(H54=2,"Angola",IF(H54=9,"Corp",IF(H54=99,"Corp",IF(H54=50,"Pixelle","???"))))) -> Hillsboro | G54: 21860 | H54: 1 | I54: NOTES PAYABLE-FSB 20YR ST | J54: B | K54: NOTES PAYABLE-FSB 20YR ST | L54: -19755.63 | M54: 0 | N54: -19755.63
A55: =G55&H55 -> 218701 | B55: BS | C55: 9. NP | E55: =IF(H55=1,"Hillsboro",IF(H55=2,"Angola",IF(H55=9,"Hillsboro",IF(H55=99,"Hillsboro",IF(H55=50,"Pixelle","???"))))) -> Hillsboro | F55: =IF(H55=1,"Hillsboro",IF(H55=2,"Angola",IF(H55=9,"Corp",IF(H55=99,"Corp",IF(H55=50,"Pixelle","???"))))) -> Hillsboro | G55: 21870 | H55: 1 | I55: NOTES PAYABLE-FSB 20YR LT | J55: B | K55: NOTES PAYABLE-FSB 20YR LT | L55: -307922.95 | M55: 66051.5 | N55: -241871.45
A56: =G56&H56 -> 230001 | B56: BS | C56: 8. Accr AP | E56: =IF(H56=1,"Hillsboro",IF(H56=2,"Angola",IF(H56=9,"Hillsboro",IF(H56=99,"Hillsboro",IF(H56=50,"Pixelle","???"))))) -> Hillsboro | F56: =IF(H56=1,"Hillsboro",IF(H56=2,"Angola",IF(H56=9,"Corp",IF(H56=99,"Corp",IF(H56=50,"Pixelle","???"))))) -> Hillsboro | G56: 23000 | H56: 1 | I56: ACCRUED TAXES-GENERAL | J56: B | L56: -48475.74 | M56: -249.1 | N56: -48724.84
A57: =G57&H57 -> 237001 | B57: BS | C57: 8. Accr AP | E57: =IF(H57=1,"Hillsboro",IF(H57=2,"Angola",IF(H57=9,"Hillsboro",IF(H57=99,"Hillsboro",IF(H57=50,"Pixelle","???"))))) -> Hillsboro | F57: =IF(H57=1,"Hillsboro",IF(H57=2,"Angola",IF(H57=9,"Corp",IF(H57=99,"Corp",IF(H57=50,"Pixelle","???"))))) -> Hillsboro | G57: 23700 | H57: 1 | I57: ACCRUED OHIO WORKER'S COM | J57: B | L57: 0 | M57: 0 | N57: 0
A58: =G58&H58 -> 239001 | B58: BS | C58: 8. Accr AP | E58: =IF(H58=1,"Hillsboro",IF(H58=2,"Angola",IF(H58=9,"Hillsboro",IF(H58=99,"Hillsboro",IF(H58=50,"Pixelle","???"))))) -> Hillsboro | F58: =IF(H58=1,"Hillsboro",IF(H58=2,"Angola",IF(H58=9,"Corp",IF(H58=99,"Corp",IF(H58=50,"Pixelle","???"))))) -> Hillsboro | G58: 23900 | H58: 1 | I58: ACCRUED FLEX PLAN-H | J58: B | L58: -9636.25 | M58: -827.5 | N58: -10463.75
A59: =G59&H59 -> 239501 | B59: BS | C59: 8. Accr AP | E59: =IF(H59=1,"Hillsboro",IF(H59=2,"Angola",IF(H59=9,"Hillsboro",IF(H59=99,"Hillsboro",IF(H59=50,"Pixelle","???"))))) -> Hillsboro | F59: =IF(H59=1,"Hillsboro",IF(H59=2,"Angola",IF(H59=9,"Corp",IF(H59=99,"Corp",IF(H59=50,"Pixelle","???"))))) -> Hillsboro | G59: 23950 | H59: 1 | I59: ACCRUED HEALTH INSURANCE | J59: B | K59: ACCRUED HEALTH INSURANCE | L59: -130845.01 | M59: 72441.83 | N59: -58403.18
A60: =G60&H60 -> 240001 | B60: BS | C60: 8. Accr AP | E60: =IF(H60=1,"Hillsboro",IF(H60=2,"Angola",IF(H60=9,"Hillsboro",IF(H60=99,"Hillsboro",IF(H60=50,"Pixelle","???"))))) -> Hillsboro | F60: =IF(H60=1,"Hillsboro",IF(H60=2,"Angola",IF(H60=9,"Corp",IF(H60=99,"Corp",IF(H60=50,"Pixelle","???"))))) -> Hillsboro | G60: 24000 | H60: 1 | I60: ACCRUED EXPENSES-OTHER | J60: B | L60: 0 | M60: 15.08 | N60: 15.08
A61: =G61&H61 -> 241001 | B61: BS | C61: 8. Accr AP | E61: =IF(H61=1,"Hillsboro",IF(H61=2,"Angola",IF(H61=9,"Hillsboro",IF(H61=99,"Hillsboro",IF(H61=50,"Pixelle","???"))))) -> Hillsboro | F61: =IF(H61=1,"Hillsboro",IF(H61=2,"Angola",IF(H61=9,"Corp",IF(H61=99,"Corp",IF(H61=50,"Pixelle","???"))))) -> Hillsboro | G61: 24100 | H61: 1 | I61: ACCRUED EMPLOYEE 401-K | J61: B | L61: 0 | M61: 0 | N61: 0
A62: =G62&H62 -> 243001 | B62: BS | C62: 8. Accr AP | E62: =IF(H62=1,"Hillsboro",IF(H62=2,"Angola",IF(H62=9,"Hillsboro",IF(H62=99,"Hillsboro",IF(H62=50,"Pixelle","???"))))) -> Hillsboro | F62: =IF(H62=1,"Hillsboro",IF(H62=2,"Angola",IF(H62=9,"Corp",IF(H62=99,"Corp",IF(H62=50,"Pixelle","???"))))) -> Hillsboro | G62: 24300 | H62: 1 | I62: ACCRUED WAGES | J62: B | L62: -51459.37 | M62: -65004.96 | N62: -116464.33
A63: =G63&H63 -> 300001 | B63: BS | C63: 9a. RE | E63: =IF(H63=1,"Hillsboro",IF(H63=2,"Angola",IF(H63=9,"Hillsboro",IF(H63=99,"Hillsboro",IF(H63=50,"Pixelle","???"))))) -> Hillsboro | F63: =IF(H63=1,"Hillsboro",IF(H63=2,"Angola",IF(H63=9,"Corp",IF(H63=99,"Corp",IF(H63=50,"Pixelle","???"))))) -> Hillsboro | G63: 30000 | H63: 1 | I63: COMMON STOCK | J63: B | L63: -1000 | M63: 0 | N63: -1000
A64: =G64&H64 -> 310001 | B64: BS | C64: 9a. RE | E64: =IF(H64=1,"Hillsboro",IF(H64=2,"Angola",IF(H64=9,"Hillsboro",IF(H64=99,"Hillsboro",IF(H64=50,"Pixelle","???"))))) -> Hillsboro | F64: =IF(H64=1,"Hillsboro",IF(H64=2,"Angola",IF(H64=9,"Corp",IF(H64=99,"Corp",IF(H64=50,"Pixelle","???"))))) -> Hillsboro | G64: 31000 | H64: 1 | I64: RETAINED EARNINGS | J64: B | L64: -2581208.7 | M64: 0 | N64: -2581208.7
A65: =G65&H65 -> 3150099 | B65: BS | C65: 9a. RE | E65: =IF(H65=1,"Hillsboro",IF(H65=2,"Angola",IF(H65=9,"Hillsboro",IF(H65=99,"Hillsboro",IF(H65=50,"Pixelle","???"))))) -> Hillsboro | F65: =IF(H65=1,"Hillsboro",IF(H65=2,"Angola",IF(H65=9,"Corp",IF(H65=99,"Corp",IF(H65=50,"Pixelle","???"))))) -> Corp | G65: 31500 | H65: 99 | I65: PAID IN CAPITAL | J65: B | K65: PAID IN CAPITAL | L65: -249000 | M65: 0 | N65: -249000
A66: =G66&H66 -> 3200099 | B66: BS | C66: 9a. RE | E66: =IF(H66=1,"Hillsboro",IF(H66=2,"Angola",IF(H66=9,"Hillsboro",IF(H66=99,"Hillsboro",IF(H66=50,"Pixelle","???"))))) -> Hillsboro | F66: =IF(H66=1,"Hillsboro",IF(H66=2,"Angola",IF(H66=9,"Corp",IF(H66=99,"Corp",IF(H66=50,"Pixelle","???"))))) -> Corp | G66: 32000 | H66: 99 | I66: DISTRIBUTION TO SHAREHOLD | J66: B | L66: 0 | M66: 40000 | N66: 40000
A67: =G67&H67 -> 134051 | B67: IS | C67: 2. Variable cost Mat | D67: 20a. Paper | E67: =IF(H67=1,"Hillsboro",IF(H67=2,"Angola",IF(H67=9,"Hillsboro",IF(H67=99,"Hillsboro",IF(H67=50,"Pixelle","???"))))) -> Hillsboro | F67: =IF(H67=1,"Hillsboro",IF(H67=2,"Angola",IF(H67=9,"Corp",IF(H67=99,"Corp",IF(H67=50,"Pixelle","???"))))) -> Hillsboro | G67: 13405 | H67: 1 | I67: FINISHED GOODS VARIBLE | J67: P | L67: 0 | M67: 20387.89 | N67: 20387.89
A68: =G68&H68 -> 134052 | B68: IS | C68: 2. Variable cost Mat | D68: 20a. Paper | E68: =IF(H68=1,"Hillsboro",IF(H68=2,"Angola",IF(H68=9,"Hillsboro",IF(H68=99,"Hillsboro",IF(H68=50,"Pixelle","???"))))) -> Angola | F68: =IF(H68=1,"Hillsboro",IF(H68=2,"Angola",IF(H68=9,"Corp",IF(H68=99,"Corp",IF(H68=50,"Pixelle","???"))))) -> Angola | G68: 13405 | H68: 2 | I68: FINISHED GOODS VARIBLE | J68: P | L68: 0 | M68: 23582.06 | N68: 23582.06
A69: =G69&H69 -> 400001 | B69: IS | C69: 1. Sales | D69: 1. Sales | E69: =IF(H69=1,"Hillsboro",IF(H69=2,"Angola",IF(H69=9,"Hillsboro",IF(H69=99,"Hillsboro",IF(H69=50,"Pixelle","???"))))) -> Hillsboro | F69: =IF(H69=1,"Hillsboro",IF(H69=2,"Angola",IF(H69=9,"Corp",IF(H69=99,"Corp",IF(H69=50,"Pixelle","???"))))) -> Hillsboro | G69: 40000 | H69: 1 | I69: SALES | J69: P | L69: 0 | M69: -2261060.7 | N69: -2261060.7
A70: =G70&H70 -> 400002 | B70: IS | C70: 1. Sales | D70: 1. Sales | E70: =IF(H70=1,"Hillsboro",IF(H70=2,"Angola",IF(H70=9,"Hillsboro",IF(H70=99,"Hillsboro",IF(H70=50,"Pixelle","???"))))) -> Angola | F70: =IF(H70=1,"Hillsboro",IF(H70=2,"Angola",IF(H70=9,"Corp",IF(H70=99,"Corp",IF(H70=50,"Pixelle","???"))))) -> Angola | G70: 40000 | H70: 2 | I70: SALES | J70: P | L70: 0 | M70: -1512908.5 | N70: -1512908.5
A71: =G71&H71 -> 4000050 | B71: IS | C71: 1. Sales | D71: 1. Sales | E71: =IF(H71=1,"Hillsboro",IF(H71=2,"Angola",IF(H71=9,"Hillsboro",IF(H71=99,"Hillsboro",IF(H71=50,"Pixelle","???"))))) -> Pixelle | F71: =IF(H71=1,"Hillsboro",IF(H71=2,"Angola",IF(H71=9,"Corp",IF(H71=99,"Corp",IF(H71=50,"Pixelle","???"))))) -> Pixelle | G71: 40000 | H71: 50 | I71: SALES | J71: P | L71: 0 | M71: -962160.67 | N71: -962160.67
A72: =G72&H72 -> 407001 | B72: IS | C72: 1. Sales | D72: 1. Sales | E72: =IF(H72=1,"Hillsboro",IF(H72=2,"Angola",IF(H72=9,"Hillsboro",IF(H72=99,"Hillsboro",IF(H72=50,"Pixelle","???"))))) -> Hillsboro | F72: =IF(H72=1,"Hillsboro",IF(H72=2,"Angola",IF(H72=9,"Corp",IF(H72=99,"Corp",IF(H72=50,"Pixelle","???"))))) -> Hillsboro | G72: 40700 | H72: 1 | I72: SALES - MISC FLAT CHARGES | J72: P | L72: 0 | M72: -3851.03 | N72: -3851.03
A73: =G73&H73 -> 407002 | B73: IS | C73: 1. Sales | D73: 1. Sales | E73: =IF(H73=1,"Hillsboro",IF(H73=2,"Angola",IF(H73=9,"Hillsboro",IF(H73=99,"Hillsboro",IF(H73=50,"Pixelle","???"))))) -> Angola | F73: =IF(H73=1,"Hillsboro",IF(H73=2,"Angola",IF(H73=9,"Corp",IF(H73=99,"Corp",IF(H73=50,"Pixelle","???"))))) -> Angola | G73: 40700 | H73: 2 | I73: SALES - MISC FLAT CHARGES | J73: P | L73: 0 | M73: -8382.26 | N73: -8382.26
A74: =G74&H74 -> 4070050 | B74: IS | C74: 1. Sales | D74: 1. Sales | E74: =IF(H74=1,"Hillsboro",IF(H74=2,"Angola",IF(H74=9,"Hillsboro",IF(H74=99,"Hillsboro",IF(H74=50,"Pixelle","???"))))) -> Pixelle | F74: =IF(H74=1,"Hillsboro",IF(H74=2,"Angola",IF(H74=9,"Corp",IF(H74=99,"Corp",IF(H74=50,"Pixelle","???"))))) -> Pixelle | G74: 40700 | H74: 50 | I74: SALES - MISC FLAT CHARGES | J74: P | L74: 0 | M74: 0 | N74: 0
A75: =G75&H75 -> 410001 | B75: IS | C75: 1. Sales | D75: 1. Sales | E75: =IF(H75=1,"Hillsboro",IF(H75=2,"Angola",IF(H75=9,"Hillsboro",IF(H75=99,"Hillsboro",IF(H75=50,"Pixelle","???"))))) -> Hillsboro | F75: =IF(H75=1,"Hillsboro",IF(H75=2,"Angola",IF(H75=9,"Corp",IF(H75=99,"Corp",IF(H75=50,"Pixelle","???"))))) -> Hillsboro | G75: 41000 | H75: 1 | I75: SALES DISCOUNTS | J75: P | L75: 0 | M75: 31735.48 | N75: 31735.48
A76: =G76&H76 -> 410002 | B76: IS | C76: 1. Sales | D76: 1. Sales | E76: =IF(H76=1,"Hillsboro",IF(H76=2,"Angola",IF(H76=9,"Hillsboro",IF(H76=99,"Hillsboro",IF(H76=50,"Pixelle","???"))))) -> Angola | F76: =IF(H76=1,"Hillsboro",IF(H76=2,"Angola",IF(H76=9,"Corp",IF(H76=99,"Corp",IF(H76=50,"Pixelle","???"))))) -> Angola | G76: 41000 | H76: 2 | I76: SALES DISCOUNTS | J76: P | L76: 0 | M76: 21096.81 | N76: 21096.81
A77: =G77&H77 -> 4100099 | B77: IS | C77: 1. Sales | D77: 1. Sales | E77: =IF(H77=1,"Hillsboro",IF(H77=2,"Angola",IF(H77=9,"Hillsboro",IF(H77=99,"Hillsboro",IF(H77=50,"Pixelle","???"))))) -> Hillsboro | F77: =IF(H77=1,"Hillsboro",IF(H77=2,"Angola",IF(H77=9,"Corp",IF(H77=99,"Corp",IF(H77=50,"Pixelle","???"))))) -> Corp | G77: 41000 | H77: 99 | I77: SALES DISCOUNTS | J77: P | L77: 0 | M77: 0 | N77: 0
A78: =G78&H78 -> 411001 | B78: IS | C78: 1. Sales | D78: 1. Sales | E78: =IF(H78=1,"Hillsboro",IF(H78=2,"Angola",IF(H78=9,"Hillsboro",IF(H78=99,"Hillsboro",IF(H78=50,"Pixelle","???"))))) -> Hillsboro | F78: =IF(H78=1,"Hillsboro",IF(H78=2,"Angola",IF(H78=9,"Corp",IF(H78=99,"Corp",IF(H78=50,"Pixelle","???"))))) -> Hillsboro | G78: 41100 | H78: 1 | I78: SALES REBATE DISCOUNTS | J78: P | K78: SALES REBATE DISCOUNTS | L78: 0 | M78: 343.2 | N78: 343.2
A79: =G79&H79 -> 420002 | B79: IS | C79: 8. Admin | D79: 8. SG&A | E79: =IF(H79=1,"Hillsboro",IF(H79=2,"Angola",IF(H79=9,"Hillsboro",IF(H79=99,"Hillsboro",IF(H79=50,"Pixelle","???"))))) -> Angola | F79: =IF(H79=1,"Hillsboro",IF(H79=2,"Angola",IF(H79=9,"Corp",IF(H79=99,"Corp",IF(H79=50,"Pixelle","???"))))) -> Angola | G79: 42000 | H79: 2 | I79: MEALS AND ENTERTAINMENT | J79: P | L79: 0 | M79: 4629.16 | N79: 4629.16
A80: =G80&H80 -> 4200099 | B80: IS | C80: 8. Admin | D80: 8. SG&A | E80: =IF(H80=1,"Hillsboro",IF(H80=2,"Angola",IF(H80=9,"Hillsboro",IF(H80=99,"Hillsboro",IF(H80=50,"Pixelle","???"))))) -> Hillsboro | F80: =IF(H80=1,"Hillsboro",IF(H80=2,"Angola",IF(H80=9,"Corp",IF(H80=99,"Corp",IF(H80=50,"Pixelle","???"))))) -> Corp | G80: 42000 | H80: 99 | I80: MEALS AND ENTERTAINMENT | J80: P | L80: 0 | M80: 202.17 | N80: 202.17 | P80: =VLOOKUP(A80,'[2]SORTED B VS P'!$A$82:$M$315,13,FALSE) -> 1447.37 | Q80: =P80/2 -> 723.685 | R80: =N80-Q80 -> -521.515
A81: =G81&H81 -> 510001 | B81: IS | C81: 2. Variable cost Mat | D81: 20. Paper | E81: =IF(H81=1,"Hillsboro",IF(H81=2,"Angola",IF(H81=9,"Hillsboro",IF(H81=99,"Hillsboro",IF(H81=50,"Pixelle","???"))))) -> Hillsboro | F81: =IF(H81=1,"Hillsboro",IF(H81=2,"Angola",IF(H81=9,"Corp",IF(H81=99,"Corp",IF(H81=50,"Pixelle","???"))))) -> Hillsboro | G81: 51000 | H81: 1 | I81: COGS-PAPER | J81: P | L81: 0 | M81: 898525.97 | N81: 898525.97
A82: =G82&H82 -> 510002 | B82: IS | C82: 2. Variable cost Mat | D82: 20. Paper | E82: =IF(H82=1,"Hillsboro",IF(H82=2,"Angola",IF(H82=9,"Hillsboro",IF(H82=99,"Hillsboro",IF(H82=50,"Pixelle","???"))))) -> Angola | F82: =IF(H82=1,"Hillsboro",IF(H82=2,"Angola",IF(H82=9,"Corp",IF(H82=99,"Corp",IF(H82=50,"Pixelle","???"))))) -> Angola | G82: 51000 | H82: 2 | I82: COGS-PAPER | J82: P | L82: 0 | M82: 656720.71 | N82: 656720.71
A83: =G83&H83 -> 520001 | B83: IS | C83: 2. Variable cost Mat | D83: 21. Carbon | E83: =IF(H83=1,"Hillsboro",IF(H83=2,"Angola",IF(H83=9,"Hillsboro",IF(H83=99,"Hillsboro",IF(H83=50,"Pixelle","???"))))) -> Hillsboro | F83: =IF(H83=1,"Hillsboro",IF(H83=2,"Angola",IF(H83=9,"Corp",IF(H83=99,"Corp",IF(H83=50,"Pixelle","???"))))) -> Hillsboro | G83: 52000 | H83: 1 | I83: COGS-CARBON | J83: P | L83: 0 | M83: 1184.61 | N83: 1184.61
A84: =G84&H84 -> 530001 | B84: IS | C84: 2. Variable cost Mat | D84: 22. Cartons | E84: =IF(H84=1,"Hillsboro",IF(H84=2,"Angola",IF(H84=9,"Hillsboro",IF(H84=99,"Hillsboro",IF(H84=50,"Pixelle","???"))))) -> Hillsboro | F84: =IF(H84=1,"Hillsboro",IF(H84=2,"Angola",IF(H84=9,"Corp",IF(H84=99,"Corp",IF(H84=50,"Pixelle","???"))))) -> Hillsboro | G84: 53000 | H84: 1 | I84: COGS-CARTONS | J84: P | L84: 0 | M84: 41215.53 | N84: 41215.53
A85: =G85&H85 -> 530002 | B85: IS | C85: 2. Variable cost Mat | D85: 22. Cartons | E85: =IF(H85=1,"Hillsboro",IF(H85=2,"Angola",IF(H85=9,"Hillsboro",IF(H85=99,"Hillsboro",IF(H85=50,"Pixelle","???"))))) -> Angola | F85: =IF(H85=1,"Hillsboro",IF(H85=2,"Angola",IF(H85=9,"Corp",IF(H85=99,"Corp",IF(H85=50,"Pixelle","???"))))) -> Angola | G85: 53000 | H85: 2 | I85: COGS-CARTONS | J85: P | L85: 0 | M85: 35491.57 | N85: 35491.57
A86: =G86&H86 -> 540001 | B86: IS | C86: 2. Variable cost Mat | D86: 23. Ink | E86: =IF(H86=1,"Hillsboro",IF(H86=2,"Angola",IF(H86=9,"Hillsboro",IF(H86=99,"Hillsboro",IF(H86=50,"Pixelle","???"))))) -> Hillsboro | F86: =IF(H86=1,"Hillsboro",IF(H86=2,"Angola",IF(H86=9,"Corp",IF(H86=99,"Corp",IF(H86=50,"Pixelle","???"))))) -> Hillsboro | G86: 54000 | H86: 1 | I86: COGS-INK | J86: P | L86: 0 | M86: 30890.26 | N86: 30890.26
A87: =G87&H87 -> 540002 | B87: IS | C87: 2. Variable cost Mat | D87: 23. Ink | E87: =IF(H87=1,"Hillsboro",IF(H87=2,"Angola",IF(H87=9,"Hillsboro",IF(H87=99,"Hillsboro",IF(H87=50,"Pixelle","???"))))) -> Angola | F87: =IF(H87=1,"Hillsboro",IF(H87=2,"Angola",IF(H87=9,"Corp",IF(H87=99,"Corp",IF(H87=50,"Pixelle","???"))))) -> Angola | G87: 54000 | H87: 2 | I87: COGS-INK | J87: P | L87: 0 | M87: 8441.74 | N87: 8441.74
A88: =G88&H88 -> 550001 | B88: IS | C88: 2. Variable cost Mat | D88: 24. Plates | E88: =IF(H89=1,"Hillsboro",IF(H89=2,"Angola",IF(H89=9,"Hillsboro",IF(H89=99,"Hillsboro",IF(H89=50,"Pixelle","???"))))) -> Angola | F88: =IF(H89=1,"Hillsboro",IF(H89=2,"Angola",IF(H89=9,"Corp",IF(H89=99,"Corp",IF(H89=50,"Pixelle","???"))))) -> Angola | G88: 55000 | H88: 1 | I88: COGS-PLATES/COMP CHARGES | J88: P | L88: 0 | M88: 49422.12 | N88: 49422.12
A89: =G89&H89 -> 550002 | B89: IS | C89: 2. Variable cost Mat | D89: 24. Plates | E89: =IF(H90=1,"Hillsboro",IF(H90=2,"Angola",IF(H90=9,"Hillsboro",IF(H90=99,"Hillsboro",IF(H90=50,"Pixelle","???"))))) -> Hillsboro | F89: =IF(H90=1,"Hillsboro",IF(H90=2,"Angola",IF(H90=9,"Corp",IF(H90=99,"Corp",IF(H90=50,"Pixelle","???"))))) -> Hillsboro | G89: 55000 | H89: 2 | I89: COGS-PLATES/COMP CHARGES | J89: P | L89: 0 | M89: 15851.79 | N89: 15851.79
A90: =G90&H90 -> 560001 | B90: IS | C90: 2. Variable cost Mat | D90: 25. Supplies | E90: =IF(H91=1,"Hillsboro",IF(H91=2,"Angola",IF(H91=9,"Hillsboro",IF(H91=99,"Hillsboro",IF(H91=50,"Pixelle","???"))))) -> Angola | F90: =IF(H91=1,"Hillsboro",IF(H91=2,"Angola",IF(H91=9,"Corp",IF(H91=99,"Corp",IF(H91=50,"Pixelle","???"))))) -> Angola | G90: 56000 | H90: 1 | I90: COGS-SUPPLIES | J90: P | L90: 0 | M90: 56554.28 | N90: 56554.28
A91: =G91&H91 -> 560002 | B91: IS | C91: 2. Variable cost Mat | D91: 25. Supplies | E91: =IF(H92=1,"Hillsboro",IF(H92=2,"Angola",IF(H92=9,"Hillsboro",IF(H92=99,"Hillsboro",IF(H92=50,"Pixelle","???"))))) -> Pixelle | F91: =IF(H92=1,"Hillsboro",IF(H92=2,"Angola",IF(H92=9,"Corp",IF(H92=99,"Corp",IF(H92=50,"Pixelle","???"))))) -> Pixelle | G91: 56000 | H91: 2 | I91: COGS-SUPPLIES | J91: P | L91: 0 | M91: 22188.07 | N91: 22188.07
A92: =G92&H92 -> 5600050 | B92: IS | C92: 2. Variable cost Mat | D92: 25. Supplies | E92: =IF(H93=1,"Hillsboro",IF(H93=2,"Angola",IF(H93=9,"Hillsboro",IF(H93=99,"Hillsboro",IF(H93=50,"Pixelle","???"))))) -> Angola | F92: =IF(H93=1,"Hillsboro",IF(H93=2,"Angola",IF(H93=9,"Corp",IF(H93=99,"Corp",IF(H93=50,"Pixelle","???"))))) -> Angola | G92: 56000 | H92: 50 | I92: COGS-SUPPLIES | J92: P | L92: 0 | M92: 21662.42 | N92: 21662.42
A93: =G93&H93 -> 562002 | B93: IS | C93: 2. Variable cost Mat | D93: 25. Supplies | E93: =IF(H94=1,"Hillsboro",IF(H94=2,"Angola",IF(H94=9,"Hillsboro",IF(H94=99,"Hillsboro",IF(H94=50,"Pixelle","???"))))) -> Hillsboro | F93: =IF(H94=1,"Hillsboro",IF(H94=2,"Angola",IF(H94=9,"Corp",IF(H94=99,"Corp",IF(H94=50,"Pixelle","???"))))) -> Hillsboro | G93: 56200 | H93: 2 | I93: COGS-SUPPLIES-LABEL | J93: P | K93: COGS-SUPPLIES | L93: 0 | M93: 66787.51 | N93: 66787.51
A94: =G94&H94 -> 565001 | B94: IS | C94: 2. Variable cost Mat | D94: 26. Integ Mat | E94: =IF(H95=1,"Hillsboro",IF(H95=2,"Angola",IF(H95=9,"Hillsboro",IF(H95=99,"Hillsboro",IF(H95=50,"Pixelle","???"))))) -> Hillsboro | F94: =IF(H95=1,"Hillsboro",IF(H95=2,"Angola",IF(H95=9,"Corp",IF(H95=99,"Corp",IF(H95=50,"Pixelle","???"))))) -> Hillsboro | G94: 56500 | H94: 1 | I94: COGS-INTEGRATED MATERIAL | J94: P | K94: COGS-TAMARACK & HUNKLER | L94: 0 | M94: 37171.24 | N94: 37171.24
A95: =G95&H95 -> 595001 | B95: IS | C95: 2a. Variable cost Mat Out/Env | D95: 28. Envelops | E95: =IF(H95=1,"Hillsboro",IF(H95=2,"Angola",IF(H95=9,"Hillsboro",IF(H95=99,"Hillsboro",IF(H95=50,"Pixelle","???"))))) -> Hillsboro | F95: =IF(H95=1,"Hillsboro",IF(H95=2,"Angola",IF(H95=9,"Corp",IF(H95=99,"Corp",IF(H95=50,"Pixelle","???"))))) -> Hillsboro | G95: 59500 | H95: 1 | I95: ENVELOPES | J95: P | L95: 0 | M95: 9098.17 | N95: 9098.17
A96: =G96&H96 -> 595501 | B96: IS | C96: 2a. Variable cost Mat Out/Env | D96: 28. Envelops | E96: =IF(H96=1,"Hillsboro",IF(H96=2,"Angola",IF(H96=9,"Hillsboro",IF(H96=99,"Hillsboro",IF(H96=50,"Pixelle","???"))))) -> Hillsboro | F96: =IF(H96=1,"Hillsboro",IF(H96=2,"Angola",IF(H96=9,"Corp",IF(H96=99,"Corp",IF(H96=50,"Pixelle","???"))))) -> Hillsboro | G96: 59550 | H96: 1 | I96: ENVELOPE-IMPRINTING COST | J96: P | L96: 0 | M96: 2610 | N96: 2610
A97: =G97&H97 -> 601001 | B97: IS | C97: 8. Admin | D97: 30. Insurance | E97: =IF(H97=1,"Hillsboro",IF(H97=2,"Angola",IF(H97=9,"Hillsboro",IF(H97=99,"Hillsboro",IF(H97=50,"Pixelle","???"))))) -> Hillsboro | F97: =IF(H97=1,"Hillsboro",IF(H97=2,"Angola",IF(H97=9,"Corp",IF(H97=99,"Corp",IF(H97=50,"Pixelle","???"))))) -> Hillsboro | G97: 60100 | H97: 1 | I97: HEALTH INSURANCE -ADMIN | J97: P | L97: 0 | M97: 26538.77 | N97: 26538.77 | P97: =VLOOKUP(A97,'[2]SORTED B VS P'!$A$82:$M$315,13,FALSE) -> 32467.32 | Q97: =P97/2 -> 16233.66 | R97: =N97-Q97 -> 10305.11
A98: =G98&H98 -> 6010099 | B98: IS | C98: 8. Admin | D98: 30. Insurance | E98: =IF(H98=1,"Hillsboro",IF(H98=2,"Angola",IF(H98=9,"Hillsboro",IF(H98=99,"Hillsboro",IF(H98=50,"Pixelle","???"))))) -> Hillsboro | F98: =IF(H98=1,"Hillsboro",IF(H98=2,"Angola",IF(H98=9,"Corp",IF(H98=99,"Corp",IF(H98=50,"Pixelle","???"))))) -> Corp | G98: 60100 | H98: 99 | I98: HEALTH INSURANCE -ADMIN | J98: P | L98: 0 | M98: 35341.54 | N98: 35341.54 | P98: =VLOOKUP(A98,'[2]SORTED B VS P'!$A$82:$M$315,13,FALSE) -> 57038.44 | Q98: =P98/2 -> 28519.22 | R98: =N98-Q98 -> 6822.32
A99: =G99&H99 -> 604001 | B99: IS | C99: 4. Mfg OVHD | E99: =IF(H99=1,"Hillsboro",IF(H99=2,"Angola",IF(H99=9,"Hillsboro",IF(H99=99,"Hillsboro",IF(H99=50,"Pixelle","???"))))) -> Hillsboro | F99: =IF(H99=1,"Hillsboro",IF(H99=2,"Angola",IF(H99=9,"Corp",IF(H99=99,"Corp",IF(H99=50,"Pixelle","???"))))) -> Hillsboro | G99: 60400 | H99: 1 | I99: CARETAKING-PRODUCTION | J99: P | K99: CARETAKING-PRODUCTION | L99: 0 | M99: 3063.96 | N99: 3063.96
A100: =G100&H100 -> 604002 | B100: IS | C100: 4. Mfg OVHD | E100: =IF(H100=1,"Hillsboro",IF(H100=2,"Angola",IF(H100=9,"Hillsboro",IF(H100=99,"Hillsboro",IF(H100=50,"Pixelle","???"))))) -> Angola | F100: =IF(H100=1,"Hillsboro",IF(H100=2,"Angola",IF(H100=9,"Corp",IF(H100=99,"Corp",IF(H100=50,"Pixelle","???"))))) -> Angola | G100: 60400 | H100: 2 | I100: CARETAKING-PRODUCTION | J100: P | K100: CARETAKING-PRODUCTION | L100: 0 | M100: 4113.31 | N100: 4113.31
A101: =G101&H101 -> 6040050 | B101: IS | C101: 4. Mfg OVHD | E101: =IF(H101=1,"Hillsboro",IF(H101=2,"Angola",IF(H101=9,"Hillsboro",IF(H101=99,"Hillsboro",IF(H101=50,"Pixelle","???"))))) -> Pixelle | F101: =IF(H101=1,"Hillsboro",IF(H101=2,"Angola",IF(H101=9,"Corp",IF(H101=99,"Corp",IF(H101=50,"Pixelle","???"))))) -> Pixelle | G101: 60400 | H101: 50 | I101: CARETAKING-PRODUCTION | J101: P | K101: CARETAKING-PRODUCTION | L101: 0 | M101: 1569.48 | N101: 1569.48
A102: =G102&H102 -> 605002 | B102: IS | C102: 4. Mfg OVHD | E102: =IF(H102=1,"Hillsboro",IF(H102=2,"Angola",IF(H102=9,"Hillsboro",IF(H102=99,"Hillsboro",IF(H102=50,"Pixelle","???"))))) -> Angola | F102: =IF(H102=1,"Hillsboro",IF(H102=2,"Angola",IF(H102=9,"Corp",IF(H102=99,"Corp",IF(H102=50,"Pixelle","???"))))) -> Angola | G102: 60500 | H102: 2 | I102: RENT | J102: P | L102: 0 | M102: 48000 | N102: 48000
A103: =G103&H103 -> 6050050 | B103: IS | C103: 4. Mfg OVHD | E103: =IF(H103=1,"Hillsboro",IF(H103=2,"Angola",IF(H103=9,"Hillsboro",IF(H103=99,"Hillsboro",IF(H103=50,"Pixelle","???"))))) -> Pixelle | F103: =IF(H103=1,"Hillsboro",IF(H103=2,"Angola",IF(H103=9,"Corp",IF(H103=99,"Corp",IF(H103=50,"Pixelle","???"))))) -> Pixelle | G103: 60500 | H103: 50 | I103: RENT | J103: P | L103: 0 | M103: 15000 | N103: 15000
A104: =G104&H104 -> 606001 | B104: IS | C104: 4. Mfg OVHD | E104: =IF(H104=1,"Hillsboro",IF(H104=2,"Angola",IF(H104=9,"Hillsboro",IF(H104=99,"Hillsboro",IF(H104=50,"Pixelle","???"))))) -> Hillsboro | F104: =IF(H104=1,"Hillsboro",IF(H104=2,"Angola",IF(H104=9,"Corp",IF(H104=99,"Corp",IF(H104=50,"Pixelle","???"))))) -> Hillsboro | G104: 60600 | H104: 1 | I104: REPAIRS & MAINTENANCE | J104: P | L104: 0 | M104: 48867.5 | N104: 48867.5
A105: =G105&H105 -> 606002 | B105: IS | C105: 4. Mfg OVHD | E105: =IF(H105=1,"Hillsboro",IF(H105=2,"Angola",IF(H105=9,"Hillsboro",IF(H105=99,"Hillsboro",IF(H105=50,"Pixelle","???"))))) -> Angola | F105: =IF(H105=1,"Hillsboro",IF(H105=2,"Angola",IF(H105=9,"Corp",IF(H105=99,"Corp",IF(H105=50,"Pixelle","???"))))) -> Angola | G105: 60600 | H105: 2 | I105: REPAIRS & MAINTENANCE | J105: P | L105: 0 | M105: 17564.43 | N105: 17564.43
A106: =G106&H106 -> 6060050 | B106: IS | C106: 4. Mfg OVHD | E106: =IF(H106=1,"Hillsboro",IF(H106=2,"Angola",IF(H106=9,"Hillsboro",IF(H106=99,"Hillsboro",IF(H106=50,"Pixelle","???"))))) -> Pixelle | F106: =IF(H106=1,"Hillsboro",IF(H106=2,"Angola",IF(H106=9,"Corp",IF(H106=99,"Corp",IF(H106=50,"Pixelle","???"))))) -> Pixelle | G106: 60600 | H106: 50 | I106: REPAIRS & MAINTENANCE | J106: P | L106: 0 | M106: 35479.6 | N106: 35479.6
A107: =G107&H107 -> 6060099 | B107: IS | C107: 4. Mfg OVHD | E107: =IF(H107=1,"Hillsboro",IF(H107=2,"Angola",IF(H107=9,"Hillsboro",IF(H107=99,"Hillsboro",IF(H107=50,"Pixelle","???"))))) -> Hillsboro | F107: =IF(H107=1,"Hillsboro",IF(H107=2,"Angola",IF(H107=9,"Corp",IF(H107=99,"Corp",IF(H107=50,"Pixelle","???"))))) -> Corp | G107: 60600 | H107: 99 | I107: REPAIRS & MAINTENANCE | J107: P | L107: 0 | M107: 6711.18 | N107: 6711.18
A108: =G108&H108 -> 607001 | B108: IS | C108: 2. Variable cost Labor | E108: =IF(H108=1,"Hillsboro",IF(H108=2,"Angola",IF(H108=9,"Hillsboro",IF(H108=99,"Hillsboro",IF(H108=50,"Pixelle","???"))))) -> Hillsboro | F108: =IF(H108=1,"Hillsboro",IF(H108=2,"Angola",IF(H108=9,"Corp",IF(H108=99,"Corp",IF(H108=50,"Pixelle","???"))))) -> Hillsboro | G108: 60700 | H108: 1 | I108: PRODUCTION WAGES | J108: P | L108: 0 | M108: 195400.87 | N108: 195400.87
...

Sheet Fordyce TB
A1: ACCOUNT# | B1: LEVEL1 | C1: DESCRIPTION | D1: ACCOUNT TYPE | E1: DESCRIPTION | F1: BEG_BAL_JAN2026 | G1: NET_CHANGE | H1: END_BAL_JUNE2026
A2: 10120 | B2: 6 | C2: CASH - MERCHANTS NAT BANK | D2: B | F2: 71603.03 | G2: =+H2-F2 -> -31898.43 | H2: 39704.6
A3: 10020 | B3: 6 | C3: PETTY CASH | D3: B | F3: 119.58 | G3: =+H3-F3 -> -99.94 | H3: 19.64
A4: 11000 | B4: 6 | C4: ACCOUNTS RECEIVABLE | D4: B | F4: 14174.39 | G4: =+H4-F4 -> 8047.51 | H4: 22221.9
A5: 17000 | B5: 6 | C5: LEASEHOLD IMPROVEMENTS | D5: B | F5: 65050 | G5: 0 | H5: 65050
A6: 20000 | B6: 6 | C6: ACCOUNTS PAYABLE | D6: B | F6: -9205.96 | G6: =+H6-F6 -> 9426.29 | H6: 220.33
A7: 31000 | B7: 6 | C7: RETAINED EARNINGS | D7: B | F7: =-94480.99-47260.05 -> -141741.04 | G7: 0 | H7: 141741.04
A8: 40000 | B8: 6 | C8: SALES | D8: P | F8: 0 | G8: -92732.68 | H8: -92732.68
A9: 40100 | B9: 6 | C9: SALES-MACHINES | D9: P | G9: 0 | H9: 0
A10: 41000 | B10: 6 | C10: SALES DISCOUNTS | D10: P | G10: 0 | H10: 0
A11: 51500 | B11: 6 | C11: COGS-RAW MATERIALS GF | D11: P | G11: 2827.87 | H11: 2827.87
A12: 51550 | B12: 6 | C12: COGS-PARTS PURCHASED GF | D12: P | G12: 42947.71 | H12: 42947.71
A13: 52500 | B13: 6 | C13: COGS-OUTSIDE SERVICES GF | D13: P | G13: 4528 | H13: 4528
A14: 56000 | B14: 6 | C14: COGS-SUPPLIES | D14: P | G14: 10.44 | H14: 10.44
A15: 60500 | B15: 6 | C15: RENT | D15: P | G15: 4800 | H15: 4800
A16: 60600 | B16: 6 | C16: REPAIRS & MAINTENANCE | D16: P | G16: 709.53 | H16: 709.53
A17: 60700 | B17: 6 | C17: PRODUCTION WAGES | D17: P | G17: 43608.46 | H17: 43608.46
A18: 66240 | B18: 6 | C18: BANK CHARGES -SERVICE & FEES | D18: P | G18: 18 | H18: 18
A19: 66600 | B19: 6 | C19: DUES & SUBSCRIPTIONS | D19: P | G19: 0 | H19: 0
A20: 67200 | B20: 6 | C20: OFFICE SUPPLIES | D20: P | G20: 1062.21 | H20: 1062.21
... A26: 90000 | B26: 6 | C26: MISC. EXPENSE | D26: P | G26: 0 | H26: 0
F28: =SUM(F2:F27) -> 0 | G28: =SUM(G2:G27) -> 9.3507424e-12 | H28: =SUM(H8:H27) -> 14524.57

Sheet Inv
A2: TYPE | B2: BS
A3: HCF FINANCIALS HY1 2026
D4: Values
A5: Cat1 | B5: ACCOUNT# | C5: DESCRIPTION | D5: Sum of BEG_BAL_JAN2026 | E5: Sum of END_BAL_JUN2026 | F5: Jun 2026 % Total
A6: 4. Inv Paper | B6: 13100 | C6: INVENTORY-BOND PAPER | D6: 860999.76 | E6: 759701.85 | F6: =E6/E$14 -> 0.69157643
A7: 4. Inv Label Mat | B7: 13150 | C7: INVENTORY-LABEL MATERIAL | D7: 29721.35 | E7: 22787.6 | F7: =E7/E$14 -> 0.020744147
A8: 4. Inv Carbon | B8: 13200 | C8: INVENTORY-CARBON | D8: 574.15 | E8: 1867.24 | F8: =E8/E$14 -> 0.0016997973
A9: 4. Inv Cartons | B9: 13300 | C9: INVENTORY-CARTONS | D9: 84639.72 | E9: 95715.9 | F9: =E9/E$14 -> 0.087132683
A10: 4. Inv FGS | B10: 13400 | C10: INVENTORY-F/G | D10: 203836.39 | E10: 159866.44 | F10: =E10/E$14 -> 0.14553059
A11: 4. Inv Supplies | B11: 13600 | C11: INVENTORY-SUPPLIES | D11: 22260.86 | E11: 11680.93 | F11: =E11/E$14 -> 0.010633456
A12: 4. Inv TAMARACK & HUNKELER | B12: 13650 | C12: INVENTORY-TAMARACK & HUNKELER | D12: 28760.58 | E12: 34474.86 | F12: =E12/E$14 -> 0.031383365
A13: 4. Inv Envelopes | B13: 13950 | C13: INVENTORY-ENVELOPES | D13: 9108.79 | E13: 12412.62 | F13: =E13/E$14 -> 0.011299532
A14: Grand Total | D14: 1239901.6 | E14: 1098507.4 | F14: =E14/E$14 -> 1
A19: TYPE | B19: BS
A20: HCF FINANCIALS HY1 2026
D21: Plant2 | E21: Values
D22: Angola | F22: Hillsboro
A23: Cat1 | B23: ACCOUNT# | C23: DESCRIPTION | D23: Sum of BEG_BAL_JAN2026 | E23: Sum of END_BAL_JUN2026 | F23: Sum of BEG_BAL_JAN2026 | G23: Sum of END_BAL_JUN2026 | H23: % Angola | I23: % Hillsboro
A24: 4. Inv Paper | B24: 13100 | C24: INVENTORY-BOND PAPER | D24: 416192.86 | E24: 382790.87 | F24: 444806.9 | G24: 376910.98 | H24: =E24/E$32 -> 0.65705114 | I24: =G24/G$32 -> 0.73056334
A25: 4. Inv Label Mat | B25: 13150 | C25: INVENTORY-LABEL MATERIAL | D25: 29721.35 | E25: 22787.6 | H25: =E25/E$32 -> 0.039114356 | I25: =G25/G$32 -> 0
A26: 4. Inv Carbon | B26: 13200 | C26: INVENTORY-CARBON | F26: 574.15 | G26: 1867.24 | H26: =E26/E$32 -> 0 | I26: =G26/G$32 -> 0.0036192554
A27: 4. Inv Cartons | B27: 13300 | C27: INVENTORY-CARTONS | D27: 51299.41 | E27: 57365.49 | F27: 33340.31 | G27: 38350.41 | H27: =E27/E$32 -> 0.098466456 | I27: =G27/G$32 -> 0.074334272
A28: 4. Inv FGS | B28: 13400 | C28: INVENTORY-F/G | D28: 139992.39 | E28: 116410.33 | F28: 63844 | G28: 43456.11 | H28: =E28/E$32 -> 0.19981548 | I28: =G28/G$32 -> 0.084230607
A29: 4. Inv Supplies | B29: 13600 | C29: INVENTORY-SUPPLIES | D29: 3642.35 | E29: 3234.87 | F29: 18618.51 | G29: 8446.06 | H29: =E29/E$32 -> 0.005552575 | I29: =G29/G$32 -> 0.016370926
A30: 4. Inv TAMARACK & HUNKELER | B30: 13650 | C30: INVENTORY-TAMARACK & HUNKELER | F30: 28760.58 | G30: 34474.86 | H30: =E30/E$32 -> 0 | I30: =G30/G$32 -> 0.066822327
A31: 4. Inv Envelopes | B31: 13950 | C31: INVENTORY-ENVELOPES | F31: 9108.79 | G31: 12412.62 | H31: =E31/E$32 -> 0 | I31: =G31/G$32 -> 0.024059275
A32: Grand Total | D32: 640848.36 | E32: 582589.16 | F32: 599053.24 | G32: 515918.28 | H32: =E32/E$32 -> 1 | I32: =G32/G$32 -> 1

Sheet BS
A2: TYPE | B2: BS
A3: HCF FINANCIALS HY1 2026
D4: Plant1 | E4: Values
D5: Angola | F5: Hillsboro | H5: Pixelle
A6: Cat1 | B6: ACCOUNT# | C6: DESCRIPTION | D6: Sum of BEG_BAL_JAN2026 | E6: Sum of END_BAL_JUN2026 | F6: Sum of BEG_BAL_JAN2026 | G6: Sum of END_BAL_JUN2026 | H6: Sum of BEG_BAL_JAN2026 | I6: Sum of END_BAL_JUN2026
A7: 1. Cash | B7: 10010 | C7: CASH - FIRST STATE BANK | F7: 534702.04 | G7: 706065.54
B8: 10020 | C8: PETTY CASH | D8: 400 | E8: 400 | F8: 400 | G8: 400
B9: 10120 | C9: CASH - HEALTH INS. ACCT | F9: 14649.31 | G9: 15159.49
B10: 10130 | C10: CASH - FSA HEALTH ACCT | F10: 17101.9 | G10: 17899.4
A11: 1. Cash Total | D11: 400 | E11: 400 | F11: 566853.25 | G11: 739524.43
A12: 2. AR | B12: 11000 | C12: ACCOUNTS RECEIVABLE | F12: 674695.59 | G12: 779487.52
B13: 11100 | C13: ACCOUNTS RECEIVABLE-OTHER | F13: 40084.73 | G13: 15.75
A14: 2. AR Total | F14: 714780.32 | G14: 779503.27
A15: 3. Prepaid | B15: 12000 | C15: PREPAID EXPENSES | F15: 4763.44 | G15: 21753.04
B16: 12100 | C16: DEPOSITS | F16: 500 | G16: 500
B17: 12110 | C17: PREPAID INSURANCE | F17: 7868 | G17: 11462.5
A18: 3. Prepaid Total | F18: 13131.44 | G18: 33715.54
A19: 4. Inv Paper | B19: 13100 | C19: INVENTORY-BOND PAPER | D19: 416192.86 | E19: 382790.87 | F19: 444806.9 | G19: 376910.98
A20: 4. Inv Paper Total | D20: 416192.86 | E20: 382790.87 | F20: 444806.9 | G20: 376910.98
A21: 4. Inv Label Mat | B21: 13150 | C21: INVENTORY-LABEL MATERIAL | D21: 29721.35 | E21: 22787.6
A22: 4. Inv Label Mat Total | D22: 29721.35 | E22: 22787.6
A23: 4. Inv Carbon | B23: 13200 | C23: INVENTORY-CARBON | F23: 574.15 | G23: 1867.24
A24: 4. Inv Carbon Total | F24: 574.15 | G24: 1867.24
A25: 4. Inv Cartons | B25: 13300 | C25: INVENTORY-CARTONS | D25: 51299.41 | E25: 57365.49 | F25: 33340.31 | G25: 38350.41
A26: 4. Inv Cartons Total | D26: 51299.41 | E26: 57365.49 | F26: 33340.31 | G26: 38350.41
A27: 4. Inv FGS | B27: 13400 | C27: INVENTORY-F/G | D27: 139992.39 | E27: 116410.33 | F27: 63844 | G27: 43456.11
A28: 4. Inv FGS Total | D28: 139992.39 | E28: 116410.33 | F28: 63844 | G28: 43456.11
A29: 4. Inv Supplies | B29: 13600 | C29: INVENTORY-SUPPLIES | D29: 3642.35 | E29: 3234.87 | F29: 18618.51 | G29: 8446.06
A30: 4. Inv Supplies Total | D30: 3642.35 | E30: 3234.87 | F30: 18618.51 | G30: 8446.06
A31: 4. Inv TAMARACK & HUNKELER | B31: 13650 | C31: INVENTORY-TAMARACK & HUNKELER | F31: 28760.58 | G31: 34474.86
A32: 4. Inv TAMARACK & HUNKELER Total | F32: 28760.58 | G32: 34474.86
A33: 4. Inv Envelopes | B33: 13950 | C33: INVENTORY-ENVELOPES | F33: 9108.79 | G33: 12412.62
A34: 4. Inv Envelopes Total | F34: 9108.79 | G34: 12412.62
A35: 5. M&E | B35: 14000 | C35: MACHINERY & EQUIPMENT | D35: 2670303.1 | E35: 2670303.1 | F35: 3796655.2 | G35: 3796655.2 | H35: 334582.36 | I35: 344582.36
B36: 14100 | C36: ACCUM.DEPR.-MACH.& EQ. | D36: -2321058.3 | E36: -2351254.5 | F36: -3390862.3 | G36: -3430135.6 | H36: -303087.13 | I36: -306220.51
B37: 15000 | C37: VEHICLES | D37: 64451.23 | E37: 64451.23 | F37: 84861.54 | G37: 84861.54
B38: 15100 | C38: ACCUM.DEPR.-VEHICLES | D38: -64451.23 | E38: -64451.23 | F38: -77553.05 | G38: -79745.63
B39: 16000 | C39: FURNITURE & FIXTURES | D39: 3603.4 | E39: 3603.4 | F39: 38802.65 | G39: 38802.65
B40: 16100 | C40: ACCUM.DEPR.-FURN.& FIX. | D40: -3602.87 | E40: -3602.87 | F40: -38802.65 | G40: -38802.65
B41: 17000 | C41: LEASEHOLD IMPROVEMENTS | D41: 127998.33 | E41: 127998.33 | F41: 922407.92 | G41: 922407.92 | H41: 27949.5 | I41: 27949.5
B42: 17100 | C42: ACCUM.DEPR.-LEASEHOLD | D42: -111642.24 | E42: -113205.9 | F42: -751680.24 | G42: -767355.96 | H42: -39765.33 | I42: -44318.85
B43: 18000 | C43: COMPUTER | D43: 8360.14 | E43: 8360.14 | F43: 180345.65 | G43: 180345.65
B44: 18100 | C44: ACCUM.DEPR.-COMPUTER | D44: -5573.42 | E44: -6966.8 | F44: -165011.04 | G44: -167370.18
B45: 19000 | C45: BUILDING AND LAND | F45: 600000 | G45: 600000
B46: 19100 | C46: ACCUM.DEPR.-BUILDING | F46: -87500 | G46: -93749.96
A47: 5. M&E Total | D47: 368388.13 | E47: 335234.95 | F47: 1111663.7 | G47: 1045913 | H47: 19679.4 | I47: 21992.5
A48: 6. Intangible | B48: 17500 | C48: GOODWILL | F48: 10000 | G48: 10000
A49: 6. Intangible Total | F49: 10000 | G49: 10000
A50: 7. AP | B50: 20000 | C50: ACCOUNTS PAYABLE | F50: -451707.84 | G50: -310086.15
B51: 21500 | C51: CUSTOMER PAYMENTS ACCOUNT | F51: 0 | G51: 0
A52: 7. AP Total | F52: -451707.84 | G52: -310086.15
A53: 9. NP | B53: 21510 | C53: NOTE PAYABLE W & J | F53: -193786.3 | G53: 0
B54: 21860 | C54: NOTES PAYABLE-FSB 20YR ST | F54: -19755.63 | G54: -19755.63
B55: 21870 | C55: NOTES PAYABLE-FSB 20YR LT | F55: -307922.95 | G55: -241871.45
A56: 9. NP Total | F56: -521464.88 | G56: -261627.08
A57: 8. Accr AP | B57: 23000 | C57: ACCRUED TAXES-GENERAL | F57: -48475.74 | G57: -48724.84
B58: 23700 | C58: ACCRUED OHIO WORKER'S COM | F58: 0 | G58: 0
B59: 23900 | C59: ACCRUED FLEX PLAN-H | F59: -9636.25 | G59: -10463.75
B60: 23950 | C60: ACCRUED HEALTH INSURANCE | F60: -130845.01 | G60: -58403.18
B61: 24000 | C61: ACCRUED EXPENSES-OTHER | F61: 0 | G61: 15.08
B62: 24100 | C62: ACCRUED EMPLOYEE 401-K | F62: 0 | G62: 0
B63: 24300 | C63: ACCRUED WAGES | F63: -51459.37 | G63: -116464.33
A64: 8. Accr AP Total | F64: -240416.37 | G64: -234041.02
A65: 9a. RE | B65: 30000 | C65: COMMON STOCK | F65: -1000 | G65: -1000
B66: 31000 | C66: RETAINED EARNINGS | F66: -2581208.7 | G66: -2581208.7
B67: 31500 | C67: PAID IN CAPITAL | F67: -249000 | G67: -249000
B68: 32000 | C68: DISTRIBUTION TO SHAREHOLD | F68: 0 | G68: 40000
A69: 9a. RE Total | F69: -2831208.7 | G69: -2791208.7
A70: Grand Total | D70: 1009636.5 | E70: 918224.11 | F70: -1029315.9 | G70: -472388.48 | H70: 19679.4 | I70: 21992.5

Sheet Sheet1
A1: ACCOUNT# | B1: LEVEL1 | C1: DESCRIPTION | D1: ACCOUNT TYPE | E1: DESCRIPTION | F1: BEG_BAL_JAN2026 | G1: NET_CHANGE | H1: END_BAL_JUN2026
A2: 10010 | B2: 1 | C2: CASH - FIRST STATE BANK | D2: B | F2: 534702.04 | G2: 171363.5 | H2: 706065.54
A3: 10020 | B3: 1 | C3: PETTY CASH | D3: B | F3: 400 | G3: 0 | H3: 400
A4: 10020 | B4: 2 | C4: PETTY CASH | D4: B | F4: 400 | G4: 0 | H4: 400
A5: 10120 | B5: 1 | C5: CASH - HEALTH INS. ACCT | D5: B | F5: 14649.31 | G5: 510.18 | H5: 15159.49
A6: 10130 | B6: 1 | C6: CASH - FSA HEALTH ACCT | D6: B | E6: CASH - FSA HEALTH ACCT | F6: 17101.9 | G6: 797.5 | H6: 17899.4
A7: 11000 | B7: 1 | C7: ACCOUNTS RECEIVABLE | D7: B | F7: 674695.59 | G7: 104791.93 | H7: 779487.52
A8: 11100 | B8: 1 | C8: ACCOUNTS RECEIVABLE-OTHER | D8: B | F8: 40084.73 | G8: -40068.98 | H8: 15.75
A9: 12000 | B9: 1 | C9: PREPAID EXPENSES | D9: B | F9: 4763.44 | G9: 16989.6 | H9: 21753.04
A10: 12100 | B10: 1 | C10: DEPOSITS | D10: B | F10: 500 | G10: 0 | H10: 500
A11: 12110 | B11: 1 | C11: PREPAID INSURANCE | D11: B | F11: 7868 | G11: 3594.5 | H11: 11462.5
A12: 13100 | B12: 1 | C12: INVENTORY-BOND PAPER | D12: B | F12: 444806.9 | G12: -67895.92 | H12: 376910.98
A13: 13100 | B13: 2 | C13: INVENTORY-BOND PAPER | D13: B | F13: 416192.86 | G13: -33401.99 | H13: 382790.87
A14: 13150 | B14: 2 | C14: INVENTORY-LABEL MATERIAL | D14: B | E14: INVENTORY-LABEL MATERIAL | F14: 29721.35 | G14: -6933.75 | H14: 22787.6
A15: 13200 | B15: 1 | C15: INVENTORY-CARBON | D15: B | F15: 574.15 | G15: 1293.09 | H15: 1867.24
A16: 13300 | B16: 1 | C16: INVENTORY-CARTONS | D16: B | F16: 33340.31 | G16: 5010.1 | H16: 38350.41
A17: 13300 | B17: 2 | C17: INVENTORY-CARTONS | D17: B | F17: 51299.41 | G17: 6066.08 | H17: 57365.49
A18: 13400 | B18: 1 | C18: INVENTORY-F/G | D18: B | F18: 63844 | G18: -20387.89 | H18: 43456.11
A19: 13400 | B19: 2 | C19: INVENTORY-F/G | D19: B | F19: 139992.39 | G19: -23582.06 | H19: 116410.33
A20: 13405 | B20: 1 | C20: FINISHED GOODS VARIBLE | D20: P | F20: 0 | G20: 20387.89 | H20: 20387.89
A21: 13405 | B21: 2 | C21: FINISHED GOODS VARIBLE | D21: P | F21: 0 | G21: 23582.06 | H21: 23582.06
A22: 13600 | B22: 1 | C22: INVENTORY-SUPPLIES | D22: B | F22: 18618.51 | G22: -10172.45 | H22: 8446.06
A23: 13600 | B23: 2 | C23: INVENTORY-SUPPLIES | D23: B | F23: 3642.35 | G23: -407.48 | H23: 3234.87
A24: 13650 | B24: 1 | C24: INVENTORY-TAMARACK & HUNKELER | D24: B | E24: INVENTORY-TAMARACK & HUNKELER | F24: 28760.58 | G24: 5714.28 | H24: 34474.86
A25: 13950 | B25: 1 | C25: INVENTORY-ENVELOPES | D25: B | F25: 9108.79 | G25: 3303.83 | H25: 12412.62
A26: 14000 | B26: 1 | C26: MACHINERY & EQUIPMENT | D26: B | F26: 3796655.2 | G26: 0 | H26: 3796655.2
A27: 14000 | B27: 2 | C27: MACHINERY & EQUIPMENT | D27: B | F27: 2670303.1 | G27: 0 | H27: 2670303.1
A28: 14000 | B28: 50 | C28: MACHINERY & EQUIPMENT | D28: B | F28: 334582.36 | G28: 10000 | H28: 344582.36
A29: 14100 | B29: 1 | C29: ACCUM.DEPR.-MACH.& EQ. | D29: B | F29: -3390862.3 | G29: -39273.3 | H29: -3430135.6
A30: 14100 | B30: 2 | C30: ACCUM.DEPR.-MACH.& EQ. | D30: B | F30: -2321058.3 | G30: -30196.14 | H30: -2351254.5
A31: 14100 | B31: 50 | C31: ACCUM.DEPR.-MACH.& EQ. | D31: B | F31: -303087.13 | G31: -3133.38 | H31: -306220.51
A32: 15000 | B32: 1 | C32: VEHICLES | D32: B | F32: 84861.54 | G32: 0 | H32: 84861.54
A33: 15000 | B33: 2 | C33: VEHICLES | D33: B | F33: 64451.23 | G33: 0 | H33: 64451.23
A34: 15100 | B34: 1 | C34: ACCUM.DEPR.-VEHICLES | D34: B | F34: -77553.05 | G34: -2192.58 | H34: -79745.63
A35: 15100 | B35: 2 | C35: ACCUM.DEPR.-VEHICLES | D35: B | F35: -64451.23 | G35: 0 | H35: -64451.23
A36: 16000 | B36: 1 | C36: FURNITURE & FIXTURES | D36: B | F36: 38802.65 | G36: 0 | H36: 38802.65
... A45: 17100 | B45: 50 | C45: ACCUM.DEPR.-LEASEHOLD | D45: B | F45: -39765.33 | G45: -4553.52 | H45: -44318.85
A46: 17500 | B46: 1 | C46: GOODWILL | D46: B | E46: GOODWILL | F46: 10000 | G46: 0 | H46: 10000
A47: 18000 | B47: 1 | C47: COMPUTER | D47: B | F47: 180345.65 | G47: 0 | H47: 180345.65
A48: 18000 | B48: 2 | C48: COMPUTER | D48: B | F48: 8360.14 | G48: 0 | H48: 8360.14
A49: 18100 | B49: 1 | C49: ACCUM.DEPR.-COMPUTER | D49: B | F49: -165011.04 | G49: -2359.14 | H49: -167370.18
A50: 18100 | B50: 2 | C50: ACCUM.DEPR.-COMPUTER | D50: B | F50: -5573.42 | G50: -1393.38 | H50: -6966.8
A51: 19000 | B51: 1 | C51: BUILDING AND LAND | D51: B | F51: 600000 | G51: 0 | H51: 600000
A52: 19100 | B52: 1 | C52: ACCUM.DEPR.-BUILDING | D52: B | F52: -87500 | G52: -6249.96 | H52: -93749.96
A53: 20000 | B53: 1 | C53: ACCOUNTS PAYABLE | D53: B | F53: -451707.84 | G53: 141621.69 | H53: -310086.15
A54: 21500 | B54: 1 | C54: CUSTOMER PAYMENTS ACCOUNT | D54: B | F54: 0 | G54: 0 | H54: 0
A55: 21510 | B55: 1 | C55: NOTE PAYABLE W & J | D55: B | E55: NOTE PAYABLE W & J | F55: -193786.3 | G55: 193786.3 | H55: 0
A56: 21860 | B56: 1 | C56: NOTES PAYABLE-FSB 20YR ST | D56: B | E56: NOTES PAYABLE-FSB 20YR ST | F56: -19755.63 | G56: 0 | H56: -19755.63
A57: 21870 | B57: 1 | C57: NOTES PAYABLE-FSB 20YR LT | D57: B | E57: NOTES PAYABLE-FSB 20YR LT | F57: -307922.95 | G57: 66051.5 | H57: -241871.45
A58: 23000 | B58: 1 | C58: ACCRUED TAXES-GENERAL | D58: B | F58: -48475.74 | G58: -249.1 | H58: -48724.84
A59: 23700 | B59: 1 | C59: ACCRUED OHIO WORKER'S COM | D59: B | F59: 0 | G59: 0 | H59: 0
A60: 23900 | B60: 1 | C60: ACCRUED FLEX PLAN-H | D60: B | F60: -9636.25 | G60: -827.5 | H60: -10463.75
A61: 23950 | B61: 1 | C61: ACCRUED HEALTH INSURANCE | D61: B | E61: ACCRUED HEALTH INSURANCE | F61: -130845.01 | G61: 72441.83 | H61: -58403.18
A62: 24000 | B62: 1 | C62: ACCRUED EXPENSES-OTHER | D62: B | F62: 0 | G62: 15.08 | H62: 15.08
A63: 24100 | B63: 1 | C63: ACCRUED EMPLOYEE 401-K | D63: B | F63: 0 | G63: 0 | H63: 0
A64: 24300 | B64: 1 | C64: ACCRUED WAGES | D64: B | F64: -51459.37 | G64: -65004.96 | H64: -116464.33
A65: 30000 | B65: 1 | C65: COMMON STOCK | D65: B | F65: -1000 | G65: 0 | H65: -1000
A66: 31000 | B66: 1 | C66: RETAINED EARNINGS | D66: B | F66: -2581208.7 | G66: 0 | H66: -2581208.7
A67: 31500 | B67: 99 | C67: PAID IN CAPITAL | D67: B | E67: PAID IN CAPITAL | F67: -249000 | G67: 0 | H67: -249000
A68: 32000 | B68: 99 | C68: DISTRIBUTION TO SHAREHOLD | D68: B | F68: 0 | G68: 40000 | H68: 40000
A69: 40000 | B69: 1 | C69: SALES | D69: P | F69: 0 | G69: -2261060.7 | H69: -2261060.7
A70: 40000 | B70: 2 | C70: SALES | D70: P | F70: 0 | G70: -1512908.5 | H70: -1512908.5
A71: 40000 | B71: 50 | C71: SALES | D71: P | F71: 0 | G71: -962160.67 | H71: -962160.67
A72: 40700 | B72: 1 | C72: SALES - MISC FLAT CHARGES | D72: P | F72: 0 | G72: -3851.03 | H72: -3851.03
A73: 40700 | B73: 2 | C73: SALES - MISC FLAT CHARGES | D73: P | F73: 0 | G73: -8382.26 | H73: -8382.26
A74: 40700 | B74: 50 | C74: SALES - MISC FLAT CHARGES | D74: P | F74: 0 | G74: 0 | H74: 0
A75: 41000 | B75: 1 | C75: SALES DISCOUNTS | D75: P | F75: 0 | G75: 31735.48 | H75: 31735.48
A76: 41000 | B76: 2 | C76: SALES DISCOUNTS | D76: P | F76: 0 | G76: 21096.81 | H76: 21096.81
A77: 41000 | B77: 99 | C77: SALES DISCOUNTS | D77: P | F77: 0 | G77: 0 | H77: 0
A78: 41100 | B78: 1 | C78: SALES REBATE DISCOUNTS | D78: P | E78: SALES REBATE DISCOUNTS | F78: 0 | G78: 343.2 | H78: 343.2
A79: 42000 | B79: 2 | C79: MEALS AND ENTERTAINMENT | D79: P | F79: 0 | G79: 4629.16 | H79: 4629.16
A80: 42000 | B80: 99 | C80: MEALS AND ENTERTAINMENT | D80: P | F80: 0 | G80: 202.17 | H80: 202.17
A81: 51000 | B81: 1 | C81: COGS-PAPER | D81: P | F81: 0 | G81: 898525.97 | H81: 898525.97
A82: 51000 | B82: 2 | C82: COGS-PAPER | D82: P | F82: 0 | G82: 656720.71 | H82: 656720.71
A83: 52000 | B83: 1 | C83: COGS-CARBON | D83: P | F83: 0 | G83: 1184.61 | H83: 1184.61
A84: 53000 | B84: 1 | C84: COGS-CARTONS | D84: P | F84: 0 | G84: 41215.53 | H84: 41215.53
A85: 53000 | B85: 2 | C85: COGS-CARTONS | D85: P | F85: 0 | G85: 35491.57 | H85: 35491.57
A86: 54000 | B86: 1 | C86: COGS-INK | D86: P | F86: 0 | G86: 30890.26 | H86: 30890.26
A87: 54000 | B87: 2 | C87: COGS-INK | D87: P | F87: 0 | G87: 8441.74 | H87: 8441.74
A88: 55000 | B88: 1 | C88: COGS-PLATES/COMP CHARGES | D88: P | F88: 0 | G88: 49422.12 | H88: 49422.12
A89: 55000 | B89: 2 | C89: COGS-PLATES/COMP CHARGES | D89: P | F89: 0 | G89: 15851.79 | H89: 15851.79
A90: 56000 | B90: 1 | C90: COGS-SUPPLIES | D90: P | F90: 0 | G90: 56554.28 | H90: 56554.28
... A92: 56000 | B92: 50 | C92: COGS-SUPPLIES | D92: P | F92: 0 | G92: 21662.42 | H92: 21662.42
A93: 56200 | B93: 2 | C93: COGS-SUPPLIES-LABEL | D93: P | E93: COGS-SUPPLIES | F93: 0 | G93: 66787.51 | H93: 66787.51
A94: 56500 | B94: 1 | C94: COGS-INTEGRATED MATERIAL | D94: P | E94: COGS-TAMARACK & HUNKLER | F94: 0 | G94: 37171.24 | H94: 37171.24
A95: 59500 | B95: 1 | C95: ENVELOPES | D95: P | F95: 0 | G95: 9098.17 | H95: 9098.17
A96: 59550 | B96: 1 | C96: ENVELOPE-IMPRINTING COST | D96: P | F96: 0 | G96: 2610 | H96: 2610
A97: 60100 | B97: 1 | C97: HEALTH INSURANCE -ADMIN | D97: P | F97: 0 | G97: 26538.77 | H97: 26538.77
A98: 60100 | B98: 99 | C98: HEALTH INSURANCE -ADMIN | D98: P | F98: 0 | G98: 35341.54 | H98: 35341.54
A99: 60400 | B99: 1 | C99: CARETAKING-PRODUCTION | D99: P | E99: CARETAKING-PRODUCTION | F99: 0 | G99: 3063.96 | H99: 3063.96
A100: 60400 | B100: 2 | C100: CARETAKING-PRODUCTION | D100: P | E100: CARETAKING-PRODUCTION | F100: 0 | G100: 4113.31 | H100: 4113.31
A101: 60400 | B101: 50 | C101: CARETAKING-PRODUCTION | D101: P | E101: CARETAKING-PRODUCTION | F101: 0 | G101: 1569.48 | H101: 1569.48
A102: 60500 | B102: 2 | C102: RENT | D102: P | F102: 0 | G102: 48000 | H102: 48000
A103: 60500 | B103: 50 | C103: RENT | D103: P | F103: 0 | G103: 15000 | H103: 15000
A104: 60600 | B104: 1 | C104: REPAIRS & MAINTENANCE | D104: P | F104: 0 | G104: 48867.5 | H104: 48867.5
A105: 60600 | B105: 2 | C105: REPAIRS & MAINTENANCE | D105: P | F105: 0 | G105: 17564.43 | H105: 17564.43
A106: 60600 | B106: 50 | C106: REPAIRS & MAINTENANCE | D106: P | F106: 0 | G106: 35479.6 | H106: 35479.6
A107: 60600 | B107: 99 | C107: REPAIRS & MAINTENANCE | D107: P | F107: 0 | G107: 6711.18 | H107: 6711.18
A108: 60700 | B108: 1 | C108: PRODUCTION WAGES | D108: P | F108: 0 | G108: 195400.87 | H108: 195400.87
A109: 60700 | B109: 2 | C109: PRODUCTION WAGES | D109: P | F109: 0 | G109: 132082.52 | H109: 132082.52
...

Sheet Sheet2
B1: Full YR
B2: BEFORE Acquire | F2: AFTER Acquire
B3: Hillsboro | D3: Synergies | F3: Hillsboro
A4: 1. Sales | B4: 7466053.9 | F4: 7466053.9
A5: 2. Variable cost Labor | B5: 1682889.3 | C5: =B5/$B$4 -> 0.22540545 | F5: 1682889.3 | G5: =F5/$F$4 -> 0.22540545
A6: 2. Variable cost Mat | B6: 3998523.8 | C6: =B6/$B$4 -> 0.53556053 | D6: -243478.01 | F6: 3755045.8 | G6: =F6/$F$4 -> 0.50294919
A7: 2a. Variable cost Mat | B7: -39214.26 | C7: =B7/$B$4 -> -0.0052523409 | F7: -39214.26 | G7: =F7/$F$4 -> -0.0052523409
A8: 8c. Frt Exp | B8: 27068.86 | C8: =B8/$B$4 -> 0.0036255913 | F8: 27068.86 | G8: =F8/$F$4 -> 0.0036255913
A9: 3. Mfg IDL | B9: 404803.02 | C9: =B9/$B$4 -> 0.05421914 | D9: -82160 | F9: 322643.02 | G9: =F9/$F$4 -> 0.043214665
A10: 4. Mfg OVHD | B10: 778419.06 | C10: =B10/$B$4 -> 0.10426111 | D10: -208158.76 | F10: 570260.3 | G10: =F10/$F$4 -> 0.076380415
A11: 7. Selling | B11: 428750.66 | C11: =B11/$B$4 -> 0.057426676 | F11: 428750.66 | G11: =F11/$F$4 -> 0.057426676
A12: 8. Admin | B12: 761485 | C12: =B12/$B$4 -> 0.10199297 | D12: -116142.92 | F12: 645342.08 | G12: =F12/$F$4 -> 0.086436836
A13: 8. Admin IT | B13: 26636.86 | C13: =B13/$B$4 -> 0.0035677294 | F13: 26636.86 | G13: =F13/$F$4 -> 0.0035677294
A14: 8a. Frt Income | B14: -662472.4 | C14: =B14/$B$4 -> -0.088731264 | F14: -662472.4 | G14: =F14/$F$4 -> -0.088731264
A15: 8b. Frt Exp | B15: 542571.08 | C15: =B15/$B$4 -> 0.072671733 | F15: 542571.08 | G15: =F15/$F$4 -> 0.072671733
A16: 9. Scrap & Misc Inc | B16: -117319.36 | C16: =B16/$B$4 -> -0.015713704 | F16: -117319.36 | G16: =F16/$F$4 -> -0.015713704
A17: 91. Other Inc/Exp | B17: 0 | C17: =B17/$B$4 -> 0 | F17: 0 | G17: =F17/$F$4 -> 0
A18: 99. Elim | B18: 0 | C18: =B18/$B$4 -> 0 | F18: 0 | G18: =F18/$F$4 -> 0
A19: 2a. Variable cost Mat Out/Env | B19: 23416.34 | C19: =B19/$B$4 -> 0.0031363743 | F19: 23416.34 | G19: =F19/$F$4 -> 0.0031363743
A20: Grand Total | B20: 389504 | C20: =B20/$B$4 -> 0.052169996 | D20: -649939.69 | F20: -260435.69 | G20: =F20/$F$4 -> -0.034882642
