Workbook

Sheet 1-T5Y IS
B2: Financial Information | C2: Highland Computer Forms, Inc.
B3: Date: 07/15/2026 | C3: Hillsboro, Ohio "S"-Corp
C4: Fiscal years ending December 31st
C6: Internal | D6: Adjusted RS | E6: Internal | F6: Adjusted RS | G6: Internal | H6: Adjusted RS | I6: Review | J6: Internal | K6: Internal | L6: Review | M6: Review | N6: Review | O6: Review | P6: Review
B7: INCOME STATEMENT | C7: 6 mo.-'26 | D7: 6 mo.-'26 | E7: Q2-'26 | F7: Q2-'26 | G7: Q1-'26 | H7: Q1-'26 | I7: FY2025 | J7: 6 mo.-'25 | K7: 6 mo.-'24 | L7: FY2024 | M7: FY2023 | N7: FY2022 | O7: FY2021 | P7: FY2020
B8: Sales
B9: HCF Sales, Net | C9: ='2024&2023'!C3 -> 4695188 | D9: =+F9+H9 -> 4695187 | E9: =C9-G9 -> 2315210 | F9: =4695187-H9 -> 2315209 | G9: ='2024&2023'!D3 -> 2379978 | H9: 2379978 | I9: ='2024&2023'!E3 -> 8533432 | J9: ='2024&2023'!F3 -> 4406436 | K9: ='2024&2023'!G3 -> 4464702 | L9: ='2024&2023'!H3 -> 8855077 | M9: ='2024&2023'!I3 -> 10655460
B10: G. Fordyce Sales, Net | I10: ='2024&2023'!E4 -> 347072 | L10: ='2024&2023'!H4 -> 370068 | M10: ='2024&2023'!I4 -> 264960
B11: Scrap Paper & Rebates | C11: ='2024&2023'!C5 -> 80502 | D11: =+F11+H11 -> 80502 | E11: =C11-G11 -> 50798 | F11: =63892+16610-29704 -> 50798 | G11: ='2024&2023'!D5 -> 29704 | H11: =27819+1885 -> 29704 | I11: ='2024&2023'!E5 -> 125545 | J11: ='2024&2023'!F5 -> 72205 | K11: ='2024&2023'!G5 -> 72457 | L11: ='2024&2023'!H5 -> 126021 | M11: ='2024&2023'!I5 -> 206685
B12: Total Sales, Net | C12: =SUM(C9:C11) -> 4775690 | D12: =SUM(D9:D11) -> 4775689 | E12: =SUM(E9:E11) -> 2366008 | F12: =SUM(F9:F11) -> 2366007 | G12: =SUM(G9:G11) -> 2409682 | H12: =SUM(H9:H11) -> 2409682 | I12: =SUM(I9:I11) -> 9006049 | J12: =SUM(J9:J11) -> 4478641 | ... M12: =SUM(M9:M11) -> 11127105 | N12: ='2024&2023'!J3 -> 11681336 | O12: ='2024&2023'!K3 -> 10246051 | P12: ='2024&2023'!L3 -> 9810201
B14: Cost of Goods Sold
B15: Materials
B16: Beginning Inventories (HCF) | C16: ='2024&2023'!C7 -> 203836 | D16: 1239901 | E16: 255947 | F16: 1202624 | G16: ='2024&2023'!D7 -> 203836 | H16: 1239901 | I16: ='2024&2023'!E7 -> 1021535 | J16: ='2024&2023'!F7 -> 226313 | K16: ='2024&2023'!G7 -> 313473 | L16: ='2024&2023'!H7 -> 1051427 | M16: ='2024&2023'!I7 -> 1733922 | N16: ='2024&2023'!J7 -> 1107863 | O16: ='2024&2023'!K7 -> 683140 | P16: ='2024&2023'!L7 -> 683140
B17: Beginning Inventories (G. Fordyce) | I17: ='2024&2023'!E8 -> 0 | L17: ='2024&2023'!H8 -> 45134 | M17: ='2024&2023'!I8 -> 0
B18: Paper | C18: ='2024&2023'!C10 -> 1555246 | D18: =+F18+H18 -> 1457822.2 | E18: =C18-G18 -> 779277 | F18: =779277+96081.2-104117 -> 771241.2 | G18: ='2024&2023'!D10 -> 775969 | H18: =775969-14910-37201-37277 -> 686581 | I18: ='2024&2023'!E10 -> 3408695 | J18: ='2024&2023'!F10 -> 1725419 | K18: ='2024&2023'!G10 -> 1808752 | L18: ='2024&2023'!H10 -> 3692358 | M18: ='2024&2023'!I10 -> 3982914 | N18: ='2024&2023'!J10 -> 5780557 | O18: ='2024&2023'!K10 -> 4920814 | P18: ='2024&2023'!L10 -> 4390895
B19: Supplies (HCF) | C19: ='2024&2023'!C37 -> 204362 | D19: =+F19+H19 -> 167191 | E19: =C19-G19 -> 103681 | F19: =100404+66787-H19 -> 81381 | G19: ='2024&2023'!D37 -> 100681 | H19: =44922+40888 -> 85810 | I19: ='2024&2023'!E15 -> 308812 | J19: ='2024&2023'!F37 -> 182646 | K19: ='2024&2023'!G37 -> 196587 | L19: ='2024&2023'!H15 -> 327826 | M19: ='2024&2023'!I15 -> 329822 | N19: ='2024&2023'!J15 -> 381473 | O19: ='2024&2023'!K15 -> 359935 | P19: ='2024&2023'!L15 -> 309092
B20: Supplies (G. Fordyce) | D20: =+F20+H20 -> 0 | E20: =C20-G20 -> 0 | I20: ='2024&2023'!E16+'2024&2023'!E38 -> 12632 | L20: ='2024&2023'!H16+'2024&2023'!H38 -> 2364 | M20: ='2024&2023'!I16+'2024&2023'!I38 -> 50791
B21: Buyouts & Outside Purchases (HCF) | C21: ='2024&2023'!C17 -> 0 | D21: =+F21+H21 -> 37171 | E21: =C21-G21 -> 0 | F21: =37171-H21 -> 22300 | G21: ='2024&2023'!D17 -> 0 | H21: =14871+0 -> 14871 | I21: ='2024&2023'!E17 -> 48537 | J21: ='2024&2023'!F17 -> 516 | K21: ='2024&2023'!G17 -> 0 | L21: ='2024&2023'!H17 -> 69427 | M21: ='2024&2023'!I17 -> 91234 | N21: ='2024&2023'!J17 -> 104261 | O21: ='2024&2023'!K17 -> 112637 | P21: ='2024&2023'!L17 -> 163690
B22: Buyouts & Outside Purchases (G. Fordyce) | C22: ='2024&2023'!C18 -> 0 | D22: =+F22+H22 -> 0 | E22: =C22-G22 -> 0 | G22: ='2024&2023'!D18 -> 0 | I22: ='2024&2023'!E18 -> 186902 | J22: ='2024&2023'!F18 -> 0 | K22: ='2024&2023'!G18 -> 0 | L22: ='2024&2023'!H18 -> 207091 | M22: ='2024&2023'!I18 -> 166233
B23: Cartons | C23: ='2024&2023'!C23 -> 76707 | D23: =+F23+H23 -> 76707 | E23: =C23-G23 -> 37188 | F23: =76707-39519 -> 37188 | G23: ='2024&2023'!D23 -> 39519 | H23: 39519 | I23: ='2024&2023'!E23 -> 160443 | J23: ='2024&2023'!F23 -> 86112 | K23: ='2024&2023'!G23 -> 91936 | L23: ='2024&2023'!H23 -> 180668 | M23: ='2024&2023'!I23 -> 225574 | N23: ='2024&2023'!J23 -> 267861 | O23: ='2024&2023'!K23 -> 205064 | P23: ='2024&2023'!L23 -> 195649
B24: Ink | C24: ='2024&2023'!C31 -> 39332 | D24: =+F24+H24 -> 39332 | E24: =C24-G24 -> 18262 | F24: =39332-21070 -> 18262 | G24: ='2024&2023'!D31 -> 21070 | H24: 21070 | I24: ='2024&2023'!E31 -> 64635 | J24: ='2024&2023'!F31 -> 33175 | K24: ='2024&2023'!G31 -> 34202 | L24: ='2024&2023'!H31 -> 94918 | M24: ='2024&2023'!I31 -> 94148 | N24: ='2024&2023'!J31 -> 116856 | O24: ='2024&2023'!K31 -> 125195 | P24: ='2024&2023'!L31 -> 131612
B25: Envelopes | C25: ='2024&2023'!C33 -> 11708 | D25: =+F25+H25 -> 11708 | E25: =C25-G25 -> 6157 | F25: =11708-5551 -> 6157 | G25: ='2024&2023'!D33 -> 5551 | H25: 5551 | I25: ='2024&2023'!E33 -> 29437 | J25: ='2024&2023'!F33 -> 17665 | K25: ='2024&2023'!G33 -> 18433 | L25: ='2024&2023'!H33 -> 31056 | M25: ='2024&2023'!I33 -> 33531 | N25: ='2024&2023'!J33 -> 40827 | O25: ='2024&2023'!K33 -> 44298 | P25: ='2024&2023'!L33 -> 39991
B26: Carbon Products | C26: ='2024&2023'!C34 -> 1184 | D26: =+F26+H26 -> 1184 | E26: =C26-G26 -> 38 | F26: =1184-1146 -> 38 | G26: ='2024&2023'!D34 -> 1146 | H26: 1146 | I26: ='2024&2023'!E34 -> 1375 | J26: ='2024&2023'!F34 -> 884 | K26: ='2024&2023'!G34 -> 4565 | L26: ='2024&2023'!H34 -> 6961 | M26: ='2024&2023'!I34 -> 6603 | N26: ='2024&2023'!J34 -> 10241 | O26: ='2024&2023'!K34 -> 2163 | P26: ='2024&2023'!L34 -> 2741
B27: Copy Paper | C27: ='2024&2023'!C36 -> 0 | D27: =+F27+H27 -> 0 | E27: =C27-G27 -> 0 | G27: ='2024&2023'!D36 -> 0 | I27: ='2024&2023'!E36 -> 0 | J27: ='2024&2023'!F36 -> 0 | K27: ='2024&2023'!G36 -> 2773 | L27: ='2024&2023'!H36 -> 2773 | M27: ='2024&2023'!I36 -> 0 | N27: ='2024&2023'!J36 -> 92 | O27: ='2024&2023'!K36 -> 135 | P27: ='2024&2023'!L36 -> 967
B28: Inventory Obsolescence | C28: 0 | D28: =+F28+H28 -> 0 | E28: =C28-G28 -> 0 | G28: 0 | I28: ='2024&2023'!E40 -> 46829 | J28: 0 | K28: 0 | L28: 0 | M28: 0 | N28: 0 | O28: 0 | P28: 0
B29: Less Purchase Discounts (HCF) | C29: ='2024&2023'!C43 -> -19607 | D29: =+F29+H29 -> -60692.72 | E29: =C29-G29 -> -10300 | F29: =-19607+9307-8369.59 -> -18669.59 | G29: ='2024&2023'!D43 -> -9307 | H29: =-9307-32716.13 -> -42023.13 | I29: ='2024&2023'!E43 -> -170697 | J29: ='2024&2023'!F43 -> -31307 | K29: ='2024&2023'!G43 -> -30420 | L29: ='2024&2023'!H43 -> -62386 | M29: ='2024&2023'!I43 -> -84956
B30: Less Purchase Discounts (G. Fordyce) | E30: =C30-G30 -> 0 | I30: ='2024&2023'!E44 -> -183 | L30: ='2024&2023'!H44 -> -246 | M30: ='2024&2023'!I44 -> -210
B31: Less Ending Inventories | C31: ='2024&2023'!C48 -> -159866 | D31: -1098507 | E31: -159866 | F31: -1098507 | G31: ='2024&2023'!D48 -> -255947 | H31: -1202624 | I31: ='2024&2023'!E48 -> -1239901 | J31: ='2024&2023'!F48 -> -225544 | K31: ='2024&2023'!G48 -> -199589 | L31: ='2024&2023'!H48 -> -1021535 | M31: ='2024&2023'!I48 -> -1096561 | N31: ='2024&2023'!J48 -> -1733922 | O31: ='2024&2023'!K48 -> -1107863 | P31: ='2024&2023'!L48 -> -632835
B32: Sub-total Materials | C32: =SUM(C16:C31) -> 1912902 | D32: =SUM(D16:D31) -> 1871816.5 | E32: =SUM(E16:E31) -> 1030384 | F32: =SUM(F16:F31) -> 1022014.6 | G32: =SUM(G16:G31) -> 882518 | H32: =SUM(H16:H31) -> 849801.87 | I32: =SUM(I16:I31) -> 3879051 | J32: =SUM(J16:J31) -> 2015879 | ... P32: =SUM(P16:P31) -> 5284942
B33: % to Total COGS | C33: =IFERROR(C32/C66,"") -> 0.51149779 | D33: =IFERROR(D32/D66,"") -> 0.49583457 | E33: =IFERROR(E32/E66,"") -> 0.51818212 | F33: =IFERROR(F32/F66,"") -> 0.50980246 | G33: =IFERROR(G32/G66,"") -> 0.50390848 | H33: =IFERROR(H32/H66,"") -> 0.48001753 | I33: =IFERROR(I32/I66,"") -> 0.5304548 | J33: =IFERROR(J32/J66,"") -> 0.55732174 | ... P33: =IFERROR(P32/P66,"") -> 0.60078079
B35: Labor
B36: Supervisors' Salaries (HCF) | C36: ='2024&2023'!C19 -> 7443 | D36: =+F36+H36 -> 148405.61 | E36: =C36-G36 -> 16164 | F36: =31420.42+39840.4+28614.88+48529.51-72182 -> 76223.21 | G36: ='2024&2023'!D19 -> -8721 | H36: =23994.88+15525.96+18501.12+14160.44 -> 72182.4 | I36: ='2024&2023'!E19 -> 297193 | J36: ='2024&2023'!F19 -> 4379 | K36: ='2024&2023'!G19 -> 42516 | L36: ='2024&2023'!H19 -> 268102 | M36: ='2024&2023'!I19 -> 280397 | N36: ='2024&2023'!J19 -> 229257 | O36: ='2024&2023'!K19 -> 198693 | P36: ='2024&2023'!L19 -> 209196
B37: Supervisors' Salaries (G. Fordyce) | D37: =+F37+H37 -> 0 | E37: =C37-G37 -> 0 | I37: ='2024&2023'!E20 -> 0 | L37: ='2024&2023'!H20 -> 980 | M37: ='2024&2023'!I20 -> 0
B38: ='2024&2023'!B11 -> Production and Collator Wages (HCF) | C38: ='2024&2023'!C11 -> 686327 | D38: =+F38+H38 -> 588773.55 | E38: =C38-G38 -> 349654 | F38: =195400.87+132082.52+192924.91+11856.83+1885.59+16086.61+13301.93+9474.5+3777.6+4738.4+3327.68+3916.4-290730 -> 298043.84 | G38: ='2024&2023'!D11 -> 336673 | H38: =96603.31+68017.23+95593.65+4546.34+1357.58+9167.59+5231.56+4529.49+1619.2+1624.4+1104.96+1334.4 -> 290729.71 | I38: ='2024&2023'!E11 -> 964599 | J38: ='2024&2023'!F11 -> 550391 | K38: ='2024&2023'!G11 -> 583091 | L38: ='2024&2023'!H11 -> 965420 | M38: ='2024&2023'!I11 -> 1082631 | N38: ='2024&2023'!J11 -> 1144403 | O38: ='2024&2023'!K11 -> 1120001 | P38: ='2024&2023'!L11 -> 1091526
B39: Production and Collator Wages (G. Fordyce) | D39: =+F39+H39 -> 0 | E39: =C39-G39 -> 0 | I39: ='2024&2023'!E12 -> 73530 | L39: ='2024&2023'!H12 -> 84107 | M39: ='2024&2023'!I12 -> 136379
B40: Shipping Wages① | C40: 0 | D40: =+F40+H40 -> 64372.38 | E40: =C40-G40 -> 0 | F40: =15699.76+18393.18+22463.2+57.9+1512.92+1626.65+1324.85+2422+409.2+463.2-32906 -> 31466.86 | G40: 0 | H40: =7971.35+8886.85+11072+683.04+600.54+978.94+2422+136.4+154.4 -> 32905.52 | I40: ='2024&2023'!E30 -> 120598 | J40: 0 | K40: 0 | L40: ='2024&2023'!H30 -> 119383 | M40: ='2024&2023'!I30 -> 93521 | N40: ='2024&2023'!J30 -> 97494 | O40: ='2024&2023'!K30 -> 100963 | P40: ='2024&2023'!L30 -> 91173
B41: ='2024&2023'!B13 -> Indirect Labor | C41: ='2024&2023'!C13 -> 297222 | D41: =+F41+H41 -> 221782.59 | E41: =C41-G41 -> 151940 | F41: =18093.38+26890.05-8500.32+1118.25+210.75+30+1260+448+800+480+672+480+35623.52+54.76+2504.83+939.6+88431.96+3399.18+3773.1+1949.6+15107.15+24574.86+19.54+1999.17+610.4+409.2+403.2-106685 -> 115097.18 | G41: ='2024&2023'!D13 -> 145282 | H41: =8751.67+13287.56-3762.29+267.19+94.5+15+744.44+160+160+224+160+17957.96+54.76+847.43+305.2+41395.52+2270.17+1718.48+559.2+8013.21+12385.73+12.79+456.09+336+136.4+134.4 -> 106685.41 | I41: ='2024&2023'!E13 -> 486589 | J41: ='2024&2023'!F13 -> 324530 | K41: ='2024&2023'!G13 -> 334157 | L41: ='2024&2023'!H13 -> 523378 | M41: ='2024&2023'!I13 -> 608621 | N41: ='2024&2023'!J13 -> 594797 | O41: ='2024&2023'!K13 -> 563755 | P41: ='2024&2023'!L13 -> 573376
B42: ='2024&2023'!B22 -> Payroll Taxes | C42: ='2024&2023'!C22 -> 95499 | D42: =+F42+H42 -> 95499 | E42: =C42-G42 -> 42313 | F42: =95499-53186 -> 42313 | G42: ='2024&2023'!D22 -> 53186 | H42: 53186 | I42: ='2024&2023'!E22 -> 200715 | J42: ='2024&2023'!F22 -> 96885 | K42: ='2024&2023'!G22 -> 101738 | L42: ='2024&2023'!H22 -> 200385 | M42: ='2024&2023'!I22 -> 232730 | N42: ='2024&2023'!J22 -> 238780 | O42: ='2024&2023'!K22 -> 198502 | P42: ='2024&2023'!L22 -> 179936
B43: Health Insurance② | C43: ='2024&2023'!C14 -> 299280 | D43: =+F43+H43 -> 299280 | E43: =C43-G43 -> 185489 | F43: =299280-113791 -> 185489 | G43: ='2024&2023'!D14 -> 113791 | H43: 113791 | I43: ='2024&2023'!E14 -> 436125 | J43: ='2024&2023'!F14 -> 221909 | K43: ='2024&2023'!G14 -> 152082 | L43: ='2024&2023'!H14 -> 383282 | M43: ='2024&2023'!I14 -> 476537 | N43: ='2024&2023'!J14 -> 491729 | O43: ='2024&2023'!K14 -> 393068 | P43: ='2024&2023'!L14 -> 452009
B44: ='2024&2023'!B32 -> Retirement Plan Expenses | C44: ='2024&2023'!C32 -> 23310 | D44: =+F44+H44 -> 23310 | E44: =C44-G44 -> 11098 | F44: =23310-12212 -> 11098 | G44: ='2024&2023'!D32 -> 12212 | H44: 12212 | I44: ='2024&2023'!E32 -> 53604 | J44: ='2024&2023'!F32 -> 25105 | K44: ='2024&2023'!G32 -> 25240 | L44: ='2024&2023'!H32 -> 53479 | M44: ='2024&2023'!I32 -> 52088 | N44: ='2024&2023'!J32 -> 49590 | O44: ='2024&2023'!K32 -> 39566 | P44: ='2024&2023'!L32 -> 36058
B45: Sub-total Labor | C45: =SUM(C36:C44) -> 1409081 | D45: =SUM(D36:D44) -> 1441423.1 | E45: =SUM(E36:E44) -> 756658 | F45: =SUM(F36:F44) -> 759731.09 | G45: =SUM(G36:G44) -> 652423 | H45: =SUM(H36:H44) -> 681692.04 | I45: =SUM(I36:I44) -> 2632953 | J45: =SUM(J36:J44) -> 1223199 | ... P45: =SUM(P36:P44) -> 2633274
B46: % to Total COGS | C46: =IFERROR(C45/C66,"") -> 0.37677927 | D46: =IFERROR(D45/D66,"") -> 0.38182559 | E46: =IFERROR(E45/E66,"") -> 0.38052478 | F46: =IFERROR(F45/F66,"") -> 0.37896991 | G46: =IFERROR(G45/G66,"") -> 0.37252666 | I46: =IFERROR(I45/I66,"") -> 0.36005264 | J46: =IFERROR(J45/J66,"") -> 0.33817278 | K46: =IFERROR(K45/K66,"") -> 0.32281096 | L46: =IFERROR(L45/L66,"") -> 0.32554039 | M46: =IFERROR(M45/M66,"") -> 0.31483127 | N46: =IFERROR(N45/N66,"") -> 0.29201062 | O46: =IFERROR(O45/O66,"") -> 0.29653374 | P46: =IFERROR(P45/P66,"") -> 0.2993449
B48: Plant Overhead
B49: Lease (80% of Total - HCF) | C49: ='2024&2023'!C24*0.8 -> 50400 | D49: =+F49+H49 -> 63000 | E49: =C49-G49 -> 25200 | F49: =63000-31500 -> 31500 | G49: ='2024&2023'!D24*0.8 -> 25200 | H49: 31500 | I49: ='2024&2023'!E24*0.8 -> 99741.6 | J49: ='2024&2023'!F24*0.8 -> 50400 | K49: ='2024&2023'!G24*0.8 -> 50400 | L49: ='2024&2023'!H24*0.8 -> 125580 | M49: ='2024&2023'!I24*0.8 -> 120676.8 | N49: ='2024&2023'!J24*0.8 -> 121005.6 | O49: ='2024&2023'!K24*0.8 -> 117783.2 | P49: ='2024&2023'!L24*0.8 -> 113744
B50: Lease (80% of Total - G. Fordyce) | D50: =+F50+H50 -> 0 | E50: =C50-G50 -> 0 | I50: ='2024&2023'!E25*0.8 -> 7680 | L50: ='2024&2023'!H25*0.8 -> 7680 | M50: ='2024&2023'!I25*0.8 -> 7680
B51: Repairs & Maintenance (HCF) | C51: ='2024&2023'!C27*1 -> 108622 | D51: =+F51+H51 -> 112714 | E51: =C51-G51 -> 49504 | F51: =108622+4092-61540 -> 51174 | G51: ='2024&2023'!D27*1 -> 59118 | H51: =59118+2422 -> 61540 | I51: ='2024&2023'!E27*1 -> 166308 | J51: ='2024&2023'!F27*1 -> 69884 | K51: ='2024&2023'!G27*1 -> 77804 | L51: ='2024&2023'!H27*1 -> 152408 | M51: ='2024&2023'!I27*1 -> 236479 | N51: ='2024&2023'!J27*1 -> 155138 | O51: ='2024&2023'!K27*1 -> 188467 | P51: ='2024&2023'!L27*1 -> 200266
B52: Repairs & Maintenance (G. Fordyce) | D52: =+F52+H52 -> 0 | E52: =C52-G52 -> 0 | I52: ='2024&2023'!E28 -> 3278 | L52: ='2024&2023'!H28 -> 0 | M52: ='2024&2023'!I28 -> 1027
B53: Utilities (80% of total) | C53: ='2024&2023'!C21*0.8 -> 125684 | D53: =+F53+H53 -> 157105 | E53: =C53-G53 -> 61055.2 | F53: =157105-80786 -> 76319 | G53: ='2024&2023'!D21*0.8 -> 64628.8 | H53: 80786 | I53: ='2024&2023'!E21*0.8 -> 231894.4 | J53: ='2024&2023'!F21*0.8 -> 106608 | K53: ='2024&2023'!G21*0.8 -> 87038.4 | L53: ='2024&2023'!H21*0.8 -> 191105.6 | M53: ='2024&2023'!I21*0.8 -> 206472.8 | N53: ='2024&2023'!J21*0.8 -> 210710.4 | O53: ='2024&2023'!K21*0.8 -> 202661.6 | P53: ='2024&2023'!L21*0.8 -> 195039.2
B54: Depreciation | C54: ='2024&2023'!C26+'2024&2023'!C35 -> 74795 | D54: =+F54+H54 -> 74795 | E54: =C54-G54 -> 37398 | F54: =72602+2193-37397 -> 37398 | G54: ='2024&2023'!D26+'2024&2023'!D35 -> 37397 | H54: =36301+1096 -> 37397 | I54: ='2024&2023'!E26+'2024&2023'!E35 -> 165106 | J54: ='2024&2023'!F26+'2024&2023'!F35 -> 80882 | K54: ='2024&2023'!G26+'2024&2023'!G35 -> 84916 | L54: ='2024&2023'!H26+'2024&2023'!H35 -> 170856 | M54: ='2024&2023'!I26+'2024&2023'!I35 -> 189544 | N54: ='2024&2023'!J26+'2024&2023'!J35 -> 198660 | O54: ='2024&2023'!K26+'2024&2023'!K35 -> 209546 | P54: ='2024&2023'!L26+'2024&2023'!L35 -> 224797
B55: Plates & Negatives | C55: ='2024&2023'!C29 -> 65273 | D55: =+F55+H55 -> 65273 | E55: =C55-G55 -> 31682 | F55: =65273-33591 -> 31682 | G55: ='2024&2023'!D29 -> 33591 | H55: 33591 | I55: ='2024&2023'!E29 -> 126210 | J55: ='2024&2023'!F29 -> 64502 | K55: ='2024&2023'!G29 -> 68559 | L55: ='2024&2023'!H29 -> 134081 | M55: ='2024&2023'!I29 -> 137702 | N55: ='2024&2023'!J29 -> 130388 | O55: ='2024&2023'!K29 -> 121256 | P55: ='2024&2023'!L29 -> 125386
B56: Truck Expenses | C56: ='2024&2023'!C39 -> 4092 | D56: =+F56+H56 -> 0 | E56: =C56-G56 -> 1670 | G56: ='2024&2023'!D39 -> 2422 | H56: 0 | I56: ='2024&2023'!E39 -> 135 | J56: ='2024&2023'!F39 -> 4032 | K56: ='2024&2023'!G39 -> 2051 | L56: ='2024&2023'!H39 -> 82 | M56: ='2024&2023'!I39 -> 2219 | N56: ='2024&2023'!J39 -> 2184 | O56: ='2024&2023'!K39 -> 111 | P56: ='2024&2023'!L39 -> 151
B57: Sub-total Plant Overhead | C57: =SUM(C49:C56) -> 428866 | D57: =SUM(D49:D56) -> 472887 | E57: =SUM(E49:E56) -> 206509.2 | F57: =SUM(F49:F56) -> 228073 | G57: =SUM(G49:G56) -> 222356.8 | H57: =SUM(H49:H56) -> 244814 | I57: =SUM(I49:I56) -> 800353 | J57: =SUM(J49:J56) -> 376308 | ... P57: =SUM(P49:P56) -> 859383.2
B58: % to Total COGS | C58: =IFERROR(C57/C66,"") -> 0.11467603 | D58: =IFERROR(D57/D66,"") -> 0.12526534 | E58: =IFERROR(E57/E66,"") -> 0.10385388 | F58: =IFERROR(F57/F66,"") -> 0.11376763 | G58: =IFERROR(G57/G66,"") -> 0.12696339 | I58: =IFERROR(I57/I66,"") -> 0.10944715 | J58: =IFERROR(J57/J66,"") -> 0.10403632 | K58: =IFERROR(K57/K66,"") -> 0.096614292 | L58: =IFERROR(L57/L66,"") -> 0.097942467 | M58: =IFERROR(M57/M66,"") -> 0.095823228 | N58: =IFERROR(N57/N66,"") -> 0.083937318 | O58: =IFERROR(O57/O66,"") -> 0.095250264 | P58: =IFERROR(P57/P66,"") -> 0.097692826
B60: Freight and Delivery | N60: ='2024&2023'!J41 -> 6147 | O60: ='2024&2023'!K41 -> 17143 | P60: ='2024&2023'!L41 -> 19190
B61: Net Freight Expense (HCF) | C61: ='2024&2023'!C41 -> -11044 | D61: =+F61+H61 -> -11044 | E61: =C61-G61 -> -5092 | F61: =-46416+35372+5952 -> -5092 | G61: ='2024&2023'!D41 -> -5952 | H61: =-18865+12913 -> -5952 | I61: ='2024&2023'!E41 -> -5884 | J61: ='2024&2023'!F41 -> 1697 | K61: ='2024&2023'!G41 -> -12690 | L61: ='2024&2023'!H41 -> -30775 | M61: ='2024&2023'!I41 -> 9173
B62: Net Freight Expense (G. Fordyce) | I62: ='2024&2023'!E42 -> 6216 | L62: ='2024&2023'!H42 -> 4792 | M62: ='2024&2023'!I42 -> 4163
B63: Sub-total Freight | C63: =SUM(C61) -> -11044 | D63: =SUM(D61) -> -11044 | E63: =C63-G63 -> -5092 | F63: =D63-H63 -> -5092 | G63: =SUM(G61) -> -5952 | H63: =SUM(H61) -> -5952 | I63: =SUM(I61:I62) -> 332 | J63: =SUM(J61:J62) -> 1697 | K63: =SUM(K61:K62) -> -12690 | L63: =SUM(L61:L62) -> -25983 | M63: =SUM(M61:M62) -> 13336
B64: % to Total COGS | C64: =IFERROR(C63/C66,"") -> -0.0029530951 | D64: =IFERROR(D63/D66,"") -> -0.0029254989 | E64: =IFERROR(E63/E66,"") -> -0.0025607767 | F64: =IFERROR(F63/F66,"") -> -0.0025399971 | G64: =IFERROR(G63/G66,"") -> -0.0033985293 | H64: =IFERROR(H63/H66,"") -> -0.0033620358 | I64: =IFERROR(I63/I66,"") -> 4.5400536e-05 | J64: =IFERROR(J63/J66,"") -> 0.00046916258 | ... M64: =IFERROR(M63/M66,"") -> 0.0014170522 | N64: =IFERROR(N60/N66,"") -> 0.00063069493 | O64: =IFERROR(O60/O66,"") -> 0.0019443047 | P64: =IFERROR(P60/P66,"") -> 0.0021814778
B66: Total Cost of Goods Sold | C66: =C32+C45+C57+C63 -> 3739805 | D66: =D32+D45+D57+D63 -> 3775082.6 | E66: =E32+E45+E57+E63 -> 1988459.2 | F66: =F32+F45+F57+F63 -> 2004726.7 | G66: =G32+G45+G57+G63 -> 1751345.8 | H66: =H32+H45+H57+H63 -> 1770355.9 | I66: =I32+I45+I57+I63 -> 7312689 | J66: =J32+J45+J57+J63 -> 3617083 | ... M66: =M32+M45+M57+M63 -> 9411085.6 | N66: =N32+N45+N57+N60 -> 9746392 | O66: =O32+O45+O57+O60 -> 8817033.8 | P66: =P32+P45+P57+P60 -> 8796789.2
B68: Gross Profit Margin $ | C68: =C12-C66 -> 1035885 | D68: =D12-D66 -> 1000606.4 | E68: =E12-E66 -> 377548.8 | F68: =F12-F66 -> 361280.3 | G68: =G12-G66 -> 658336.2 | H68: =H12-H66 -> 639326.09 | I68: =I12-I66 -> 1693360 | J68: =J12-J66 -> 861558 | ... P68: =P12-P66 -> 1013411.8
B69: Gross Profit Margin % (to Total Revenue) | C69: =IFERROR(C68/C12,"") -> 0.21690792 | D69: =IFERROR(D68/D12,"") -> 0.20952084 | E69: =IFERROR(E68/E12,"") -> 0.15957207 | F69: =IFERROR(F68/F12,"") -> 0.15269621 | G69: =IFERROR(G68/G12,"") -> 0.2732046 | H69: =IFERROR(H68/H12,"") -> 0.26531554 | I69: =IFERROR(I68/I12,"") -> 0.18802474 | J69: =IFERROR(J68/J12,"") -> 0.19237041 | ... P69: =IFERROR(P68/P12,"") -> 0.10330184
B70: ①The internals seem to have placed "Shipping Wages" into the "Indirect Labor" line item.
B71: ②The Company has a self-funded insurance plan. The estimated cost of this self-funded insurance plan is developed from actual claims paid prior to year-end, and is adjusted using historical claims data and incurred-but-not-received factors.

Sheet 2-T5Y IS (Cont.)
B2: Financial Information | C2: Highland Computer Forms, Inc.
B3: Date: 07/15/2026 | C3: Hillsboro, Ohio "S"-Corp
C4: Fiscal years ending December 31st
C6: Internal | D6: Adjusted RS | E6: Internal | F6: Adjusted RS | G6: Internal | H6: Adjusted -RS | I6: Review | J6: Internal | K6: Internal | L6: Review | M6: Review | N6: Review | O6: Review | P6: Review
B7: INCOME STATEMENT | C7: 6 mo.-'26 | D7: 6 mo.-'26 | E7: Q2-'26 | F7: 6 mo.-'26 | G7: Q1-'26 | H7: Q1-'26 | I7: FY2025 | J7: 6 mo.-'25 | K7: 6-mo.-'24 | L7: FY2024 | M7: FY2023 | N7: FY2022 | O7: FY2021 | P7: FY2020
B8: Gross Profit Margin $ | C8: ='1-T5Y IS'!C68 -> 1035885 | D8: ='1-T5Y IS'!D68 -> 1000606.4 | E8: ='1-T5Y IS'!E68 -> 377548.8 | F8: ='1-T5Y IS'!F68 -> 361280.3 | G8: ='1-T5Y IS'!G68 -> 658336.2 | H8: ='1-T5Y IS'!H68 -> 639326.09 | I8: ='1-T5Y IS'!I68 -> 1693360 | J8: ='1-T5Y IS'!J68 -> 861558 | ... P8: ='1-T5Y IS'!P68 -> 1013411.8
B9: Gross Profit Margin % (to Total Revenue) | C9: ='1-T5Y IS'!C69 -> 0.21690792 | D9: ='1-T5Y IS'!D69 -> 0.20952084 | E9: ='1-T5Y IS'!E69 -> 0.15957207 | F9: ='1-T5Y IS'!F69 -> 0.15269621 | G9: ='1-T5Y IS'!G69 -> 0.2732046 | H9: ='1-T5Y IS'!H69 -> 0.26531554 | I9: ='1-T5Y IS'!I69 -> 0.18802474 | J9: ='1-T5Y IS'!J69 -> 0.19237041 | ... P9: ='1-T5Y IS'!P69 -> 0.10330184
B10: S, G & A Expenses
B11: Selling Expenses
B12: Advertising | C12: ='2024&2023'!C76 -> 1531 | D12: =+F12+H12 -> 1531 | E12: =C12-G12 -> 1016 | F12: =1531-515 -> 1016 | G12: ='2024&2023'!D76 -> 515 | H12: 515 | I12: ='2024&2023'!E76 -> 7823 | J12: ='2024&2023'!F76 -> 3474 | K12: ='2024&2023'!G76 -> 8845 | L12: ='2024&2023'!H76 -> 10995 | M12: ='2024&2023'!I76 -> 12447 | N12: ='2024&2023'!J76 -> 25516 | O12: ='2024&2023'!K76 -> 0 | P12: ='2024&2023'!L76 -> 0
B13: ='2024&2023'!B67 -> Travel and Entertainment (HCF) | C13: ='2024&2023'!C67 -> 10973 | D13: =+F13+H13 -> 10973 | E13: =C13-G13 -> 5765 | F13: =6142+4831-5208 -> 5765 | G13: ='2024&2023'!D67 -> 5208 | H13: =4085+1123 -> 5208 | I13: ='2024&2023'!E67 -> 15274 | J13: ='2024&2023'!F67 -> 4516 | K13: ='2024&2023'!G67 -> 13063 | L13: ='2024&2023'!H67 -> 23822 | M13: ='2024&2023'!I67 -> 41639 | N13: ='2024&2023'!J67 -> 23791 | O13: ='2024&2023'!K67 -> 23622 | P13: ='2024&2023'!L67 -> 7286
B14: ='2024&2023'!B68 -> Travel and Entertainment (G. Fordyce) | C14: ='2024&2023'!C68 -> 0 | D14: =+F14+H14 -> 0 | E14: =C14-G14 -> 0 | G14: ='2024&2023'!D68 -> 0 | I14: ='2024&2023'!E68 -> 3679 | J14: ='2024&2023'!F68 -> 0 | K14: ='2024&2023'!G68 -> 0 | L14: ='2024&2023'!H68 -> 5497 | M14: ='2024&2023'!I68 -> 1611
B15: Salaries - Sales Service | C15: ='2024&2023'!C86 -> 148173 | D15: =+F15+H15 -> 0 | E15: =C15-G15 -> 74047 | G15: ='2024&2023'!D86 -> 74126 | I15: ='2024&2023'!E86 -> 0 | J15: ='2024&2023'!F86 -> 165564 | K15: ='2024&2023'!G86 -> 167528 | L15: 0 | M15: 0 | N15: 0 | O15: 0 | P15: 0
B16: Salaries - Outside Sales | C16: ='2024&2023'!C87 -> 62136 | D16: =+F16+H16 -> 0 | E16: =C16-G16 -> 31434 | G16: ='2024&2023'!D87 -> 30702 | I16: ='2024&2023'!E87 -> 0 | J16: ='2024&2023'!F87 -> 61884 | K16: ='2024&2023'!G87 -> 74441 | L16: 0 | M16: 0 | N16: 0 | O16: 0 | P16: 0 | S16: 1. Do not substract the other income, since this other income is rebates and scrap paper sales. It is indeed arguably a parrt of operational costs and income
B17: ='2024&2023'!B79 -> Selling Expenses | C17: ='2024&2023'!C79 -> 1534 | D17: =+F17+H17 -> 1534 | E17: =C17-G17 -> 982 | F17: =1534-552 -> 982 | G17: ='2024&2023'!D79 -> 552 | H17: 552 | I17: ='2024&2023'!E79 -> 505 | J17: ='2024&2023'!F79 -> 207 | K17: ='2024&2023'!G79 -> 1734 | L17: ='2024&2023'!H79 -> 1753 | M17: ='2024&2023'!I79 -> 10325 | N17: ='2024&2023'!J79 -> 571 | O17: ='2024&2023'!K79 -> 129 | P17: ='2024&2023'!L79 -> 0 | S17: 2. Make sure to correct the depreciation amount.
B18: ='2024&2023'!B84 -> Dues and Subscriptions (HCF) | C18: ='2024&2023'!C84 -> 0 | D18: =+F18+H18 -> 0 | E18: =C18-G18 -> 0 | G18: ='2024&2023'!D84 -> 0 | I18: ='2024&2023'!E84 -> 6 | J18: ='2024&2023'!F84 -> 8 | K18: ='2024&2023'!G84 -> 99 | L18: ='2024&2023'!H84 -> 99 | M18: ='2024&2023'!I84 -> 99 | N18: ='2024&2023'!J84 -> 298 | O18: ='2024&2023'!K84 -> 299 | P18: ='2024&2023'!L84 -> 95 | S18: 3. Make sure to itemize and bake in the G. Fordyce amounts into the financials to match the Reviews
B19: ='2024&2023'!B85 -> Dues and Subscriptions (G. Fordyce) | C19: ='2024&2023'!C85 -> 0 | D19: =+F19+H19 -> 0 | E19: =C19-G19 -> 0 | G19: ='2024&2023'!D85 -> 0 | I19: ='2024&2023'!E85 -> 171 | J19: ='2024&2023'!F85 -> 0 | K19: ='2024&2023'!G85 -> 0 | L19: ='2024&2023'!H85 -> 166 | M19: ='2024&2023'!I85 -> 160
B20: Sub-total Selling Expenses | C20: =SUM(C12:C19) -> 224347 | D20: =SUM(D12:D19) -> 14038 | E20: =SUM(E12:E19) -> 113244 | F20: =SUM(F12:F19) -> 7763 | G20: =SUM(G12:G19) -> 111103 | H20: =SUM(H12:H19) -> 6275 | I20: =SUM(I12:I19) -> 27458 | J20: =SUM(J12:J18) -> 235653 | K20: =SUM(K12:K18) -> 265710 | L20: =SUM(L12:L19) -> 42332 | M20: =SUM(M12:M19) -> 66281 | N20: =SUM(N12:N18) -> 50176 | O20: =SUM(O12:O18) -> 24050 | P20: =SUM(P12:P18) -> 7381 | S20: 4. Make sure to talk about thse self-funded insurance plan.
B22: General & Administrative
B23: ='2024&2023'!B54 -> Office Salaries | C23: ='2024&2023'!C54 -> 0 | D23: =+F23+H23 -> 210305 | E23: =C23-G23 -> 0 | F23: =148173+62136-104827-4 -> 105478 | G23: ='2024&2023'!D54 -> 0 | H23: =74126+30702-1 -> 104827 | I23: ='2024&2023'!E54-244188 -> 438733 | J23: ='2024&2023'!F54 -> 0 | K23: ='2024&2023'!G54 -> 0 | L23: ='2024&2023'!H54-102120 -> 473197 | M23: ='2024&2023'!I54-55340 -> 579472 | N23: ='2024&2023'!J54 -> 775051 | O23: ='2024&2023'!K54 -> 683480 | P23: ='2024&2023'!L54 -> 535262 | Q23: *** pulled out bonus amount fr 25 and 24 and 23
B24: ='2024&2023'!B56 -> Administrative Salaries | C24: ='2024&2023'!C56 -> 65997 | D24: =+F24+H24 -> 65997 | E24: =C24-G24 -> 33478 | F24: =65997-32519 -> 33478 | G24: ='2024&2023'!D56 -> 32519 | H24: 32519 | I24: ='2024&2023'!E56 -> 129211 | J24: ='2024&2023'!F56 -> 63483 | K24: ='2024&2023'!G56 -> 63975 | L24: ='2024&2023'!H56 -> 128935 | M24: ='2024&2023'!I56 -> 127950 | N24: ='2024&2023'!J56 -> 119896 | O24: ='2024&2023'!K56 -> 115656 | P24: ='2024&2023'!L56 -> 119624
B25: Employee Bonus | C25: ='2024&2023'!C73 -> 38088 | D25: =+F25+H25 -> 38088 | E25: =C25-G25 -> 3968 | F25: =38088-H25 -> 3968 | G25: ='2024&2023'!D73 -> 34120 | H25: 34120 | I25: 244188 | J25: ='2024&2023'!F73 -> 59055 | K25: ='2024&2023'!G73 -> 73000 | L25: 102120 | M25: 55340 | N25: 0 | O25: 0 | P25: 0 | Q25: reclassified from office salaries
B26: ='2024&2023'!B63 -> Payroll Taxes | C26: ='2024&2023'!C63 -> 19095 | D26: =+F26+H26 -> 19095 | E26: =C26-G26 -> 8565 | F26: =19095-10530 -> 8565 | G26: ='2024&2023'!D63 -> 10530 | H26: 10530 | I26: ='2024&2023'!E63 -> 41164 | J26: ='2024&2023'!F63 -> 21560 | K26: ='2024&2023'!G63 -> 22732 | L26: ='2024&2023'!H63 -> 43462 | M26: ='2024&2023'!I63 -> 54543 | N26: ='2024&2023'!J63 -> 51840 | O26: ='2024&2023'!K63 -> 48608 | P26: ='2024&2023'!L63 -> 46821
B27: ='2024&2023'!B70 -> Retirement Plan Expenses | C27: ='2024&2023'!C70 -> 10982 | D27: =+F27+H27 -> 10982 | E27: =C27-G27 -> 5091 | F27: =10982-5891 -> 5091 | G27: ='2024&2023'!D70 -> 5891 | H27: 5891 | I27: ='2024&2023'!E70 -> 21536 | J27: ='2024&2023'!F70 -> 11009 | K27: ='2024&2023'!G70 -> 11290 | L27: ='2024&2023'!H70 -> 22199 | M27: ='2024&2023'!I70 -> 23682 | N27: ='2024&2023'!J70 -> 23252 | O27: ='2024&2023'!K70 -> 21563 | P27: ='2024&2023'!L70 -> 19755
B28: Lease (20% of Total - HCF) | C28: =('2024&2023'!C24*0.2)+'2024&2023'!C88 -> 12600 | D28: =+F28+H28 -> 0 | E28: =C28-G28 -> 6300 | G28: =('2024&2023'!D24*0.2)+'2024&2023'!D88 -> 6300 | I28: =('2024&2023'!E24*0.2)+'2024&2023'!E88 -> 24935.4 | J28: =('2024&2023'!F24*0.2)+'2024&2023'!F88 -> 11278 | K28: =('2024&2023'!G24*0.2)+'2024&2023'!G88 -> 31313 | L28: ='2024&2023'!H24*0.2 -> 31395 | M28: ='2024&2023'!I24*0.2 -> 30169.2 | N28: ='2024&2023'!J24*0.2 -> 30251.4 | O28: ='2024&2023'!K24*0.2 -> 29445.8 | P28: ='2024&2023'!L24*0.2 -> 28436
B29: Lease (20% of Total - G. Fordyce) | D29: =+F29+H29 -> 0 | E29: =C29-G29 -> 0 | I29: ='2024&2023'!E25*0.2 -> 1920 | L29: ='2024&2023'!H25*0.2 -> 1920 | M29: ='2024&2023'!I25*0.2 -> 1920
B30: Utilities (20% of Total) | C30: ='2024&2023'!C21*0.2 -> 31421 | D30: =+F30+H30 -> 0 | E30: =C30-G30 -> 15263.8 | G30: ='2024&2023'!D21*0.2 -> 16157.2 | I30: ='2024&2023'!E21*0.2 -> 57973.6 | J30: ='2024&2023'!F21*0.2 -> 26652 | K30: ='2024&2023'!G21*0.2 -> 21759.6 | L30: ='2024&2023'!H21*0.2 -> 47776.4 | M30: ='2024&2023'!I21*0.2 -> 51618.2 | N30: ='2024&2023'!J21*0.2 -> 52677.6 | O30: ='2024&2023'!K21*0.2 -> 50665.4 | P30: ='2024&2023'!L21*0.2 -> 48759.8
B31: ='2024&2023'!B55 -> Insurance | C31: ='2024&2023'!C55+'2024&2023'!C45 -> 98449 | D31: =+F31+H31 -> 98449 | E31: =C31-G31 -> 56031 | F31: =61880+6163+30406-42418 -> 56031 | G31: ='2024&2023'!D55+'2024&2023'!D45 -> 42418 | H31: =24134+3081+15203 -> 42418 | I31: ='2024&2023'!E55+'2024&2023'!E45 -> 160790 | J31: ='2024&2023'!F55+'2024&2023'!F45 -> 85102 | K31: ='2024&2023'!G55+'2024&2023'!G45 -> 54904 | L31: ='2024&2023'!H55 -> 146115 | M31: ='2024&2023'!I55 -> 147445 | N31: ='2024&2023'!J55 -> 144638 | O31: ='2024&2023'!K55 -> 102067 | P31: ='2024&2023'!L55 -> 128258
B32: ='2024&2023'!B57 -> Professional Fees | C32: ='2024&2023'!C57 -> 55949 | D32: =+F32+H32 -> 55949 | E32: =C32-G32 -> 15544 | F32: =55949-40405 -> 15544 | G32: ='2024&2023'!D57 -> 40405 | H32: 40405 | I32: ='2024&2023'!E57 -> 85592 | J32: ='2024&2023'!F57 -> 52728 | K32: ='2024&2023'!G57 -> 67530 | L32: ='2024&2023'!H57 -> 90099 | M32: ='2024&2023'!I57 -> 112984 | N32: ='2024&2023'!J57 -> 120304 | O32: ='2024&2023'!K57 -> 196583 | P32: ='2024&2023'!L57 -> 107547
B33: ='2024&2023'!B58 -> Depreciation (HCF) | C33: ='2024&2023'!C58 -> 31793 | D33: =+F33+H33 -> 31793 | E33: =C33-G33 -> 15897 | F33: =3752+21792+6249-15896 -> 15897 | G33: ='2024&2023'!D58 -> 15896 | H33: =1876+10896+3124 -> 15896 | I33: ='2024&2023'!E58 -> 63962 | J33: ='2024&2023'!F58 -> 35231 | K33: ='2024&2023'!G58 -> 30799 | L33: ='2024&2023'!H58 -> 66605 | M33: ='2024&2023'!I58 -> 57511 | N33: ='2024&2023'!J58 -> 59433 | O33: ='2024&2023'!K58 -> 59486 | P33: ='2024&2023'!L58 -> 59449
B34: ='2024&2023'!B59 -> Depreciation (G. Fordyce) | D34: =+F34+H34 -> 0 | E34: =C34-G34 -> 0 | I34: ='2024&2023'!E59 -> 6505 | L34: ='2024&2023'!H59 -> 6505 | M34: ='2024&2023'!I59 -> 7913
B35: ='2024&2023'!B60 -> Bad Debt Expense | C35: ='2024&2023'!C60 -> 0 | D35: =+F35+H35 -> 0 | E35: =C35-G35 -> 0 | G35: ='2024&2023'!D60 -> 0 | I35: ='2024&2023'!E60 -> 6597 | J35: ='2024&2023'!F60 -> 2198 | K35: ='2024&2023'!G60 -> 1493 | L35: ='2024&2023'!H60 -> 50879 | M35: ='2024&2023'!I60 -> 1704 | N35: ='2024&2023'!J60 -> 57 | O35: ='2024&2023'!K60 -> 5840 | P35: ='2024&2023'!L60 -> 2810
B36: ='2024&2023'!B61 -> General Taxes | C36: ='2024&2023'!C61 -> 24950 | D36: =+F36+H36 -> 24950 | E36: =C36-G36 -> 12692 | F36: =24950-12258 -> 12692 | G36: ='2024&2023'!D61 -> 12258 | H36: 12258 | I36: ='2024&2023'!E61 -> 54835 | J36: ='2024&2023'!F61 -> 29289 | K36: ='2024&2023'!G61 -> 23864 | L36: ='2024&2023'!H61 -> 46939 | M36: ='2024&2023'!I61 -> 57431 | N36: ='2024&2023'!J61 -> 96595 | O36: ='2024&2023'!K61 -> 44146 | P36: ='2024&2023'!L61 -> 49266
B37: ='2024&2023'!B62 -> Caretaking Expenses | C37: ='2024&2023'!C62 -> 15908 | D37: =+F37+H37 -> 24654 | E37: =C37-G37 -> 7950 | F37: =8746+15908-11405 -> 13249 | G37: ='2024&2023'!D62 -> 7958 | H37: =3447+7958 -> 11405 | I37: ='2024&2023'!E62 -> 53893 | J37: ='2024&2023'!F62 -> 18911 | K37: ='2024&2023'!G62 -> 8927 | L37: ='2024&2023'!H62 -> 46071 | M37: ='2024&2023'!I62 -> 63705 | N37: ='2024&2023'!J62 -> 76067 | O37: ='2024&2023'!K62 -> 59648 | P37: ='2024&2023'!L62 -> 54602
B38: ='2024&2023'!B64 -> Bank and Payroll Service Charges (HCF) | C38: ='2024&2023'!C64 -> 25874 | D38: =+F38+H38 -> 25874 | E38: =C38-G38 -> 12309 | F38: =17884+7990-13566 -> 12308 | G38: ='2024&2023'!D64 -> 13565 | H38: =9018+4548 -> 13566 | I38: ='2024&2023'!E64 -> 43303 | J38: ='2024&2023'!F64 -> 20966 | K38: ='2024&2023'!G64 -> 22813 | L38: ='2024&2023'!H64 -> 42997 | M38: ='2024&2023'!I64 -> 39709 | N38: ='2024&2023'!J64 -> 76511 | O38: ='2024&2023'!K64 -> 99314 | P38: ='2024&2023'!L64 -> 109300
B39: ='2024&2023'!B65 -> Bank and Payroll Service Charges (G. Fordyce) | C39: ='2024&2023'!C65 -> 0 | D39: =+F39+H39 -> 0 | E39: =C39-G39 -> 0 | G39: ='2024&2023'!D65 -> 0 | I39: ='2024&2023'!E65 -> 156 | J39: ='2024&2023'!F65 -> 0 | K39: ='2024&2023'!G65 -> 0 | L39: ='2024&2023'!H65 -> 36 | M39: ='2024&2023'!I65 -> 164
B40: ='2024&2023'!B66 -> Office Repairs and Maintenance | C40: ='2024&2023'!C66 -> 13222 | D40: =+F40+H40 -> 13222 | E40: =C40-G40 -> 6611 | F40: =13222-6611 -> 6611 | G40: ='2024&2023'!D66 -> 6611 | H40: 6611 | I40: ='2024&2023'!E66 -> 29691 | J40: ='2024&2023'!F66 -> 12994 | K40: ='2024&2023'!G66 -> 17626 | L40: ='2024&2023'!H66 -> 42669 | M40: ='2024&2023'!I66 -> 23969 | N40: ='2024&2023'!J66 -> 24119 | O40: ='2024&2023'!K66 -> 25649 | P40: ='2024&2023'!L66 -> 24175
B41: ='2024&2023'!B69 -> Telephone and Internet | C41: ='2024&2023'!C69 -> 14143 | D41: =+F41+H41 -> 14143 | E41: =C41-G41 -> 6655 | F41: =4305+9838-7488 -> 6655 | G41: ='2024&2023'!D69 -> 7488 | H41: =2173+5315 -> 7488 | I41: ='2024&2023'!E69 -> 24328 | J41: ='2024&2023'!F69 -> 13541 | K41: ='2024&2023'!G69 -> 15458 | L41: ='2024&2023'!H69 -> 28373 | M41: ='2024&2023'!I69 -> 32412 | N41: ='2024&2023'!J69 -> 33368 | O41: ='2024&2023'!K69 -> 38805 | P41: ='2024&2023'!L69 -> 36491
B42: Office Supplies (HCF) | C42: ='2024&2023'!C71 -> 7095 | D42: =+F42+H42 -> 7095 | E42: =C42-G42 -> 2969 | F42: =7095-4126 -> 2969 | G42: ='2024&2023'!D71 -> 4126 | H42: 4126 | I42: ='2024&2023'!E71 -> 21002 | J42: ='2024&2023'!F71 -> 9564 | K42: ='2024&2023'!G71 -> 11638 | L42: ='2024&2023'!H71 -> 20600 | M42: ='2024&2023'!I71 -> 32828 | N42: ='2024&2023'!J71 -> 33223 | O42: ='2024&2023'!K71 -> 26639 | P42: ='2024&2023'!L71 -> 26432
B43: ='2024&2023'!B72 -> Office Supplies (G. Fordyce) | C43: ='2024&2023'!C72 -> 0 | D43: =+F43+H43 -> 0 | E43: =C43-G43 -> 0 | G43: ='2024&2023'!D72 -> 0 | I43: ='2024&2023'!E72 -> 1339 | J43: ='2024&2023'!F72 -> 0 | K43: ='2024&2023'!G72 -> 0 | L43: ='2024&2023'!H72 -> 1093 | M43: ='2024&2023'!I72 -> 1158
B44: Employee Relations (HCF) | C44: ='2024&2023'!C74 -> 7143 | D44: =+F44+H44 -> 7143 | E44: =C44-G44 -> 218 | F44: =7143-6925 -> 218 | G44: ='2024&2023'!D74 -> 6925 | H44: 6925 | I44: ='2024&2023'!E74 -> 5430 | J44: ='2024&2023'!F74 -> 1648 | K44: ='2024&2023'!G74 -> 6231 | L44: ='2024&2023'!H74 -> 10599 | M44: ='2024&2023'!I74 -> 7875 | N44: ='2024&2023'!J74 -> 8928 | O44: ='2024&2023'!K74 -> 12153 | P44: ='2024&2023'!L74 -> 17311
B45: ='2024&2023'!B75 -> Employee Relations (G. Fordyce) | C45: ='2024&2023'!C75 -> 0 | D45: =+F45+H45 -> 0 | E45: =C45-G45 -> 0 | G45: ='2024&2023'!D75 -> 0 | I45: ='2024&2023'!E75 -> 0 | J45: ='2024&2023'!F75 -> 0 | K45: ='2024&2023'!G75 -> 0 | L45: ='2024&2023'!H75 -> 550 | M45: ='2024&2023'!I75 -> 400
B46: ='2024&2023'!B77 -> Postage | C46: ='2024&2023'!C77 -> 1739 | D46: =+F46+H46 -> 1739 | E46: =C46-G46 -> 665 | F46: =1739-1074 -> 665 | G46: ='2024&2023'!D77 -> 1074 | H46: 1074 | I46: ='2024&2023'!E77 -> 3405 | J46: ='2024&2023'!F77 -> 1561 | K46: ='2024&2023'!G77 -> 2187 | L46: ='2024&2023'!H77 -> 4009 | M46: ='2024&2023'!I77 -> 6408 | N46: ='2024&2023'!J77 -> 5824 | O46: ='2024&2023'!K77 -> 1339 | P46: ='2024&2023'!L77 -> 8669
B47: ='2024&2023'!B78 -> Postage (G. Fordyce) | C47: ='2024&2023'!C78 -> 0 | D47: =+F47+H47 -> 0 | E47: =C47-G47 -> 0 | G47: ='2024&2023'!D78 -> 0 | I47: ='2024&2023'!E78 -> 266 | J47: ='2024&2023'!F78 -> 0 | K47: ='2024&2023'!G78 -> 0 | L47: ='2024&2023'!H78 -> 261 | M47: ='2024&2023'!I78 -> 181
B48: ='2024&2023'!B80 -> Charitable Contributions | C48: ='2024&2023'!C80 -> 0 | D48: =+F48+H48 -> 0 | E48: =C48-G48 -> 0 | G48: ='2024&2023'!D80 -> 0 | I48: ='2024&2023'!E80 -> 1000 | J48: ='2024&2023'!F80 -> 500 | K48: ='2024&2023'!G80 -> 750 | L48: ='2024&2023'!H80 -> 1500 | M48: ='2024&2023'!I80 -> 7429 | N48: ='2024&2023'!J80 -> 241 | O48: ='2024&2023'!K80 -> 566 | P48: ='2024&2023'!L80 -> 18
B49: ='2024&2023'!B81 -> Training and Education | C49: ='2024&2023'!C81 -> 1235 | D49: =+F49+H49 -> 1235 | E49: =C49-G49 -> 180 | F49: =1000+235-1055 -> 180 | G49: ='2024&2023'!D81 -> 1055 | H49: =1000+55 -> 1055 | I49: ='2024&2023'!E81 -> 4290 | J49: ='2024&2023'!F81 -> 1205 | K49: ='2024&2023'!G81 -> 1155 | L49: ='2024&2023'!H81 -> 1425 | M49: ='2024&2023'!I81 -> 1410 | N49: ='2024&2023'!J81 -> 1834 | O49: ='2024&2023'!K81 -> 3033 | P49: ='2024&2023'!L81 -> 1260
B50: ='2024&2023'!B82 -> Miscellaneous Expenses (HCF) | C50: ='2024&2023'!C82 -> 0 | D50: =+F50+H50 -> 0 | E50: =C50-G50 -> 0 | G50: ='2024&2023'!D82 -> 0 | I50: ='2024&2023'!E82 -> 2227 | J50: ='2024&2023'!F82 -> 0 | K50: ='2024&2023'!G82 -> 0 | L50: ='2024&2023'!H82 -> -24 | M50: ='2024&2023'!I82 -> 0 | N50: ='2024&2023'!J82 -> 68 | O50: ='2024&2023'!K82 -> 56 | P50: ='2024&2023'!L82 -> 806
B51: ='2024&2023'!B83 -> Miscellaneous Expenses (G. Foryce) | C51: ='2024&2023'!C83 -> 0 | D51: =+F51+H51 -> 0 | E51: =C51-G51 -> 0 | G51: ='2024&2023'!D83 -> 0 | I51: ='2024&2023'!E83 -> 0 | J51: ='2024&2023'!F83 -> 0 | K51: ='2024&2023'!G83 -> 0 | L51: ='2024&2023'!H83 -> 1279 | M51: ='2024&2023'!I83 -> 576
B52: Sub-Total G & A Expenses | C52: =SUM(C23:C51) -> 475683 | D52: =SUM(D23:D51) -> 650713 | E52: =SUM(E23:E51) -> 210386.8 | F52: =SUM(F23:F51) -> 299599 | G52: =SUM(G23:G51) -> 265296.2 | H52: =SUM(H23:H51) -> 351114 | I52: =SUM(I23:I51) -> 1528272 | J52: =SUM(J23:J51) -> 478475 | ... M52: =SUM(M23:M51) -> 1527906.4 | N52: =SUM(N23:N50) -> 1734178 | O52: =SUM(O23:O50) -> 1624742.2 | P52: =SUM(P23:P50) -> 1425051.8
B54: Total S, G & A Expenses | C54: =SUM(C20,C52) -> 700030 | D54: =SUM(D20,D52) -> 664751 | E54: =SUM(E20,E52) -> 323630.8 | F54: =SUM(F20,F52) -> 307362 | G54: =SUM(G20,G52) -> 376399.2 | H54: =SUM(H20,H52) -> 357389 | I54: =SUM(I20,I52) -> 1555730 | J54: =SUM(J20,J52) -> 714128 | ... P54: =SUM(P20,P52) -> 1432432.8
B56: Net Operating Income | C56: =C8-C54 -> 335855 | D56: =D8-D54 -> 335855.39 | E56: =E8-E54 -> 53918 | F56: =F8-F54 -> 53918.3 | G56: =G8-G54 -> 281937 | H56: =H8-H54 -> 281937.09 | I56: =I8-I54 -> 137630 | J56: =J8-J54 -> 147430 | ... P56: =P8-P54 -> -419021
B58: Other Income (Expense)
B59: Other Income* | N59: ='2024&2023'!J5 -> 388325 | O59: ='2024&2023'!K5 -> 279481 | P59: ='2024&2023'!L5 -> 591937
B60: Purchase Discounts | N60: =-'2024&2023'!J43 -> 108616 | O60: =-'2024&2023'!K43 -> 100887 | P60: =-'2024&2023'!L43 -> 49024
B61: Interest Expense | C61: ='2024&2023'!C94+'2024&2023'!C93 -> -1785 | D61: =+F61+H61 -> -1785 | E61: =C61-G61 -> 5287 | F61: =9237-11022+7072 -> 5287 | G61: ='2024&2023'!D94+'2024&2023'!D93 -> -7072 | H61: =-8329+1257 -> -7072 | I61: ='2024&2023'!E94+'2024&2023'!E93 -> -15331 | J61: ='2024&2023'!F94+'2024&2023'!F93 -> -9887 | K61: ='2024&2023'!G94+'2024&2023'!G93 -> -9669 | L61: ='2024&2023'!H94+'2024&2023'!H93 -> -19142 | M61: ='2024&2023'!I94+'2024&2023'!I93 -> -22060 | N61: ='2024&2023'!J94+'2024&2023'!J93 -> -121245 | O61: ='2024&2023'!K94+'2024&2023'!K93 -> -88472 | P61: ='2024&2023'!L94+'2024&2023'!L93 -> -137472
B62: Gain on Disposal of Fixed Assets | C62: ='2024&2023'!C95 -> 0 | E62: =C62-G62 -> 0 | G62: ='2024&2023'!D95 -> 0 | I62: ='2024&2023'!E95 -> 0 | J62: ='2024&2023'!F95 -> 0 | K62: ='2024&2023'!G95 -> 2666 | L62: ='2024&2023'!H95 -> 2667 | M62: ='2024&2023'!I95 -> 0 | N62: ='2024&2023'!J95 -> 0 | O62: ='2024&2023'!K95 -> 1500 | P62: ='2024&2023'!L95 -> 0
B63: Recovery of Bad Debt | C63: ='2024&2023'!C96 -> 0 | E63: =C63-G63 -> 0 | G63: ='2024&2023'!D96 -> 0 | I63: ='2024&2023'!E96 -> 0 | J63: ='2024&2023'!F96 -> 576 | K63: ='2024&2023'!G96 -> 0
B64: Misc. Expense | C64: ='2024&2023'!C97 -> -4 | D64: =+F64+H64 -> -4 | E64: =C64-G64 -> 0 | F64: 0 | G64: ='2024&2023'!D97 -> -4 | H64: -4 | I64: ='2024&2023'!E97 -> 0 | J64: ='2024&2023'!F97 -> 0 | K64: ='2024&2023'!G97 -> -15
B65: Employee Retention Credit | C65: ='2024&2023'!C99 -> 0 | E65: =C65-G65 -> 0 | G65: ='2024&2023'!D99 -> 0 | I65: ='2024&2023'!E99 -> 0 | J65: ='2024&2023'!F99 -> 0 | K65: ='2024&2023'!G99 -> 0 | L65: ='2024&2023'!H99 -> 0 | M65: ='2024&2023'!I99 -> 0 | N65: ='2024&2023'!J99 -> 0 | O65: ='2024&2023'!K99 -> 1352277 | P65: ='2024&2023'!L99 -> 0
B66: Debt Forgiven | C66: ='2024&2023'!C98 -> 133786 | D66: =+F66+H66 -> 133786 | E66: =C66-G66 -> 133786 | F66: 133786
B67: PPP Loan Debt Forgiven | C67: 0 | E67: =C67-G67 -> 0 | G67: 0 | I67: 0 | J67: 0 | K67: 0 | L67: 0 | M67: 0 | N67: ='2024&2023'!J98 -> 688137 | O67: ='2024&2023'!K98 -> 862310 | P67: ='2024&2023'!L98 -> 0
B68: Net Total Other Income (Expense) | C68: =SUM(C59:C67) -> 131997 | D68: =SUM(D59:D67) -> 131997 | E68: =SUM(E59:E67) -> 139073 | F68: =SUM(F59:F67) -> 139073 | G68: =SUM(G59:G67) -> -7076 | H68: =SUM(H59:H67) -> -7076 | I68: =SUM(I59:I67) -> -15331 | J68: =SUM(J59:J67) -> -9311 | ... P68: =SUM(P59:P67) -> 503489
B70: Net Income | C70: =SUM(C56,C68)+-24+N("Rounding Error Correction") -> 467828 | D70: =SUM(D56,D68)+-24+N("Rounding Error Correction") -> 467828.39 | E70: =SUM(E56,E68)+-3+N("Rounding Error Correction") -> 192988 | F70: =SUM(F56,F68)+-3+N("Rounding Error Correction") -> 192988.3 | G70: =SUM(G56,G68)+-21+N("Rounding Error Correction") -> 274840 | H70: =SUM(H56,H68)+-21+N("Rounding Error Correction") -> 274840.09 | I70: =SUM(I56,I68)-0+N("Rounding Error Correction") -> 122299 | J70: =SUM(J56,J68)-21+N("Rounding Error Correction") -> 138098 | K70: =SUM(K56,K68)-10+N("Rounding Error Correction") -> -62638 | L70: =SUM(L56,L68)-0+N("Rounding Error Correction") -> -149387 | M70: =SUM(M56,M68)-0+N("Rounding Error Correction") -> 99772 | N70: =SUM(N56,N68) -> 1214423 | O70: =SUM(O56,O68) -> 2288208 | P70: =SUM(P56,P68) -> 84468
B71: *Other income is primarily rebates from paper manufacturers (phased out in FY2023) and scrap paper sales (ongoing).

Sheet 3-Balance Sheet
B2: Financial Information | C2: Highland Computer Forms, Inc.
B3: Date: 07/15/2026 | C3: Hillsboro, Ohio "S"-Corp
C4: Fiscal years ending December 31st
C6: Internal | D6: Internal | E6: Review | F6: Internal | G6: Review | H6: Internal | I6: Review | J6: Review | K6: Review | L6: Review
B7: BALANCE SHEET | C7: Q2-'26 | D7: Q1-'26 | E7: FY2025 | F7: Q2-'25 | G7: FY2024 | H7: Q2-'24 | I7: FY2023 | J7: FY2022 | K7: FY2021 | L7: FY2020
B8: Current Assets
B9: Cash and Cash Equivalents (HCF) | C9: =739924 -> 739924 | D9: 543005 | E9: 254337 | F9: 739103 | G9: 286933 | H9: 641003 | I9: 519446 | J9: 113938 | K9: 49473 | L9: 175518
B10: Cash and Cash Equivalents (G. Fordyce) | E10: 71723 | G10: 21799 | I10: 87219
B11: Certificates of Deposit | D11: 0 | E11: 312916 | F11: 0 | G11: 300000 | H11: 0 | I11: 0 | J11: 0 | K11: 0 | L11: 0
B12: A/R, Trade
B13: A/R, Trade (HCF) | C13: 779487 | D13: 1010922 | E13: 674696 | F13: 624234 | G13: 600833 | H13: =739879 -> 739879 | I13: 825739 | J13: 1162502 | K13: 1033535 | L13: 838596
B14: A/R, Trade (G. Fordyce) | E14: 14174 | G14: 15236 | I14: 101789
B15: (Less Eliminating Entry) | C15: 0 | D15: 0 | E15: 0 | F15: 0 | G15: -7603 | H15: 0 | I15: -9935 | J15: 13420 | K15: 21353 | L15: =11296+6000 -> 17296
B16: Sub-Total A/P, Trade | C16: =SUM(C13:C15) -> 779487 | D16: =SUM(D13:D15) -> 1010922 | E16: =SUM(E13:E15) -> 688870 | F16: =SUM(F13:F15) -> 624234 | G16: =SUM(G13:G15) -> 608466 | H16: =SUM(H13:H15) -> 739879 | I16: =SUM(I13:I15) -> 917593
B17: A/R, Other
B18: A/R, Other (HCF) | C18: 15 | D18: 44939 | E18: 40085 | F18: 8401 | G18: 8193 | H18: =6459 -> 6459 | I18: 90154
B19: A/R, Other (G. Fordyce) | E19: 0 | G19: 0 | I19: 0
B20: (Less Eliminating Entry) | C20: 0 | D20: 0 | E20: -9206 | F20: 0 | G20: 0 | H20: 0 | I20: 0
B21: Sub-Total A/P, Other | C21: =SUM(C18:C20) -> 15 | D21: =SUM(D18:D20) -> 44939 | E21: =SUM(E18:E20) -> 30879 | F21: =SUM(F18:F20) -> 8401 | G21: =SUM(G18:G20) -> 8193 | H21: =SUM(H18:H20) -> 6459 | I21: =SUM(I18:I20) -> 90154
B22: Inventories (HCF) | C22: 1098507 | D22: 1202624 | E22: 1239901 | F22: 1050542 | G22: 1021535 | H22: =909413 -> 909413 | I22: 1051427 | J22: 1733922 | K22: 1107863 | L22: 632835
B23: Inventories (G. Fordyce) | C23: 0 | D23: 0 | E23: 0 | F23: 0 | G23: 0 | H23: 0 | I23: 45134
B24: Employee Retention Credits Receivable | D24: 0 | E24: 0 | F24: 0 | G24: 0 | H24: 0 | I24: 0 | J24: 1352277 | K24: 1352277 | L24: 0
B25: Prepaid Expenses | C25: 33215 | D25: 18804 | E25: 12631 | F25: 14221 | G25: 5961 | H25: =17236 -> 17236 | I25: 11844 | J25: 5804 | K25: 4863 | L25: 4523
B26: Total Current Assets | C26: =SUM(C9:C11,C16,C21,C22,C25) -> 2651148 | D26: =SUM(D9:D11,D16,D21,D22,D25) -> 2820294 | E26: =SUM(E9:E11,E16,E21,E22,E25) -> 2611257 | F26: =SUM(F9:F11,F16,F21,F22,F25) -> 2436501 | G26: =SUM(G9:G11,G16,G21,G22,G25) -> 2252887 | H26: =SUM(H9:H11,H16,H21,H22,H25) -> 2313990 | I26: =SUM(I9:I11,I16,I21,I22,I25,I23) -> 2722817 | J26: =SUM(J9:J25) -> 4381863 | K26: =SUM(K9:K25) -> 3569364 | L26: =SUM(L9:L25) -> 1668768
B28: Property, Plant and Equipment
B29: Land | C29: 600000 | D29: 600000 | E29: 100000 | F29: 600000 | G29: 100000 | H29: 600000 | I29: 100000 | J29: 100000 | K29: 100000 | L29: 100000
B30: Buildings | E30: 500000 | G30: 500000 | I30: 500000 | J30: 500000 | K30: 500000 | L30: 500000
B31: Leasehold Improvements (HCF) | C31: 1078355 | D31: 1078355 | E31: 1078356 | F31: 1078355 | G31: 1078356 | H31: 1056776 | I31: 1027967 | J31: 1001669 | K31: 1001669 | L31: 1001669
B32: Leasehold Improvements (G. Fordyce) | E32: 65050 | F32: 0 | G32: 65050 | H32: 0 | I32: 65050
B33: Machinery and Equipment | C33: 6811540 | D33: 6811540 | E33: 6801540 | F33: =6777168+188705 -> 6965873 | G33: 6759705 | H33: =6713457+199516 -> 6912973 | I33: 6717643 | J33: 6638006 | K33: 6638006 | L33: 6483888
B34: Vehicles | C34: 149312 | D34: 149312 | E34: 149313 | F34: 149312 | G34: 149313 | H34: 149312 | I34: 149313 | J34: 149313 | K34: 127387 | L34: 324668
B35: Furniture, Fixtures & Office Equip. | C35: =42406+188705 -> 231111 | D35: =42406+188705 -> 231111 | E35: 231112 | F35: 42406 | G35: 231112 | H35: =42406 -> 42406 | I35: 209970 | J35: 209970 | K35: 209970 | L35: 200911
B36: Total Fixed Assets at Cost | C36: =SUM(C29:C35) -> 8870318 | D36: =SUM(D29:D35) -> 8870318 | E36: =SUM(E29:E35) -> 8925371 | F36: =SUM(F29:F35) -> 8835946 | G36: =SUM(G29:G35) -> 8883536 | H36: =SUM(H29:H35) -> 8761467 | I36: =SUM(I29:I35) -> 8769943 | J36: =SUM(J29:J35) -> 8598958 | ... L36: =SUM(L29:L35) -> 8611136
B37: (Less Accumulated Depreciation) | C37: -7467180 | D37: =-7413885 -> -7413885 | E37: =-7339665-20923 -> -7360588 | F37: =-7241132 -> -7241132 | G37: =-7110597-14418 -> -7125015 | H37: =-7007577 -> -7007577 | I37: =-6889114-7913 -> -6897027 | J37: -6639871 | K37: -6381778 | L37: -6310027
B38: Total Net Fixed Assets | C38: =SUM(C36:C37) -> 1403138 | D38: =SUM(D36:D37) -> 1456433 | E38: =SUM(E36:E37) -> 1564783 | F38: =SUM(F36:F37) -> 1594814 | G38: =SUM(G36:G37) -> 1758521 | H38: =SUM(H36:H37) -> 1753890 | I38: =SUM(I36:I37) -> 1872916 | J38: =SUM(J36:J37) -> 1959087 | ... L38: =SUM(L36:L37) -> 2301109
B40: Other Assets
B41: Right-of-use assets, operating | D41: 0 | E41: 0 | F41: 0 | G41: 0 | H41: 0 | I41: 7572 | J41: 22269 | K41: 0 | L41: 0
B42: Cash Value of Life Insurance | D42: 0 | E42: 0 | F42: 0 | G42: 0 | H42: 0 | I42: 0 | J42: 176655 | K42: 168892 | L42: 160874
B43: Deferred Financing Fees, net | D43: 0 | E43: 0 | F43: 0 | G43: 0 | H43: 0 | I43: 0 | J43: 0 | K43: 20806 | L43: 41613
B44: Goodwill | C44: 10000 | D44: 10000 | E44: 10000 | F44: 10000 | G44: 10000 | H44: 10000 | I44: 10000 | J44: 10000 | K44: 10000 | L44: 10000
B45: Deposits | C45: 500 | D45: 500 | E45: 500 | F45: 500 | G45: 500 | H45: 1772 | I45: 10009 | J45: 20523 | K45: 9913 | L45: 8488
B46: Total Other Assets | C46: =SUM(C41:C45) -> 10500 | D46: =SUM(D41:D45) -> 10500 | E46: =SUM(E41:E45) -> 10500 | F46: =SUM(F41:F45) -> 10500 | G46: =SUM(G41:G45) -> 10500 | H46: =SUM(H41:H45) -> 11772 | I46: =SUM(I41:I45) -> 27581 | J46: =SUM(J41:J45) -> 229447 | ... L46: =SUM(L41:L45) -> 220975
B48: Total Assets | C48: =SUM(C26,C38,C46)+3+N("Rounding Error Correction") -> 4064789 | D48: =SUM(D26,D38,D46)+3+N("Rounding Error Correction") -> 4287230 | E48: =SUM(E26,E38,E46)+0+N("Rounding Error Correction") -> 4186540 | F48: =SUM(F26,F38,F46)+5+N("Rounding Error Correction") -> 4041820 | G48: =SUM(G26,G38,G46) -> 4021908 | H48: =SUM(H26,H38,H46)+5+N("Rounding Error Correction") -> 4079657 | I48: =SUM(I26,I38,I46) -> 4623314 | J48: =SUM(J26,J38,J46) -> 6570397 | K48: =SUM(K26,K38,K46) -> 5974229 | L48: =SUM(L26,L38,L46) -> 4190852
B50: LIABILITIES
B51: Current Liabilities
B52: Long-term debt, Current Portion | C52: 0 | D52: 0 | E52: 22707 | F52: 0 | G52: 15885 | H52: 0 | I52: 18817 | J52: 17991 | K52: 17201 | L52: 16445
B53: Line of Credit | D53: 0 | E53: 0 | F53: 0 | G53: 0 | H53: 0 | I53: 0 | J53: 700000 | K53: 548922 | L53: 0
B54: Finance Lease, Current Portion | C54: 0 | D54: 0 | E54: 0 | F54: 0 | G54: 0 | H54: 0 | I54: 3001 | J54: 8667 | K54: 8154 | L54: 7668
B55: Operating Lease, Current Portion | C55: 0 | D55: 0 | E55: 0 | F55: 0 | G55: 0 | H55: 0 | I55: 7572 | J55: 14698 | K55: 0 | L55: 0
B56: PPP Loan | D56: 0 | E56: 0 | F56: 0 | G56: 0 | H56: 0 | I56: 0 | J56: 0 | K56: 688137 | L56: 862310
B57: A/P, Trade
B58: A/P, Trade (HCF) | C58: 310086 | D58: 413053 | E58: 451708 | F58: 219210 | G58: 281913 | H58: 230561 | I58: 284395 | J58: 1181015 | K58: 642630 | L58: 758243
B59: A/P, Trade (G. Fordyce) | E59: 9206 | G59: 7603 | I59: 9935
B60: (Less Eliminating Entry) | C60: 0 | D60: 0 | E60: =-9206 -> -9206 | F60: 0 | G60: -7603 | H60: 0 | I60: -9935
B61: Sub-Total A/P, Trade | C61: =SUM(C58:C60) -> 310086 | D61: =SUM(D58:D60) -> 413053 | E61: =SUM(E58:E60) -> 451708 | F61: =SUM(F58:F60) -> 219210 | G61: =SUM(G58:G60) -> 281913 | H61: =SUM(H58:H60) -> 230561 | I61: =SUM(I58:I60) -> 284395 | J61: =SUM(J58:J60) -> 1181015 | ... L61: =SUM(L58:L60) -> 758243
B62: N/P, W & J | C62: 0 | D62: 193786 | E62: 193786 | F62: 193786 | G62: 0 | H62: 193786 | I62: 0 | J62: 0 | K62: 0 | L62: 0
B63: N/P, First State Bank | C63: 19755 | D63: 19755 | E63: 0 | F63: 19755 | G63: 0 | H63: 19244 | I63: 0 | J63: 0 | K63: 0 | L63: 0
B64: Accrued Payroll & Related Costs | C64: 0 | D64: 0 | E64: 191940 | F64: -8105 | G64: 237167 | H64: -1418 | I64: 295060 | J64: 328523 | K64: 346244 | L64: 221770
B65: Accrued Expenses | C65: 234041 | D65: 296870 | E65: 0 | F65: 345336 | G65: 0 | H65: 332945 | I65: 0 | J65: 0 | K65: 0 | L65: 0
B66: Accrued Rent, Affiliates | C66: 0 | D66: 0 | E66: 0 | F66: 0 | G66: 0 | H66: 0 | I66: 77500 | J66: 105500 | K66: 140500 | L66: 143000
B67: Accrued Taxes | C67: 0 | D67: 0 | E67: 48476 | F67: 0 | G67: 43283 | H67: 0 | I67: 43884 | J67: 44827 | K67: 41624 | L67: 47321
B68: Accrued Interest | D68: 0 | E68: 0 | F68: 0 | G68: 0 | H68: 0 | I68: 0 | J68: 3296 | K68: 0 | L68: 0
B69: Customer Deposits | C69: 0 | D69: 0 | E69: 0 | F69: 0 | G69: 0 | H69: 0 | I69: 202140
B70: Total Current Liabilities | C70: =SUM(C52:C56,C61:C68) -> 563882 | D70: =SUM(D52:D56,D61:D68) -> 923464 | E70: =SUM(E52:E56,E61:E68) -> 908617 | F70: =SUM(F52:F56,F61:F68) -> 769982 | G70: =SUM(G52:G56,G61:G68) -> 578248 | H70: =SUM(H52:H56,H61:H68) -> 775118 | I70: =SUM(I52:I56,I61:I69) -> 932369 | J70: =SUM(J52:J68) -> 3585532 | K70: =SUM(K52:K68) -> 3076042 | L70: =SUM(L52:L68) -> 2815000
B72: Long Term Liabilities
B73: N/P, Affiliate | C73: 0 | D73: 0 | E73: 0 | F73: 0 | G73: 193786 | H73: 0 | I73: 193786 | J73: 193786 | K73: 193786 | L73: 193786
B74: N/P, First State Bank - Long term | C74: =241871 -> 241871 | D74: 275154 | E74: 304972 | F74: 377563 | G74: 0 | H74: 405376 | I74: 0
B75: Line of Credit | D75: 0 | E75: 0 | F75: 0 | G75: 0 | H75: 0 | I75: 0 | J75: 0 | K75: 0 | L75: 733570
B76: Long-term debt, Net of Current Portion | C76: 0 | D76: 0 | E76: 0 | F76: 0 | G76: 399222 | H76: 0 | I76: 415107 | J76: 433924 | K76: 451915 | L76: 469115
B77: Finance lease, Net of Current Portion | D77: 0 | E77: 0 | F77: 0 | G77: 0 | H77: 0 | I77: 0 | J77: 1500 | K77: 10164 | L77: 18317
B78: Operating Lease, Net of Current Portion | D78: 0 | E78: 0 | F78: 0 | G78: 0 | H78: 0 | I78: 0 | J78: 7571 | K78: 0 | L78: 0
B79: Total Long-Term Liabilities | C79: =SUM(C73:C78) -> 241871 | D79: =SUM(D73:D78) -> 275154 | E79: =SUM(E73:E78) -> 304972 | F79: =SUM(F73:F78) -> 377563 | G79: =SUM(G73:G78) -> 593008 | H79: =SUM(H73:H78) -> 405376 | I79: =SUM(I73:I78) -> 608893 | J79: =SUM(J73:J78) -> 636781 | ... L79: =SUM(L73:L78) -> 1414788
B81: Total Liabilities | C81: =SUM(C70,C79)+1+N("Rounding Error Correction") -> 805754 | D81: =SUM(D70,D79)+2+N("Rounding Error Correction") -> 1198620 | E81: =SUM(E70,E79)+0+N("Rounding Error Correction") -> 1213589 | F81: =SUM(F70,F79)+2+N("Rounding Error Correction") -> 1147547 | G81: =SUM(G70,G79) -> 1171256 | H81: =SUM(H70,H79) -> 1180494 | I81: =SUM(I70,I79) -> 1541262 | J81: =SUM(J70,J79) -> 4222313 | K81: =SUM(K70,K79) -> 3731907 | L81: =SUM(L70,L79) -> 4229788
B83: Stockholders' Equity | C83: =C48-C81 -> 3259035 | D83: =D48-D81 -> 3088610 | E83: =E48-E81 -> 2972951 | F83: =F48-F81 -> 2894273 | G83: =G48-G81 -> 2850652 | H83: =H48-H81 -> 2899163 | I83: =I48-I81 -> 3082052 | J83: =J48-J81 -> 2348084 | ... L83: =L48-L81 -> -38936
C84: =C7 -> Q2-'26 | D84: =D7 -> Q1-'26 | E84: FY2025 | F84: =F7 -> Q2-'25 | G84: FY2024 | H84: 6-mo'-FY'24 | I84: FY2023 | J84: FY2022 | K84: FY2021 | L84: FY2020

Sheet 4-EBITDA
B2: Financial Information | C2: Highland Computer Forms, Inc.
B3: Date: 07/15/2026 | C3: Hillsboro, Ohio "S"-Corp
C4: Fiscal years ending December 31st
C6: Extrapolation④ | D6: Internal | E6: Internal | F6: Internal | G6: Review | H6: Internal | I6: Internal | J6: Review | K6: Review | L6: Review | M6: Review | N6: Review
B7: "Adjusted" EBITDA CALCULATION | C7: FY2026 | D7: 6 mo.-'26 | E7: Q2-'26 | F7: Q1-'26 | G7: FY2025 | H7: 6 mo.-'25 | I7: 6mo.-'24 | J7: FY2024 | K7: FY2023 | L7: FY2022 | M7: FY2021 | N7: FY2020
B8: Net Revenue | C8: =D8*2 -> 9551380 | D8: ='1-T5Y IS'!C12 -> 4775690 | E8: =D8-F8 -> 2366008 | F8: ='1-T5Y IS'!G12 -> 2409682 | G8: ='1-T5Y IS'!I12 -> 9006049 | H8: ='1-T5Y IS'!J12 -> 4478641 | I8: ='1-T5Y IS'!K12 -> 4537159 | J8: ='1-T5Y IS'!L12 -> 9351166 | K8: ='1-T5Y IS'!M12 -> 11127105 | L8: ='1-T5Y IS'!N12 -> 11681336 | M8: ='1-T5Y IS'!O12 -> 10246051 | N8: ='1-T5Y IS'!P12 -> 9810201
B9: Gross Margin $ | C9: =D9*2 -> 2071770 | D9: ='1-T5Y IS'!C68 -> 1035885 | E9: =D9-F9 -> 377548.8 | F9: ='1-T5Y IS'!G68 -> 658336.2 | G9: ='1-T5Y IS'!I68 -> 1693360 | H9: ='1-T5Y IS'!J68 -> 861558 | I9: ='1-T5Y IS'!K68 -> 699544.6 | J9: ='1-T5Y IS'!L68 -> 1369004.4 | K9: ='1-T5Y IS'!M68 -> 1716019.4 | L9: ='1-T5Y IS'!N68 -> 1934944 | M9: ='1-T5Y IS'!O68 -> 1429017.2 | N9: ='1-T5Y IS'!P68 -> 1013411.8
B10: Gross Margin % | C10: =C9/C8 -> 0.21690792 | D10: ='1-T5Y IS'!C69 -> 0.21690792 | E10: =E9/E8 -> 0.15957207 | F10: ='1-T5Y IS'!G69 -> 0.2732046 | G10: ='1-T5Y IS'!I69 -> 0.18802474 | H10: ='1-T5Y IS'!J69 -> 0.19237041 | I10: ='1-T5Y IS'!K69 -> 0.1541812 | J10: ='1-T5Y IS'!L69 -> 0.14639933 | K10: ='1-T5Y IS'!M69 -> 0.15421975 | L10: ='1-T5Y IS'!N69 -> 0.16564407 | M10: ='1-T5Y IS'!O69 -> 0.13947005 | N10: ='1-T5Y IS'!P69 -> 0.10330184
B11: Net Income (Loss) | C11: =D11*2 -> 935656 | D11: ='2-T5Y IS (Cont.)'!C70 -> 467828 | E11: =D11-F11 -> 192988 | F11: ='2-T5Y IS (Cont.)'!G70 -> 274840 | G11: ='2-T5Y IS (Cont.)'!I70 -> 122299 | H11: ='2-T5Y IS (Cont.)'!J70 -> 138098 | I11: ='2-T5Y IS (Cont.)'!K70 -> -62638 | J11: ='2-T5Y IS (Cont.)'!L70 -> -149387 | K11: ='2-T5Y IS (Cont.)'!M70 -> 99772 | L11: ='2-T5Y IS (Cont.)'!N70 -> 1214423 | M11: ='2-T5Y IS (Cont.)'!O70 -> 2288208 | N11: ='2-T5Y IS (Cont.)'!P70 -> 84468
B13: Add back Interest Expense | C13: =D13*2 -> 3570 | D13: =-'2-T5Y IS (Cont.)'!C61 -> 1785 | E13: =D13-F13 -> -5287 | F13: =-'2-T5Y IS (Cont.)'!G61 -> 7072 | G13: =-'2-T5Y IS (Cont.)'!I61 -> 15331 | H13: =-'2-T5Y IS (Cont.)'!J61 -> 9887 | I13: =-'2-T5Y IS (Cont.)'!K61 -> 9669 | J13: =-'2-T5Y IS (Cont.)'!L61 -> 19142 | K13: =-'2-T5Y IS (Cont.)'!M61 -> 22060 | L13: =-'2-T5Y IS (Cont.)'!N61 -> 121245 | M13: =-'2-T5Y IS (Cont.)'!O61 -> 88472 | N13: =-'2-T5Y IS (Cont.)'!P61 -> 137472
B14: Add back Income Taxes | E14: =D14-F14 -> 0 | J14: 0 | K14: 0 | L14: 1 | M14: 2 | N14: 3
B15: Add back Depreciation | C15: =D15*2 -> 213176 | D15: ='2-T5Y IS (Cont.)'!C33+'1-T5Y IS'!C54 -> 106588 | E15: =D15-F15 -> 53295 | F15: ='2-T5Y IS (Cont.)'!G33+'1-T5Y IS'!G54 -> 53293 | G15: ='2-T5Y IS (Cont.)'!I33+'1-T5Y IS'!I54+'2-T5Y IS (Cont.)'!I34 -> 235573 | H15: ='2-T5Y IS (Cont.)'!J33+'1-T5Y IS'!J54+'2-T5Y IS (Cont.)'!J34 -> 116113 | I15: ='2-T5Y IS (Cont.)'!K33+'1-T5Y IS'!K54+'2-T5Y IS (Cont.)'!K34 -> 115715 | J15: ='2-T5Y IS (Cont.)'!L33+'1-T5Y IS'!L54+'2-T5Y IS (Cont.)'!L34 -> 243966 | K15: ='2-T5Y IS (Cont.)'!M33+'1-T5Y IS'!M54+'2-T5Y IS (Cont.)'!M34 -> 254968 | L15: ='2-T5Y IS (Cont.)'!N33 -> 59433 | M15: ='2-T5Y IS (Cont.)'!O33 -> 59486 | N15: ='2-T5Y IS (Cont.)'!P33 -> 59449
B16: Less Depreciation of Building | C16: 0 | D16: 0 | E16: =D16-F16 -> 0 | F16: 0 | G16: 0 | H16: 0 | I16: 0 | J16: 0 | K16: 0 | L16: 0 | M16: 0 | N16: 0
B17: Estimated Fair Market Rent | C17: 0 | D17: 0 | E17: =D17-F17 -> 0 | F17: 0 | G17: 0 | H17: 0 | I17: 0 | J17: 0 | K17: 0 | L17: 0 | M17: 0 | N17: 0
B18: Add back Bank Charges② | C18: =D18*2 -> 35768 | D18: ='2024&2023'!C119 -> 17884 | E18: =D18-F18 -> 8866 | F18: ='2024&2023'!D119 -> 9018 | G18: ='2024&2023'!E119 -> 0 | H18: ='2024&2023'!F119 -> 13390 | I18: ='2024&2023'!G119 -> 15941 | J18: 0 | K18: 0 | L18: 0 | M18: 0 | N18: 0
B19: Add back Bad Debt③ | C19: 0 | D19: =-'2-T5Y IS (Cont.)'!C63 -> 0 | E19: =D19-F19 -> 0 | F19: =-'2-T5Y IS (Cont.)'!G63 -> 0 | G19: =-'2-T5Y IS (Cont.)'!I63 -> 0 | H19: =-'2-T5Y IS (Cont.)'!J63 -> -576 | I19: =-'2-T5Y IS (Cont.)'!K63 -> 0 | J19: 45648 | K19: 0 | L19: 0 | M19: 0 | N19: 0
B20: Deduct Gain on Sale of Assets | C20: 0 | D20: =-'2-T5Y IS (Cont.)'!C62 -> 0 | E20: =D20-F20 -> 0 | F20: =-'2-T5Y IS (Cont.)'!G62 -> 0 | G20: =-'2-T5Y IS (Cont.)'!I62 -> 0 | H20: =-'2-T5Y IS (Cont.)'!J62 -> 0 | I20: =-'2-T5Y IS (Cont.)'!K62 -> -2666 | J20: =-'2-T5Y IS (Cont.)'!L62 -> -2667 | K20: =-'2-T5Y IS (Cont.)'!M62 -> 0 | L20: =-'2-T5Y IS (Cont.)'!N62 -> 0 | M20: =-'2-T5Y IS (Cont.)'!O62 -> -1500 | N20: =-'2-T5Y IS (Cont.)'!P62 -> 0
B21: Deduct ERC Funds | D21: =-'2-T5Y IS (Cont.)'!C65 -> 0 | E21: =D21-F21 -> 0 | F21: =-'2-T5Y IS (Cont.)'!G65 -> 0 | G21: =-'2-T5Y IS (Cont.)'!I65 -> 0 | H21: =-'2-T5Y IS (Cont.)'!J65 -> 0 | I21: =-'2-T5Y IS (Cont.)'!K65 -> 0 | J21: =-'2-T5Y IS (Cont.)'!L65 -> 0 | K21: =-'2-T5Y IS (Cont.)'!M65 -> 0 | L21: =-'2-T5Y IS (Cont.)'!N65 -> 0 | M21: =-'2-T5Y IS (Cont.)'!O65 -> -1352277 | N21: =-'2-T5Y IS (Cont.)'!P65 -> 0
B22: Deduct PPP Loan Funds | D22: =-'2-T5Y IS (Cont.)'!C67 -> 0 | E22: =D22-F22 -> 0 | F22: =-'2-T5Y IS (Cont.)'!G67 -> 0 | G22: =-'2-T5Y IS (Cont.)'!I67 -> 0 | H22: =-'2-T5Y IS (Cont.)'!J67 -> 0 | I22: =-'2-T5Y IS (Cont.)'!K67 -> 0 | J22: =-'2-T5Y IS (Cont.)'!L67 -> 0 | K22: =-'2-T5Y IS (Cont.)'!M67 -> 0 | L22: =-'2-T5Y IS (Cont.)'!N67 -> -688137 | M22: =-'2-T5Y IS (Cont.)'!O67 -> -862310 | N22: =-'2-T5Y IS (Cont.)'!P67 -> 0
B23: Deduct Purchase Discounts | D23: =-'2-T5Y IS (Cont.)'!C60 -> 0 | E23: =D23-F23 -> 0 | F23: =-'2-T5Y IS (Cont.)'!G60 -> 0 | G23: =-'2-T5Y IS (Cont.)'!I60 -> 0 | H23: =-'2-T5Y IS (Cont.)'!J60 -> 0 | I23: =-'2-T5Y IS (Cont.)'!K60 -> 0 | J23: =-'2-T5Y IS (Cont.)'!L60 -> 0 | K23: =-'2-T5Y IS (Cont.)'!M60 -> 0 | L23: =-'2-T5Y IS (Cont.)'!N60 -> -108616 | M23: =-'2-T5Y IS (Cont.)'!O60 -> -100887 | N23: =-'2-T5Y IS (Cont.)'!P60 -> -49024
B24: Deduct Other Income④ | D24: =-'2-T5Y IS (Cont.)'!C59 -> 0 | E24: =D24-F24 -> 0 | F24: =-'2-T5Y IS (Cont.)'!G59 -> 0 | G24: =-'2-T5Y IS (Cont.)'!I59 -> 0 | H24: =-'2-T5Y IS (Cont.)'!J59 -> 0 | I24: =-'2-T5Y IS (Cont.)'!K59 -> 0 | J24: =-'2-T5Y IS (Cont.)'!L59 -> 0 | K24: =-'2-T5Y IS (Cont.)'!M59 -> 0 | L24: =-'2-T5Y IS (Cont.)'!N59 -> -388325 | M24: =-'2-T5Y IS (Cont.)'!O59 -> -279481 | N24: =-'2-T5Y IS (Cont.)'!P59 -> -591937
B25: Deduct Debt Forgiveness | C25: =D25 -> -133786 | D25: =-'2-T5Y IS (Cont.)'!C66 -> -133786 | E25: =D25-F25 -> -133786 | F25: =-'2-T5Y IS (Cont.)'!G66 -> 0 | G25: =-'2-T5Y IS (Cont.)'!I66 -> 0 | H25: =-'2-T5Y IS (Cont.)'!J66 -> 0 | I25: =-'2-T5Y IS (Cont.)'!K66 -> 0 | J25: =-'2-T5Y IS (Cont.)'!L66 -> 0 | K25: =-'2-T5Y IS (Cont.)'!M66 -> 0
B26: Add back Est. Owners' Perqs | C26: 0 | E26: =D26-F26 -> 0 | H26: 0 | I26: 0 | J26: 0 | K26: 0 | L26: 0 | M26: 0 | N26: 0
B27: ① "Adjusted" EBITDA $ | C27: =SUM(C11:C26) -> 1054384 | D27: =SUM(D11:D26) -> 460299 | E27: =SUM(E11:E26) -> 116076 | F27: =SUM(F11:F26) -> 344223 | G27: =SUM(G11:G26) -> 373203 | H27: =SUM(H11:H26) -> 276912 | I27: =SUM(I11:I26) -> 76021 | J27: =SUM(J11:J26) -> 156702 | ... N27: =SUM(N11:N26) -> -359569
B28: ① "Adjusted" EBITDA % | C28: =IFERROR(C27/C8,"") -> 0.11039075 | D28: =IFERROR(D27/D8,"") -> 0.096383769 | E28: =IFERROR(E27/E8,"") -> 0.049059851 | F28: =IFERROR(F27/F8,"") -> 0.14284997 | G28: =IFERROR(G27/G8,"") -> 0.041439148 | H28: =IFERROR(H27/H8,"") -> 0.06182947 | I28: =IFERROR(I27/I8,"") -> 0.016755199 | J28: =IFERROR(J27/J8,"") -> 0.016757482 | ... N28: =IFERROR(N27/N8,"") -> -0.036652562
B29: ① Pretax Income (Earnings) less Interest, Taxes, Depreciation/Amortization & "unusual" Expenses
B30: ②The internals separate bank charges from payroll charges. The Reviews do not.
B31: ③A large customer filed bankruptcy in 2024. Rare event.
B32: ④Straight-line extrapolation based on 6-mo'-FY'26 figures.

Sheet 5-Working Cap
B1: HCF's Working Capital Computation
C4: 3-mo'-FY'26 | D4: FY2025 | E4: 6-mo'-FY'25 | F4: 6-mo'-FY'24 | G4: FY2024 | H4: FY2023 | I4: FY2022 | J4: FY2021 | K4: FY2020
B5: CASH* | C5: ='3-Balance Sheet'!D9+'3-Balance Sheet'!D11 -> 543005 | D5: ='3-Balance Sheet'!E9+'3-Balance Sheet'!E11 -> 567253 | E5: ='3-Balance Sheet'!F9+'3-Balance Sheet'!F11 -> 739103 | F5: ='3-Balance Sheet'!H9+'3-Balance Sheet'!H11 -> 641003 | G5: ='3-Balance Sheet'!G9+'3-Balance Sheet'!G11 -> 586933 | H5: ='3-Balance Sheet'!I9+'3-Balance Sheet'!I11 -> 519446 | I5: ='3-Balance Sheet'!J9+'3-Balance Sheet'!J11 -> 113938 | J5: ='3-Balance Sheet'!K9+'3-Balance Sheet'!K11 -> 49473 | K5: ='3-Balance Sheet'!L9+'3-Balance Sheet'!L11 -> 175518
B7: A/R | C7: ='3-Balance Sheet'!D13 -> 1010922 | D7: ='3-Balance Sheet'!E13 -> 674696 | E7: ='3-Balance Sheet'!F13 -> 624234 | F7: ='3-Balance Sheet'!H13 -> 739879 | G7: ='3-Balance Sheet'!G13 -> 600833 | H7: ='3-Balance Sheet'!I13 -> 825739 | I7: ='3-Balance Sheet'!J13 -> 1162502 | J7: ='3-Balance Sheet'!K13 -> 1033535 | K7: ='3-Balance Sheet'!L13 -> 838596
B8: INV | C8: ='3-Balance Sheet'!D22 -> 1202624 | D8: ='3-Balance Sheet'!E22 -> 1239901 | E8: ='3-Balance Sheet'!F22 -> 1050542 | F8: ='3-Balance Sheet'!H22 -> 909413 | G8: ='3-Balance Sheet'!G22 -> 1021535 | H8: ='3-Balance Sheet'!I22 -> 1051427 | I8: ='3-Balance Sheet'!J22 -> 1733922 | J8: ='3-Balance Sheet'!K22 -> 1107863 | K8: ='3-Balance Sheet'!L22 -> 632835
B9: A/P | C9: ='3-Balance Sheet'!D58 -> 413053 | D9: ='3-Balance Sheet'!E58 -> 451708 | E9: ='3-Balance Sheet'!F58 -> 219210 | F9: ='3-Balance Sheet'!H58 -> 230561 | G9: ='3-Balance Sheet'!G58 -> 281913 | H9: ='3-Balance Sheet'!I58 -> 284395 | I9: ='3-Balance Sheet'!J58 -> 1181015 | J9: ='3-Balance Sheet'!K58 -> 642630 | K9: ='3-Balance Sheet'!L58 -> 758243
B10: Net | C10: =C7+C8-C9 -> 1800493 | D10: =D7+D8-D9 -> 1462889 | E10: =E7+E8-E9 -> 1455566 | F10: =F7+F8-F9 -> 1418731 | G10: =G7+G8-G9 -> 1340455 | H10: =H7+H8-H9 -> 1592771 | I10: =I7+I8-I9 -> 1715409 | J10: =J7+J8-J9 -> 1498768 | K10: =K7+K8-K9 -> 713188
B11: *Includes $300k in Certificates of Deposit for FY2024 and $313k for FY2025.

Sheet 5-Core NWC of HCF
B2: Financial Information | C2: Highland Computer Forms, Inc.
B3: Date: 7/15/2026 | C3: Hillsboro, Ohio "S"-Corp
C4: Fiscal Year Ends December 31st
C6: Average | D6: Internal | E6: Internal | F6: Internal | G6: Internal | H6: Review | I6: Internal | J6: Review | K6: Internal | L6: Review | M6: Review | N6: Review | O6: Review
C7: Trailing ? | D7: June-'26 | E7: May-'26 | F7: Apr-'26 | G7: Mar-'26 | H7: Dec-'25 | I7: 45838 | J7: Dec-'24 | K7: 45473 | L7: Dec-'23 | M7: Dec-'22 | N7: Dec-'21 | O7: Dec-'20
B8: Working Capital Computation
B10: CASH | D10: =SUM('3-Balance Sheet'!C9:C11) -> 739924 | E10: 0 | F10: 0 | G10: =SUM('3-Balance Sheet'!D9:D11) -> 543005 | H10: =SUM('3-Balance Sheet'!E9:E11) -> 638976 | I10: =SUM('3-Balance Sheet'!F9:F11) -> 739103 | J10: =SUM('3-Balance Sheet'!G9:G11) -> 608732 | K10: =SUM('3-Balance Sheet'!H9:H11) -> 641003 | L10: =SUM('3-Balance Sheet'!I9:I11) -> 606665 | M10: ='3-Balance Sheet'!J9+'3-Balance Sheet'!J11 -> 113938 | N10: ='3-Balance Sheet'!K9+'3-Balance Sheet'!K11 -> 49473 | O10: ='3-Balance Sheet'!L9+'3-Balance Sheet'!L11 -> 175518
B12: Current Assets
B13: Accounts Receivable - Trade | D13: =SUM('3-Balance Sheet'!C13:C15) -> 779487 | E13: 0 | F13: 0 | G13: =SUM('3-Balance Sheet'!D13:D15) -> 1010922 | H13: =SUM('3-Balance Sheet'!E13:E15) -> 688870 | I13: =SUM('3-Balance Sheet'!F13:F15) -> 624234 | J13: =SUM('3-Balance Sheet'!G13:G15) -> 608466 | K13: =SUM('3-Balance Sheet'!H13:H15) -> 739879 | L13: =SUM('3-Balance Sheet'!I13:I15) -> 917593 | M13: ='3-Balance Sheet'!J13 -> 1162502 | N13: ='3-Balance Sheet'!K13 -> 1033535 | O13: ='3-Balance Sheet'!L13 -> 838596
B14: Inventory | D14: =SUM('3-Balance Sheet'!C22:C23) -> 1098507 | E14: 0 | F14: 0 | G14: =SUM('3-Balance Sheet'!D22:D23) -> 1202624 | H14: =SUM('3-Balance Sheet'!E22:E23) -> 1239901 | I14: =SUM('3-Balance Sheet'!F22:F23) -> 1050542 | J14: =SUM('3-Balance Sheet'!G22:G23) -> 1021535 | K14: =SUM('3-Balance Sheet'!H22:H23) -> 909413 | L14: =SUM('3-Balance Sheet'!I22:I23) -> 1096561 | M14: ='3-Balance Sheet'!J22 -> 1733922 | N14: ='3-Balance Sheet'!K22 -> 1107863 | O14: ='3-Balance Sheet'!L22 -> 632835
B15: Total Current Asset Components of Working Capital | D15: =SUM(D13:D14) -> 1877994 | E15: =SUM(E13:E14) -> 0 | F15: =SUM(F13:F14) -> 0 | G15: =SUM(G13:G14) -> 2213546 | H15: =SUM(H13:H14) -> 1928771 | I15: =SUM(I13:I14) -> 1674776 | J15: =SUM(J13:J14) -> 1630001 | K15: =SUM(K13:K14) -> 1649292 | ... O15: =SUM(O13:O14) -> 1471431
B17: Current Liabilities
B18: Accounts Payable - Trade | D18: =SUM('3-Balance Sheet'!C58:C60) -> 310086 | E18: 0 | F18: 0 | G18: =SUM('3-Balance Sheet'!D58:D60) -> 413053 | H18: =SUM('3-Balance Sheet'!E58:E60) -> 451708 | I18: =SUM('3-Balance Sheet'!F58:F60) -> 219210 | J18: =SUM('3-Balance Sheet'!G58:G60) -> 281913 | K18: =SUM('3-Balance Sheet'!H58:H60) -> 230561 | L18: =SUM('3-Balance Sheet'!I58:I60) -> 284395 | M18: ='3-Balance Sheet'!J58 -> 1181015 | N18: ='3-Balance Sheet'!K58 -> 642630 | O18: ='3-Balance Sheet'!L58 -> 758243
B19: Total Current Liability Components of Working Capital | D19: =SUM(D18) -> 310086 | E19: =SUM(E18) -> 0 | F19: =SUM(F18) -> 0 | G19: =SUM(G18) -> 413053 | H19: =SUM(H18) -> 451708 | I19: =SUM(I18) -> 219210 | J19: =SUM(J18) -> 281913 | K19: =SUM(K18) -> 230561 | ... O19: =SUM(O18) -> 758243
B21: Net Working Capital (sans Cash) | D21: =D15-D19 -> 1567908 | E21: =E15-E19 -> 0 | F21: =F15-F19 -> 0 | G21: =G15-G19 -> 1800493 | H21: =H15-H19 -> 1477063 | I21: =I15-I19 -> 1455566 | J21: =J15-J19 -> 1348088 | K21: =K15-K19 -> 1418731 | ... O21: =O15-O19 -> 713188
B22: Average Ratio of "Core" NWC (sans Cash)® | D22: =IFERROR(D15/D19,"") -> 6.056365 | E22: =IFERROR(E15/E19,"") | F22: =IFERROR(F15/F19,"") | G22: =IFERROR(G15/G19,"") -> 5.3589878 | H22: =H15/H19 -> 4.2699509 | I22: =I15/I19 -> 7.6400529 | J22: =J15/J19 -> 5.7819292 | K22: =K15/K19 -> 7.1533867 | L22: =L15/L19 -> 7.0822412 | M22: =M15/M19 -> 2.4524871 | N22: =N15/N19 -> 3.3322409 | O22: =O15/O19 -> 1.9405797
C23: Trailing ? | D23: =D7 -> June-'26 | E23: =E7 -> May-'26 | F23: =F7 -> Apr-'26 | G23: =G7 -> Mar-'26 | H23: =H7 -> Dec-'25 | I23: 45838 | J23: =J7 -> Dec-'24 | K23: =K7 -> 45473 | L23: =L7 -> Dec-'23 | M23: June-'24 | N23: Mar-'24 | O23: Dec-'23
C24: Average

Sheet Mfg. Costs
B2: FY2024 | C2: Total | D2: Hillsboro #1 | E2: Hillsboro #2 | F2: Angola | G2: ALLOCATED | H2: Agg | O2: 1271667 | Q2: 601238
Q3: 475329
B4: COGS - Manufactured | Q4: 148011
Q5: =SUM(Q2:Q4) -> 1224578 | R5: =O2-Q5 -> 47089
B6: Direct Materials
A7: Materials | B7: Paper | C7: =SUM(D7:F7) -> 3635090 | D7: 1914909 | E7: -382 | F7: 1720563 | H7: =SUM(D7:F7) -> 3635090 | O7: 4651591 | P7: 4592992
A8: Materials | B8: Carbon | C8: =SUM(D8:F8) -> 6960 | D8: 5661 | E8: 0 | F8: 1299 | H8: =SUM(D8:F8) -> 6960 | O8: 4050352 | P8: 59870
A9: Materials | B9: Cartons | C9: =SUM(D9:F9) -> 180668 | D9: 95916 | F9: 84752 | H9: =SUM(D9:F9) -> 180668 | O9: =O7-O8 -> 601239 | P9: =SUM(P7:P8) -> 4652862 | Q9: =O7-P9 -> -1271
A10: Materials | B10: Ink | C10: =SUM(D10:F10) -> 94917 | D10: 76717 | E10: 1873 | F10: 16327 | H10: =SUM(D10:F10) -> 94917
A11: Materials | B11: Materials + Supplies | C11: =SUM(D11:F11) -> 206347 | D11: 138195 | E11: 4832 | F11: 63320 | H11: =SUM(D11:F11) -> 206347 | R11: 530396
A12: Materials | B12: Label Material | C12: =SUM(D12:F12) -> 121477 | E12: 0 | F12: 121477 | H12: =SUM(D12:F12) -> 121477 | O12: 4076396 | R12: 320852
A13: Materials | B13: Integrated Material | C13: =SUM(D13:F13) -> 69426 | D13: 69426 | E13: 0 | F13: 0 | H13: =SUM(D13:F13) -> 69426 | O13: 3347128 | R13: 136816
A14: Plant Overhead | B14: Plates + Comp Charges | C14: =SUM(D14:F14) -> 134079 | D14: 105961 | E14: 0 | F14: 28118 | H14: =SUM(D14:F14) -> 134079 | O14: 389727 | R14: =SUM(R11:R13) -> 988064
B15: Total Direct Materials | C15: =SUM(D15:F15) -> 4448964 | D15: =SUM(D7:D14) -> 2406785 | E15: =SUM(E7:E14) -> 6323 | F15: =SUM(F7:F14) -> 2035856 | H15: =SUM(D15:F15) -> 4448964 | O15: 172398 | R15: -34148
O16: -59870 | R16: =R14+R15 -> 953916
B17: Labor | O17: -54667 | P17: 537739 | R17: -1110653
A18: Labor | B18: Direct Labor Wages | C18: =SUM(D18:F18) -> 1171096 | D18: 723248 | E18: 139496 | F18: 308352 | H18: =SUM(D18:F18) -> 1171096 | O18: 276 | P18: -382 | R18: =SUM(R16:R17) -> -156737
A19: Labor | B19: Indirect Labor Wages | C19: =SUM(D19:F19) -> 638970 | D19: 236265 | E19: 82781 | F19: 319924 | H19: =SUM(D19:F19) -> 638970 | P19: =P17+P18 -> 537357
A20: Labor | B20: Supervisor's Salaries | C20: =SUM(D20:F20) -> -32017 | D20: 0 | E20: -32017 | F20: 0 | H20: =SUM(D20:F20) -> -32017 | O20: =SUM(O12:O18) -> 7871388
B21: Total Labor | C21: =SUM(D21:F21) -> 1778049 | D21: =SUM(D18:D20) -> 959513 | E21: =SUM(E18:E20) -> 190260 | F21: =SUM(F18:F20) -> 628276 | H21: =SUM(D21:F21) -> 1778049
O22: 7709431
B23: Factory Overhead | O23: =O22-O20 -> -161957 | Q23: 133332 | R23: 15954
A24: Plant Overhead | B24: Depreciation Equipment | C24: =SUM(D24:F24) -> 166470 | D24: 96101 | E24: 3757 | F24: 66612 | H24: =SUM(D24:F24) -> 166470 | Q24: 117147 | R24: 131716
A25: Plant Overhead | B25: Depreciation Trucks | C25: =SUM(D25:F25) -> 4385 | D25: 4385 | E25: 0 | F25: 0 | H25: =SUM(D25:F25) -> 4385 | O25: =-1-(O23/O20) -> -0.97942459 | Q25: 34059
A26: Labor | B26: Caretaking-Production | C26: =SUM(D26:F26) -> 29974 | D26: 19408 | E26: 3472 | F26: 7094 | H26: =SUM(D26:F26) -> 29974 | Q26: 15954
B27: Equipment Leasing | C27: =SUM(D27:F27) -> 0 | D27: 0 | E27: 0 | F27: 0 | H27: =SUM(D27:F27) -> 0 | Q27: 1011807
A28: Labor | B28: Insurance - Prod Health | C28: =SUM(D28:F28) -> 355893 | D28: 183496 | E28: 63575 | F28: 108822 | H28: =SUM(D28:F28) -> 355893
A29: Labor | B29: Taxes - Prod Payroll | C29: =SUM(D29:F29) -> 177233 | D29: 77804 | E29: 23956 | F29: 75473 | H29: =SUM(D29:F29) -> 177233
A30: Labor | B30: 401k Match - Prod | C30: =SUM(D30:F30) -> 44374 | D30: 15905 | E30: 11410 | F30: 17059 | H30: =SUM(D30:F30) -> 44374 | Q30: =SUM(Q23:Q29) -> 1312299
A31: Plant Overhead | B31: Insurance - General | C31: =SUM(D31:F31) -> 53729 | D31: 27996 | E31: 3167 | F31: 22566 | H31: =SUM(D31:F31) -> 53729
A32: Plant Overhead | B32: Taxes - General | C32: =SUM(D32:F32) -> 44005 | D32: 10274 | E32: 6807 | F32: 26924 | H32: =SUM(D32:F32) -> 44005 | Q32: 1405438
A33: Plant Overhead | B33: Training & Education | C33: =SUM(D33:F33) -> 315 | D33: 315 | E33: 0 | F33: 0 | H33: =SUM(D33:F33) -> 315 | Q33: =Q32-Q30 -> 93139
A34: Plant Overhead | B34: Rent | C34: =SUM(D34:F34) -> 126000 | D34: 0 | E34: 30000 | F34: 96000 | H34: =SUM(D34:F34) -> 126000
A35: Plant Overhead | B35: Repairs + Maintenance | C35: =SUM(D35:F35) -> 137971 | D35: 67316 | E35: 22352 | F35: 48303 | H35: =SUM(D35:F35) -> 137971 | Q35: =Q33/Q32 -> 0.066270444
A36: Plant Overhead | B36: Truck Expenses | C36: =SUM(D36:F36) -> 2960 | D36: 2960 | E36: 0 | F36: 0 | H36: =SUM(D36:F36) -> 2960
A37: Plant Overhead | B37: Utilities | C37: =SUM(D37:F37) -> 238879 | D37: 110041 | E37: 24643 | F37: 104195 | H37: =SUM(D37:F37) -> 238879
A38: Freight | B38: Freight in Price Expenses | C38: =SUM(D38:F38) -> 83397 | D38: 68402 | E38: 0 | F38: 14995 | H38: =SUM(D38:F38) -> 83397
B39: Total Factory Overhead | C39: =SUM(D39:F39) -> 1465585 | D39: =SUM(D24:D38) -> 684403 | E39: =SUM(E24:E38) -> 193139 | F39: =SUM(F24:F38) -> 588043 | H39: =SUM(D39:F39) -> 1465585
B41: Total Mfg Cost | C41: =SUM(D41:F41) -> 7692598 | D41: =D15+D21+D39 -> 4050701 | E41: =E15+E21+E39 -> 389722 | F41: =F15+F21+F39 -> 3252175 | G41: 172398 | H41: =SUM(D41:F41) -> 7692598
B43: PRODUCTION | C43: =SUM(D43:F43) -> 8916843 | D43: 4651591 | E43: 537739 | F43: 3727513 | H43: =SUM(D43:F43) -> 8916843
B45: Gross Margin (of Production Sales) | C45: =SUM(D45:F45) -> 1224245 | D45: =D43-D41 -> 600890 | E45: =E43-E41 -> 148017 | F45: =F43-F41 -> 475338 | H45: =SUM(D45:F45) -> 1224245
B47: Beg Inventories | C47: =SUM(D47:F47) -> 313472 | D47: 68571 | E47: 0 | F47: 244901 | H47: =SUM(D47:F47) -> 313472
B48: Less Ending Inventories | C48: =SUM(D48:F48) -> 226313 | D48: 73583 | E48: 0 | F48: 152730 | H48: =SUM(D48:F48) -> 226313
B50: Total COGS | C50: =SUM(D50:G50) -> 7985649 | D50: 4076396 | E50: 389727 | F50: 3347128 | G50: =172398 -> 172398 | H50: =SUM(D50:G50) -> 7985649
B53: Variance (Math vs Internals)
D56: 4050352 | E56: 389727 | F56: 3252184
D57: =D56-D41 -> -349 | E57: =E56-E41 -> 5 | F57: =F56-F41 -> 9

Sheet P&L Assistant
C4: Total | D4: Hillsboro #1 | E4: Hillsboro #2 | F4: Angola | G4: Total
B5: Sales | C5: =SUM(D5:F5) -> 9008622 | D5: 4669840 | E5: 537398 | F5: 3801384 | G5: =SUM(D5:F5) -> 9008622
B6: Freight Charged to Customer | C6: =SUM(D6:F6) -> 673988 | D6: 339450 | E6: 0 | F6: 334538 | G6: =SUM(D6:F6) -> 673988 | I6: =-F6 -> -334538
B7: Less Sales Discount | C7: =SUM(D7:F7) -> -153544 | D7: -76847 | E7: 0 | F7: -76697 | G7: =SUM(D7:F7) -> -153544
B8: Net Sales | C8: =SUM(D8:F8) -> 9529066 | D8: =SUM(D5:D7) -> 4932443 | E8: =SUM(E5:E7) -> 537398 | F8: =SUM(F5:F7) -> 4059225 | G8: =SUM(D8:F8) -> 9529066
B10: Cost of Goods Sold
B12: Beginning Inventory | C12: =SUM(D12:F12) -> 313472 | D12: ='Mfg. Costs'!D47 -> 68571 | E12: ='Mfg. Costs'!E47 -> 0 | F12: ='Mfg. Costs'!F47 -> 244901 | G12: =SUM(D12:F12) -> 313472
B13: Beginning Inventory (Correction to Review)
B15: Paper | C15: =SUM(D15:F15) -> 3635090 | D15: ='Mfg. Costs'!D7 -> 1914909 | E15: ='Mfg. Costs'!E7 -> -382 | F15: ='Mfg. Costs'!F7 -> 1720563 | G15: =SUM(D15:F15) -> 3635090 | I15: Total COGs | J15: =SUM(D44:F44) -> 7692598
B16: Carbon & Cartons | C16: =SUM(D16:F16) -> 187628 | D16: ='Mfg. Costs'!D8+'Mfg. Costs'!D9 -> 101577 | E16: ='Mfg. Costs'!E8+'Mfg. Costs'!E9 -> 0 | F16: ='Mfg. Costs'!F8+'Mfg. Costs'!F9 -> 86051 | G16: =SUM(D16:F16) -> 187628 | I16: Unallocated COGs | J16: 172398
B17: Ink | C17: =SUM(D17:F17) -> 94917 | D17: ='Mfg. Costs'!D10 -> 76717 | E17: ='Mfg. Costs'!E10 -> 1873 | F17: ='Mfg. Costs'!F10 -> 16327 | G17: =SUM(D17:F17) -> 94917 | I17: Grand Total | J17: =SUM(J15:J16) -> 7864996
B18: Materials + Supplies | C18: =SUM(D18:F18) -> 206347 | D18: ='Mfg. Costs'!D11 -> 138195 | E18: ='Mfg. Costs'!E11 -> 4832 | F18: ='Mfg. Costs'!F11 -> 63320 | G18: =SUM(D18:F18) -> 206347
B19: Label Material | C19: =SUM(D19:F19) -> 121477 | D19: ='Mfg. Costs'!D12 -> 0 | E19: ='Mfg. Costs'!E12 -> 0 | F19: ='Mfg. Costs'!F12 -> 121477 | G19: =SUM(D19:F19) -> 121477
B20: Integrated Material | C20: =SUM(D20:F20) -> 69426 | D20: ='Mfg. Costs'!D13 -> 69426 | E20: ='Mfg. Costs'!E13 -> 0 | F20: ='Mfg. Costs'!F13 -> 0 | G20: =SUM(D20:F20) -> 69426 | I20: Mfg. Cost Portion % - H1 | J20: =D44/J15 -> 0.52657126
B21: Envelopes | C21: =SUM(D21:F21) -> 31055 | D21: 31055 | E21: 0 | F21: 0 | G21: =SUM(D21:F21) -> 31055 | I21: Mfg. Cost Portion % - H2 | J21: =E44/J15 -> 0.050661948
B22: Copy Paper | C22: =SUM(D22:F22) -> 2773 | D22: 0 | E22: 0 | F22: 2773 | G22: =SUM(D22:F22) -> 2773 | I22: Mfg. Cost Portion % - A | J22: =F44/J15 -> 0.42276679
B23: Sub-Total Materials | C23: =SUM(C15:C22) -> 4348713 | D23: =SUM(D15:D22) -> 2331879 | E23: =SUM(E15:E22) -> 6323 | F23: =SUM(F15:F22) -> 2010511 | G23: =SUM(D23:F23) -> 4348713
B25: Labor | I25: Unallocated G&A | J25: 1011807
B26: ='Mfg. Costs'!B18 -> Direct Labor Wages | C26: =SUM(D26:F26) -> 1171096 | D26: ='Mfg. Costs'!D18 -> 723248 | E26: ='Mfg. Costs'!E18 -> 139496 | F26: ='Mfg. Costs'!F18 -> 308352 | G26: =SUM(D26:F26) -> 1171096 | I26: Des Moines G&A | J26: =34059+88 -> 34147 | K26: <-Include $88 in Des Moines Freight (not a plant, definitely a G&A item).
B27: ='Mfg. Costs'!B19 -> Indirect Labor Wages | C27: =SUM(D27:F27) -> 638970 | D27: ='Mfg. Costs'!D19 -> 236265 | E27: ='Mfg. Costs'!E19 -> 82781 | F27: ='Mfg. Costs'!F19 -> 319924 | G27: =SUM(D27:F27) -> 638970 | I27: Unallocated Freight | J27: 276
B28: ='Mfg. Costs'!B29 -> Taxes - Prod Payroll | C28: =SUM(D28:F28) -> 177233 | D28: ='Mfg. Costs'!D29 -> 77804 | E28: ='Mfg. Costs'!E29 -> 23956 | F28: ='Mfg. Costs'!F29 -> 75473 | G28: =SUM(D28:F28) -> 177233
B29: ='Mfg. Costs'!B20 -> Supervisor's Salaries | C29: =SUM(D29:F29) -> -32017 | D29: ='Mfg. Costs'!D20 -> 0 | E29: ='Mfg. Costs'!E20 -> -32017 | F29: ='Mfg. Costs'!F20 -> 0 | G29: =SUM(D29:F29) -> -32017
B30: ='Mfg. Costs'!B26 -> Caretaking-Production | C30: =SUM(D30:F30) -> 29974 | D30: ='Mfg. Costs'!D26 -> 19408 | E30: ='Mfg. Costs'!E26 -> 3472 | F30: ='Mfg. Costs'!F26 -> 7094 | G30: =SUM(D30:F30) -> 29974 | I30: Hillsboro #1 Net Profit(loss) | J30: 530386
B31: Benefits (Health Ins. + 401k) | C31: =SUM(D31:F31) -> 400267 | D31: ='Mfg. Costs'!D28+'Mfg. Costs'!D30 -> 199401 | E31: ='Mfg. Costs'!E28+'Mfg. Costs'!E30 -> 74985 | F31: ='Mfg. Costs'!F28+'Mfg. Costs'!F30 -> 125881 | G31: =SUM(D31:F31) -> 400267 | I31: Hillsboro #2 Net Profit(loss) | J31: 136816
B32: Sub-Total Labor | C32: =SUM(C26:C31) -> 2385523 | D32: =SUM(D26:D31) -> 1256126 | E32: =SUM(E26:E31) -> 292673 | F32: =SUM(F26:F31) -> 836724 | G32: =SUM(D32:F32) -> 2385523 | I32: Angola Net Profit(loss) | J32: 320852
I33: Des moines Net Profit(loss) | J33: -34148
B34: Plant Overhead | I34: Allocated Net Profit(loss) | J34: -1110653
B35: Rent | C35: =SUM(D35:F35) -> 126000 | D35: ='Mfg. Costs'!D34 -> 0 | E35: ='Mfg. Costs'!E34 -> 30000 | F35: ='Mfg. Costs'!F34 -> 96000 | G35: =SUM(D35:F35) -> 126000 | I35: Total | J35: =SUM(J30:J34) -> -156747
B36: Utilities | C36: =SUM(D36:F36) -> 238879 | D36: ='Mfg. Costs'!D37 -> 110041 | E36: ='Mfg. Costs'!E37 -> 24643 | F36: ='Mfg. Costs'!F37 -> 104195 | G36: =SUM(D36:F36) -> 238879
B37: Depreciation | C37: =SUM(D37:F37) -> 170855 | D37: ='Mfg. Costs'!D24+'Mfg. Costs'!D25 -> 100486 | E37: ='Mfg. Costs'!E24+'Mfg. Costs'!E25 -> 3757 | F37: ='Mfg. Costs'!F24+'Mfg. Costs'!F25 -> 66612 | G37: =SUM(D37:F37) -> 170855
B38: Repairs & Maintenance | C38: =SUM(D38:F38) -> 137971 | D38: ='Mfg. Costs'!D35 -> 67316 | E38: ='Mfg. Costs'!E35 -> 22352 | F38: ='Mfg. Costs'!F35 -> 48303 | G38: =SUM(D38:F38) -> 137971
B39: Plates & Comp Charges | C39: =SUM(D39:F39) -> 134079 | D39: ='Mfg. Costs'!D14 -> 105961 | E39: ='Mfg. Costs'!E14 -> 0 | F39: ='Mfg. Costs'!F14 -> 28118 | G39: =SUM(D39:F39) -> 134079 | I39: Unallocated Misc. Income | J39: 27919
B40: Misc. Plant Overhead | C40: =SUM(D40:F40) -> 101009 | D40: ='Mfg. Costs'!D31+'Mfg. Costs'!D32+'Mfg. Costs'!D33+'Mfg. Costs'!D36 -> 41545 | E40: ='Mfg. Costs'!E31+'Mfg. Costs'!E32+'Mfg. Costs'!E33+'Mfg. Costs'!E36 -> 9974 | F40: ='Mfg. Costs'!F31+'Mfg. Costs'!F32+'Mfg. Costs'!F33+'Mfg. Costs'!F36 -> 49490 | G40: =SUM(D40:F40) -> 101009 | I40: Unallocated Interst Income | J40: 7
B41: Sub-Total Plant Overhead | C41: =SUM(C35:C40) -> 908793 | D41: =SUM(D35:D40) -> 425349 | E41: =SUM(E35:E40) -> 90726 | F41: =SUM(F35:F40) -> 392718 | G41: =SUM(D41:F41) -> 908793 | I41: Unallocated Interest Expense | J41: -19149
I42: Unallocated Loss of Sale of Property | J42: 2666
B43: Less Ending Inventory | C43: =SUM(D43:F43) -> -226313 | D43: =-'Mfg. Costs'!D48 -> -73583 | E43: =-'Mfg. Costs'!E48 -> 0 | F43: =-'Mfg. Costs'!F48 -> -152730 | G43: =SUM(D43:F43) -> -226313 | I43: Unallocated Purchase Discounts | J43: 62385
B44: Total COGs(per Internals) | C44: =SUM(D44:F44) -> 7692598 | D44: =SUM(D15:D20,D26:D31,D35:D40)+D46 -> 4050701 | E44: =SUM(E15:E20,E26:E31,E35:E40)+E46 -> 389722 | F44: =SUM(F15:F20,F26:F31,F35:F40)+F46 -> 3252175 | G44: =SUM(D44:F44) -> 7692598
B46: Freight In Price Expenses | C46: =SUM(D46:F46) -> 83397 | D46: ='Mfg. Costs'!D38 -> 68402 | E46: ='Mfg. Costs'!E38 -> 0 | F46: ='Mfg. Costs'!F38 -> 14995 | G46: =SUM(D46:F46) -> 83397 | I46: Beginning Inventories (review) | J46: 1051427
B47: Freight Expense | C47: =SUM(D47:F47) -> 540101 | D47: 268916 | E47: 0 | F47: 271185 | G47: =SUM(D47:F47) -> 540101 | I47: Ending Inventories (review) | J47: -1021535
B48: Intercompany Freight | C48: =SUM(D48:F48) -> 8812 | D48: 6256 | E48: 0 | F48: 2556 | G48: =SUM(D48:F48) -> 8812 | J48: =J46+J47 -> 29892
B49: Unreconciled Freight | C49: =SUM(D49:F49) -> 10536 | D49: 4407 | E49: 0 | F49: 6129 | G49: =SUM(D49:F49) -> 10536
B50: Unallocated Freight | C50: =SUM(D50:F50) -> 276 | D50: =J27*J20 -> 145.33367 | E50: =J27*J21 -> 13.982698 | F50: =J27*J22 -> 116.68364 | G50: =SUM(D50:F50) -> 276
B52: Total Freight | C52: =SUM(D52:F52) -> 643122 | D52: =SUM(D46:D50) -> 348126.33 | E52: =SUM(E46:E50) -> 13.982698 | F52: =SUM(F46:F50) -> 294981.68 | G52: =SUM(D52:F52) -> 643122
B54: Total COGs(per CDA) | C54: =SUM(C23,C32,C41,C12,C43,C52,C56) -> 8545708 | D54: =SUM(D23,D32,D41,D12,D43,D52,D56) -> 4447248.2 | E54: =SUM(E23,E32,E41,E12,E43,E52,E56) -> 398470 | F54: =SUM(F23,F32,F41,F12,F43,F52,F56) -> 3699989.8 | G54: =SUM(D54:F54) -> 8545708
B56: Unallocated COGs | C56: =SUM(D56:F56) -> 172398 | D56: =J20*J16 -> 90779.832 | E56: =J21*J16 -> 8734.0185 | F56: =J22*J16 -> 72884.15 | G56: =SUM(D56:F56) -> 172398
B58: G&A Expenses | C58: =SUM(D58:F58) -> 266433 | D58: 133332 | E58: 15954 | F58: 117147 | G58: =SUM(D58:F58) -> 266433
B59: Unallocated G&A Expenses | C59: =SUM(D59:F59) -> 1011807 | D59: =J20*J25 -> 532788.48 | E59: =J21*J25 -> 51260.114 | F59: =J22*J25 -> 427758.4 | G59: =SUM(D59:F59) -> 1011807
B60: Des Moines G&A Expenses | C60: =SUM(D60:F60) -> 34147 | D60: =J26*J20 -> 17980.829 | E60: =J21*J26 -> 1729.9535 | F60: =J22*J26 -> 14436.218 | G60: =SUM(D60:F60) -> 34147
B62: Gross Margin | C62: =C8-C54 -> 983358 | D62: =D8-D54 -> 485194.83 | E62: =E8-E54 -> 138928 | F62: =F8-F54 -> 359235.17 | G62: =SUM(D62:F62) -> 983358
C63: =C62/C8 -> 0.10319563 | D63: =D62/D8 -> 0.098368057 | E63: =E62/E8 -> 0.25851975 | F63: =F62/F8 -> 0.088498461 | G63: =G62/G8 -> 0.10319563
B65: Operating Profit | C65: =C62-C58-C59-C60 -> -329029 | D65: =D62-D58-D59-D60 -> -198906.48 | E65: =E62-E58-E59-E60 -> 69983.932 | F65: =F62-F58-F59-F60 -> -200106.45 | G65: =SUM(D65:F65) -> -329029
B67: Other Income
B68: Sale of Scrap | C68: =SUM(D68:F68) -> 98050 | D68: 87202 | E68: 5100 | F68: 5748 | G68: =SUM(D68:F68) -> 98050
B69: Misc. Income | C69: =SUM(D69:F69) -> 74 | D69: 50 | E69: 0 | F69: 24 | G69: =SUM(D69:F69) -> 74
B70: Interest Income | C70: =SUM(D70:F70) -> 0 | D70: 0 | E70: 0 | F70: 0 | G70: =SUM(D70:F70) -> 0
B71: Interest Expense | C71: =SUM(D71:F71) -> 0 | D71: 0 | E71: 0 | F71: 0 | G71: =SUM(D71:F71) -> 0
B72: Loss on sale of Property | C72: =SUM(D72:F72) -> 0 | D72: 0 | E72: 0 | F72: 0 | G72: =SUM(D72:F72) -> 0
B73: Purchase Discounts | C73: =SUM(D73:F73) -> 0 | D73: 0 | E73: 0 | F73: 0 | G73: =SUM(D73:F73) -> 0
B74: Unallocated Misc. Income | C74: =SUM(D74:F74) -> 27919 | D74: =J39*$J$20 -> 14701.343 | E74: =$J$21*J39 -> 1414.4309 | F74: =J39*$J$22 -> 11803.226 | G74: =SUM(D74:F74) -> 27919
B75: Unallocated Interst Income | C75: =SUM(D75:F75) -> 7 | D75: =J40*$J$20 -> 3.6859988 | E75: =$J$21*J40 -> 0.35463364 | F75: =J40*$J$22 -> 2.9593676 | G75: =SUM(D75:F75) -> 7
B76: Unallocated Interest Expense | C76: =SUM(D76:F76) -> -19149 | D76: =J41*$J$20 -> -10083.313 | E76: =$J$21*J41 -> -970.12564 | F76: =J41*$J$22 -> -8095.5614 | G76: =SUM(D76:F76) -> -19149
B77: Unallocated Loss of Sale of Property | C77: =SUM(D77:F77) -> 2666 | D77: =J42*$J$20 -> 1403.839 | E77: =$J$21*J42 -> 135.06475 | F77: =J42*$J$22 -> 1127.0963 | G77: =SUM(D77:F77) -> 2666
B78: Unallocated Purchase Discounts | C78: =SUM(D78:F78) -> 62385 | D78: =J43*$J$20 -> 32850.148 | E78: =$J$21*J43 -> 3160.5456 | F78: =J43*$J$22 -> 26374.306 | G78: =SUM(D78:F78) -> 62385
B79: Total Other Income | C79: =SUM(C68:C78) -> 171952 | D79: =SUM(D68:D78) -> 126127.7 | E79: =SUM(E68:E78) -> 8840.2703 | F79: =SUM(F68:F78) -> 36984.027 | G79: =SUM(D79:F79) -> 171952
B81: Total Other Income (no Unallocated) | C81: =SUM(C68:C73) -> 98124 | D81: =SUM(D68:D73) -> 87252 | E81: =SUM(E68:E73) -> 5100 | F81: =SUM(F68:F73) -> 5772 | G81: =SUM(D81:F81) -> 98124
B83: Net Profit | C83: =C65+C79 -> -157077 | D83: =D65+D79 -> -72778.775 | E83: =E65+E79 -> 78824.202 | F83: =F65+F79 -> -163122.43 | G83: =SUM(D83:F83) -> -157077
C86: =C83+335-5 -> -156747

Sheet 2024&2023
A1: asdfads | C1: 6 month 2026 | D1: 3 month 2026 | E1: 2025 | F1: 6 month 2025 | G1: 6 month 2024 | H1: 2024 | I1: 2023 | J1: 2022 | K1: 2021 | L1: 2020
B3: Sales, net (HFC Division) | C3: =4748363-53175 -> 4695188 | D3: =2401975-21997 -> 2379978 | E3: 8533432 | F3: 4406436 | G3: 4464702 | H3: 8855077 | I3: 10655460 | J3: 11681336 | K3: 10246051 | L3: 9810201
B4: Sales, net (G.Fordyce Div.) | C4: in Above Cell. | D4: in Above Cell. | E4: 347072 | H4: 370068 | I4: 264960
A5: Other Income | B5: Other Income | C5: =63892+16610 -> 80502 | D5: =27819+1885 -> 29704 | E5: 125545 | F5: =37848+34357 -> 72205 | G5: =51113+21344 -> 72457 | H5: 126021 | I5: 206685 | J5: 388325 | K5: 279481 | L5: 591937
A7: Materials | B7: Beginning Inventories (HCF) | C7: 203836 | D7: 203836 | E7: 1021535 | F7: 226313 | G7: 313473 | H7: 1051427 | I7: 1733922 | J7: 1107863 | K7: 683140 | L7: 683140
B8: Beginning Inventories (G. Fordyce) | H8: 45134
B9: Purchases & other Costs:
A10: Materials | B10: Paper | C10: 1555246 | D10: 775969 | E10: 3408695 | F10: 1725419 | G10: 1808752 | H10: 3692358 | I10: 3982914 | J10: 5780557 | K10: 4920814 | L10: 4390895
A11: Labor | B11: Production and Collator Wages (HCF) | C11: =686327 -> 686327 | D11: 336673 | E11: 964599 | F11: 550391 | G11: =583091 -> 583091 | H11: 965420 | I11: =1219010-136379 -> 1082631 | J11: 1144403 | K11: 1120001 | L11: 1091526
B12: Production and Collator Wages (G.Fordyce) | E12: 73530 | H12: 84107 | I12: 136379
A13: Labor | B13: Indirect Labor | C13: =288476+8746 -> 297222 | D13: =141835+3447 -> 145282 | E13: 486589 | F13: =314028+10502 -> 324530 | G13: =317594+16563 -> 334157 | H13: 523378 | I13: 608621 | J13: 594797 | K13: 563755 | L13: 573376
A14: labor | B14: Health Insurance | C14: =299280 -> 299280 | D14: 113791 | E14: 436125 | F14: 221909 | G14: =152082 -> 152082 | H14: 383282 | I14: 476537 | J14: 491729 | K14: 393068 | L14: 452009
A15: Materials | B15: Supplies (HCF) | C15: In Materials | D15: In Materials | E15: 308812 | F15: In Materials | G15: In Materials | H15: 327826 | I15: =331999-2177 -> 329822 | J15: 381473 | K15: 359935 | L15: 309092
A16: Materials | B16: Supplies (G. Fordyce) | C16: In Materials | D16: In Materials | E16: 4947 | H16: 463 | I16: 2177
A17: Materials | B17: Buyouts and Outside Purchases (HCF) | C17: 0 | D17: 0 | E17: 48537 | F17: 516 | G17: 0 | H17: 69427 | I17: =257467-166233 -> 91234 | J17: 104261 | K17: 112637 | L17: 163690
A18: Materials | B18: Buyouts and Outside Purchases (G. Fordyce) | C18: 0 | D18: 0 | E18: 186902 | H18: 207091 | I18: 166233
A19: Labor | B19: Supervisors' Salaries (HCF) | C19: 7443 | D19: -8721 | E19: 297193 | F19: 4379 | G19: =42516 -> 42516 | H19: 268102 | I19: =280397 -> 280397 | J19: 229257 | K19: 198693 | L19: 209196
B20: Supervisors' Salaries (G. Fordyce) | H20: 980
A21: Plant Overhead | B21: Utilities | C21: 157105 | D21: =_xlfn.XLOOKUP(B21,'[1]G&A Expenses'!$A:$A,'[1]G&A Expenses'!$D:$D,_xlfn.XLOOKUP(B21,'[1]COGS Manufactured'!$A:$A,'[1]COGS Manufactured'!$D:$D)) -> 80786 | E21: 289868 | F21: 133260 | G21: =108798 -> 108798 | H21: 238882 | I21: 258091 | J21: 263388 | K21: 253327 | L21: 243799
A22: Labor | B22: Payroll Taxes | C22: 95499 | D22: 53186 | E22: 200715 | F22: 96885 | G22: =101738 -> 101738 | H22: 200385 | I22: 232730 | J22: 238780 | K22: 198502 | L22: 179936
A23: Materials | B23: Cartons | C23: 76707 | D23: =_xlfn.XLOOKUP(B23,'[1]G&A Expenses'!$A:$A,'[1]G&A Expenses'!$D:$D,_xlfn.XLOOKUP(B23,'[1]COGS Manufactured'!$A:$A,'[1]COGS Manufactured'!$D:$D)) -> 39519 | E23: 160443 | F23: 86112 | G23: 91936 | H23: 180668 | I23: 225574 | J23: 267861 | K23: 205064 | L23: 195649
A24: Plant Overhead | B24: Lease (HCF) | C24: 63000 | D24: 31500 | E24: 124677 | F24: =63000 -> 63000 | G24: =63000 -> 63000 | H24: =166575-9600 -> 156975 | I24: =160446-9600 -> 150846 | J24: 151257 | K24: 147229 | L24: 142180
A25: Plant Overhead | B25: Lease (G. Fordyce) | E25: 9600 | H25: 9600 | I25: 9600
A26: Plant Overhead | B26: Equipment Depreciation | C26: 72602 | D26: 36301 | E26: 160722 | F26: 78690 | G26: 82724 | H26: 166471 | I26: 185159 | J26: 197198 | K26: 208008 | L26: 223259
A27: Plant Overhead | B27: Repairs and Maintenance (HCF) | C27: 108622 | D27: 59118 | E27: 166308 | F27: 69884 | G27: =77804 -> 77804 | H27: =153388-980 -> 152408 | I27: =237506-1027 -> 236479 | J27: 155138 | K27: 188467 | L27: 200266
A28: Plant Overhead | B28: ='Mfg. Costs'!B29 -> Taxes - Prod Payroll | E28: 3278 | H28: 0 | I28: 1027
A29: Plant Overhead | B29: Plates and Negatives | C29: 65273 | D29: 33591 | E29: 126210 | F29: 64502 | G29: 68559 | H29: 134081 | I29: 137702 | J29: 130388 | K29: 121256 | L29: 125386
A30: Freight | B30: Shipping Wages | C30: In Indirect Labor | D30: In Indirect Labor | E30: 120598 | F30: In Indirect Labor | G30: In Indirect Labor | H30: 119383 | I30: 93521 | J30: 97494 | K30: 100963 | L30: 91173
A31: Materials | B31: Ink | C31: 39332 | D31: =_xlfn.XLOOKUP(B31,'[1]G&A Expenses'!$A:$A,'[1]G&A Expenses'!$D:$D,_xlfn.XLOOKUP(B31,'[1]COGS Manufactured'!$A:$A,'[1]COGS Manufactured'!$D:$D)) -> 21070 | E31: 64635 | F31: 33175 | G31: 34202 | H31: 94918 | I31: 94148 | J31: 116856 | K31: 125195 | L31: 131612
A32: Labor | B32: Retirement Plan Expenses | C32: 23310 | D32: 12212 | E32: 53604 | F32: 25105 | G32: 25240 | H32: 53479 | I32: 52088 | J32: 49590 | K32: 39566 | L32: 36058
A33: Materials | B33: Envelopes | C33: 11708 | D33: 5551 | E33: 29437 | F33: 17665 | G33: 18433 | H33: 31056 | I33: 33531 | J33: 40827 | K33: 44298 | L33: 39991
A34: Materials | B34: Carbon Products | C34: 1184 | D34: 1146 | E34: 1375 | F34: 884 | G34: 4565 | H34: 6961 | I34: 6603 | J34: 10241 | K34: 2163 | L34: 2741
A35: Plant Overhead | B35: Vehicle Depreciation | C35: 2193 | D35: 1096 | E35: 4384 | F35: 2192 | G35: 2192 | H35: 4385 | I35: 4385 | J35: 1462 | K35: 1538 | L35: 1538
A36: Materials | B36: Copy Paper | C36: 0 | D36: 0 | E36: 0 | F36: 0 | G36: 2773 | H36: 2773 | I36: 0 | J36: 92 | K36: 135 | L36: 967
A37: Materials | B37: Materials (HCF) | C37: =100404+66787+37171 -> 204362 | D37: =44922+40888+14871 -> 100681 | E37: 0 | F37: =94661+60689+27296 -> 182646 | G37: =106042+60581+29964 -> 196587 | H37: =1901-1901 -> 0 | I37: =48614-48614 -> 0 | J37: 0 | K37: 0 | L37: 0
A38: Materials | B38: Materials (G. Fordyce) | E38: 7685 | H38: 1901 | I38: 48614
A39: Plant Overhead | B39: Truck Expenses | C39: 4092 | D39: =_xlfn.XLOOKUP(B39,'[1]G&A Expenses'!$A:$A,'[1]G&A Expenses'!$D:$D,_xlfn.XLOOKUP(B39,'[1]COGS Manufactured'!$A:$A,'[1]COGS Manufactured'!$D:$D)) -> 2422 | E39: 135 | F39: 4032 | G39: 2051 | H39: 82 | I39: 2219 | J39: 2184 | K39: 111 | L39: 151
A40: Materials | B40: Inventory Obsolescence | D40: 0 | E40: 46829
A41: Freight | B41: Net Freight Expense (HCF) | C41: =-(46416-35372) -> -11044 | D41: =-(18865-12913) -> -5952 | E41: -5884 | F41: =48863-47166 -> 1697 | G41: =-(53008-40318) -> -12690 | H41: =-25983-4792 -> -30775 | I41: =13336-4163 -> 9173 | J41: 6147 | K41: 17143 | L41: 19190
A42: Freight | B42: Net Frieght (Income) Expense (G. Fordyce) | E42: 6216 | H42: 4792 | I42: 4163
A43: Other Income | B43: Purchase Discounts (HCF) | C43: -19607 | D43: =-9307 -> -9307 | E43: -170697 | F43: -31307 | G43: =-30420 -> -30420 | H43: =-62632+246 -> -62386 | I43: =-85166+210 -> -84956 | J43: -108616 | K43: -100887 | L43: -49024
B44: Purchase Discounts (G.Fordyce) | E44: -183 | H44: -246 | I44: -210
A45: G&A | B45: Insurance - General | C45: =30406 -> 30406 | D45: 15203 | F45: 28228 | G45: 23280
B46: Total Goods Available for sale | C46: =SUM(C7:C45) -> 3974098 | D46: =SUM(D7:D45) -> 2044953 | E46: =SUM(E7:E45) -> 8637419 | F46: =SUM(F7:F45) -> 3910107 | G46: =SUM(G7:G45) -> 4094843 | H46: =SUM(H7:H45) -> 9084788 | I46: =SUM(I7:I44) -> 10591354 | J46: =SUM(J7:J43) -> 11454627 | K46: =SUM(K7:K43) -> 9904121 | L46: =SUM(L7:L43) -> 9457796
A48: Materials | B48: Less Ending Inventories | C48: -159866 | D48: -255947 | E48: -1239901 | F48: -225544 | G48: -199589 | H48: =-1021535 -> -1021535 | I48: =-1051427-45134 -> -1096561 | J48: -1733922 | K48: -1107863 | L48: -632835
B50: Cost of Goods Sold | C50: =SUM(C46:C48) -> 3814232 | D50: =SUM(D46:D48) -> 1789006 | E50: =SUM(E46:E48) -> 7397518 | F50: =SUM(F46:F48) -> 3684563 | G50: =SUM(G46:G48) -> 3895254 | H50: =SUM(H46:H48) -> 8063253 | I50: =SUM(I46:I48) -> 9494793 | J50: =SUM(J46:J48) -> 9720705 | ... L50: =SUM(L46:L48) -> 8824961
B52: Gross Profit | C52: =C3+C5-C50 -> 961458 | D52: =D3+D5-D50 -> 620676 | E52: =E3+E5+E4-E50 -> 1608531 | F52: =F3+F5-F50 -> 794078 | G52: =G3+G5-G50 -> 641905 | H52: =H3+H5+H4-H50 -> 1287913 | I52: =I3+I5+I4-I50 -> 1632312 | J52: =J3+J5-J50 -> 2348956 | K52: =K3+K5-K50 -> 1729274 | L52: =L3+L5-L50 -> 1577177
A54: G&A | B54: Office Salaries | E54: 682921 | H54: 575317 | I54: 634812 | J54: 775051 | K54: 683480 | L54: 535262
A55: G&A | B55: Insurance | C55: =61880+6163 -> 68043 | D55: =24134+3081 -> 27215 | E55: 160790 | F55: =50863+6011 -> 56874 | G55: =23659+7965 -> 31624 | H55: 146115 | I55: 147445 | J55: 144638 | K55: 102067 | L55: 128258
A56: G&A | B56: Administrative Salaries | C56: =65997 -> 65997 | D56: =32519 -> 32519 | E56: 129211 | F56: 63483 | G56: 63975 | H56: 128935 | I56: 127950 | J56: 119896 | K56: 115656 | L56: 119624
A57: G&A | B57: Professional Fees | C57: =55949 -> 55949 | D57: 40405 | E57: 85592 | F57: 52728 | G57: 67530 | H57: 90099 | I57: 112984 | J57: 120304 | K57: 196583 | L57: 107547
A58: G&A | B58: Depreciation (HCF) | C58: =3752+0+21792+6249 -> 31793 | D58: =1876+10896+3124 -> 15896 | E58: 63962 | F58: =3752+25230+6249 -> 35231 | G58: =2878+21672+6249 -> 30799 | H58: 66605 | I58: 57511 | J58: 59433 | K58: 59486 | L58: 59449
A59: G&A | B59: Depreciation (G. Fordyce) | E59: 6505 | H59: 6505 | I59: 7913
A60: G&A | B60: Bad Debt Expense | C60: 0 | D60: 0 | E60: 6597 | F60: 2198 | G60: 1493 | H60: 50879 | I60: 1704 | J60: 57 | K60: 5840 | L60: 2810
A61: G&A | B61: General Taxes | C61: =24950 -> 24950 | D61: 12258 | E61: 54835 | F61: 29289 | G61: 23864 | H61: 46939 | I61: 57431 | J61: 96595 | K61: 44146 | L61: 49266 | M61: <-property taxes in here? Income taxes?
A62: G&A | B62: Caretaking Expenses | C62: =15908 -> 15908 | D62: 7958 | E62: 53893 | F62: 18911 | G62: 8927 | H62: 46071 | I62: 63705 | J62: 76067 | K62: 59648 | L62: 54602
A63: G&A | B63: Payroll Taxes | C63: 19095 | D63: 10530 | E63: 41164 | F63: 21560 | G63: 22732 | H63: 43462 | I63: 54543 | J63: 51840 | K63: 48608 | L63: 46821
A64: G&A | B64: Bank and Payroll Service Charges (HCF) | C64: =17884+7990 -> 25874 | D64: =9017+4548 -> 13565 | E64: 43303 | F64: =13390+7576 -> 20966 | G64: =15941+6872 -> 22813 | H64: 42997 | I64: 39709 | J64: 76511 | K64: 99314 | L64: 109300 | M64: <- split these apart? So we can add back bank fees/charges
B65: Bank and Payroll Service Charges (G. Fordyce) | E65: 156 | H65: 36 | I65: 164
A66: G&A | B66: Office Repairs and Maintenance | C66: =13222 -> 13222 | D66: 6611 | E66: 29691 | F66: 12994 | G66: 17626 | H66: 42669 | I66: 23969 | J66: 24119 | K66: 25649 | L66: 24175
A67: Selling | B67: Travel and Entertainment (HCF) | C67: =6142+4831 -> 10973 | D67: =4085+1123 -> 5208 | E67: 15274 | F67: =1723+2793 -> 4516 | G67: =8555+4508 -> 13063 | H67: 23822 | I67: 41639 | J67: 23791 | K67: 23622 | L67: 7286
B68: Travel and Entertainment (G. Fordyce) | E68: 3679 | H68: 5497 | I68: 1611
A69: G&A | B69: Telephone and Internet | C69: =4305+9838 -> 14143 | D69: =2173+5315 -> 7488 | E69: 24328 | F69: =4639+8902 -> 13541 | G69: =5039+10419 -> 15458 | H69: 28373 | I69: 32412 | J69: 33368 | K69: 38805 | L69: 36491
A70: G&A | B70: Retirement Plan Expenses | C70: =10982 -> 10982 | D70: 5891 | E70: 21536 | F70: 11009 | G70: 11290 | H70: 22199 | I70: 23682 | J70: 23252 | K70: 21563 | L70: 19755
A71: G&A | B71: Office Supplies | C71: =7095 -> 7095 | D71: =_xlfn.XLOOKUP(B71,'[1]G&A Expenses'!$A:$A,'[1]G&A Expenses'!$D:$D) -> 4126 | E71: 21002 | F71: 9564 | G71: 11638 | H71: 20600 | I71: 32828 | J71: 33223 | K71: 26639 | L71: 26432
B72: Office Supplies (G. Fordyce) | E72: 1339 | H72: 1093 | I72: 1158
A73: G&A | B73: Employee Bonus | C73: =38088 -> 38088 | D73: =_xlfn.XLOOKUP(B73,'[1]G&A Expenses'!$A:$A,'[1]G&A Expenses'!$D:$D) -> 34120 | F73: 59055 | G73: 73000 | H73: 0 | I73: 0 | J73: 0 | K73: 0 | L73: 0
A74: G&A | B74: Employee Relations | C74: =7143 -> 7143 | D74: =_xlfn.XLOOKUP(B74,'[1]G&A Expenses'!$A:$A,'[1]G&A Expenses'!$D:$D) -> 6925 | E74: 5430 | F74: =1648 -> 1648 | G74: 6231 | H74: 10599 | I74: 7875 | J74: 8928 | K74: 12153 | L74: 17311
B75: Employee Relations (G. Fordyce) | H75: 550 | I75: 400
A76: Selling | B76: Advertising | C76: =1531 -> 1531 | D76: =_xlfn.XLOOKUP(B76,'[1]G&A Expenses'!$A:$A,'[1]G&A Expenses'!$D:$D) -> 515 | E76: 7823 | F76: 3474 | G76: 8845 | H76: 10995 | I76: 12447 | J76: 25516 | K76: 0 | L76: 0
A77: G&A | B77: Postage | C77: =1739 -> 1739 | D77: =_xlfn.XLOOKUP(B77,'[1]G&A Expenses'!$A:$A,'[1]G&A Expenses'!$D:$D) -> 1074 | E77: 3405 | F77: 1561 | G77: 2187 | H77: 4009 | I77: 6408 | J77: 5824 | K77: 1339 | L77: 8669
B78: Postage (G. Fordyce) | E78: 266 | H78: 261 | I78: 181
A79: Selling | B79: Selling Expenses | C79: =1534 -> 1534 | D79: 552 | E79: 505 | F79: 207 | G79: 1734 | H79: 1753 | I79: 10325 | J79: 571 | K79: 129 | L79: 0
A80: G&A | B80: Charitable Contributions | C80: =0 -> 0 | D80: 0 | E80: 1000 | F80: 500 | G80: 750 | H80: 1500 | I80: 7429 | J80: 241 | K80: 566 | L80: 18
A81: G&A | B81: Training and Education | C81: =1000+235 -> 1235 | D81: =1000+55 -> 1055 | E81: 4290 | F81: =135+1070 -> 1205 | G81: =85+1070 -> 1155 | H81: 1425 | I81: 1410 | J81: 1834 | K81: 3033 | L81: 1260
A82: G&A | B82: Miscellaneous Expenses (HCF) | E82: 2227 | F82: 0 | H82: -24 | I82: 0 | J82: 68 | K82: 56 | L82: 806
B83: Miscellaneous Expenses (G. Foryce) | H83: 1279 | I83: 576
A84: Selling | B84: Dues and Subscriptions (HCF) | C84: 0 | D84: 0 | E84: 6 | F84: 8 | G84: 99 | H84: 99 | I84: 99 | J84: 298 | K84: 299 | L84: 95
B85: Dues and Subscriptions (G. Fordyce) | E85: 171 | H85: 166 | I85: 160
A86: Selling | B86: Salaries -Sales Service | C86: =148173 -> 148173 | D86: =_xlfn.XLOOKUP(B86,'[1]G&A Expenses'!$A:$A,'[1]G&A Expenses'!$D:$D) -> 74126 | F86: 165564 | G86: 167528
A87: Selling | B87: Salaries - Outside Sales | C87: =62136 -> 62136 | D87: 30702 | F87: 61884 | G87: 74441
A88: G&A | B88: Rent- Administrative | C88: 0 | D88: 0 | F88: =-1322 -> -1322 | G88: 18713
B89: Total SGA | C89: =SUM(C54:C88) -> 625603 | D89: =SUM(D54:D88) -> 338739 | E89: =SUM(E54:E88) -> 1470901 | F89: =SUM(F54:F88) -> 646648 | G89: =SUM(G54:G88) -> 697515 | H89: =SUM(H54:H85) -> 1420825 | I89: =SUM(I54:I85) -> 1510480 | J89: =SUM(J54:J84) -> 1701425 | K89: =SUM(K54:K84) -> 1568681 | L89: =SUM(L54:L84) -> 1355237
B91: Income (Loss) from Operations | C91: =C3+C5-C50-C89 -> 335855 | D91: =D3+D5-D50-D89 -> 281937 | E91: =E52-E89 -> 137630 | F91: =F3+F5-F50-F89 -> 147430 | G91: =G3+G5-G50-G89 -> -55610 | H91: =H52-H89 -> -132912 | I91: =I52-I89 -> 121832 | J91: =J3+J5-J50-J89 -> 647531 | K91: =K3+K5-K50-K89 -> 160593 | L91: =L3+L5-L50-L89 -> 221940
A93: Other Income | B93: Interest Expense | C93: -11022 | D93: -8329 | E93: -31884 | F93: -15604 | G93: -9669 | H93: 7 | I93: -22060 | J93: -121245 | K93: -88472 | L93: -137472
A94: Other Income | B94: Interest Income | C94: =9237 -> 9237 | D94: 1257 | E94: 16553 | F94: 5717 | H94: -19149 | I94: 0 | J94: 0 | K94: 0 | L94: 0
A95: Other Income | B95: gain on dispoal of fixed assets | C95: 0 | F95: 0 | G95: 2666 | H95: 2667 | I95: 0 | J95: 0 | K95: 1500 | L95: 0
A96: Other Income | B96: Recovery of Bad Debt | F96: 576
A97: Other Income | B97: Misc. Expense | C97: -4 | D97: -4 | G97: -15
A98: Other Income | B98: Debt Forgiven | C98: =133786 -> 133786 | H98: 0 | I98: 0 | J98: 688137 | K98: 862310 | L98: 0
A99: Other Income | B99: Employee Retention Credits | H99: 0 | I99: 0 | J99: 0 | K99: 1352277 | L99: 0
B101: Net Income (Loss) | C101: =C91+C93+C94+C95+C96+C97+C98 -> 467852 | D101: =D91+D93+D94+D95+D96+D97 -> 274861 | E101: =E91+E93+E94+E95+E96 -> 122299 | F101: =F91+F93+F94+F95+F96 -> 138119 | G101: =G91+G93+G94+G95+G97 -> -62628 | H101: =H91+H93+H94+H95 -> -149387 | I101: =I91+I93+I94+I95 -> 99772 | J101: =J91+J93+J94+J95+J98+J99 -> 1214423 | K101: =K91+K93+K94+K95+K98+K99 -> 2288208 | L101: =L91+L93+L94+L95+L98+L99 -> 84468
C104: 467828 | D104: 274840 | F104: 138098 | G104: -62638
C105: =C101-C104 -> 24 | D105: =D101-D104 -> 21 | E105: =E101-E104 -> 122299 | F105: =F101-F104 -> 21 | G105: =G101-G104 -> 10
C106: =C105/2 -> 12 | D106: =D105/2 -> 10.5
F108: =F96*2 -> 1152
F109: =F105/2 -> 10.5
F110: ^rounding errors | G110: ^rounding errors
B119: Bank Charges (Solo) | C119: 17884 | D119: 9018 | F119: =13390 -> 13390 | G119: =15941 -> 15941
D131: 1066084
...

Sheet 2024&2023-CPA Rev
C1: 2024 | D1: 2023 | E1: 2022 | F1: 2021
B3: Sales, net | C3: 8855077 | D3: 10655460
B4: Other Income | C4: 126021 | D4: 206685
B6: Beginning Inventories | C6: 1051427 | D6: 1733922
B7: Purchases & other Costs:
B8: Paper | C8: 3692358 | D8: 3982914
B9: Production and Collator Wages | C9: 965420 | D9: =1219010-136379 -> 1082631
B10: Indirect Labor | C10: 523378 | D10: 608621
B11: Health Insurance | C11: 383282 | D11: 476537
B12: Supplies | C12: 327826 | D12: =331999-2177 -> 329822
B13: Buyouts and Outside Purchases | C13: 69427 | D13: =257467-166233 -> 91234
B14: Supervisors' Salaries | C14: 268102 | D14: =280397 -> 280397
B15: Utilities | C15: 238882 | D15: 258091
B16: Payroll Taxes | C16: 200385 | D16: 232730
B17: Cartons | C17: 180668 | D17: 225574
B18: Lease | C18: =166575-9600 -> 156975 | D18: =160446-9600 -> 150846
B19: Equipment Depreciation | C19: 166471 | D19: 185159
B20: Repairs and Maintenance | C20: =153388-980 -> 152408 | D20: =237506-1027 -> 236479
B21: Plates and Negatives | C21: 134081 | D21: 137702
B22: Shipping Wages | C22: 119383 | D22: 93521
B23: Ink | C23: 94918 | D23: 94148
B24: Retirement Plan Expenses | C24: 53479 | D24: 52088
B25: Envelopes | C25: 31056 | D25: 33531
B26: Carbon Products | C26: 6961 | D26: 6603
B27: Vehicle Depreciation | C27: 4385 | D27: 4385
B28: Copy Paper | C28: 2773 | D28: 0
B29: Materials | C29: =1901-1901 -> 0 | D29: =48614-48614 -> 0
B30: Truck Expenses | C30: 82 | D30: 2219
B31: Net Freight Expense | C31: =-25983-4792 -> -30775 | D31: =13336-4163 -> 9173
B32: Purchase Discounts | C32: =-62632+246 -> -62386 | D32: =-85166+210 -> -84956
B33: total goods available for sale | C33: =SUM(C6:C32) -> 8730966 | D33: =SUM(D6:D32) -> 10223371
B34: Less Ending Inventories | C34: =-1021535 -> -1021535 | D34: =-1051427 -> -1051427
B36: Cost of Goods Sold | C36: =SUM(C33:C34) -> 7709431 | D36: =SUM(D33:D34) -> 9171944
B38: Gross Profit | C38: =C3+C4-C36 -> 1271667 | D38: =D3+D4-D36 -> 1690201
B40: Office Salaries | C40: 575317 | D40: 634812
B41: Insurance | C41: 146115 | D41: 147445
B42: Administrative Salaries | C42: 128935 | D42: 127950
B43: Professional Fees | C43: 90099 | D43: 112984
B44: Depreciation | C44: 66605 | D44: 57511
B45: Bad Debt Expense | C45: 50879 | D45: 1704
B46: General Taxes | C46: 46939 | D46: 57431
B47: Caretaking Expenses | C47: 46071 | D47: 63705
B48: Payroll Taxes | C48: 43462 | D48: 54543
B49: Bank and Payroll Service Charges | C49: 42997 | D49: 39709
B50: Office Repairs and Maintenance | C50: 42669 | D50: 23969
A51: Selling | B51: Travel and Entertainment | C51: 23822 | D51: 41639
B52: Telephone and Internet | C52: 28373 | D52: 32412
B53: Retirement Plan Expenses | C53: 22199 | D53: 23682
B54: Office Supplies | C54: 20600 | D54: 32828
B55: Employee Relations | C55: 10599 | D55: 7875
B56: Advertising | C56: 10995 | D56: 12447
B57: Postage | C57: 4009 | D57: 6408
A58: Selling | B58: Selling Expenses | C58: 1753 | D58: 10325
B59: Charitable Contributions | C59: 1500 | D59: 7429
B60: Training and Education | C60: 1425 | D60: 1410
B61: Miscellaneous Expenses | C61: -24 | D61: 0
A62: Selling | B62: Dues and Subscriptions | C62: 99 | D62: 99
B63: Total SGA | C63: =SUM(C40:C62) -> 1405438 | D63: =SUM(D40:D62) -> 1498317
B65: Income (Loss) from Operations | C65: =C3+C4-C36-C63 -> -133771 | D65: =D3+D4-D36-D63 -> 191884
B67: Interest Expense | C67: 7 | D67: -22060
B68: Interest Income | C68: -19149
B69: gain on dispoal of fixed assets | C69: 2667
B72: Net Income (Loss) | C72: =C65+C67+C68+C69 -> -150246 | D72: =D65+D67 -> 169824

Sheet Sheet1
C12: Payroll Taxes | D12: 21560
C13: Bank and Payroll Service Charges | D13: =13390+7576 -> 20966 | G13: Insurance - General
C14: Office Repairs and Maintenance | D14: 12994 | G14: Employee Bonus
C15: Travel and Entertainment | D15: =1723+1793 -> 3516 | G15: Salaries -Sales Service
C16: Telephone and Internet | D16: =4639+8902 -> 13541 | G16: Salaries - Outside Sales
C17: Retirement Plan Expenses | D17: 11009 | G17: Rent- Administrative
C18: Office Supplies | D18: 9564 | G18: Recovery of Bad Debt
C19: Employee Bonus | D19: 59055 | G19: Misc. Expense
C20: Employee Relations | D20: =1648 -> 1648
C21: Advertising | D21: 3474

Sheet P&L Assistant2
C4: Total | D4: Hillsboro #1 | E4: Hillsboro #2 | F4: Angola | G4: Total
B5: Sales | C5: =SUM(D5:F5) -> 9008622 | D5: 4669840 | E5: 537398 | F5: 3801384 | G5: =SUM(D5:F5) -> 9008622
B6: Freight Charged to Customer | C6: =SUM(D6:F6) -> 673988 | D6: 339450 | E6: 0 | F6: 334538 | G6: =SUM(D6:F6) -> 673988 | I6: =-F6 -> -334538
B7: Less Sales Discount | C7: =SUM(D7:F7) -> -153544 | D7: -76847 | E7: 0 | F7: -76697 | G7: =SUM(D7:F7) -> -153544
B8: Net Sales | C8: =SUM(D8:F8) -> 9529066 | D8: =SUM(D5:D7) -> 4932443 | E8: =SUM(E5:E7) -> 537398 | F8: =SUM(F5:F7) -> 4059225 | G8: =SUM(D8:F8) -> 9529066
B10: Cost of Goods Sold
B12: Beginning Inventory | C12: =SUM(D12:F12) -> 313472 | D12: ='Mfg. Costs'!D47 -> 68571 | E12: ='Mfg. Costs'!E47 -> 0 | F12: ='Mfg. Costs'!F47 -> 244901 | G12: =SUM(D12:F12) -> 313472
B13: Beginning Inventory (Correction to Review)
B15: Paper | C15: =SUM(D15:F15) -> 3635090 | D15: ='Mfg. Costs'!D7 -> 1914909 | E15: ='Mfg. Costs'!E7 -> -382 | F15: ='Mfg. Costs'!F7 -> 1720563 | G15: =SUM(D15:F15) -> 3635090 | I15: Total COGs | J15: =SUM(D44:F44) -> 7692598
B16: Carbon & Cartons | C16: =SUM(D16:F16) -> 187628 | D16: ='Mfg. Costs'!D8+'Mfg. Costs'!D9 -> 101577 | E16: ='Mfg. Costs'!E8+'Mfg. Costs'!E9 -> 0 | F16: ='Mfg. Costs'!F8+'Mfg. Costs'!F9 -> 86051 | G16: =SUM(D16:F16) -> 187628 | I16: Unallocated COGs | J16: 172398
B17: Ink | C17: =SUM(D17:F17) -> 94917 | D17: ='Mfg. Costs'!D10 -> 76717 | E17: ='Mfg. Costs'!E10 -> 1873 | F17: ='Mfg. Costs'!F10 -> 16327 | G17: =SUM(D17:F17) -> 94917 | I17: Grand Total | J17: =SUM(J15:J16) -> 7864996
B18: Materials + Supplies | C18: =SUM(D18:F18) -> 206347 | D18: ='Mfg. Costs'!D11 -> 138195 | E18: ='Mfg. Costs'!E11 -> 4832 | F18: ='Mfg. Costs'!F11 -> 63320 | G18: =SUM(D18:F18) -> 206347
B19: Label Material | C19: =SUM(D19:F19) -> 121477 | D19: ='Mfg. Costs'!D12 -> 0 | E19: ='Mfg. Costs'!E12 -> 0 | F19: ='Mfg. Costs'!F12 -> 121477 | G19: =SUM(D19:F19) -> 121477
B20: Integrated Material | C20: =SUM(D20:F20) -> 69426 | D20: ='Mfg. Costs'!D13 -> 69426 | E20: ='Mfg. Costs'!E13 -> 0 | F20: ='Mfg. Costs'!F13 -> 0 | G20: =SUM(D20:F20) -> 69426 | I20: Mfg. Cost Portion % - H1 | J20: =D44/J15 -> 0.52657126
B21: Envelopes | C21: =SUM(D21:F21) -> 31055 | D21: 31055 | E21: 0 | F21: 0 | G21: =SUM(D21:F21) -> 31055 | I21: Mfg. Cost Portion % - H2 | J21: =E44/J15 -> 0.050661948
B22: Copy Paper | C22: =SUM(D22:F22) -> 2773 | D22: 0 | E22: 0 | F22: 2773 | G22: =SUM(D22:F22) -> 2773 | I22: Mfg. Cost Portion % - A | J22: =F44/J15 -> 0.42276679
B23: Sub-Total Materials | C23: =SUM(C15:C22) -> 4348713 | D23: =SUM(D15:D22) -> 2331879 | E23: =SUM(E15:E22) -> 6323 | F23: =SUM(F15:F22) -> 2010511 | G23: =SUM(D23:F23) -> 4348713
B25: Labor | I25: Unallocated G&A | J25: 1011807
B26: ='Mfg. Costs'!B18 -> Direct Labor Wages | C26: =SUM(D26:F26) -> 1171096 | D26: ='Mfg. Costs'!D18 -> 723248 | E26: ='Mfg. Costs'!E18 -> 139496 | F26: ='Mfg. Costs'!F18 -> 308352 | G26: =SUM(D26:F26) -> 1171096 | I26: Des Moines G&A | J26: =34059+88 -> 34147 | K26: <-Include $88 in Des Moines Freight (not a plant, definitely a G&A item).
B27: ='Mfg. Costs'!B19 -> Indirect Labor Wages | C27: =SUM(D27:F27) -> 638970 | D27: ='Mfg. Costs'!D19 -> 236265 | E27: ='Mfg. Costs'!E19 -> 82781 | F27: ='Mfg. Costs'!F19 -> 319924 | G27: =SUM(D27:F27) -> 638970 | I27: Unallocated Freight | J27: 276
B28: ='Mfg. Costs'!B29 -> Taxes - Prod Payroll | C28: =SUM(D28:F28) -> 177233 | D28: ='Mfg. Costs'!D29 -> 77804 | E28: ='Mfg. Costs'!E29 -> 23956 | F28: ='Mfg. Costs'!F29 -> 75473 | G28: =SUM(D28:F28) -> 177233
B29: ='Mfg. Costs'!B20 -> Supervisor's Salaries | C29: =SUM(D29:F29) -> -32017 | D29: ='Mfg. Costs'!D20 -> 0 | E29: ='Mfg. Costs'!E20 -> -32017 | F29: ='Mfg. Costs'!F20 -> 0 | G29: =SUM(D29:F29) -> -32017
B30: ='Mfg. Costs'!B26 -> Caretaking-Production | C30: =SUM(D30:F30) -> 29974 | D30: ='Mfg. Costs'!D26 -> 19408 | E30: ='Mfg. Costs'!E26 -> 3472 | F30: ='Mfg. Costs'!F26 -> 7094 | G30: =SUM(D30:F30) -> 29974 | I30: Hillsboro #1 Net Profit(loss) | J30: 530386
B31: Benefits (Health Ins. + 401k) | C31: =SUM(D31:F31) -> 400267 | D31: ='Mfg. Costs'!D28+'Mfg. Costs'!D30 -> 199401 | E31: ='Mfg. Costs'!E28+'Mfg. Costs'!E30 -> 74985 | F31: ='Mfg. Costs'!F28+'Mfg. Costs'!F30 -> 125881 | G31: =SUM(D31:F31) -> 400267 | I31: Hillsboro #2 Net Profit(loss) | J31: 136816
B32: Sub-Total Labor | C32: =SUM(C26:C31) -> 2385523 | D32: =SUM(D26:D31) -> 1256126 | E32: =SUM(E26:E31) -> 292673 | F32: =SUM(F26:F31) -> 836724 | G32: =SUM(D32:F32) -> 2385523 | I32: Angola Net Profit(loss) | J32: 320852
I33: Des moines Net Profit(loss) | J33: -34148
B34: Plant Overhead | I34: Allocated Net Profit(loss) | J34: -1110653
B35: Rent | C35: =SUM(D35:F35) -> 126000 | D35: ='Mfg. Costs'!D34 -> 0 | E35: ='Mfg. Costs'!E34 -> 30000 | F35: ='Mfg. Costs'!F34 -> 96000 | G35: =SUM(D35:F35) -> 126000 | I35: Total | J35: =SUM(J30:J34) -> -156747
B36: Utilities | C36: =SUM(D36:F36) -> 238879 | D36: ='Mfg. Costs'!D37 -> 110041 | E36: ='Mfg. Costs'!E37 -> 24643 | F36: ='Mfg. Costs'!F37 -> 104195 | G36: =SUM(D36:F36) -> 238879
B37: Depreciation | C37: =SUM(D37:F37) -> 170855 | D37: ='Mfg. Costs'!D24+'Mfg. Costs'!D25 -> 100486 | E37: ='Mfg. Costs'!E24+'Mfg. Costs'!E25 -> 3757 | F37: ='Mfg. Costs'!F24+'Mfg. Costs'!F25 -> 66612 | G37: =SUM(D37:F37) -> 170855
B38: Repairs & Maintenance | C38: =SUM(D38:F38) -> 137971 | D38: ='Mfg. Costs'!D35 -> 67316 | E38: ='Mfg. Costs'!E35 -> 22352 | F38: ='Mfg. Costs'!F35 -> 48303 | G38: =SUM(D38:F38) -> 137971
B39: Plates & Comp Charges | C39: =SUM(D39:F39) -> 134079 | D39: ='Mfg. Costs'!D14 -> 105961 | E39: ='Mfg. Costs'!E14 -> 0 | F39: ='Mfg. Costs'!F14 -> 28118 | G39: =SUM(D39:F39) -> 134079 | I39: Unallocated Misc. Income | J39: 27919
B40: Misc. Plant Overhead | C40: =SUM(D40:F40) -> 101009 | D40: ='Mfg. Costs'!D31+'Mfg. Costs'!D32+'Mfg. Costs'!D33+'Mfg. Costs'!D36 -> 41545 | E40: ='Mfg. Costs'!E31+'Mfg. Costs'!E32+'Mfg. Costs'!E33+'Mfg. Costs'!E36 -> 9974 | F40: ='Mfg. Costs'!F31+'Mfg. Costs'!F32+'Mfg. Costs'!F33+'Mfg. Costs'!F36 -> 49490 | G40: =SUM(D40:F40) -> 101009 | I40: Unallocated Interst Income | J40: 7
B41: Sub-Total Plant Overhead | C41: =SUM(C35:C40) -> 908793 | D41: =SUM(D35:D40) -> 425349 | E41: =SUM(E35:E40) -> 90726 | F41: =SUM(F35:F40) -> 392718 | G41: =SUM(D41:F41) -> 908793 | I41: Unallocated Interest Expense | J41: -19149
I42: Unallocated Loss of Sale of Property | J42: 2666
B43: Less Ending Inventory | C43: =SUM(D43:F43) -> -226313 | D43: =-'Mfg. Costs'!D48 -> -73583 | E43: =-'Mfg. Costs'!E48 -> 0 | F43: =-'Mfg. Costs'!F48 -> -152730 | G43: =SUM(D43:F43) -> -226313 | I43: Unallocated Purchase Discounts | J43: 62385
B44: Total COGs(per Internals) | C44: =SUM(D44:F44) -> 7692598 | D44: =SUM(D15:D20,D26:D31,D35:D40)+D46 -> 4050701 | E44: =SUM(E15:E20,E26:E31,E35:E40)+E46 -> 389722 | F44: =SUM(F15:F20,F26:F31,F35:F40)+F46 -> 3252175 | G44: =SUM(D44:F44) -> 7692598
B46: Freight In Price Expenses | C46: =SUM(D46:F46) -> 83397 | D46: ='Mfg. Costs'!D38 -> 68402 | E46: ='Mfg. Costs'!E38 -> 0 | F46: ='Mfg. Costs'!F38 -> 14995 | G46: =SUM(D46:F46) -> 83397 | I46: Beginning Inventories (review) | J46: 1051427
B47: Freight Expense | C47: =SUM(D47:F47) -> 540101 | D47: 268916 | E47: 0 | F47: 271185 | G47: =SUM(D47:F47) -> 540101 | I47: Ending Inventories (review) | J47: -1021535
B48: Intercompany Freight | C48: =SUM(D48:F48) -> 8812 | D48: 6256 | E48: 0 | F48: 2556 | G48: =SUM(D48:F48) -> 8812 | J48: =J46+J47 -> 29892
B49: Unreconciled Freight | C49: =SUM(D49:F49) -> 10536 | D49: 4407 | E49: 0 | F49: 6129 | G49: =SUM(D49:F49) -> 10536
B50: Unallocated Freight | C50: =SUM(D50:F50) -> 276 | D50: =J27*J20 -> 145.33367 | E50: =J27*J21 -> 13.982698 | F50: =J27*J22 -> 116.68364 | G50: =SUM(D50:F50) -> 276
B52: Total Freight | C52: =SUM(D52:F52) -> 643122 | D52: =SUM(D46:D50) -> 348126.33 | E52: =SUM(E46:E50) -> 13.982698 | F52: =SUM(F46:F50) -> 294981.68 | G52: =SUM(D52:F52) -> 643122
B54: Total COGs(per CDA) | C54: =SUM(C23,C32,C41,C12,C43,C52,C56) -> 8545708 | D54: =SUM(D23,D32,D41,D12,D43,D52,D56) -> 4447248.2 | E54: =SUM(E23,E32,E41,E12,E43,E52,E56) -> 398470 | F54: =SUM(F23,F32,F41,F12,F43,F52,F56) -> 3699989.8 | G54: =SUM(D54:F54) -> 8545708
B56: Unallocated COGs | C56: =SUM(D56:F56) -> 172398 | D56: =J20*J16 -> 90779.832 | E56: =J21*J16 -> 8734.0185 | F56: =J22*J16 -> 72884.15 | G56: =SUM(D56:F56) -> 172398
B58: G&A Expenses | C58: =SUM(D58:F58) -> 266433 | D58: 133332 | E58: 15954 | F58: 117147 | G58: =SUM(D58:F58) -> 266433
B59: Unallocated G&A Expenses | C59: =SUM(D59:F59) -> 1011807 | D59: =J20*J25 -> 532788.48 | E59: =J21*J25 -> 51260.114 | F59: =J22*J25 -> 427758.4 | G59: =SUM(D59:F59) -> 1011807
B60: Des Moines G&A Expenses | C60: =SUM(D60:F60) -> 34147 | D60: =J26*J20 -> 17980.829 | E60: =J21*J26 -> 1729.9535 | F60: =J22*J26 -> 14436.218 | G60: =SUM(D60:F60) -> 34147
B62: Gross Margin | C62: =C8-C54 -> 983358 | D62: =D8-D54 -> 485194.83 | E62: =E8-E54 -> 138928 | F62: =F8-F54 -> 359235.17 | G62: =SUM(D62:F62) -> 983358
C63: =C62/C8 -> 0.10319563 | D63: =D62/D8 -> 0.098368057 | E63: =E62/E8 -> 0.25851975 | F63: =F62/F8 -> 0.088498461 | G63: =G62/G8 -> 0.10319563
B65: Operating Profit | C65: =C62-C58-C59-C60 -> -329029 | D65: =D62-D58-D59-D60 -> -198906.48 | E65: =E62-E58-E59-E60 -> 69983.932 | F65: =F62-F58-F59-F60 -> -200106.45 | G65: =SUM(D65:F65) -> -329029
B67: Other Income
B68: Sale of Scrap | C68: =SUM(D68:F68) -> 98050 | D68: 87202 | E68: 5100 | F68: 5748 | G68: =SUM(D68:F68) -> 98050
B69: Misc. Income | C69: =SUM(D69:F69) -> 74 | D69: 50 | E69: 0 | F69: 24 | G69: =SUM(D69:F69) -> 74
B70: Interest Income | C70: =SUM(D70:F70) -> 0 | D70: 0 | E70: 0 | F70: 0 | G70: =SUM(D70:F70) -> 0
B71: Interest Expense | C71: =SUM(D71:F71) -> 0 | D71: 0 | E71: 0 | F71: 0 | G71: =SUM(D71:F71) -> 0
B72: Loss on sale of Property | C72: =SUM(D72:F72) -> 0 | D72: 0 | E72: 0 | F72: 0 | G72: =SUM(D72:F72) -> 0
B73: Purchase Discounts | C73: =SUM(D73:F73) -> 0 | D73: 0 | E73: 0 | F73: 0 | G73: =SUM(D73:F73) -> 0
B74: Unallocated Misc. Income | C74: =SUM(D74:F74) -> 27919 | D74: =J39*$J$20 -> 14701.343 | E74: =$J$21*J39 -> 1414.4309 | F74: =J39*$J$22 -> 11803.226 | G74: =SUM(D74:F74) -> 27919
B75: Unallocated Interst Income | C75: =SUM(D75:F75) -> 7 | D75: =J40*$J$20 -> 3.6859988 | E75: =$J$21*J40 -> 0.35463364 | F75: =J40*$J$22 -> 2.9593676 | G75: =SUM(D75:F75) -> 7
B76: Unallocated Interest Expense | C76: =SUM(D76:F76) -> -19149 | D76: =J41*$J$20 -> -10083.313 | E76: =$J$21*J41 -> -970.12564 | F76: =J41*$J$22 -> -8095.5614 | G76: =SUM(D76:F76) -> -19149
B77: Unallocated Loss of Sale of Property | C77: =SUM(D77:F77) -> 2666 | D77: =J42*$J$20 -> 1403.839 | E77: =$J$21*J42 -> 135.06475 | F77: =J42*$J$22 -> 1127.0963 | G77: =SUM(D77:F77) -> 2666
B78: Unallocated Purchase Discounts | C78: =SUM(D78:F78) -> 62385 | D78: =J43*$J$20 -> 32850.148 | E78: =$J$21*J43 -> 3160.5456 | F78: =J43*$J$22 -> 26374.306 | G78: =SUM(D78:F78) -> 62385
B79: Total Other Income | C79: =SUM(C68:C78) -> 171952 | D79: =SUM(D68:D78) -> 126127.7 | E79: =SUM(E68:E78) -> 8840.2703 | F79: =SUM(F68:F78) -> 36984.027 | G79: =SUM(D79:F79) -> 171952
B81: Total Other Income (no Unallocated) | C81: =SUM(C68:C73) -> 98124 | D81: =SUM(D68:D73) -> 87252 | E81: =SUM(E68:E73) -> 5100 | F81: =SUM(F68:F73) -> 5772 | G81: =SUM(D81:F81) -> 98124
B83: Net Profit | C83: =C65+C79 -> -157077 | D83: =D65+D79 -> -72778.775 | E83: =E65+E79 -> 78824.202 | F83: =F65+F79 -> -163122.43 | G83: =SUM(D83:F83) -> -157077
C86: =C83+335-5 -> -156747

Sheet Mfg. Costs2
B2: FY2024 | C2: Total | D2: Hillsboro #1 | E2: Hillsboro #2 | F2: Angola | G2: ALLOCATED | H2: Agg | O2: 1271667 | Q2: 601238
Q3: 475329
B4: COGS - Manufactured | Q4: 148011
Q5: =SUM(Q2:Q4) -> 1224578 | R5: =O2-Q5 -> 47089
B6: Direct Materials
A7: Materials | B7: Paper | C7: =SUM(D7:F7) -> 3635090 | D7: 1914909 | E7: -382 | F7: 1720563 | H7: =SUM(D7:F7) -> 3635090 | O7: 4651591 | P7: 4592992
A8: Materials | B8: Carbon | C8: =SUM(D8:F8) -> 6960 | D8: 5661 | E8: 0 | F8: 1299 | H8: =SUM(D8:F8) -> 6960 | O8: 4050352 | P8: 59870
A9: Materials | B9: Cartons | C9: =SUM(D9:F9) -> 180668 | D9: 95916 | F9: 84752 | H9: =SUM(D9:F9) -> 180668 | O9: =O7-O8 -> 601239 | P9: =SUM(P7:P8) -> 4652862 | Q9: =O7-P9 -> -1271
A10: Materials | B10: Ink | C10: =SUM(D10:F10) -> 94917 | D10: 76717 | E10: 1873 | F10: 16327 | H10: =SUM(D10:F10) -> 94917
A11: Materials | B11: Materials + Supplies | C11: =SUM(D11:F11) -> 206347 | D11: 138195 | E11: 4832 | F11: 63320 | H11: =SUM(D11:F11) -> 206347 | R11: 530396
A12: Materials | B12: Label Material | C12: =SUM(D12:F12) -> 121477 | E12: 0 | F12: 121477 | H12: =SUM(D12:F12) -> 121477 | O12: 4076396 | R12: 320852
A13: Materials | B13: Integrated Material | C13: =SUM(D13:F13) -> 69426 | D13: 69426 | E13: 0 | F13: 0 | H13: =SUM(D13:F13) -> 69426 | O13: 3347128 | R13: 136816
A14: Plant Overhead | B14: Plates + Comp Charges | C14: =SUM(D14:F14) -> 134079 | D14: 105961 | E14: 0 | F14: 28118 | H14: =SUM(D14:F14) -> 134079 | O14: 389727 | R14: =SUM(R11:R13) -> 988064
B15: Total Direct Materials | C15: =SUM(D15:F15) -> 4448964 | D15: =SUM(D7:D14) -> 2406785 | E15: =SUM(E7:E14) -> 6323 | F15: =SUM(F7:F14) -> 2035856 | H15: =SUM(D15:F15) -> 4448964 | O15: 172398 | R15: -34148
O16: -59870 | R16: =R14+R15 -> 953916
B17: Labor | O17: -54667 | P17: 537739 | R17: -1110653
A18: Labor | B18: Direct Labor Wages | C18: =SUM(D18:F18) -> 1171096 | D18: 723248 | E18: 139496 | F18: 308352 | H18: =SUM(D18:F18) -> 1171096 | O18: 276 | P18: -382 | R18: =SUM(R16:R17) -> -156737
A19: Labor | B19: Indirect Labor Wages | C19: =SUM(D19:F19) -> 638970 | D19: 236265 | E19: 82781 | F19: 319924 | H19: =SUM(D19:F19) -> 638970 | P19: =P17+P18 -> 537357
A20: Labor | B20: Supervisor's Salaries | C20: =SUM(D20:F20) -> -32017 | D20: 0 | E20: -32017 | F20: 0 | H20: =SUM(D20:F20) -> -32017 | O20: =SUM(O12:O18) -> 7871388
B21: Total Labor | C21: =SUM(D21:F21) -> 1778049 | D21: =SUM(D18:D20) -> 959513 | E21: =SUM(E18:E20) -> 190260 | F21: =SUM(F18:F20) -> 628276 | H21: =SUM(D21:F21) -> 1778049
O22: 7709431
B23: Factory Overhead | O23: =O22-O20 -> -161957 | Q23: 133332 | R23: 15954
A24: Plant Overhead | B24: Depreciation Equipment | C24: =SUM(D24:F24) -> 166470 | D24: 96101 | E24: 3757 | F24: 66612 | H24: =SUM(D24:F24) -> 166470 | Q24: 117147 | R24: 131716
A25: Plant Overhead | B25: Depreciation Trucks | C25: =SUM(D25:F25) -> 4385 | D25: 4385 | E25: 0 | F25: 0 | H25: =SUM(D25:F25) -> 4385 | O25: =-1-(O23/O20) -> -0.97942459 | Q25: 34059
A26: Labor | B26: Caretaking-Production | C26: =SUM(D26:F26) -> 29974 | D26: 19408 | E26: 3472 | F26: 7094 | H26: =SUM(D26:F26) -> 29974 | Q26: 15954
B27: Equipment Leasing | C27: =SUM(D27:F27) -> 0 | D27: 0 | E27: 0 | F27: 0 | H27: =SUM(D27:F27) -> 0 | Q27: 1011807
A28: Labor | B28: Insurance - Prod Health | C28: =SUM(D28:F28) -> 355893 | D28: 183496 | E28: 63575 | F28: 108822 | H28: =SUM(D28:F28) -> 355893
A29: Labor | B29: Taxes - Prod Payroll | C29: =SUM(D29:F29) -> 177233 | D29: 77804 | E29: 23956 | F29: 75473 | H29: =SUM(D29:F29) -> 177233
A30: Labor | B30: 401k Match - Prod | C30: =SUM(D30:F30) -> 44374 | D30: 15905 | E30: 11410 | F30: 17059 | H30: =SUM(D30:F30) -> 44374 | Q30: =SUM(Q23:Q29) -> 1312299
A31: Plant Overhead | B31: Insurance - General | C31: =SUM(D31:F31) -> 53729 | D31: 27996 | E31: 3167 | F31: 22566 | H31: =SUM(D31:F31) -> 53729
A32: Plant Overhead | B32: Taxes - General | C32: =SUM(D32:F32) -> 44005 | D32: 10274 | E32: 6807 | F32: 26924 | H32: =SUM(D32:F32) -> 44005 | Q32: 1405438
A33: Plant Overhead | B33: Training & Education | C33: =SUM(D33:F33) -> 315 | D33: 315 | E33: 0 | F33: 0 | H33: =SUM(D33:F33) -> 315 | Q33: =Q32-Q30 -> 93139
A34: Plant Overhead | B34: Rent | C34: =SUM(D34:F34) -> 126000 | D34: 0 | E34: 30000 | F34: 96000 | H34: =SUM(D34:F34) -> 126000
A35: Plant Overhead | B35: Repairs + Maintenance | C35: =SUM(D35:F35) -> 137971 | D35: 67316 | E35: 22352 | F35: 48303 | H35: =SUM(D35:F35) -> 137971 | Q35: =Q33/Q32 -> 0.066270444
A36: Plant Overhead | B36: Truck Expenses | C36: =SUM(D36:F36) -> 2960 | D36: 2960 | E36: 0 | F36: 0 | H36: =SUM(D36:F36) -> 2960
A37: Plant Overhead | B37: Utilities | C37: =SUM(D37:F37) -> 238879 | D37: 110041 | E37: 24643 | F37: 104195 | H37: =SUM(D37:F37) -> 238879
A38: Freight | B38: Freight in Price Expenses | C38: =SUM(D38:F38) -> 83397 | D38: 68402 | E38: 0 | F38: 14995 | H38: =SUM(D38:F38) -> 83397
B39: Total Factory Overhead | C39: =SUM(D39:F39) -> 1465585 | D39: =SUM(D24:D38) -> 684403 | E39: =SUM(E24:E38) -> 193139 | F39: =SUM(F24:F38) -> 588043 | H39: =SUM(D39:F39) -> 1465585
B41: Total Mfg Cost | C41: =SUM(D41:F41) -> 7692598 | D41: =D15+D21+D39 -> 4050701 | E41: =E15+E21+E39 -> 389722 | F41: =F15+F21+F39 -> 3252175 | G41: 172398 | H41: =SUM(D41:F41) -> 7692598
B43: PRODUCTION | C43: =SUM(D43:F43) -> 8916843 | D43: 4651591 | E43: 537739 | F43: 3727513 | H43: =SUM(D43:F43) -> 8916843
B45: Gross Margin (of Production Sales) | C45: =SUM(D45:F45) -> 1224245 | D45: =D43-D41 -> 600890 | E45: =E43-E41 -> 148017 | F45: =F43-F41 -> 475338 | H45: =SUM(D45:F45) -> 1224245
B47: Beg Inventories | C47: =SUM(D47:F47) -> 313472 | D47: 68571 | E47: 0 | F47: 244901 | H47: =SUM(D47:F47) -> 313472
B48: Less Ending Inventories | C48: =SUM(D48:F48) -> 226313 | D48: 73583 | E48: 0 | F48: 152730 | H48: =SUM(D48:F48) -> 226313
B50: Total COGS | C50: =SUM(D50:G50) -> 7985649 | D50: 4076396 | E50: 389727 | F50: 3347128 | G50: =172398 -> 172398 | H50: =SUM(D50:G50) -> 7985649
B53: Variance (Math vs Internals)
D56: 4050352 | E56: 389727 | F56: 3252184
D57: =D56-D41 -> -349 | E57: =E56-E41 -> 5 | F57: =F56-F41 -> 9

Sheet 1-Plant Breakdown(FY24)
B2: Financial Information | C2: Highland Computer Forms, Inc.
B3: Date: 4/9/2025 | C3: Hillsboro, Ohio "S"-Corp
C4: Fiscal Year 2024 - Ended December 31st
C6: Internal | D6: Internal | E6: Internal | F6: Internal
B7: Income Statement | C7: Total | D7: Hillsboro #1 | E7: Hillsboro #2 | F7: Angola
B8: Sales
B9: ='P&L Assistant'!B5 -> Sales | C9: ='P&L Assistant'!C5 -> 9008622 | D9: ='P&L Assistant'!D5 -> 4669840 | E9: ='P&L Assistant'!E5 -> 537398 | F9: ='P&L Assistant'!F5 -> 3801384
B10: ='P&L Assistant'!B6 -> Freight Charged to Customer | C10: ='P&L Assistant'!C6 -> 673988 | D10: ='P&L Assistant'!D6 -> 339450 | E10: ='P&L Assistant'!E6 -> 0 | F10: ='P&L Assistant'!F6 -> 334538
B11: Less Sales Discount | C11: ='P&L Assistant'!C7 -> -153544 | D11: ='P&L Assistant'!D7 -> -76847 | E11: ='P&L Assistant'!E7 -> 0 | F11: ='P&L Assistant'!F7 -> -76697
B12: Total Sales, net | C12: =SUM(C9:C11) -> 9529066 | D12: =SUM(D9:D11) -> 4932443 | E12: =SUM(E9:E11) -> 537398 | F12: =SUM(F9:F11) -> 4059225
B14: Cost of Goods Sold
B15: Materials
B16: Beginning Inventory | C16: ='P&L Assistant'!C12 -> 313472 | D16: ='P&L Assistant'!D12 -> 68571 | E16: ='P&L Assistant'!E12 -> 0 | F16: ='P&L Assistant'!F12 -> 244901
B17: ='P&L Assistant'!B15 -> Paper | C17: ='P&L Assistant'!C15 -> 3635090 | D17: ='P&L Assistant'!D15 -> 1914909 | E17: ='P&L Assistant'!E15 -> -382 | F17: ='P&L Assistant'!F15 -> 1720563
B18: ='P&L Assistant'!B16 -> Carbon & Cartons | C18: ='P&L Assistant'!C16 -> 187628 | D18: ='P&L Assistant'!D16 -> 101577 | E18: ='P&L Assistant'!E16 -> 0 | F18: ='P&L Assistant'!F16 -> 86051
B19: ='P&L Assistant'!B17 -> Ink | C19: ='P&L Assistant'!C17 -> 94917 | D19: ='P&L Assistant'!D17 -> 76717 | E19: ='P&L Assistant'!E17 -> 1873 | F19: ='P&L Assistant'!F17 -> 16327
B20: ='P&L Assistant'!B18 -> Materials + Supplies | C20: ='P&L Assistant'!C18 -> 206347 | D20: ='P&L Assistant'!D18 -> 138195 | E20: ='P&L Assistant'!E18 -> 4832 | F20: ='P&L Assistant'!F18 -> 63320
B21: ='P&L Assistant'!B19 -> Label Material | C21: ='P&L Assistant'!C19 -> 121477 | D21: ='P&L Assistant'!D19 -> 0 | E21: ='P&L Assistant'!E19 -> 0 | F21: ='P&L Assistant'!F19 -> 121477
B22: ='P&L Assistant'!B20 -> Integrated Material | C22: ='P&L Assistant'!C20 -> 69426 | D22: ='P&L Assistant'!D20 -> 69426 | E22: ='P&L Assistant'!E20 -> 0 | F22: ='P&L Assistant'!F20 -> 0
B23: ='P&L Assistant'!B21 -> Envelopes | C23: ='P&L Assistant'!C21 -> 31055 | D23: ='P&L Assistant'!D21 -> 31055 | E23: ='P&L Assistant'!E21 -> 0 | F23: ='P&L Assistant'!F21 -> 0
B24: ='P&L Assistant'!B22 -> Copy Paper | C24: ='P&L Assistant'!C22 -> 2773 | D24: ='P&L Assistant'!D22 -> 0 | E24: ='P&L Assistant'!E22 -> 0 | F24: ='P&L Assistant'!F22 -> 2773
B25: Less Ending Inventory | C25: ='P&L Assistant'!C43 -> -226313 | D25: ='P&L Assistant'!D43 -> -73583 | E25: ='P&L Assistant'!E43 -> 0 | F25: ='P&L Assistant'!F43 -> -152730
B26: ='P&L Assistant'!B23 -> Sub-Total Materials | C26: =SUM(C16:C25) -> 4435872 | D26: =SUM(D16:D25) -> 2326867 | E26: =SUM(E16:E25) -> 6323 | F26: =SUM(F16:F25) -> 2102682
B27: % to Total COGS | C27: =C26/C55 -> 0.52199428 | D27: =D26/D55 -> 0.52581713 | E27: =E26/E55 -> 0.016066925 | F27: =F26/F55 -> 0.57151286
B28: ='Mfg. Costs'!B29 -> Taxes - Prod Payroll
B29: Labor
B30: ='P&L Assistant'!B26 -> Direct Labor Wages | C30: ='P&L Assistant'!C26 -> 1171096 | D30: ='P&L Assistant'!D26 -> 723248 | E30: ='P&L Assistant'!E26 -> 139496 | F30: ='P&L Assistant'!F26 -> 308352
B31: ='P&L Assistant'!B27 -> Indirect Labor Wages | C31: ='P&L Assistant'!C27 -> 638970 | D31: ='P&L Assistant'!D27 -> 236265 | E31: ='P&L Assistant'!E27 -> 82781 | F31: ='P&L Assistant'!F27 -> 319924
B32: ='P&L Assistant'!B28 -> Taxes - Prod Payroll | C32: ='P&L Assistant'!C28 -> 177233 | D32: ='P&L Assistant'!D28 -> 77804 | E32: ='P&L Assistant'!E28 -> 23956 | F32: ='P&L Assistant'!F28 -> 75473
B33: ='P&L Assistant'!B29 -> Supervisor's Salaries | C33: ='P&L Assistant'!C29 -> -32017 | D33: ='P&L Assistant'!D29 -> 0 | E33: ='P&L Assistant'!E29 -> -32017 | F33: ='P&L Assistant'!F29 -> 0
B34: ='P&L Assistant'!B30 -> Caretaking-Production | C34: ='P&L Assistant'!C30 -> 29974 | D34: ='P&L Assistant'!D30 -> 19408 | E34: ='P&L Assistant'!E30 -> 3472 | F34: ='P&L Assistant'!F30 -> 7094
B35: Benefits (Health Ins. & 401k) | C35: ='P&L Assistant'!C31 -> 400267 | D35: ='P&L Assistant'!D31 -> 199401 | E35: ='P&L Assistant'!E31 -> 74985 | F35: ='P&L Assistant'!F31 -> 125881
B36: ='P&L Assistant'!B32 -> Sub-Total Labor | C36: ='P&L Assistant'!C32 -> 2385523 | D36: ='P&L Assistant'!D32 -> 1256126 | E36: ='P&L Assistant'!E32 -> 292673 | F36: ='P&L Assistant'!F32 -> 836724
B37: % to Total COGs | C37: =C36/C55 -> 0.28071806 | D37: =D36/D55 -> 0.28385489 | E37: =E36/E55 -> 0.7436905 | F37: =F36/F55 -> 0.22742313
B39: Plant Overhead
B40: ='P&L Assistant'!B35 -> Rent | C40: ='P&L Assistant'!C35 -> 126000 | D40: ='P&L Assistant'!D35 -> 0 | E40: ='P&L Assistant'!E35 -> 30000 | F40: ='P&L Assistant'!F35 -> 96000
B41: Utilities (80%) | C41: ='P&L Assistant'!C36*0.8 -> 191103.2 | D41: ='P&L Assistant'!D36*0.8 -> 88032.8 | E41: ='P&L Assistant'!E36*0.8 -> 19714.4 | F41: ='P&L Assistant'!F36*0.8 -> 83356
B42: ='P&L Assistant'!B37 -> Depreciation | C42: ='P&L Assistant'!C37 -> 170855 | D42: ='P&L Assistant'!D37 -> 100486 | E42: ='P&L Assistant'!E37 -> 3757 | F42: ='P&L Assistant'!F37 -> 66612
B43: ='P&L Assistant'!B38 -> Repairs & Maintenance | C43: ='P&L Assistant'!C38 -> 137971 | D43: ='P&L Assistant'!D38 -> 67316 | E43: ='P&L Assistant'!E38 -> 22352 | F43: ='P&L Assistant'!F38 -> 48303
B44: ='P&L Assistant'!B39 -> Plates & Comp Charges | C44: ='P&L Assistant'!C39 -> 134079 | D44: ='P&L Assistant'!D39 -> 105961 | E44: ='P&L Assistant'!E39 -> 0 | F44: ='P&L Assistant'!F39 -> 28118
B45: ='P&L Assistant'!B40 -> Misc. Plant Overhead | C45: ='P&L Assistant'!C40 -> 101009 | D45: ='P&L Assistant'!D40 -> 41545 | E45: ='P&L Assistant'!E40 -> 9974 | F45: ='P&L Assistant'!F40 -> 49490
B46: ='P&L Assistant'!B41 -> Sub-Total Plant Overhead | C46: =SUM(C40:C45) -> 861017.2 | D46: =SUM(D40:D45) -> 403340.8 | E46: =SUM(E40:E45) -> 85797.4 | F46: =SUM(F40:F45) -> 371879
B47: % to Total COGS | C47: =C46/C55 -> 0.10132079 | D47: =D46/D55 -> 0.091145521 | E47: =E46/E55 -> 0.21801366 | F47: =F46/F55 -> 0.1010774
B49: Freight and Delivery | C49: ='P&L Assistant'!C46+'P&L Assistant'!C47+'P&L Assistant'!C48+'P&L Assistant'!C49+'P&L Assistant'!C50 -> 643122 | D49: ='P&L Assistant'!D46+'P&L Assistant'!D47+'P&L Assistant'!D48+'P&L Assistant'!D49+'P&L Assistant'!D50 -> 348126.33 | E49: ='P&L Assistant'!E46+'P&L Assistant'!E47+'P&L Assistant'!E48+'P&L Assistant'!E49+'P&L Assistant'!E50 -> 13.982698 | F49: ='P&L Assistant'!F46+'P&L Assistant'!F47+'P&L Assistant'!F48+'P&L Assistant'!F49+'P&L Assistant'!F50 -> 294981.68
B50: % to Total COGS | C50: =C49/C55 -> 0.075679822 | D50: =D49/D55 -> 0.078668352 | E50: =E49/E55 -> 3.5530436e-05 | F50: =F49/F55 -> 0.080176567
B52: Allocated COGS* | C52: ='P&L Assistant'!C56 -> 172398 | D52: ='P&L Assistant'!D56 -> 90779.832 | E52: ='P&L Assistant'!E56 -> 8734.0185 | F52: ='P&L Assistant'!F56 -> 72884.15
B53: % to Total COGS | C53: =C52/C55 -> 0.020287053 | D53: =D52/D55 -> 0.020514104 | E53: =E52/E55 -> 0.022193392 | F53: =F52/F55 -> 0.019810047
B55: Total COGS | C55: =C26+C36+C46+C49+C52 -> 8497932.2 | D55: =D26+D36+D46+D49+D52 -> 4425240 | E55: =E26+E36+E46+E49+E52 -> 393541.4 | F55: =F26+F36+F46+F49+F52 -> 3679150.8
B57: Gross Margin $ | C57: =C12-C55 -> 1031133.8 | D57: =D12-D55 -> 507203.03 | E57: =E12-E55 -> 143856.6 | F57: =F12-F55 -> 380074.17
B58: Gross Margin % | C58: =C57/C12 -> 0.10820933 | D58: =D57/D12 -> 0.10282998 | E58: =E57/E12 -> 0.26769098 | F58: =F57/F12 -> 0.0936322
B60: G&A Expenses | C60: ='P&L Assistant'!C58+'P&L Assistant'!C59+'P&L Assistant'!C60 -> 1312387 | D60: ='P&L Assistant'!D58+'P&L Assistant'!D59+'P&L Assistant'!D60 -> 684101.31 | E60: ='P&L Assistant'!E58+'P&L Assistant'!E59+'P&L Assistant'!E60 -> 68944.067 | F60: ='P&L Assistant'!F58+'P&L Assistant'!F59+'P&L Assistant'!F60 -> 559341.62
B61: Utilities (20%) | C61: ='P&L Assistant'!C36*0.2 -> 47775.8 | D61: ='P&L Assistant'!D36*0.2 -> 22008.2 | E61: ='P&L Assistant'!E36*0.2 -> 4928.6 | F61: ='P&L Assistant'!F36*0.2 -> 20839
B62: Total G&A Expenses | C62: =SUM(C60:C61) -> 1360162.8 | D62: =SUM(D60:D61) -> 706109.51 | E62: =SUM(E60:E61) -> 73872.667 | F62: =SUM(F60:F61) -> 580180.62
B64: Operating Profit (Loss) | C64: =C57-C62 -> -329029 | D64: =D57-D62 -> -198906.48 | E64: =E57-E62 -> 69983.932 | F64: =F57-F62 -> -200106.45
B66: Other Income
B67: Scrap Paper | C67: ='P&L Assistant'!C68 -> 98050 | D67: ='P&L Assistant'!D68 -> 87202 | E67: ='P&L Assistant'!E68 -> 5100 | F67: ='P&L Assistant'!F68 -> 5748
B68: Interest Expense | C68: ='P&L Assistant'!C75+'P&L Assistant'!C76 -> -19142 | D68: ='P&L Assistant'!D75+'P&L Assistant'!D76 -> -10079.627 | E68: ='P&L Assistant'!E75+'P&L Assistant'!E76 -> -969.77101 | F68: ='P&L Assistant'!F75+'P&L Assistant'!F76 -> -8092.602
B69: Gain on Sale of Assets | C69: ='P&L Assistant'!C72+'P&L Assistant'!C77 -> 2666 | D69: ='P&L Assistant'!D72+'P&L Assistant'!D77 -> 1403.839 | E69: ='P&L Assistant'!E72+'P&L Assistant'!E77 -> 135.06475 | F69: ='P&L Assistant'!F72+'P&L Assistant'!F77 -> 1127.0963
B70: Purchase Discounts | C70: ='P&L Assistant'!C73+'P&L Assistant'!C78 -> 62385 | D70: ='P&L Assistant'!D73+'P&L Assistant'!D78 -> 32850.148 | E70: ='P&L Assistant'!E73+'P&L Assistant'!E78 -> 3160.5456 | F70: ='P&L Assistant'!F73+'P&L Assistant'!F78 -> 26374.306
B71: Misc. Income | C71: ='P&L Assistant'!C69+'P&L Assistant'!C74 -> 27993 | D71: ='P&L Assistant'!D69+'P&L Assistant'!D74 -> 14751.343 | E71: ='P&L Assistant'!E69+'P&L Assistant'!E74 -> 1414.4309 | F71: ='P&L Assistant'!F69+'P&L Assistant'!F74 -> 11827.226
B72: Total Other Income | C72: =SUM(C67:C71) -> 171952 | D72: =SUM(D67:D71) -> 126127.7 | E72: =SUM(E67:E71) -> 8840.2703 | F72: =SUM(F67:F71) -> 36984.027
B74: Net Profit (Loss) | C74: =C64+C72+330+N("Rounding Error Correction") -> -156747 | D74: =D64+D72 -> -72778.775 | E74: =E64+E72 -> 78824.202 | F74: =F64+F72 -> -163122.43
B75: *COGs not assigned to any plant. Allocated proportionally by each plant's share of total manufacturing cost.
B77: Note: About $1m in G&A expenses were not allocated to any plant. Allocated proportionally by each plant's share of total manufacturing cost.
B79: Note 2: Sales figures differ because we have included "Freight Charged to Customer" as Revenue. The 2024 CPA review says such revenue is included in Sales, although comparing the Internals and the 2024 Review indicate otherwise.
B82: Note 3: Beginning and Ending Inventory figures differ greatly between the 2024 Review and the Internals.

Sheet 1-Plant Breakdown(2024)
B2: Financial Information | C2: Highland Computer Forms, Inc.
B3: Date: 4/9/2025 | C3: Hillsboro, Ohio "S"-Corp
C4: Fiscal Year 2024 - Ended December 31st
C6: Internal | D6: Internal | E6: Internal | F6: Internal
B7: Income Statement | C7: Total | D7: Hillsboro #1 | E7: Hillsboro #2 | F7: Angola
B8: Sales
B9: ='P&L Assistant'!B5 -> Sales | C9: ='P&L Assistant'!C5 -> 9008622 | D9: ='P&L Assistant'!D5 -> 4669840 | E9: ='P&L Assistant'!E5 -> 537398 | F9: ='P&L Assistant'!F5 -> 3801384
B10: ='P&L Assistant'!B6 -> Freight Charged to Customer | C10: ='P&L Assistant'!C6 -> 673988 | D10: ='P&L Assistant'!D6 -> 339450 | E10: ='P&L Assistant'!E6 -> 0 | F10: ='P&L Assistant'!F6 -> 334538
B11: Less Sales Discount | C11: ='P&L Assistant'!C7 -> -153544 | D11: ='P&L Assistant'!D7 -> -76847 | E11: ='P&L Assistant'!E7 -> 0 | F11: ='P&L Assistant'!F7 -> -76697
B12: Total Sales, net | C12: =SUM(C9:C11) -> 9529066 | D12: =SUM(D9:D11) -> 4932443 | E12: =SUM(E9:E11) -> 537398 | F12: =SUM(F9:F11) -> 4059225
B14: Cost of Goods Sold
B15: Materials
B16: Beginning Inventory | C16: ='P&L Assistant'!C12 -> 313472 | D16: ='P&L Assistant'!D12 -> 68571 | E16: ='P&L Assistant'!E12 -> 0 | F16: ='P&L Assistant'!F12 -> 244901
B17: ='P&L Assistant'!B15 -> Paper | C17: ='P&L Assistant'!C15 -> 3635090 | D17: ='P&L Assistant'!D15 -> 1914909 | E17: ='P&L Assistant'!E15 -> -382 | F17: ='P&L Assistant'!F15 -> 1720563
B18: ='P&L Assistant'!B16 -> Carbon & Cartons | C18: ='P&L Assistant'!C16 -> 187628 | D18: ='P&L Assistant'!D16 -> 101577 | E18: ='P&L Assistant'!E16 -> 0 | F18: ='P&L Assistant'!F16 -> 86051
B19: ='P&L Assistant'!B17 -> Ink | C19: ='P&L Assistant'!C17 -> 94917 | D19: ='P&L Assistant'!D17 -> 76717 | E19: ='P&L Assistant'!E17 -> 1873 | F19: ='P&L Assistant'!F17 -> 16327
B20: ='P&L Assistant'!B18 -> Materials + Supplies | C20: ='P&L Assistant'!C18 -> 206347 | D20: ='P&L Assistant'!D18 -> 138195 | E20: ='P&L Assistant'!E18 -> 4832 | F20: ='P&L Assistant'!F18 -> 63320
B21: ='P&L Assistant'!B19 -> Label Material | C21: ='P&L Assistant'!C19 -> 121477 | D21: ='P&L Assistant'!D19 -> 0 | E21: ='P&L Assistant'!E19 -> 0 | F21: ='P&L Assistant'!F19 -> 121477
B22: ='P&L Assistant'!B20 -> Integrated Material | C22: ='P&L Assistant'!C20 -> 69426 | D22: ='P&L Assistant'!D20 -> 69426 | E22: ='P&L Assistant'!E20 -> 0 | F22: ='P&L Assistant'!F20 -> 0
B23: ='P&L Assistant'!B21 -> Envelopes | C23: ='P&L Assistant'!C21 -> 31055 | D23: ='P&L Assistant'!D21 -> 31055 | E23: ='P&L Assistant'!E21 -> 0 | F23: ='P&L Assistant'!F21 -> 0
B24: ='P&L Assistant'!B22 -> Copy Paper | C24: ='P&L Assistant'!C22 -> 2773 | D24: ='P&L Assistant'!D22 -> 0 | E24: ='P&L Assistant'!E22 -> 0 | F24: ='P&L Assistant'!F22 -> 2773
B25: Less Ending Inventory | C25: ='P&L Assistant'!C43 -> -226313 | D25: ='P&L Assistant'!D43 -> -73583 | E25: ='P&L Assistant'!E43 -> 0 | F25: ='P&L Assistant'!F43 -> -152730
B26: ='P&L Assistant'!B23 -> Sub-Total Materials | C26: =SUM(C16:C25) -> 4435872 | D26: =SUM(D16:D25) -> 2326867 | E26: =SUM(E16:E25) -> 6323 | F26: =SUM(F16:F25) -> 2102682
B27: % to Total COGS | C27: =C26/C55 -> 0.52199428 | D27: =D26/D55 -> 0.52581713 | E27: =E26/E55 -> 0.016066925 | F27: =F26/F55 -> 0.57151286
B29: Labor
B30: ='P&L Assistant'!B26 -> Direct Labor Wages | C30: ='P&L Assistant'!C26 -> 1171096 | D30: ='P&L Assistant'!D26 -> 723248 | E30: ='P&L Assistant'!E26 -> 139496 | F30: ='P&L Assistant'!F26 -> 308352
B31: ='P&L Assistant'!B27 -> Indirect Labor Wages | C31: ='P&L Assistant'!C27 -> 638970 | D31: ='P&L Assistant'!D27 -> 236265 | E31: ='P&L Assistant'!E27 -> 82781 | F31: ='P&L Assistant'!F27 -> 319924
B32: ='P&L Assistant'!B28 -> Taxes - Prod Payroll | C32: ='P&L Assistant'!C28 -> 177233 | D32: ='P&L Assistant'!D28 -> 77804 | E32: ='P&L Assistant'!E28 -> 23956 | F32: ='P&L Assistant'!F28 -> 75473
B33: ='P&L Assistant'!B29 -> Supervisor's Salaries | C33: ='P&L Assistant'!C29 -> -32017 | D33: ='P&L Assistant'!D29 -> 0 | E33: ='P&L Assistant'!E29 -> -32017 | F33: ='P&L Assistant'!F29 -> 0
B34: ='P&L Assistant'!B30 -> Caretaking-Production | C34: ='P&L Assistant'!C30 -> 29974 | D34: ='P&L Assistant'!D30 -> 19408 | E34: ='P&L Assistant'!E30 -> 3472 | F34: ='P&L Assistant'!F30 -> 7094
B35: Benefits (Health Ins. & 401k) | C35: ='P&L Assistant'!C31 -> 400267 | D35: ='P&L Assistant'!D31 -> 199401 | E35: ='P&L Assistant'!E31 -> 74985 | F35: ='P&L Assistant'!F31 -> 125881
B36: ='P&L Assistant'!B32 -> Sub-Total Labor | C36: ='P&L Assistant'!C32 -> 2385523 | D36: ='P&L Assistant'!D32 -> 1256126 | E36: ='P&L Assistant'!E32 -> 292673 | F36: ='P&L Assistant'!F32 -> 836724
B37: % to Total COGs | C37: =C36/C55 -> 0.28071806 | D37: =D36/D55 -> 0.28385489 | E37: =E36/E55 -> 0.7436905 | F37: =F36/F55 -> 0.22742313
B39: Plant Overhead
B40: ='P&L Assistant'!B35 -> Rent | C40: ='P&L Assistant'!C35 -> 126000 | D40: ='P&L Assistant'!D35 -> 0 | E40: ='P&L Assistant'!E35 -> 30000 | F40: ='P&L Assistant'!F35 -> 96000
B41: Utilities (80%) | C41: ='P&L Assistant'!C36*0.8 -> 191103.2 | D41: ='P&L Assistant'!D36*0.8 -> 88032.8 | E41: ='P&L Assistant'!E36*0.8 -> 19714.4 | F41: ='P&L Assistant'!F36*0.8 -> 83356
B42: ='P&L Assistant'!B37 -> Depreciation | C42: ='P&L Assistant'!C37 -> 170855 | D42: ='P&L Assistant'!D37 -> 100486 | E42: ='P&L Assistant'!E37 -> 3757 | F42: ='P&L Assistant'!F37 -> 66612
B43: ='P&L Assistant'!B38 -> Repairs & Maintenance | C43: ='P&L Assistant'!C38 -> 137971 | D43: ='P&L Assistant'!D38 -> 67316 | E43: ='P&L Assistant'!E38 -> 22352 | F43: ='P&L Assistant'!F38 -> 48303
B44: ='P&L Assistant'!B39 -> Plates & Comp Charges | C44: ='P&L Assistant'!C39 -> 134079 | D44: ='P&L Assistant'!D39 -> 105961 | E44: ='P&L Assistant'!E39 -> 0 | F44: ='P&L Assistant'!F39 -> 28118
B45: ='P&L Assistant'!B40 -> Misc. Plant Overhead | C45: ='P&L Assistant'!C40 -> 101009 | D45: ='P&L Assistant'!D40 -> 41545 | E45: ='P&L Assistant'!E40 -> 9974 | F45: ='P&L Assistant'!F40 -> 49490
B46: ='P&L Assistant'!B41 -> Sub-Total Plant Overhead | C46: =SUM(C40:C45) -> 861017.2 | D46: =SUM(D40:D45) -> 403340.8 | E46: =SUM(E40:E45) -> 85797.4 | F46: =SUM(F40:F45) -> 371879
B47: % to Total COGS | C47: =C46/C55 -> 0.10132079 | D47: =D46/D55 -> 0.091145521 | E47: =E46/E55 -> 0.21801366 | F47: =F46/F55 -> 0.1010774
B49: Freight and Delivery | C49: ='P&L Assistant'!C46+'P&L Assistant'!C47+'P&L Assistant'!C48+'P&L Assistant'!C49+'P&L Assistant'!C50 -> 643122 | D49: ='P&L Assistant'!D46+'P&L Assistant'!D47+'P&L Assistant'!D48+'P&L Assistant'!D49+'P&L Assistant'!D50 -> 348126.33 | E49: ='P&L Assistant'!E46+'P&L Assistant'!E47+'P&L Assistant'!E48+'P&L Assistant'!E49+'P&L Assistant'!E50 -> 13.982698 | F49: ='P&L Assistant'!F46+'P&L Assistant'!F47+'P&L Assistant'!F48+'P&L Assistant'!F49+'P&L Assistant'!F50 -> 294981.68
B50: % to Total COGS | C50: =C49/C55 -> 0.075679822 | D50: =D49/D55 -> 0.078668352 | E50: =E49/E55 -> 3.5530436e-05 | F50: =F49/F55 -> 0.080176567
B52: Allocated COGS* | C52: ='P&L Assistant'!C56 -> 172398 | D52: ='P&L Assistant'!D56 -> 90779.832 | E52: ='P&L Assistant'!E56 -> 8734.0185 | F52: ='P&L Assistant'!F56 -> 72884.15
B53: % to Total COGS | C53: =C52/C55 -> 0.020287053 | D53: =D52/D55 -> 0.020514104 | E53: =E52/E55 -> 0.022193392 | F53: =F52/F55 -> 0.019810047
B55: Total COGS | C55: =C26+C36+C46+C49+C52 -> 8497932.2 | D55: =D26+D36+D46+D49+D52 -> 4425240 | E55: =E26+E36+E46+E49+E52 -> 393541.4 | F55: =F26+F36+F46+F49+F52 -> 3679150.8
B57: Gross Margin $ | C57: =C12-C55 -> 1031133.8 | D57: =D12-D55 -> 507203.03 | E57: =E12-E55 -> 143856.6 | F57: =F12-F55 -> 380074.17
B58: Gross Margin % | C58: =C57/C12 -> 0.10820933 | D58: =D57/D12 -> 0.10282998 | E58: =E57/E12 -> 0.26769098 | F58: =F57/F12 -> 0.0936322
B60: G&A Expenses | C60: ='P&L Assistant'!C58+'P&L Assistant'!C59+'P&L Assistant'!C60 -> 1312387 | D60: ='P&L Assistant'!D58+'P&L Assistant'!D59+'P&L Assistant'!D60 -> 684101.31 | E60: ='P&L Assistant'!E58+'P&L Assistant'!E59+'P&L Assistant'!E60 -> 68944.067 | F60: ='P&L Assistant'!F58+'P&L Assistant'!F59+'P&L Assistant'!F60 -> 559341.62
B61: Utilities (20%) | C61: ='P&L Assistant'!C36*0.2 -> 47775.8 | D61: ='P&L Assistant'!D36*0.2 -> 22008.2 | E61: ='P&L Assistant'!E36*0.2 -> 4928.6 | F61: ='P&L Assistant'!F36*0.2 -> 20839
B62: Total G&A Expenses | C62: =SUM(C60:C61) -> 1360162.8 | D62: =SUM(D60:D61) -> 706109.51 | E62: =SUM(E60:E61) -> 73872.667 | F62: =SUM(F60:F61) -> 580180.62
B64: Operating Profit (Loss) | C64: =C57-C62 -> -329029 | D64: =D57-D62 -> -198906.48 | E64: =E57-E62 -> 69983.932 | F64: =F57-F62 -> -200106.45
B66: Other Income
B67: Scrap Paper | C67: ='P&L Assistant'!C68 -> 98050 | D67: ='P&L Assistant'!D68 -> 87202 | E67: ='P&L Assistant'!E68 -> 5100 | F67: ='P&L Assistant'!F68 -> 5748
B68: Interest Expense | C68: ='P&L Assistant'!C75+'P&L Assistant'!C76 -> -19142 | D68: ='P&L Assistant'!D75+'P&L Assistant'!D76 -> -10079.627 | E68: ='P&L Assistant'!E75+'P&L Assistant'!E76 -> -969.77101 | F68: ='P&L Assistant'!F75+'P&L Assistant'!F76 -> -8092.602
B69: Gain on Sale of Assets | C69: ='P&L Assistant'!C72+'P&L Assistant'!C77 -> 2666 | D69: ='P&L Assistant'!D72+'P&L Assistant'!D77 -> 1403.839 | E69: ='P&L Assistant'!E72+'P&L Assistant'!E77 -> 135.06475 | F69: ='P&L Assistant'!F72+'P&L Assistant'!F77 -> 1127.0963
B70: Purchase Discounts | C70: ='P&L Assistant'!C73+'P&L Assistant'!C78 -> 62385 | D70: ='P&L Assistant'!D73+'P&L Assistant'!D78 -> 32850.148 | E70: ='P&L Assistant'!E73+'P&L Assistant'!E78 -> 3160.5456 | F70: ='P&L Assistant'!F73+'P&L Assistant'!F78 -> 26374.306
B71: Misc. Income | C71: ='P&L Assistant'!C69+'P&L Assistant'!C74 -> 27993 | D71: ='P&L Assistant'!D69+'P&L Assistant'!D74 -> 14751.343 | E71: ='P&L Assistant'!E69+'P&L Assistant'!E74 -> 1414.4309 | F71: ='P&L Assistant'!F69+'P&L Assistant'!F74 -> 11827.226
B72: Total Other Income | C72: =SUM(C67:C71) -> 171952 | D72: =SUM(D67:D71) -> 126127.7 | E72: =SUM(E67:E71) -> 8840.2703 | F72: =SUM(F67:F71) -> 36984.027
B74: Net Profit (Loss) | C74: =C64+C72+330+N("Rounding Error Correction") -> -156747 | D74: =D64+D72 -> -72778.775 | E74: =E64+E72 -> 78824.202 | F74: =F64+F72 -> -163122.43
B75: *COGs not assigned to any plant. Allocated proportionally by each plant's share of total manufacturing cost.
B77: Note: About $1m in G&A expenses were not allocated to any plant. Allocated proportionally by each plant's share of total manufacturing cost.
B79: Note 2: Sales figures differ because we have included "Freight Charged to Customer" as Revenue. The 2024 CPA review says such revenue is included in Sales, although comparing the Internals and the 2024 Review indicate otherwise.
B82: Note 3: Beginning and Ending Inventory figures differ greatly between the 2024 Review and the Internals.

Sheet 1-Inc. Statements
A1: FINANCIAL INFORMATION | D1: Highland Computer Forms, Inc. and Affiliates
A2: Date: 12/14/18 v2 | D2: Hillsboro, OH
D3: OH "S" corp-from CPA Reviewed Statements
D4: Fiscal Years ending December 31st
D5: (000's omitted)
D7: Internal
C8: Extrapolation | D8: Jan-Oct | E8: Review | F8: Review | G8: Review | H8: Review
A9: INCOME STATEMENT | C9: 2018 | D9: 2018 | E9: 2017 | F9: 2016 | G9: 2015 | H9: 2014
B10: Revenue
B11: Net Sales | C11: 15796 | D11: 13163 | E11: 17905 | F11: 18613 | G11: 20081 | H11: 22786
B12: Other Income | C12: 703 | D12: 586 | E12: 693 | F12: 701 | G12: 689 | H12: 577
B13: Total Net Revenue | C13: =SUM(C11:C12) -> 16499 | D13: =SUM(D11:D12) -> 13749 | E13: =SUM(E11:E12) -> 18598 | F13: =SUM(F11:F12) -> 19314 | G13: =SUM(G11:G12) -> 20770 | H13: =SUM(H11:H12) -> 23363
B15: Cost of Goods Sold
B16: Beginning Inventory | C16: 0 | D16: 0 | E16: 1388 | F16: 1509 | G16: 1914 | H16: 2154
B17: Manufacturing Expense Detail (Tab 2) | C17: 14809 | D17: 12341 | E17: 15854 | F17: 16768 | G17: 17676 | H17: 20705
B18: Less: Ending Inventory | C18: 0 | D18: 0 | E18: -896 | F18: -1388 | G18: -1509 | H18: -1914
B19: Total Cost of Goods Sold | C19: =SUM(C16:C18) -> 14809 | D19: =SUM(D16:D18) -> 12341 | E19: =SUM(E16:E18) -> 16346 | F19: =SUM(F16:F18) -> 16889 | G19: =SUM(G16:G18) -> 18081 | H19: =SUM(H16:H18) -> 20945
B21: Gross Margin $ | C21: 1690 | D21: 1408 | E21: 2252 | F21: 2425 | G21: 2689 | H21: 2418
B22: Gross Margin % (to Total Net Revenue) | C22: 0.102 | D22: 0.102 | E22: 0.121 | F22: 0.126 | G22: 0.13 | H22: 0.104
B24: Operating Expenses
B25: Operating Expenses (Tab 3) | C25: 1579 | D25: 1316 | E25: 2050 | F25: 2135 | G25: 2163 | H25: 2396
B26: Total Operating Expenses | C26: =SUM(C25) -> 1579 | D26: =SUM(D25) -> 1316 | E26: =SUM(E25) -> 2050 | F26: =SUM(F25) -> 2135 | G26: =SUM(G25) -> 2163 | H26: =SUM(H25) -> 2396
B28: Income from Operations $ | C28: 111 | D28: 92 | E28: 202 | F28: 290 | G28: 526 | H28: 22
B29: Income from Operations % | C29: >1% | D29: >1% | E29: 0.011 | F29: 0.015 | G29: 0.025 | H29: <1%
B31: Other Income (Expense)
B32: Interest Expense net of Income | C32: -258 | D32: -215 | E32: -274 | F32: -300 | G32: -407 | H32: -322
B33: Gain on disposal of Fixed Assets | C33: 0 | D33: 0 | E33: 14 | F33: 0 | G33: 0 | H33: 0
B34: Total other Income (Expense) | C34: =SUM(C32:C33) -> -258 | D34: =SUM(D32:D33) -> -215 | E34: =SUM(E32:E33) -> -260 | F34: =SUM(F32:F33) -> -300 | G34: =SUM(G32:G33) -> -407 | H34: =SUM(H32:H33) -> -322
B36: Pretax Income (Loss) | C36: -147 | D36: -123 | E36: -58 | F36: -10 | G36: 119 | H36: -300
B38: "Adjusted" EBITDA
B39: (Earnings Before Int., Taxes, Dep. & Amort.) | C39: Extp.-2018 | D39: 10 mo. 2018 | E39: 2017 | F39: 2016 | G39: 2015 | H39: 2014
B40: Total Net Sales | C40: 16499 | D40: 13749 | E40: 18598 | F40: 19314 | G40: 20770 | H40: 23363
B41: Pretax Income (Loss) | C41: -147 | D41: -123 | E41: -58 | F41: -10 | G41: 119 | H41: -300
B42: Reverse non-operating (Income)/Losses | C42: 0 | D42: 0 | E42: 14 | F42: 0 | G42: 0 | H42: 0
B43: Interest Expense | C43: 258 | D43: 215 | E43: 274 | F43: 300 | G43: 407 | H43: 322
B44: Depreciation & Amortization | C44: 341 | D44: 284 | E44: 365 | F44: 404 | G44: 406 | H44: 417
B45: "Adjusted" EBITDA $ | C45: =SUM(C41:C44) -> 452 | D45: =SUM(D41:D44) -> 376 | E45: =SUM(E41:E44) -> 595 | F45: =SUM(F41:F44) -> 694 | G45: =SUM(G41:G44) -> 932 | H45: =SUM(H41:H44) -> 439
B46: "Adjusted" EBITDA % | C46: 0.027 | D46: 0.027 | E46: 0.032 | F46: 0.036 | G46: 0.045 | H46: 0.019

Sheet 2-Mfg. Exp. Detail
A1: FINANCIAL INFORMATION | B1: Highland Computer Forms, Inc.
A2: Date: 12/14/18 v2 | B2: Hillsboro, OH
B3: OH "S" corp-from CPA Reviewed Statements
B4: Fiscal Years ending December 31st
B7: Internal
B8: 9 mo. | C8: Review | D8: Review | E8: Did not break out 2015 and 2014
A9: Manufacturing Expenses | B9: 2018 | C9: 2017 | D9: 2016
A11: Paper Purchases | C11: 7393101 | D11: 8235750
A12: Production wages | C12: 1807217 | D12: 1880894
A13: Supplies Purchased | C13: 1554803 | D13: 1757565
A14: Indirect Labor | B14: Did | C14: 862409 | D14: 934190
A15: Buyouts & outside purchases | B15: not | C15: 628475 | D15: 427726
A16: Health Insurance | B16: break | C16: 490180 | D16: 450684
A17: Supervisors' Salaries | B17: out | C17: 486462 | D17: 470404
A18: Cartons | C18: 360708 | D18: 380017
A19: Payroll Taxes | C19: 343742 | D19: 361638
A20: Utilities | C20: 336396 | D20: 331374
A21: Rep. & Maintenance | C21: 322541 | D21: 349649
A22: Equipment Depreciation | C22: 289207 | D22: 323660
A23: Rent | C23: 204832 | D23: 199666
A24: Shipping wages | C24: 158346 | D24: 135167
A25: Plates & negatives | C25: 158208 | D25: 177443
A26: Ink | C26: 142535 | D26: 162053
A27: Net Freight Expense | C27: 129564 | D27: 44235
A28: Envelopes | C28: 74503 | D28: 89935
A29: Retirement plan expenses | C29: 69026 | D29: 67569
... A33: Purchase discounts | C33: -14975 | D33: -42169
A34: Mfg. Expense Detail | B34: 0 | C34: =SUM(C11:C33) -> 15853198 | D34: =SUM(D11:D33) -> 16767708

Sheet 3-Operating Exp.
A1: FINANCIAL INFORMATION | B1: Highland Computer Forms, Inc.
A2: Date: 12/14/18 v2 | B2: Hillsboro, OH
B3: OH "S" corp-from CPA Reviewed Statements
B4: Fiscal Years ending December 31st
B7: Internal
B8: 10 mo. | C8: Review | D8: Review
A9: Operating Expenses | B9: 2018 | C9: 2017 | D9: 2016
A10: Office Salaries | C10: 646402 | D10: 668660
A11: Administrative Salaries | C11: 268428 | D11: 278012
A12: Professional Fees | C12: 164431 | D12: 150799
A13: Insurance | B13: Did | C13: 154936 | D13: 135590
A14: Bank/Payroll Fees | B14: not | C14: 136474 | D14: 128846
A15: Caretaking Expenses | B15: break | C15: 135396 | D15: 145380
A16: General Taxes | B16: out | C16: 118997 | D16: 109469
A17: Depreciation | B17: for | C17: 75949 | D17: 79688
A18: Telephone & Internet | B18: the | C18: 74711 | D18: 87136
A19: Payroll Taxes | B19: 10 mo. | C19: 63758 | D19: 73929
A20: Travel & Entertainment | B20: period | C20: 49190 | D20: 73139
A21: Bad Debt Expense | C21: 42349 | D21: 5000
A22: Office Supplies | C22: 36463 | D22: 41084
A23: Retirement Plan Expense | C23: 27347 | D23: 29073
A24: Office Repairs & Maint. | C24: 26141 | D24: 31680
A25: Employee Relations | C25: 11286 | D25: 11058
A26: Postage | C26: 10200 | D26: 13970
A27: Training & Education | C27: 3285 | D27: 5405
A28: Advertising | C28: 2202 | D28: 39154
A29: Charitable Contributions | C29: 1589 | D29: 1283
A30: Dues & Subscriptions | C30: 451 | D30: 2023
A31: Selling Expenses | C31: 425 | D31: 24786
A32: Misc. Expenses | C32: -247 | D32: -71
A33: Total Operating Expenses | B33: 0 | C33: =SUM(C10:C32) -> 2050163 | D33: =SUM(D10:D32) -> 2135093

Sheet 4-Balance Sheets
A1: FINANCIAL INFORMATION | C1: Highland Computer Forms, Inc.
A2: Date: 12/14/18 v2 | C2: Hillsboro, OH
C3: OH "S" corp-from CPA Reviewed Statements
C4: Fiscal Years ending December 31st
C7: Internal | D7: Review | E7: Review
A8: BALANCE SHEET | C8: 43404 | D8: 2017 | E8: 2016
A9: ASSETS
B10: Current Assets
B11: Cash & Cash Equivalents | C11: -31954 | D11: 47309 | E11: 156976
B12: Accounts Receivable-Trade | C12: 1507097 | D12: 1578706 | E12: 1529648
B13: Accounts Receivable-Other | C13: 33173 | D13: 27478 | E13: 21113
B14: Accounts Receivable-Related party | C14: 0 | D14: 48572 | E14: 48572
B15: Inventories | C15: 926294 | D15: 895487 | E15: 1388309
B16: Prepaid Expenses | C16: 12389 | D16: 8312 | E16: 16707
B17: Total Current Assets | C17: 2447002 | D17: =SUM(D11:D16) -> 2605864 | E17: =SUM(E11:E16) -> 3161325
B19: Plant, Property & Equipment
B20: Land | C20: 175730 | D20: 88000 | E20: 88000
B21: Buildings | C21: 1095186 | D21: 1182916 | E21: 1182916
B22: Leasehold Improvements | C22: 1594653 | D22: 1594653 | E22: 1535364
B23: Machinery & Equipment | C23: 11502424 | D23: 11454410 | E23: 11426702
B24: Vehicles | C24: 320055 | D24: 320055 | E24: 320055
B25: Furniture, Fixtures & Office Equip. | C25: 702558 | D25: 692558 | E25: 692558
B26: Sub-total P&E (at Cost) | C26: 15390607 | D26: =SUM(D20:D25) -> 15332592 | E26: =SUM(E20:E25) -> 15245595
B27: Less: Accumulated Depreciation | C27: -12803817 | D27: -12519356 | E27: -12154201
B28: Net Plant, Property & Equipment | C28: =SUM(C26:C27) -> 2586790 | D28: =SUM(D26:D27) -> 2813236 | E28: =SUM(E26:E27) -> 3091394
B30: Other Assets
B31: Cash Value of Life Insurance | C31: 217605 | D31: 214477 | E31: 209952
B32: Goodwill | C32: 0 | D32: 10000 | E32: 10000
B33: Deposits | C33: 7173 | D33: 2697 | E33: 2697
B34: Total Other Assets | C34: =SUM(C31:C33) -> 224778 | D34: =SUM(D31:D33) -> 227174 | E34: =SUM(E31:E33) -> 222649
B36: TOTAL ASSETS | C36: 5258571 | D36: 5646274 | E36: 6475368
A38: LIABILITIES AND
A39: SHAREHOLDERS' EQUITY
A40: LIABILITIES
B41: Current Liabilities
B42: Capital Lease, current portion | C42: 9238 | D42: 24648 | E42: 53721
B43: Long-term Debt, current portion | C43: 120000 | D43: 120000 | E43: 470365
B44: Accounts Payable, trade | C44: 2415200 | D44: 2726174 | E44: 2765674
B45: Accrued Payroll & Related costs | C45: 194180 | D45: 132858 | E45: 147025
B46: Accrued Rent, related parties | C46: 0 | D46: 75500 | E46: 67500
B47: Accrued taxes | C47: 0 | D47: 46261 | E47: 45040
B48: Accrued Interest | C48: 18491 | D48: 15740 | E48: 16910
B49: Advance from Officer | C49: 0 | D49: 0 | E49: 26543
B50: Total Current Liabilities | C50: 2757110 | D50: =SUM(D42:D49) -> 3141181 | E50: =SUM(E42:E49) -> 3592778
B52: Long-term Liabilities
B53: Line of Credit | C53: 1242019 | D53: 1294116 | E53: 1316609
B54: Capital Lease, net of current portion | C54: 0 | D54: 5006 | E54: 29650
B55: Long-term Debt, net of current portion | C55: 140000 | D55: 240000 | E55: 360000
B56: Total Long-term Liabilities | C56: =SUM(C53:C55) -> 1382019 | D56: =SUM(D53:D55) -> 1539122 | E56: =SUM(E53:E55) -> 1706259
B58: TOTAL LIABILITIES | C58: 4139129 | D58: 4680303 | E58: 5299037
B60: SHAREHOLDERS' EQUITY | C60: 1119443 | D60: 965971 | E60: 1176331
C61: 10/31/18 | D61: 2017 | E61: 2016

Sheet 5-Debt

Sheet 6-Comp to EBF
A1: FINANCIAL INFORMATION | C1: Comp of HCF to EBF
A2: Date: 12/14/18 v2 | C2: (000's omitted)
C5: HCF | D5: EBF
A6: INCOME STATEMENT | C6: 2017 | D6: 2017
B7: Revenue
B8: Net Sales | C8: 17905 | D8: 370171
B9: Other Income | C9: 693 | D9: 0
B10: Total Net Revenue | C10: =SUM(C8:C9) -> 18598 | D10: =SUM(D8:D9) -> 370171
B12: Cost of Goods Sold
B13: Beginning Inventory | C13: 1388 | D13: 0
B14: Manufacturing Expenses | C14: 15854 | D14: 0
B15: Less: Ending Inventory | C15: -896 | D15: 0
B16: Total Cost of Goods Sold | C16: =SUM(C13:C15) -> 16346 | D16: 253257
B18: Gross Margin $ | C18: 2252 | D18: 116914
B19: Gross Margin % (to Total Net Revenue) | C19: 0.121 | D19: 0.316
B21: Total Operating Expenses | C21: 2050 | D21: 69451
B22: Operating Exp. % (to Total Net Revenue) | C22: 0.11 | D22: 0.188
B24: Income from Operations $ | C24: 202 | D24: 47463
B25: Income from Operations % | C25: 0.011 | D25: 0.128
B27: Other Income (Expense)
B28: Interest Expense net of Income | C28: -274 | D28: 0
B29: Gain (Loss) on disposal of Assets | C29: 14 | D29: -162
B30: Other Expense | C30: 0 | D30: -392
B31: Total other Income (Expense) | C31: =SUM(C28:C30) -> -260 | D31: =SUM(D28:D30) -> -554
B33: Pretax Income (Loss) | C33: -58 | D33: 46909
B35: "Adjusted" EBITDA | C35: HCF | D35: EBF | E35: Note re: EBF:
B36: (Earnings Before Int., Taxes, Dep. & Amort.) | C36: 2017 | D36: 2017 | E36: As of the market close on Thurs 12/13/18,
B37: Total Net Sales | C37: 18598 | D37: 370171 | E37: shares of EBF were trading at $17.82.
B38: Pretax Income (Loss) | C38: -58 | D38: 46909 | E38: EBF has 26.32MM shares outstanding
B39: Reverse non-operating (Income)/Losses | C39: 14 | D39: 162 | E39: so that gives it a Market Cap of ~$469MM.
B40: Interest Expense | C40: 274 | D40: 777 | E40: EBF has Cash on hand of ~$79MM and
B41: Depreciation & Amortization | C41: 365 | D41: 8033 | E41: only $30MM in Debt yielding a Total
B42: "Adjusted" EBITDA $ | C42: =SUM(C38:C41) -> 595 | D42: =SUM(D38:D41) -> 55881 | E42: Enterprise Value (TEV) of ~$420MM.
B43: "Adjusted" EBITDA % | C43: 0.032 | D43: 0.151 | E43: So, EBF is trading at 7.5X EBITDA
B44: Note re: HCF:
B45: At 10/31/18 HCF had negative Cash of -$32K and
B46: Total Debt of $1.5MM.
B47: 5X EBITDA would equal ~$3MM in TEV so that
B48: amount minus $1.5MM in Debt and minus $32K in
B49: negative Cash produces an Equity value of $1.5MM.
